package com.google.android.gms.internal.measurement;

import android.app.Application;
import android.content.Context;
import android.net.Uri;
import android.net.Uri.Builder;
import android.support.v4.util.ArrayMap;
import android.text.TextUtils;
import android.util.Pair;
import com.google.android.gms.common.api.internal.GoogleServices;
import com.google.android.gms.common.internal.Preconditions;
import com.google.android.gms.common.util.Clock;
import com.google.android.gms.common.util.DefaultClock;
import com.google.android.gms.common.wrappers.PackageManagerWrapper;
import com.google.android.gms.common.wrappers.Wrappers;
import com.google.android.gms.measurement.AppMeasurement;
import com.google.firebase.analytics.FirebaseAnalytics;
import java.net.MalformedURLException;
import java.net.URL;
import java.security.SecureRandom;
import java.util.ArrayList;
import java.util.Collection;
import java.util.Iterator;
import java.util.List;
import java.util.Map;
import java.util.concurrent.atomic.AtomicReference;

public class zzgl
{
  private static volatile zzgl zzamc;
  private final long zzaeh;
  private final zzeh zzamd;
  private final zzfr zzame;
  private final zzfg zzamf;
  private final zzgg zzamg;
  private final zzjk zzamh;
  private final zzgf zzami;
  private final AppMeasurement zzamj;
  private final FirebaseAnalytics zzamk;
  private final zzjv zzaml;
  private final zzfe zzamm;
  private final zzfk zzamn;
  private final zzih zzamo;
  private final zzhm zzamp;
  private final zzdx zzamq;
  private zzei zzamr;
  private zzfc zzams;
  private zzil zzamt;
  private zzeo zzamu;
  private zzfb zzamv;
  private zzfp zzamw;
  private zzjq zzamx;
  private zzee zzamy;
  private zzfx zzamz;
  private boolean zzana;
  private Boolean zzanb;
  private long zzanc;
  private List<Long> zzanf;
  private List<Runnable> zzang;
  private int zzanh;
  private int zzani;
  private long zzanj;
  private long zzank;
  private boolean zzanl;
  private boolean zzanm;
  private boolean zzann;
  private final Context zzqs;
  private final Clock zzrj;
  private boolean zzvj = false;
  
  private zzgl(zzhl paramzzhl)
  {
    Preconditions.checkNotNull(paramzzhl);
    this.zzqs = paramzzhl.zzqs;
    this.zzanj = -1L;
    this.zzrj = DefaultClock.getInstance();
    this.zzaeh = this.zzrj.currentTimeMillis();
    this.zzamd = new zzeh(this);
    Object localObject = new zzfr(this);
    ((zzhk)localObject).zzm();
    this.zzame = ((zzfr)localObject);
    localObject = new zzfg(this);
    ((zzhk)localObject).zzm();
    this.zzamf = ((zzfg)localObject);
    localObject = new zzjv(this);
    ((zzhk)localObject).zzm();
    this.zzaml = ((zzjv)localObject);
    localObject = new zzfe(this);
    ((zzhk)localObject).zzm();
    this.zzamm = ((zzfe)localObject);
    this.zzamq = new zzdx(this);
    localObject = new zzfk(this);
    ((zzhk)localObject).zzm();
    this.zzamn = ((zzfk)localObject);
    localObject = new zzih(this);
    ((zzhk)localObject).zzm();
    this.zzamo = ((zzih)localObject);
    localObject = new zzhm(this);
    ((zzhk)localObject).zzm();
    this.zzamp = ((zzhm)localObject);
    this.zzamj = new AppMeasurement(this);
    this.zzamk = new FirebaseAnalytics(this);
    localObject = new zzjk(this);
    ((zzhk)localObject).zzm();
    this.zzamh = ((zzjk)localObject);
    localObject = new zzgf(this);
    ((zzhk)localObject).zzm();
    this.zzami = ((zzgf)localObject);
    localObject = new zzgg(this);
    ((zzhk)localObject).zzm();
    this.zzamg = ((zzgg)localObject);
    if ((this.zzqs.getApplicationContext() instanceof Application))
    {
      zzhm localzzhm = zzfu();
      if ((localzzhm.getContext().getApplicationContext() instanceof Application))
      {
        localObject = (Application)localzzhm.getContext().getApplicationContext();
        if (localzzhm.zzaoi == null) {
          localzzhm.zzaoi = new zzif(localzzhm, null);
        }
        ((Application)localObject).unregisterActivityLifecycleCallbacks(localzzhm.zzaoi);
        ((Application)localObject).registerActivityLifecycleCallbacks(localzzhm.zzaoi);
        localzzhm.zzgg().zzir().log("Registered activity lifecycle callback");
      }
    }
    for (;;)
    {
      this.zzamg.zzc(new zzgm(this, paramzzhl));
      return;
      zzgg().zzin().log("Application context is not an Application");
    }
  }
  
  private static void zza(zzhj paramzzhj)
  {
    if (paramzzhj == null) {
      throw new IllegalStateException("Component not created");
    }
  }
  
  private static void zza(zzhk paramzzhk)
  {
    if (paramzzhk == null) {
      throw new IllegalStateException("Component not created");
    }
    if (!paramzzhk.isInitialized())
    {
      paramzzhk = String.valueOf(paramzzhk.getClass());
      throw new IllegalStateException(String.valueOf(paramzzhk).length() + 27 + "Component not initialized: " + paramzzhk);
    }
  }
  
  private final void zza(zzhl paramzzhl)
  {
    zzgf().zzab();
    paramzzhl = new zzeo(this);
    paramzzhl.zzm();
    this.zzamu = paramzzhl;
    paramzzhl = new zzfb(this);
    paramzzhl.zzm();
    this.zzamv = paramzzhl;
    Object localObject = new zzei(this);
    ((zzhk)localObject).zzm();
    this.zzamr = ((zzei)localObject);
    localObject = new zzfc(this);
    ((zzhk)localObject).zzm();
    this.zzams = ((zzfc)localObject);
    localObject = new zzee(this);
    ((zzhk)localObject).zzm();
    this.zzamy = ((zzee)localObject);
    localObject = new zzil(this);
    ((zzhk)localObject).zzm();
    this.zzamt = ((zzil)localObject);
    localObject = new zzjq(this);
    ((zzhk)localObject).zzm();
    this.zzamx = ((zzjq)localObject);
    this.zzamw = new zzfp(this);
    this.zzaml.zzkd();
    this.zzame.zzkd();
    this.zzamz = new zzfx(this);
    this.zzamv.zzkd();
    zzgg().zzip().zzg("App measurement is starting up, version", Long.valueOf(12451L));
    zzgg().zzip().log("To enable debug logging run: adb shell setprop log.tag.FA VERBOSE");
    paramzzhl = paramzzhl.zzah();
    if (zzgc().zzcc(paramzzhl))
    {
      localObject = zzgg().zzip();
      paramzzhl = "Faster debug mode event logging enabled. To disable, run:\n  adb shell setprop debug.firebase.analytics.app .none.";
    }
    for (;;)
    {
      ((zzfi)localObject).log(paramzzhl);
      zzgg().zziq().log("Debug-level message logging enabled");
      if (this.zzanh != this.zzani) {
        zzgg().zzil().zze("Not all components initialized", Integer.valueOf(this.zzanh), Integer.valueOf(this.zzani));
      }
      this.zzvj = true;
      return;
      localObject = zzgg().zzip();
      paramzzhl = String.valueOf(paramzzhl);
      if (paramzzhl.length() != 0) {
        paramzzhl = "To enable faster debug mode event logging run:\n  adb shell setprop debug.firebase.analytics.app ".concat(paramzzhl);
      } else {
        paramzzhl = new String("To enable faster debug mode event logging run:\n  adb shell setprop debug.firebase.analytics.app ");
      }
    }
  }
  
  private final zzkh[] zza(String paramString, zzkn[] paramArrayOfzzkn, zzki[] paramArrayOfzzki)
  {
    Preconditions.checkNotEmpty(paramString);
    return zzft().zza(paramString, paramArrayOfzzki, paramArrayOfzzkn);
  }
  
  private final void zzb(zzeb paramzzeb)
  {
    zzgf().zzab();
    if (TextUtils.isEmpty(paramzzeb.getGmpAppId()))
    {
      zzb(paramzzeb.zzah(), 204, null, null, null);
      return;
    }
    Object localObject1 = paramzzeb.getGmpAppId();
    Object localObject2 = paramzzeb.getAppInstanceId();
    Object localObject3 = new Uri.Builder();
    Object localObject4 = ((Uri.Builder)localObject3).scheme((String)zzew.zzagp.get()).encodedAuthority((String)zzew.zzagq.get());
    localObject1 = String.valueOf(localObject1);
    if (((String)localObject1).length() != 0)
    {
      localObject1 = "config/app/".concat((String)localObject1);
      label99:
      ((Uri.Builder)localObject4).path((String)localObject1).appendQueryParameter("app_instance_id", (String)localObject2).appendQueryParameter("platform", "android").appendQueryParameter("gmp_version", "12451");
      localObject3 = ((Uri.Builder)localObject3).build().toString();
    }
    for (;;)
    {
      try
      {
        localObject4 = new java/net/URL;
        ((URL)localObject4).<init>((String)localObject3);
        zzgg().zzir().zzg("Fetching remote configuration", paramzzeb.zzah());
        localObject1 = zzgd().zzbp(paramzzeb.zzah());
        localObject2 = zzgd().zzbq(paramzzeb.zzah());
        if ((localObject1 == null) || (TextUtils.isEmpty((CharSequence)localObject2))) {
          break label348;
        }
        localObject1 = new android/support/v4/util/ArrayMap;
        ((ArrayMap)localObject1).<init>();
        ((Map)localObject1).put("If-Modified-Since", localObject2);
        this.zzanl = true;
        zzfk localzzfk = zzjq();
        String str2 = paramzzeb.zzah();
        zzgp localzzgp = new com/google/android/gms/internal/measurement/zzgp;
        localzzgp.<init>(this);
        localzzfk.zzab();
        localzzfk.zzch();
        Preconditions.checkNotNull(localObject4);
        Preconditions.checkNotNull(localzzgp);
        zzgg localzzgg = localzzfk.zzgf();
        localObject2 = new com/google/android/gms/internal/measurement/zzfo;
        ((zzfo)localObject2).<init>(localzzfk, str2, (URL)localObject4, null, (Map)localObject1, localzzgp);
        localzzgg.zzd((Runnable)localObject2);
      }
      catch (MalformedURLException localMalformedURLException)
      {
        zzgg().zzil().zze("Failed to parse config URL. Not fetching. appId", zzfg.zzbh(paramzzeb.zzah()), localObject3);
      }
      break;
      String str1 = new String("config/app/");
      break label99;
      label348:
      str1 = null;
    }
  }
  
  /* Error */
  private final boolean zzd(String paramString, long paramLong)
  {
    // Byte code:
    //   0: aload_0
    //   1: invokevirtual 566	com/google/android/gms/internal/measurement/zzgl:zzga	()Lcom/google/android/gms/internal/measurement/zzei;
    //   4: invokevirtual 569	com/google/android/gms/internal/measurement/zzei:beginTransaction	()V
    //   7: new 6	com/google/android/gms/internal/measurement/zzgl$zza
    //   10: astore 4
    //   12: aload 4
    //   14: aload_0
    //   15: aconst_null
    //   16: invokespecial 572	com/google/android/gms/internal/measurement/zzgl$zza:<init>	(Lcom/google/android/gms/internal/measurement/zzgl;Lcom/google/android/gms/internal/measurement/zzgm;)V
    //   19: aload_0
    //   20: invokevirtual 566	com/google/android/gms/internal/measurement/zzgl:zzga	()Lcom/google/android/gms/internal/measurement/zzei;
    //   23: astore 5
    //   25: aconst_null
    //   26: astore 6
    //   28: aload_0
    //   29: getfield 102	com/google/android/gms/internal/measurement/zzgl:zzanj	J
    //   32: lstore 7
    //   34: aload 4
    //   36: invokestatic 93	com/google/android/gms/common/internal/Preconditions:checkNotNull	(Ljava/lang/Object;)Ljava/lang/Object;
    //   39: pop
    //   40: aload 5
    //   42: invokevirtual 310	com/google/android/gms/internal/measurement/zzhj:zzab	()V
    //   45: aload 5
    //   47: invokevirtual 542	com/google/android/gms/internal/measurement/zzhk:zzch	()V
    //   50: aconst_null
    //   51: astore 9
    //   53: aconst_null
    //   54: astore 10
    //   56: aload 10
    //   58: astore_1
    //   59: aload 9
    //   61: astore 11
    //   63: aload 6
    //   65: astore 12
    //   67: aload 5
    //   69: invokevirtual 576	com/google/android/gms/internal/measurement/zzei:getWritableDatabase	()Landroid/database/sqlite/SQLiteDatabase;
    //   72: astore 13
    //   74: aload 10
    //   76: astore_1
    //   77: aload 9
    //   79: astore 11
    //   81: aload 6
    //   83: astore 12
    //   85: aconst_null
    //   86: invokestatic 445	android/text/TextUtils:isEmpty	(Ljava/lang/CharSequence;)Z
    //   89: ifeq +686 -> 775
    //   92: lload 7
    //   94: ldc2_w 99
    //   97: lcmp
    //   98: ifeq +447 -> 545
    //   101: aload 10
    //   103: astore_1
    //   104: aload 9
    //   106: astore 11
    //   108: aload 6
    //   110: astore 12
    //   112: iconst_2
    //   113: anewarray 280	java/lang/String
    //   116: dup
    //   117: iconst_0
    //   118: lload 7
    //   120: invokestatic 579	java/lang/String:valueOf	(J)Ljava/lang/String;
    //   123: aastore
    //   124: dup
    //   125: iconst_1
    //   126: lload_2
    //   127: invokestatic 579	java/lang/String:valueOf	(J)Ljava/lang/String;
    //   130: aastore
    //   131: astore 14
    //   133: lload 7
    //   135: ldc2_w 99
    //   138: lcmp
    //   139: ifeq +433 -> 572
    //   142: ldc_w 581
    //   145: astore 15
    //   147: aload 10
    //   149: astore_1
    //   150: aload 9
    //   152: astore 11
    //   154: aload 6
    //   156: astore 12
    //   158: aload 15
    //   160: invokestatic 284	java/lang/String:valueOf	(Ljava/lang/Object;)Ljava/lang/String;
    //   163: invokevirtual 290	java/lang/String:length	()I
    //   166: istore 16
    //   168: aload 10
    //   170: astore_1
    //   171: aload 9
    //   173: astore 11
    //   175: aload 6
    //   177: astore 12
    //   179: new 286	java/lang/StringBuilder
    //   182: astore 17
    //   184: aload 10
    //   186: astore_1
    //   187: aload 9
    //   189: astore 11
    //   191: aload 6
    //   193: astore 12
    //   195: aload 17
    //   197: iload 16
    //   199: sipush 148
    //   202: iadd
    //   203: invokespecial 293	java/lang/StringBuilder:<init>	(I)V
    //   206: aload 10
    //   208: astore_1
    //   209: aload 9
    //   211: astore 11
    //   213: aload 6
    //   215: astore 12
    //   217: aload 13
    //   219: aload 17
    //   221: ldc_w 583
    //   224: invokevirtual 299	java/lang/StringBuilder:append	(Ljava/lang/String;)Ljava/lang/StringBuilder;
    //   227: aload 15
    //   229: invokevirtual 299	java/lang/StringBuilder:append	(Ljava/lang/String;)Ljava/lang/StringBuilder;
    //   232: ldc_w 585
    //   235: invokevirtual 299	java/lang/StringBuilder:append	(Ljava/lang/String;)Ljava/lang/StringBuilder;
    //   238: invokevirtual 303	java/lang/StringBuilder:toString	()Ljava/lang/String;
    //   241: aload 14
    //   243: invokevirtual 591	android/database/sqlite/SQLiteDatabase:rawQuery	(Ljava/lang/String;[Ljava/lang/String;)Landroid/database/Cursor;
    //   246: astore 14
    //   248: aload 14
    //   250: astore_1
    //   251: aload 14
    //   253: astore 11
    //   255: aload 6
    //   257: astore 12
    //   259: aload 14
    //   261: invokeinterface 596 1 0
    //   266: istore 18
    //   268: iload 18
    //   270: ifne +310 -> 580
    //   273: aload 14
    //   275: ifnull +10 -> 285
    //   278: aload 14
    //   280: invokeinterface 599 1 0
    //   285: aload 4
    //   287: getfield 602	com/google/android/gms/internal/measurement/zzgl$zza:zzanu	Ljava/util/List;
    //   290: ifnull +16 -> 306
    //   293: aload 4
    //   295: getfield 602	com/google/android/gms/internal/measurement/zzgl$zza:zzanu	Ljava/util/List;
    //   298: invokeinterface 606 1 0
    //   303: ifeq +1401 -> 1704
    //   306: iconst_1
    //   307: istore 16
    //   309: iload 16
    //   311: ifne +4464 -> 4775
    //   314: iconst_0
    //   315: istore 18
    //   317: aload 4
    //   319: getfield 610	com/google/android/gms/internal/measurement/zzgl$zza:zzans	Lcom/google/android/gms/internal/measurement/zzkl;
    //   322: astore 12
    //   324: aload 12
    //   326: aload 4
    //   328: getfield 602	com/google/android/gms/internal/measurement/zzgl$zza:zzanu	Ljava/util/List;
    //   331: invokeinterface 613 1 0
    //   336: anewarray 615	com/google/android/gms/internal/measurement/zzki
    //   339: putfield 621	com/google/android/gms/internal/measurement/zzkl:zzatd	[Lcom/google/android/gms/internal/measurement/zzki;
    //   342: iconst_0
    //   343: istore 16
    //   345: lconst_0
    //   346: lstore_2
    //   347: aload_0
    //   348: getfield 125	com/google/android/gms/internal/measurement/zzgl:zzamd	Lcom/google/android/gms/internal/measurement/zzeh;
    //   351: aload 12
    //   353: getfield 625	com/google/android/gms/internal/measurement/zzkl:zztd	Ljava/lang/String;
    //   356: invokevirtual 628	com/google/android/gms/internal/measurement/zzeh:zzau	(Ljava/lang/String;)Z
    //   359: istore 19
    //   361: iconst_0
    //   362: istore 20
    //   364: iload 20
    //   366: aload 4
    //   368: getfield 602	com/google/android/gms/internal/measurement/zzgl$zza:zzanu	Ljava/util/List;
    //   371: invokeinterface 613 1 0
    //   376: if_icmpge +2262 -> 2638
    //   379: aload 4
    //   381: getfield 602	com/google/android/gms/internal/measurement/zzgl$zza:zzanu	Ljava/util/List;
    //   384: iload 20
    //   386: invokeinterface 631 2 0
    //   391: checkcast 615	com/google/android/gms/internal/measurement/zzki
    //   394: astore 14
    //   396: aload_0
    //   397: invokevirtual 512	com/google/android/gms/internal/measurement/zzgl:zzgd	()Lcom/google/android/gms/internal/measurement/zzgf;
    //   400: aload 4
    //   402: getfield 610	com/google/android/gms/internal/measurement/zzgl$zza:zzans	Lcom/google/android/gms/internal/measurement/zzkl;
    //   405: getfield 625	com/google/android/gms/internal/measurement/zzkl:zztd	Ljava/lang/String;
    //   408: aload 14
    //   410: getfield 634	com/google/android/gms/internal/measurement/zzki:name	Ljava/lang/String;
    //   413: invokevirtual 638	com/google/android/gms/internal/measurement/zzgf:zzn	(Ljava/lang/String;Ljava/lang/String;)Z
    //   416: ifeq +1300 -> 1716
    //   419: aload_0
    //   420: invokevirtual 254	com/google/android/gms/internal/measurement/zzgl:zzgg	()Lcom/google/android/gms/internal/measurement/zzfg;
    //   423: invokevirtual 257	com/google/android/gms/internal/measurement/zzfg:zzin	()Lcom/google/android/gms/internal/measurement/zzfi;
    //   426: ldc_w 640
    //   429: aload 4
    //   431: getfield 610	com/google/android/gms/internal/measurement/zzgl$zza:zzans	Lcom/google/android/gms/internal/measurement/zzkl;
    //   434: getfield 625	com/google/android/gms/internal/measurement/zzkl:zztd	Ljava/lang/String;
    //   437: invokestatic 557	com/google/android/gms/internal/measurement/zzfg:zzbh	(Ljava/lang/String;)Ljava/lang/Object;
    //   440: aload_0
    //   441: invokevirtual 644	com/google/android/gms/internal/measurement/zzgl:zzgb	()Lcom/google/android/gms/internal/measurement/zzfe;
    //   444: aload 14
    //   446: getfield 634	com/google/android/gms/internal/measurement/zzki:name	Ljava/lang/String;
    //   449: invokevirtual 647	com/google/android/gms/internal/measurement/zzfe:zzbe	(Ljava/lang/String;)Ljava/lang/String;
    //   452: invokevirtual 412	com/google/android/gms/internal/measurement/zzfi:zze	(Ljava/lang/String;Ljava/lang/Object;Ljava/lang/Object;)V
    //   455: aload_0
    //   456: invokevirtual 383	com/google/android/gms/internal/measurement/zzgl:zzgc	()Lcom/google/android/gms/internal/measurement/zzjv;
    //   459: aload 4
    //   461: getfield 610	com/google/android/gms/internal/measurement/zzgl$zza:zzans	Lcom/google/android/gms/internal/measurement/zzkl;
    //   464: getfield 625	com/google/android/gms/internal/measurement/zzkl:zztd	Ljava/lang/String;
    //   467: invokevirtual 650	com/google/android/gms/internal/measurement/zzjv:zzce	(Ljava/lang/String;)Z
    //   470: ifne +21 -> 491
    //   473: aload_0
    //   474: invokevirtual 383	com/google/android/gms/internal/measurement/zzgl:zzgc	()Lcom/google/android/gms/internal/measurement/zzjv;
    //   477: aload 4
    //   479: getfield 610	com/google/android/gms/internal/measurement/zzgl$zza:zzans	Lcom/google/android/gms/internal/measurement/zzkl;
    //   482: getfield 625	com/google/android/gms/internal/measurement/zzkl:zztd	Ljava/lang/String;
    //   485: invokevirtual 653	com/google/android/gms/internal/measurement/zzjv:zzcf	(Ljava/lang/String;)Z
    //   488: ifeq +1222 -> 1710
    //   491: iconst_1
    //   492: istore 21
    //   494: iload 21
    //   496: ifne +4354 -> 4850
    //   499: ldc_w 655
    //   502: aload 14
    //   504: getfield 634	com/google/android/gms/internal/measurement/zzki:name	Ljava/lang/String;
    //   507: invokevirtual 659	java/lang/String:equals	(Ljava/lang/Object;)Z
    //   510: ifne +4340 -> 4850
    //   513: aload_0
    //   514: invokevirtual 383	com/google/android/gms/internal/measurement/zzgl:zzgc	()Lcom/google/android/gms/internal/measurement/zzjv;
    //   517: aload 4
    //   519: getfield 610	com/google/android/gms/internal/measurement/zzgl$zza:zzans	Lcom/google/android/gms/internal/measurement/zzkl;
    //   522: getfield 625	com/google/android/gms/internal/measurement/zzkl:zztd	Ljava/lang/String;
    //   525: bipush 11
    //   527: ldc_w 661
    //   530: aload 14
    //   532: getfield 634	com/google/android/gms/internal/measurement/zzki:name	Ljava/lang/String;
    //   535: iconst_0
    //   536: invokevirtual 664	com/google/android/gms/internal/measurement/zzjv:zza	(Ljava/lang/String;ILjava/lang/String;Ljava/lang/String;I)V
    //   539: iinc 20 1
    //   542: goto -178 -> 364
    //   545: aload 10
    //   547: astore_1
    //   548: aload 9
    //   550: astore 11
    //   552: aload 6
    //   554: astore 12
    //   556: iconst_1
    //   557: anewarray 280	java/lang/String
    //   560: dup
    //   561: iconst_0
    //   562: lload_2
    //   563: invokestatic 579	java/lang/String:valueOf	(J)Ljava/lang/String;
    //   566: aastore
    //   567: astore 14
    //   569: goto -436 -> 133
    //   572: ldc_w 666
    //   575: astore 15
    //   577: goto -430 -> 147
    //   580: aload 14
    //   582: astore_1
    //   583: aload 14
    //   585: astore 11
    //   587: aload 6
    //   589: astore 12
    //   591: aload 14
    //   593: iconst_0
    //   594: invokeinterface 670 2 0
    //   599: astore 15
    //   601: aload 14
    //   603: astore_1
    //   604: aload 14
    //   606: astore 11
    //   608: aload 15
    //   610: astore 12
    //   612: aload 14
    //   614: iconst_1
    //   615: invokeinterface 670 2 0
    //   620: astore 6
    //   622: aload 14
    //   624: astore_1
    //   625: aload 14
    //   627: astore 11
    //   629: aload 15
    //   631: astore 12
    //   633: aload 14
    //   635: invokeinterface 599 1 0
    //   640: aload 6
    //   642: astore 11
    //   644: aload 14
    //   646: astore_1
    //   647: aload 15
    //   649: astore 12
    //   651: aload 11
    //   653: astore 15
    //   655: aload 12
    //   657: astore 11
    //   659: aload_1
    //   660: astore 12
    //   662: aload 13
    //   664: ldc_w 672
    //   667: iconst_1
    //   668: anewarray 280	java/lang/String
    //   671: dup
    //   672: iconst_0
    //   673: ldc_w 674
    //   676: aastore
    //   677: ldc_w 676
    //   680: iconst_2
    //   681: anewarray 280	java/lang/String
    //   684: dup
    //   685: iconst_0
    //   686: aload 11
    //   688: aastore
    //   689: dup
    //   690: iconst_1
    //   691: aload 15
    //   693: aastore
    //   694: aconst_null
    //   695: aconst_null
    //   696: ldc_w 678
    //   699: ldc_w 680
    //   702: invokevirtual 684	android/database/sqlite/SQLiteDatabase:query	(Ljava/lang/String;[Ljava/lang/String;Ljava/lang/String;[Ljava/lang/String;Ljava/lang/String;Ljava/lang/String;Ljava/lang/String;Ljava/lang/String;)Landroid/database/Cursor;
    //   705: astore 14
    //   707: aload 14
    //   709: astore 12
    //   711: aload 14
    //   713: astore_1
    //   714: aload 14
    //   716: invokeinterface 596 1 0
    //   721: ifne +326 -> 1047
    //   724: aload 14
    //   726: astore 12
    //   728: aload 14
    //   730: astore_1
    //   731: aload 5
    //   733: invokevirtual 232	com/google/android/gms/internal/measurement/zzhj:zzgg	()Lcom/google/android/gms/internal/measurement/zzfg;
    //   736: invokevirtual 401	com/google/android/gms/internal/measurement/zzfg:zzil	()Lcom/google/android/gms/internal/measurement/zzfi;
    //   739: ldc_w 686
    //   742: aload 11
    //   744: invokestatic 557	com/google/android/gms/internal/measurement/zzfg:zzbh	(Ljava/lang/String;)Ljava/lang/Object;
    //   747: invokevirtual 374	com/google/android/gms/internal/measurement/zzfi:zzg	(Ljava/lang/String;Ljava/lang/Object;)V
    //   750: aload 14
    //   752: ifnull -467 -> 285
    //   755: aload 14
    //   757: invokeinterface 599 1 0
    //   762: goto -477 -> 285
    //   765: astore_1
    //   766: aload_0
    //   767: invokevirtual 566	com/google/android/gms/internal/measurement/zzgl:zzga	()Lcom/google/android/gms/internal/measurement/zzei;
    //   770: invokevirtual 689	com/google/android/gms/internal/measurement/zzei:endTransaction	()V
    //   773: aload_1
    //   774: athrow
    //   775: lload 7
    //   777: ldc2_w 99
    //   780: lcmp
    //   781: ifeq +186 -> 967
    //   784: aload 10
    //   786: astore_1
    //   787: aload 9
    //   789: astore 11
    //   791: aload 6
    //   793: astore 12
    //   795: iconst_2
    //   796: anewarray 280	java/lang/String
    //   799: dup
    //   800: iconst_0
    //   801: aconst_null
    //   802: aastore
    //   803: dup
    //   804: iconst_1
    //   805: lload 7
    //   807: invokestatic 579	java/lang/String:valueOf	(J)Ljava/lang/String;
    //   810: aastore
    //   811: astore 14
    //   813: lload 7
    //   815: ldc2_w 99
    //   818: lcmp
    //   819: ifeq +172 -> 991
    //   822: ldc_w 691
    //   825: astore 15
    //   827: aload 10
    //   829: astore_1
    //   830: aload 9
    //   832: astore 11
    //   834: aload 6
    //   836: astore 12
    //   838: aload 15
    //   840: invokestatic 284	java/lang/String:valueOf	(Ljava/lang/Object;)Ljava/lang/String;
    //   843: invokevirtual 290	java/lang/String:length	()I
    //   846: istore 16
    //   848: aload 10
    //   850: astore_1
    //   851: aload 9
    //   853: astore 11
    //   855: aload 6
    //   857: astore 12
    //   859: new 286	java/lang/StringBuilder
    //   862: astore 17
    //   864: aload 10
    //   866: astore_1
    //   867: aload 9
    //   869: astore 11
    //   871: aload 6
    //   873: astore 12
    //   875: aload 17
    //   877: iload 16
    //   879: bipush 84
    //   881: iadd
    //   882: invokespecial 293	java/lang/StringBuilder:<init>	(I)V
    //   885: aload 10
    //   887: astore_1
    //   888: aload 9
    //   890: astore 11
    //   892: aload 6
    //   894: astore 12
    //   896: aload 13
    //   898: aload 17
    //   900: ldc_w 693
    //   903: invokevirtual 299	java/lang/StringBuilder:append	(Ljava/lang/String;)Ljava/lang/StringBuilder;
    //   906: aload 15
    //   908: invokevirtual 299	java/lang/StringBuilder:append	(Ljava/lang/String;)Ljava/lang/StringBuilder;
    //   911: ldc_w 695
    //   914: invokevirtual 299	java/lang/StringBuilder:append	(Ljava/lang/String;)Ljava/lang/StringBuilder;
    //   917: invokevirtual 303	java/lang/StringBuilder:toString	()Ljava/lang/String;
    //   920: aload 14
    //   922: invokevirtual 591	android/database/sqlite/SQLiteDatabase:rawQuery	(Ljava/lang/String;[Ljava/lang/String;)Landroid/database/Cursor;
    //   925: astore 14
    //   927: aload 14
    //   929: astore_1
    //   930: aload 14
    //   932: astore 11
    //   934: aload 6
    //   936: astore 12
    //   938: aload 14
    //   940: invokeinterface 596 1 0
    //   945: istore 18
    //   947: iload 18
    //   949: ifne +50 -> 999
    //   952: aload 14
    //   954: ifnull -669 -> 285
    //   957: aload 14
    //   959: invokeinterface 599 1 0
    //   964: goto -679 -> 285
    //   967: aload 10
    //   969: astore_1
    //   970: aload 9
    //   972: astore 11
    //   974: aload 6
    //   976: astore 12
    //   978: iconst_1
    //   979: anewarray 280	java/lang/String
    //   982: dup
    //   983: iconst_0
    //   984: aconst_null
    //   985: aastore
    //   986: astore 14
    //   988: goto -175 -> 813
    //   991: ldc_w 666
    //   994: astore 15
    //   996: goto -169 -> 827
    //   999: aload 14
    //   1001: astore_1
    //   1002: aload 14
    //   1004: astore 11
    //   1006: aload 6
    //   1008: astore 12
    //   1010: aload 14
    //   1012: iconst_0
    //   1013: invokeinterface 670 2 0
    //   1018: astore 15
    //   1020: aload 14
    //   1022: astore_1
    //   1023: aload 14
    //   1025: astore 11
    //   1027: aload 6
    //   1029: astore 12
    //   1031: aload 14
    //   1033: invokeinterface 599 1 0
    //   1038: aload 14
    //   1040: astore_1
    //   1041: aconst_null
    //   1042: astore 11
    //   1044: goto -385 -> 659
    //   1047: aload 14
    //   1049: astore 12
    //   1051: aload 14
    //   1053: astore_1
    //   1054: aload 14
    //   1056: iconst_0
    //   1057: invokeinterface 699 2 0
    //   1062: astore 6
    //   1064: aload 14
    //   1066: astore 12
    //   1068: aload 14
    //   1070: astore_1
    //   1071: aload 6
    //   1073: iconst_0
    //   1074: aload 6
    //   1076: arraylength
    //   1077: invokestatic 704	com/google/android/gms/internal/measurement/zzaba:zza	([BII)Lcom/google/android/gms/internal/measurement/zzaba;
    //   1080: astore 10
    //   1082: aload 14
    //   1084: astore 12
    //   1086: aload 14
    //   1088: astore_1
    //   1089: new 617	com/google/android/gms/internal/measurement/zzkl
    //   1092: astore 6
    //   1094: aload 14
    //   1096: astore 12
    //   1098: aload 14
    //   1100: astore_1
    //   1101: aload 6
    //   1103: invokespecial 705	com/google/android/gms/internal/measurement/zzkl:<init>	()V
    //   1106: aload 14
    //   1108: astore 12
    //   1110: aload 14
    //   1112: astore_1
    //   1113: aload 6
    //   1115: aload 10
    //   1117: invokevirtual 710	com/google/android/gms/internal/measurement/zzabj:zzb	(Lcom/google/android/gms/internal/measurement/zzaba;)Lcom/google/android/gms/internal/measurement/zzabj;
    //   1120: pop
    //   1121: aload 14
    //   1123: astore 12
    //   1125: aload 14
    //   1127: astore_1
    //   1128: aload 14
    //   1130: invokeinterface 713 1 0
    //   1135: ifeq +29 -> 1164
    //   1138: aload 14
    //   1140: astore 12
    //   1142: aload 14
    //   1144: astore_1
    //   1145: aload 5
    //   1147: invokevirtual 232	com/google/android/gms/internal/measurement/zzhj:zzgg	()Lcom/google/android/gms/internal/measurement/zzfg;
    //   1150: invokevirtual 257	com/google/android/gms/internal/measurement/zzfg:zzin	()Lcom/google/android/gms/internal/measurement/zzfi;
    //   1153: ldc_w 715
    //   1156: aload 11
    //   1158: invokestatic 557	com/google/android/gms/internal/measurement/zzfg:zzbh	(Ljava/lang/String;)Ljava/lang/Object;
    //   1161: invokevirtual 374	com/google/android/gms/internal/measurement/zzfi:zzg	(Ljava/lang/String;Ljava/lang/Object;)V
    //   1164: aload 14
    //   1166: astore 12
    //   1168: aload 14
    //   1170: astore_1
    //   1171: aload 14
    //   1173: invokeinterface 599 1 0
    //   1178: aload 14
    //   1180: astore 12
    //   1182: aload 14
    //   1184: astore_1
    //   1185: aload 4
    //   1187: aload 6
    //   1189: invokeinterface 720 2 0
    //   1194: lload 7
    //   1196: ldc2_w 99
    //   1199: lcmp
    //   1200: ifeq +207 -> 1407
    //   1203: ldc_w 722
    //   1206: astore 6
    //   1208: aload 14
    //   1210: astore 12
    //   1212: aload 14
    //   1214: astore_1
    //   1215: iconst_3
    //   1216: anewarray 280	java/lang/String
    //   1219: astore 10
    //   1221: aload 10
    //   1223: iconst_0
    //   1224: aload 11
    //   1226: aastore
    //   1227: aload 10
    //   1229: iconst_1
    //   1230: aload 15
    //   1232: aastore
    //   1233: aload 14
    //   1235: astore 12
    //   1237: aload 14
    //   1239: astore_1
    //   1240: aload 10
    //   1242: iconst_2
    //   1243: lload 7
    //   1245: invokestatic 579	java/lang/String:valueOf	(J)Ljava/lang/String;
    //   1248: aastore
    //   1249: aload 10
    //   1251: astore 15
    //   1253: aload 14
    //   1255: astore 12
    //   1257: aload 14
    //   1259: astore_1
    //   1260: aload 13
    //   1262: ldc_w 724
    //   1265: iconst_4
    //   1266: anewarray 280	java/lang/String
    //   1269: dup
    //   1270: iconst_0
    //   1271: ldc_w 678
    //   1274: aastore
    //   1275: dup
    //   1276: iconst_1
    //   1277: ldc_w 725
    //   1280: aastore
    //   1281: dup
    //   1282: iconst_2
    //   1283: ldc_w 727
    //   1286: aastore
    //   1287: dup
    //   1288: iconst_3
    //   1289: ldc_w 729
    //   1292: aastore
    //   1293: aload 6
    //   1295: aload 15
    //   1297: aconst_null
    //   1298: aconst_null
    //   1299: ldc_w 678
    //   1302: aconst_null
    //   1303: invokevirtual 684	android/database/sqlite/SQLiteDatabase:query	(Ljava/lang/String;[Ljava/lang/String;Ljava/lang/String;[Ljava/lang/String;Ljava/lang/String;Ljava/lang/String;Ljava/lang/String;Ljava/lang/String;)Landroid/database/Cursor;
    //   1306: astore 14
    //   1308: aload 14
    //   1310: astore 12
    //   1312: aload 12
    //   1314: astore_1
    //   1315: aload 12
    //   1317: invokeinterface 596 1 0
    //   1322: ifne +173 -> 1495
    //   1325: aload 12
    //   1327: astore_1
    //   1328: aload 5
    //   1330: invokevirtual 232	com/google/android/gms/internal/measurement/zzhj:zzgg	()Lcom/google/android/gms/internal/measurement/zzfg;
    //   1333: invokevirtual 257	com/google/android/gms/internal/measurement/zzfg:zzin	()Lcom/google/android/gms/internal/measurement/zzfi;
    //   1336: ldc_w 731
    //   1339: aload 11
    //   1341: invokestatic 557	com/google/android/gms/internal/measurement/zzfg:zzbh	(Ljava/lang/String;)Ljava/lang/Object;
    //   1344: invokevirtual 374	com/google/android/gms/internal/measurement/zzfi:zzg	(Ljava/lang/String;Ljava/lang/Object;)V
    //   1347: aload 12
    //   1349: ifnull -1064 -> 285
    //   1352: aload 12
    //   1354: invokeinterface 599 1 0
    //   1359: goto -1074 -> 285
    //   1362: astore 15
    //   1364: aload 14
    //   1366: astore 12
    //   1368: aload 14
    //   1370: astore_1
    //   1371: aload 5
    //   1373: invokevirtual 232	com/google/android/gms/internal/measurement/zzhj:zzgg	()Lcom/google/android/gms/internal/measurement/zzfg;
    //   1376: invokevirtual 401	com/google/android/gms/internal/measurement/zzfg:zzil	()Lcom/google/android/gms/internal/measurement/zzfi;
    //   1379: ldc_w 733
    //   1382: aload 11
    //   1384: invokestatic 557	com/google/android/gms/internal/measurement/zzfg:zzbh	(Ljava/lang/String;)Ljava/lang/Object;
    //   1387: aload 15
    //   1389: invokevirtual 412	com/google/android/gms/internal/measurement/zzfi:zze	(Ljava/lang/String;Ljava/lang/Object;Ljava/lang/Object;)V
    //   1392: aload 14
    //   1394: ifnull -1109 -> 285
    //   1397: aload 14
    //   1399: invokeinterface 599 1 0
    //   1404: goto -1119 -> 285
    //   1407: ldc_w 676
    //   1410: astore 6
    //   1412: aload 14
    //   1414: astore 12
    //   1416: aload 14
    //   1418: astore_1
    //   1419: iconst_2
    //   1420: anewarray 280	java/lang/String
    //   1423: astore 10
    //   1425: aload 10
    //   1427: iconst_0
    //   1428: aload 11
    //   1430: aastore
    //   1431: aload 10
    //   1433: iconst_1
    //   1434: aload 15
    //   1436: aastore
    //   1437: aload 10
    //   1439: astore 15
    //   1441: goto -188 -> 1253
    //   1444: astore 14
    //   1446: aload 12
    //   1448: astore_1
    //   1449: aload 11
    //   1451: astore 12
    //   1453: aload_1
    //   1454: astore 11
    //   1456: aload 11
    //   1458: astore_1
    //   1459: aload 5
    //   1461: invokevirtual 232	com/google/android/gms/internal/measurement/zzhj:zzgg	()Lcom/google/android/gms/internal/measurement/zzfg;
    //   1464: invokevirtual 401	com/google/android/gms/internal/measurement/zzfg:zzil	()Lcom/google/android/gms/internal/measurement/zzfi;
    //   1467: ldc_w 735
    //   1470: aload 12
    //   1472: invokestatic 557	com/google/android/gms/internal/measurement/zzfg:zzbh	(Ljava/lang/String;)Ljava/lang/Object;
    //   1475: aload 14
    //   1477: invokevirtual 412	com/google/android/gms/internal/measurement/zzfi:zze	(Ljava/lang/String;Ljava/lang/Object;Ljava/lang/Object;)V
    //   1480: aload 11
    //   1482: ifnull -1197 -> 285
    //   1485: aload 11
    //   1487: invokeinterface 599 1 0
    //   1492: goto -1207 -> 285
    //   1495: aload 12
    //   1497: astore_1
    //   1498: aload 12
    //   1500: iconst_0
    //   1501: invokeinterface 739 2 0
    //   1506: lstore_2
    //   1507: aload 12
    //   1509: astore_1
    //   1510: aload 12
    //   1512: iconst_3
    //   1513: invokeinterface 699 2 0
    //   1518: astore 14
    //   1520: aload 12
    //   1522: astore_1
    //   1523: aload 14
    //   1525: iconst_0
    //   1526: aload 14
    //   1528: arraylength
    //   1529: invokestatic 704	com/google/android/gms/internal/measurement/zzaba:zza	([BII)Lcom/google/android/gms/internal/measurement/zzaba;
    //   1532: astore 15
    //   1534: aload 12
    //   1536: astore_1
    //   1537: new 615	com/google/android/gms/internal/measurement/zzki
    //   1540: astore 14
    //   1542: aload 12
    //   1544: astore_1
    //   1545: aload 14
    //   1547: invokespecial 740	com/google/android/gms/internal/measurement/zzki:<init>	()V
    //   1550: aload 12
    //   1552: astore_1
    //   1553: aload 14
    //   1555: aload 15
    //   1557: invokevirtual 710	com/google/android/gms/internal/measurement/zzabj:zzb	(Lcom/google/android/gms/internal/measurement/zzaba;)Lcom/google/android/gms/internal/measurement/zzabj;
    //   1560: pop
    //   1561: aload 12
    //   1563: astore_1
    //   1564: aload 14
    //   1566: aload 12
    //   1568: iconst_1
    //   1569: invokeinterface 670 2 0
    //   1574: putfield 634	com/google/android/gms/internal/measurement/zzki:name	Ljava/lang/String;
    //   1577: aload 12
    //   1579: astore_1
    //   1580: aload 14
    //   1582: aload 12
    //   1584: iconst_2
    //   1585: invokeinterface 739 2 0
    //   1590: invokestatic 370	java/lang/Long:valueOf	(J)Ljava/lang/Long;
    //   1593: putfield 744	com/google/android/gms/internal/measurement/zzki:zzasw	Ljava/lang/Long;
    //   1596: aload 12
    //   1598: astore_1
    //   1599: aload 4
    //   1601: lload_2
    //   1602: aload 14
    //   1604: invokeinterface 747 4 0
    //   1609: istore 18
    //   1611: iload 18
    //   1613: ifne +44 -> 1657
    //   1616: aload 12
    //   1618: ifnull -1333 -> 285
    //   1621: aload 12
    //   1623: invokeinterface 599 1 0
    //   1628: goto -1343 -> 285
    //   1631: astore 14
    //   1633: aload 12
    //   1635: astore_1
    //   1636: aload 5
    //   1638: invokevirtual 232	com/google/android/gms/internal/measurement/zzhj:zzgg	()Lcom/google/android/gms/internal/measurement/zzfg;
    //   1641: invokevirtual 401	com/google/android/gms/internal/measurement/zzfg:zzil	()Lcom/google/android/gms/internal/measurement/zzfi;
    //   1644: ldc_w 749
    //   1647: aload 11
    //   1649: invokestatic 557	com/google/android/gms/internal/measurement/zzfg:zzbh	(Ljava/lang/String;)Ljava/lang/Object;
    //   1652: aload 14
    //   1654: invokevirtual 412	com/google/android/gms/internal/measurement/zzfi:zze	(Ljava/lang/String;Ljava/lang/Object;Ljava/lang/Object;)V
    //   1657: aload 12
    //   1659: astore_1
    //   1660: aload 12
    //   1662: invokeinterface 713 1 0
    //   1667: istore 18
    //   1669: iload 18
    //   1671: ifne -176 -> 1495
    //   1674: aload 12
    //   1676: ifnull -1391 -> 285
    //   1679: aload 12
    //   1681: invokeinterface 599 1 0
    //   1686: goto -1401 -> 285
    //   1689: astore 11
    //   1691: aload_1
    //   1692: ifnull +9 -> 1701
    //   1695: aload_1
    //   1696: invokeinterface 599 1 0
    //   1701: aload 11
    //   1703: athrow
    //   1704: iconst_0
    //   1705: istore 16
    //   1707: goto -1398 -> 309
    //   1710: iconst_0
    //   1711: istore 21
    //   1713: goto -1219 -> 494
    //   1716: aload_0
    //   1717: invokevirtual 512	com/google/android/gms/internal/measurement/zzgl:zzgd	()Lcom/google/android/gms/internal/measurement/zzgf;
    //   1720: aload 4
    //   1722: getfield 610	com/google/android/gms/internal/measurement/zzgl$zza:zzans	Lcom/google/android/gms/internal/measurement/zzkl;
    //   1725: getfield 625	com/google/android/gms/internal/measurement/zzkl:zztd	Ljava/lang/String;
    //   1728: aload 14
    //   1730: getfield 634	com/google/android/gms/internal/measurement/zzki:name	Ljava/lang/String;
    //   1733: invokevirtual 752	com/google/android/gms/internal/measurement/zzgf:zzo	(Ljava/lang/String;Ljava/lang/String;)Z
    //   1736: istore 22
    //   1738: iload 22
    //   1740: ifne +23 -> 1763
    //   1743: aload_0
    //   1744: invokevirtual 383	com/google/android/gms/internal/measurement/zzgl:zzgc	()Lcom/google/android/gms/internal/measurement/zzjv;
    //   1747: pop
    //   1748: iload 18
    //   1750: istore 23
    //   1752: aload 14
    //   1754: getfield 634	com/google/android/gms/internal/measurement/zzki:name	Ljava/lang/String;
    //   1757: invokestatic 755	com/google/android/gms/internal/measurement/zzjv:zzcg	(Ljava/lang/String;)Z
    //   1760: ifeq +813 -> 2573
    //   1763: iconst_0
    //   1764: istore 24
    //   1766: iconst_0
    //   1767: istore 21
    //   1769: aload 14
    //   1771: getfield 759	com/google/android/gms/internal/measurement/zzki:zzasv	[Lcom/google/android/gms/internal/measurement/zzkj;
    //   1774: ifnonnull +12 -> 1786
    //   1777: aload 14
    //   1779: iconst_0
    //   1780: anewarray 761	com/google/android/gms/internal/measurement/zzkj
    //   1783: putfield 759	com/google/android/gms/internal/measurement/zzki:zzasv	[Lcom/google/android/gms/internal/measurement/zzkj;
    //   1786: aload 14
    //   1788: getfield 759	com/google/android/gms/internal/measurement/zzki:zzasv	[Lcom/google/android/gms/internal/measurement/zzkj;
    //   1791: astore_1
    //   1792: aload_1
    //   1793: arraylength
    //   1794: istore 25
    //   1796: iconst_0
    //   1797: istore 26
    //   1799: iload 26
    //   1801: iload 25
    //   1803: if_icmpge +70 -> 1873
    //   1806: aload_1
    //   1807: iload 26
    //   1809: aaload
    //   1810: astore 11
    //   1812: ldc_w 763
    //   1815: aload 11
    //   1817: getfield 764	com/google/android/gms/internal/measurement/zzkj:name	Ljava/lang/String;
    //   1820: invokevirtual 659	java/lang/String:equals	(Ljava/lang/Object;)Z
    //   1823: ifeq +21 -> 1844
    //   1826: aload 11
    //   1828: lconst_1
    //   1829: invokestatic 370	java/lang/Long:valueOf	(J)Ljava/lang/Long;
    //   1832: putfield 767	com/google/android/gms/internal/measurement/zzkj:zzasz	Ljava/lang/Long;
    //   1835: iconst_1
    //   1836: istore 24
    //   1838: iinc 26 1
    //   1841: goto -42 -> 1799
    //   1844: ldc_w 769
    //   1847: aload 11
    //   1849: getfield 764	com/google/android/gms/internal/measurement/zzkj:name	Ljava/lang/String;
    //   1852: invokevirtual 659	java/lang/String:equals	(Ljava/lang/Object;)Z
    //   1855: ifeq +2992 -> 4847
    //   1858: aload 11
    //   1860: lconst_1
    //   1861: invokestatic 370	java/lang/Long:valueOf	(J)Ljava/lang/Long;
    //   1864: putfield 767	com/google/android/gms/internal/measurement/zzkj:zzasz	Ljava/lang/Long;
    //   1867: iconst_1
    //   1868: istore 21
    //   1870: goto -32 -> 1838
    //   1873: iload 24
    //   1875: ifne +93 -> 1968
    //   1878: iload 22
    //   1880: ifeq +88 -> 1968
    //   1883: aload_0
    //   1884: invokevirtual 254	com/google/android/gms/internal/measurement/zzgl:zzgg	()Lcom/google/android/gms/internal/measurement/zzfg;
    //   1887: invokevirtual 236	com/google/android/gms/internal/measurement/zzfg:zzir	()Lcom/google/android/gms/internal/measurement/zzfi;
    //   1890: ldc_w 771
    //   1893: aload_0
    //   1894: invokevirtual 644	com/google/android/gms/internal/measurement/zzgl:zzgb	()Lcom/google/android/gms/internal/measurement/zzfe;
    //   1897: aload 14
    //   1899: getfield 634	com/google/android/gms/internal/measurement/zzki:name	Ljava/lang/String;
    //   1902: invokevirtual 647	com/google/android/gms/internal/measurement/zzfe:zzbe	(Ljava/lang/String;)Ljava/lang/String;
    //   1905: invokevirtual 374	com/google/android/gms/internal/measurement/zzfi:zzg	(Ljava/lang/String;Ljava/lang/Object;)V
    //   1908: aload 14
    //   1910: getfield 759	com/google/android/gms/internal/measurement/zzki:zzasv	[Lcom/google/android/gms/internal/measurement/zzkj;
    //   1913: aload 14
    //   1915: getfield 759	com/google/android/gms/internal/measurement/zzki:zzasv	[Lcom/google/android/gms/internal/measurement/zzkj;
    //   1918: arraylength
    //   1919: iconst_1
    //   1920: iadd
    //   1921: invokestatic 777	java/util/Arrays:copyOf	([Ljava/lang/Object;I)[Ljava/lang/Object;
    //   1924: checkcast 778	[Lcom/google/android/gms/internal/measurement/zzkj;
    //   1927: astore 11
    //   1929: new 761	com/google/android/gms/internal/measurement/zzkj
    //   1932: astore_1
    //   1933: aload_1
    //   1934: invokespecial 779	com/google/android/gms/internal/measurement/zzkj:<init>	()V
    //   1937: aload_1
    //   1938: ldc_w 763
    //   1941: putfield 764	com/google/android/gms/internal/measurement/zzkj:name	Ljava/lang/String;
    //   1944: aload_1
    //   1945: lconst_1
    //   1946: invokestatic 370	java/lang/Long:valueOf	(J)Ljava/lang/Long;
    //   1949: putfield 767	com/google/android/gms/internal/measurement/zzkj:zzasz	Ljava/lang/Long;
    //   1952: aload 11
    //   1954: aload 11
    //   1956: arraylength
    //   1957: iconst_1
    //   1958: isub
    //   1959: aload_1
    //   1960: aastore
    //   1961: aload 14
    //   1963: aload 11
    //   1965: putfield 759	com/google/android/gms/internal/measurement/zzki:zzasv	[Lcom/google/android/gms/internal/measurement/zzkj;
    //   1968: iload 21
    //   1970: ifne +88 -> 2058
    //   1973: aload_0
    //   1974: invokevirtual 254	com/google/android/gms/internal/measurement/zzgl:zzgg	()Lcom/google/android/gms/internal/measurement/zzfg;
    //   1977: invokevirtual 236	com/google/android/gms/internal/measurement/zzfg:zzir	()Lcom/google/android/gms/internal/measurement/zzfi;
    //   1980: ldc_w 781
    //   1983: aload_0
    //   1984: invokevirtual 644	com/google/android/gms/internal/measurement/zzgl:zzgb	()Lcom/google/android/gms/internal/measurement/zzfe;
    //   1987: aload 14
    //   1989: getfield 634	com/google/android/gms/internal/measurement/zzki:name	Ljava/lang/String;
    //   1992: invokevirtual 647	com/google/android/gms/internal/measurement/zzfe:zzbe	(Ljava/lang/String;)Ljava/lang/String;
    //   1995: invokevirtual 374	com/google/android/gms/internal/measurement/zzfi:zzg	(Ljava/lang/String;Ljava/lang/Object;)V
    //   1998: aload 14
    //   2000: getfield 759	com/google/android/gms/internal/measurement/zzki:zzasv	[Lcom/google/android/gms/internal/measurement/zzkj;
    //   2003: aload 14
    //   2005: getfield 759	com/google/android/gms/internal/measurement/zzki:zzasv	[Lcom/google/android/gms/internal/measurement/zzkj;
    //   2008: arraylength
    //   2009: iconst_1
    //   2010: iadd
    //   2011: invokestatic 777	java/util/Arrays:copyOf	([Ljava/lang/Object;I)[Ljava/lang/Object;
    //   2014: checkcast 778	[Lcom/google/android/gms/internal/measurement/zzkj;
    //   2017: astore 11
    //   2019: new 761	com/google/android/gms/internal/measurement/zzkj
    //   2022: astore_1
    //   2023: aload_1
    //   2024: invokespecial 779	com/google/android/gms/internal/measurement/zzkj:<init>	()V
    //   2027: aload_1
    //   2028: ldc_w 769
    //   2031: putfield 764	com/google/android/gms/internal/measurement/zzkj:name	Ljava/lang/String;
    //   2034: aload_1
    //   2035: lconst_1
    //   2036: invokestatic 370	java/lang/Long:valueOf	(J)Ljava/lang/Long;
    //   2039: putfield 767	com/google/android/gms/internal/measurement/zzkj:zzasz	Ljava/lang/Long;
    //   2042: aload 11
    //   2044: aload 11
    //   2046: arraylength
    //   2047: iconst_1
    //   2048: isub
    //   2049: aload_1
    //   2050: aastore
    //   2051: aload 14
    //   2053: aload 11
    //   2055: putfield 759	com/google/android/gms/internal/measurement/zzki:zzasv	[Lcom/google/android/gms/internal/measurement/zzkj;
    //   2058: aload_0
    //   2059: invokevirtual 566	com/google/android/gms/internal/measurement/zzgl:zzga	()Lcom/google/android/gms/internal/measurement/zzei;
    //   2062: aload_0
    //   2063: invokespecial 784	com/google/android/gms/internal/measurement/zzgl:zzjv	()J
    //   2066: aload 4
    //   2068: getfield 610	com/google/android/gms/internal/measurement/zzgl$zza:zzans	Lcom/google/android/gms/internal/measurement/zzkl;
    //   2071: getfield 625	com/google/android/gms/internal/measurement/zzkl:zztd	Ljava/lang/String;
    //   2074: iconst_0
    //   2075: iconst_0
    //   2076: iconst_0
    //   2077: iconst_0
    //   2078: iconst_1
    //   2079: invokevirtual 787	com/google/android/gms/internal/measurement/zzei:zza	(JLjava/lang/String;ZZZZZ)Lcom/google/android/gms/internal/measurement/zzej;
    //   2082: getfield 792	com/google/android/gms/internal/measurement/zzej:zzafg	J
    //   2085: aload_0
    //   2086: getfield 125	com/google/android/gms/internal/measurement/zzgl:zzamd	Lcom/google/android/gms/internal/measurement/zzeh;
    //   2089: aload 4
    //   2091: getfield 610	com/google/android/gms/internal/measurement/zzgl$zza:zzans	Lcom/google/android/gms/internal/measurement/zzkl;
    //   2094: getfield 625	com/google/android/gms/internal/measurement/zzkl:zztd	Ljava/lang/String;
    //   2097: invokevirtual 796	com/google/android/gms/internal/measurement/zzeh:zzar	(Ljava/lang/String;)I
    //   2100: i2l
    //   2101: lcmp
    //   2102: ifle +2739 -> 4841
    //   2105: iconst_0
    //   2106: istore 21
    //   2108: iload 18
    //   2110: istore 27
    //   2112: iload 21
    //   2114: aload 14
    //   2116: getfield 759	com/google/android/gms/internal/measurement/zzki:zzasv	[Lcom/google/android/gms/internal/measurement/zzkj;
    //   2119: arraylength
    //   2120: if_icmpge +90 -> 2210
    //   2123: ldc_w 769
    //   2126: aload 14
    //   2128: getfield 759	com/google/android/gms/internal/measurement/zzki:zzasv	[Lcom/google/android/gms/internal/measurement/zzkj;
    //   2131: iload 21
    //   2133: aaload
    //   2134: getfield 764	com/google/android/gms/internal/measurement/zzkj:name	Ljava/lang/String;
    //   2137: invokevirtual 659	java/lang/String:equals	(Ljava/lang/Object;)Z
    //   2140: ifeq +229 -> 2369
    //   2143: aload 14
    //   2145: getfield 759	com/google/android/gms/internal/measurement/zzki:zzasv	[Lcom/google/android/gms/internal/measurement/zzkj;
    //   2148: arraylength
    //   2149: iconst_1
    //   2150: isub
    //   2151: anewarray 761	com/google/android/gms/internal/measurement/zzkj
    //   2154: astore_1
    //   2155: iload 21
    //   2157: ifle +16 -> 2173
    //   2160: aload 14
    //   2162: getfield 759	com/google/android/gms/internal/measurement/zzki:zzasv	[Lcom/google/android/gms/internal/measurement/zzkj;
    //   2165: iconst_0
    //   2166: aload_1
    //   2167: iconst_0
    //   2168: iload 21
    //   2170: invokestatic 802	java/lang/System:arraycopy	(Ljava/lang/Object;ILjava/lang/Object;II)V
    //   2173: iload 21
    //   2175: aload_1
    //   2176: arraylength
    //   2177: if_icmpge +23 -> 2200
    //   2180: aload 14
    //   2182: getfield 759	com/google/android/gms/internal/measurement/zzki:zzasv	[Lcom/google/android/gms/internal/measurement/zzkj;
    //   2185: iload 21
    //   2187: iconst_1
    //   2188: iadd
    //   2189: aload_1
    //   2190: iload 21
    //   2192: aload_1
    //   2193: arraylength
    //   2194: iload 21
    //   2196: isub
    //   2197: invokestatic 802	java/lang/System:arraycopy	(Ljava/lang/Object;ILjava/lang/Object;II)V
    //   2200: aload 14
    //   2202: aload_1
    //   2203: putfield 759	com/google/android/gms/internal/measurement/zzki:zzasv	[Lcom/google/android/gms/internal/measurement/zzkj;
    //   2206: iload 18
    //   2208: istore 27
    //   2210: iload 27
    //   2212: istore 23
    //   2214: aload 14
    //   2216: getfield 634	com/google/android/gms/internal/measurement/zzki:name	Ljava/lang/String;
    //   2219: invokestatic 805	com/google/android/gms/internal/measurement/zzjv:zzbv	(Ljava/lang/String;)Z
    //   2222: ifeq +351 -> 2573
    //   2225: iload 27
    //   2227: istore 23
    //   2229: iload 22
    //   2231: ifeq +342 -> 2573
    //   2234: iload 27
    //   2236: istore 23
    //   2238: aload_0
    //   2239: invokevirtual 566	com/google/android/gms/internal/measurement/zzgl:zzga	()Lcom/google/android/gms/internal/measurement/zzei;
    //   2242: aload_0
    //   2243: invokespecial 784	com/google/android/gms/internal/measurement/zzgl:zzjv	()J
    //   2246: aload 4
    //   2248: getfield 610	com/google/android/gms/internal/measurement/zzgl$zza:zzans	Lcom/google/android/gms/internal/measurement/zzkl;
    //   2251: getfield 625	com/google/android/gms/internal/measurement/zzkl:zztd	Ljava/lang/String;
    //   2254: iconst_0
    //   2255: iconst_0
    //   2256: iconst_1
    //   2257: iconst_0
    //   2258: iconst_0
    //   2259: invokevirtual 787	com/google/android/gms/internal/measurement/zzei:zza	(JLjava/lang/String;ZZZZZ)Lcom/google/android/gms/internal/measurement/zzej;
    //   2262: getfield 808	com/google/android/gms/internal/measurement/zzej:zzafe	J
    //   2265: aload_0
    //   2266: getfield 125	com/google/android/gms/internal/measurement/zzgl:zzamd	Lcom/google/android/gms/internal/measurement/zzeh;
    //   2269: aload 4
    //   2271: getfield 610	com/google/android/gms/internal/measurement/zzgl$zza:zzans	Lcom/google/android/gms/internal/measurement/zzkl;
    //   2274: getfield 625	com/google/android/gms/internal/measurement/zzkl:zztd	Ljava/lang/String;
    //   2277: getstatic 811	com/google/android/gms/internal/measurement/zzew:zzagy	Lcom/google/android/gms/internal/measurement/zzex;
    //   2280: invokevirtual 814	com/google/android/gms/internal/measurement/zzeh:zzb	(Ljava/lang/String;Lcom/google/android/gms/internal/measurement/zzex;)I
    //   2283: i2l
    //   2284: lcmp
    //   2285: ifle +288 -> 2573
    //   2288: aload_0
    //   2289: invokevirtual 254	com/google/android/gms/internal/measurement/zzgl:zzgg	()Lcom/google/android/gms/internal/measurement/zzfg;
    //   2292: invokevirtual 257	com/google/android/gms/internal/measurement/zzfg:zzin	()Lcom/google/android/gms/internal/measurement/zzfi;
    //   2295: ldc_w 816
    //   2298: aload 4
    //   2300: getfield 610	com/google/android/gms/internal/measurement/zzgl$zza:zzans	Lcom/google/android/gms/internal/measurement/zzkl;
    //   2303: getfield 625	com/google/android/gms/internal/measurement/zzkl:zztd	Ljava/lang/String;
    //   2306: invokestatic 557	com/google/android/gms/internal/measurement/zzfg:zzbh	(Ljava/lang/String;)Ljava/lang/Object;
    //   2309: invokevirtual 374	com/google/android/gms/internal/measurement/zzfi:zzg	(Ljava/lang/String;Ljava/lang/Object;)V
    //   2312: iconst_0
    //   2313: istore 26
    //   2315: aconst_null
    //   2316: astore_1
    //   2317: aload 14
    //   2319: getfield 759	com/google/android/gms/internal/measurement/zzki:zzasv	[Lcom/google/android/gms/internal/measurement/zzkj;
    //   2322: astore 15
    //   2324: aload 15
    //   2326: arraylength
    //   2327: istore 24
    //   2329: iconst_0
    //   2330: istore 21
    //   2332: iload 21
    //   2334: iload 24
    //   2336: if_icmpge +59 -> 2395
    //   2339: aload 15
    //   2341: iload 21
    //   2343: aaload
    //   2344: astore 11
    //   2346: ldc_w 763
    //   2349: aload 11
    //   2351: getfield 764	com/google/android/gms/internal/measurement/zzkj:name	Ljava/lang/String;
    //   2354: invokevirtual 659	java/lang/String:equals	(Ljava/lang/Object;)Z
    //   2357: ifeq +18 -> 2375
    //   2360: aload 11
    //   2362: astore_1
    //   2363: iinc 21 1
    //   2366: goto -34 -> 2332
    //   2369: iinc 21 1
    //   2372: goto -264 -> 2108
    //   2375: ldc_w 655
    //   2378: aload 11
    //   2380: getfield 764	com/google/android/gms/internal/measurement/zzkj:name	Ljava/lang/String;
    //   2383: invokevirtual 659	java/lang/String:equals	(Ljava/lang/Object;)Z
    //   2386: ifeq +2452 -> 4838
    //   2389: iconst_1
    //   2390: istore 26
    //   2392: goto -29 -> 2363
    //   2395: iload 26
    //   2397: ifeq +120 -> 2517
    //   2400: aload_1
    //   2401: ifnull +116 -> 2517
    //   2404: aload 14
    //   2406: aload 14
    //   2408: getfield 759	com/google/android/gms/internal/measurement/zzki:zzasv	[Lcom/google/android/gms/internal/measurement/zzkj;
    //   2411: iconst_1
    //   2412: anewarray 761	com/google/android/gms/internal/measurement/zzkj
    //   2415: dup
    //   2416: iconst_0
    //   2417: aload_1
    //   2418: aastore
    //   2419: invokestatic 822	com/google/android/gms/common/util/ArrayUtils:removeAll	([Ljava/lang/Object;[Ljava/lang/Object;)[Ljava/lang/Object;
    //   2422: checkcast 778	[Lcom/google/android/gms/internal/measurement/zzkj;
    //   2425: putfield 759	com/google/android/gms/internal/measurement/zzki:zzasv	[Lcom/google/android/gms/internal/measurement/zzkj;
    //   2428: iload 27
    //   2430: istore 18
    //   2432: iload 19
    //   2434: ifeq +2401 -> 4835
    //   2437: ldc_w 824
    //   2440: aload 14
    //   2442: getfield 634	com/google/android/gms/internal/measurement/zzki:name	Ljava/lang/String;
    //   2445: invokevirtual 659	java/lang/String:equals	(Ljava/lang/Object;)Z
    //   2448: ifeq +2387 -> 4835
    //   2451: aload 14
    //   2453: getfield 759	com/google/android/gms/internal/measurement/zzki:zzasv	[Lcom/google/android/gms/internal/measurement/zzkj;
    //   2456: ifnull +12 -> 2468
    //   2459: aload 14
    //   2461: getfield 759	com/google/android/gms/internal/measurement/zzki:zzasv	[Lcom/google/android/gms/internal/measurement/zzkj;
    //   2464: arraylength
    //   2465: ifne +115 -> 2580
    //   2468: aload_0
    //   2469: invokevirtual 254	com/google/android/gms/internal/measurement/zzgl:zzgg	()Lcom/google/android/gms/internal/measurement/zzfg;
    //   2472: invokevirtual 257	com/google/android/gms/internal/measurement/zzfg:zzin	()Lcom/google/android/gms/internal/measurement/zzfi;
    //   2475: ldc_w 826
    //   2478: aload 4
    //   2480: getfield 610	com/google/android/gms/internal/measurement/zzgl$zza:zzans	Lcom/google/android/gms/internal/measurement/zzkl;
    //   2483: getfield 625	com/google/android/gms/internal/measurement/zzkl:zztd	Ljava/lang/String;
    //   2486: invokestatic 557	com/google/android/gms/internal/measurement/zzfg:zzbh	(Ljava/lang/String;)Ljava/lang/Object;
    //   2489: invokevirtual 374	com/google/android/gms/internal/measurement/zzfi:zzg	(Ljava/lang/String;Ljava/lang/Object;)V
    //   2492: aload 12
    //   2494: getfield 621	com/google/android/gms/internal/measurement/zzkl:zzatd	[Lcom/google/android/gms/internal/measurement/zzki;
    //   2497: astore_1
    //   2498: iload 16
    //   2500: iconst_1
    //   2501: iadd
    //   2502: istore 21
    //   2504: aload_1
    //   2505: iload 16
    //   2507: aload 14
    //   2509: aastore
    //   2510: iload 21
    //   2512: istore 16
    //   2514: goto -1975 -> 539
    //   2517: aload_1
    //   2518: ifnull +27 -> 2545
    //   2521: aload_1
    //   2522: ldc_w 655
    //   2525: putfield 764	com/google/android/gms/internal/measurement/zzkj:name	Ljava/lang/String;
    //   2528: aload_1
    //   2529: ldc2_w 827
    //   2532: invokestatic 370	java/lang/Long:valueOf	(J)Ljava/lang/Long;
    //   2535: putfield 767	com/google/android/gms/internal/measurement/zzkj:zzasz	Ljava/lang/Long;
    //   2538: iload 27
    //   2540: istore 18
    //   2542: goto -110 -> 2432
    //   2545: aload_0
    //   2546: invokevirtual 254	com/google/android/gms/internal/measurement/zzgl:zzgg	()Lcom/google/android/gms/internal/measurement/zzfg;
    //   2549: invokevirtual 401	com/google/android/gms/internal/measurement/zzfg:zzil	()Lcom/google/android/gms/internal/measurement/zzfi;
    //   2552: ldc_w 830
    //   2555: aload 4
    //   2557: getfield 610	com/google/android/gms/internal/measurement/zzgl$zza:zzans	Lcom/google/android/gms/internal/measurement/zzkl;
    //   2560: getfield 625	com/google/android/gms/internal/measurement/zzkl:zztd	Ljava/lang/String;
    //   2563: invokestatic 557	com/google/android/gms/internal/measurement/zzfg:zzbh	(Ljava/lang/String;)Ljava/lang/Object;
    //   2566: invokevirtual 374	com/google/android/gms/internal/measurement/zzfi:zzg	(Ljava/lang/String;Ljava/lang/Object;)V
    //   2569: iload 27
    //   2571: istore 23
    //   2573: iload 23
    //   2575: istore 18
    //   2577: goto -145 -> 2432
    //   2580: aload_0
    //   2581: invokevirtual 383	com/google/android/gms/internal/measurement/zzgl:zzgc	()Lcom/google/android/gms/internal/measurement/zzjv;
    //   2584: pop
    //   2585: aload 14
    //   2587: ldc_w 832
    //   2590: invokestatic 835	com/google/android/gms/internal/measurement/zzjv:zzb	(Lcom/google/android/gms/internal/measurement/zzki;Ljava/lang/String;)Ljava/lang/Object;
    //   2593: checkcast 367	java/lang/Long
    //   2596: astore_1
    //   2597: aload_1
    //   2598: ifnonnull +30 -> 2628
    //   2601: aload_0
    //   2602: invokevirtual 254	com/google/android/gms/internal/measurement/zzgl:zzgg	()Lcom/google/android/gms/internal/measurement/zzfg;
    //   2605: invokevirtual 257	com/google/android/gms/internal/measurement/zzfg:zzin	()Lcom/google/android/gms/internal/measurement/zzfi;
    //   2608: ldc_w 837
    //   2611: aload 4
    //   2613: getfield 610	com/google/android/gms/internal/measurement/zzgl$zza:zzans	Lcom/google/android/gms/internal/measurement/zzkl;
    //   2616: getfield 625	com/google/android/gms/internal/measurement/zzkl:zztd	Ljava/lang/String;
    //   2619: invokestatic 557	com/google/android/gms/internal/measurement/zzfg:zzbh	(Ljava/lang/String;)Ljava/lang/Object;
    //   2622: invokevirtual 374	com/google/android/gms/internal/measurement/zzfi:zzg	(Ljava/lang/String;Ljava/lang/Object;)V
    //   2625: goto -133 -> 2492
    //   2628: lload_2
    //   2629: aload_1
    //   2630: invokevirtual 840	java/lang/Long:longValue	()J
    //   2633: ladd
    //   2634: lstore_2
    //   2635: goto -143 -> 2492
    //   2638: iload 16
    //   2640: aload 4
    //   2642: getfield 602	com/google/android/gms/internal/measurement/zzgl$zza:zzanu	Ljava/util/List;
    //   2645: invokeinterface 613 1 0
    //   2650: if_icmpge +21 -> 2671
    //   2653: aload 12
    //   2655: aload 12
    //   2657: getfield 621	com/google/android/gms/internal/measurement/zzkl:zzatd	[Lcom/google/android/gms/internal/measurement/zzki;
    //   2660: iload 16
    //   2662: invokestatic 777	java/util/Arrays:copyOf	([Ljava/lang/Object;I)[Ljava/lang/Object;
    //   2665: checkcast 841	[Lcom/google/android/gms/internal/measurement/zzki;
    //   2668: putfield 621	com/google/android/gms/internal/measurement/zzkl:zzatd	[Lcom/google/android/gms/internal/measurement/zzki;
    //   2671: iload 19
    //   2673: ifeq +243 -> 2916
    //   2676: aload_0
    //   2677: invokevirtual 566	com/google/android/gms/internal/measurement/zzgl:zzga	()Lcom/google/android/gms/internal/measurement/zzei;
    //   2680: aload 12
    //   2682: getfield 625	com/google/android/gms/internal/measurement/zzkl:zztd	Ljava/lang/String;
    //   2685: ldc_w 843
    //   2688: invokevirtual 846	com/google/android/gms/internal/measurement/zzei:zzg	(Ljava/lang/String;Ljava/lang/String;)Lcom/google/android/gms/internal/measurement/zzju;
    //   2691: astore_1
    //   2692: aload_1
    //   2693: ifnull +10 -> 2703
    //   2696: aload_1
    //   2697: getfield 852	com/google/android/gms/internal/measurement/zzju:value	Ljava/lang/Object;
    //   2700: ifnonnull +545 -> 3245
    //   2703: new 848	com/google/android/gms/internal/measurement/zzju
    //   2706: astore_1
    //   2707: aload_1
    //   2708: aload 12
    //   2710: getfield 625	com/google/android/gms/internal/measurement/zzkl:zztd	Ljava/lang/String;
    //   2713: ldc_w 854
    //   2716: ldc_w 843
    //   2719: aload_0
    //   2720: getfield 110	com/google/android/gms/internal/measurement/zzgl:zzrj	Lcom/google/android/gms/common/util/Clock;
    //   2723: invokeinterface 116 1 0
    //   2728: lload_2
    //   2729: invokestatic 370	java/lang/Long:valueOf	(J)Ljava/lang/Long;
    //   2732: invokespecial 857	com/google/android/gms/internal/measurement/zzju:<init>	(Ljava/lang/String;Ljava/lang/String;Ljava/lang/String;JLjava/lang/Object;)V
    //   2735: new 859	com/google/android/gms/internal/measurement/zzkn
    //   2738: astore 11
    //   2740: aload 11
    //   2742: invokespecial 860	com/google/android/gms/internal/measurement/zzkn:<init>	()V
    //   2745: aload 11
    //   2747: ldc_w 843
    //   2750: putfield 861	com/google/android/gms/internal/measurement/zzkn:name	Ljava/lang/String;
    //   2753: aload 11
    //   2755: aload_0
    //   2756: getfield 110	com/google/android/gms/internal/measurement/zzgl:zzrj	Lcom/google/android/gms/common/util/Clock;
    //   2759: invokeinterface 116 1 0
    //   2764: invokestatic 370	java/lang/Long:valueOf	(J)Ljava/lang/Long;
    //   2767: putfield 864	com/google/android/gms/internal/measurement/zzkn:zzaui	Ljava/lang/Long;
    //   2770: aload 11
    //   2772: aload_1
    //   2773: getfield 852	com/google/android/gms/internal/measurement/zzju:value	Ljava/lang/Object;
    //   2776: checkcast 367	java/lang/Long
    //   2779: putfield 865	com/google/android/gms/internal/measurement/zzkn:zzasz	Ljava/lang/Long;
    //   2782: iconst_0
    //   2783: istore 20
    //   2785: iconst_0
    //   2786: istore 16
    //   2788: iload 20
    //   2790: istore 21
    //   2792: iload 16
    //   2794: aload 12
    //   2796: getfield 869	com/google/android/gms/internal/measurement/zzkl:zzate	[Lcom/google/android/gms/internal/measurement/zzkn;
    //   2799: arraylength
    //   2800: if_icmpge +36 -> 2836
    //   2803: ldc_w 843
    //   2806: aload 12
    //   2808: getfield 869	com/google/android/gms/internal/measurement/zzkl:zzate	[Lcom/google/android/gms/internal/measurement/zzkn;
    //   2811: iload 16
    //   2813: aaload
    //   2814: getfield 861	com/google/android/gms/internal/measurement/zzkn:name	Ljava/lang/String;
    //   2817: invokevirtual 659	java/lang/String:equals	(Ljava/lang/Object;)Z
    //   2820: ifeq +471 -> 3291
    //   2823: aload 12
    //   2825: getfield 869	com/google/android/gms/internal/measurement/zzkl:zzate	[Lcom/google/android/gms/internal/measurement/zzkn;
    //   2828: iload 16
    //   2830: aload 11
    //   2832: aastore
    //   2833: iconst_1
    //   2834: istore 21
    //   2836: iload 21
    //   2838: ifne +46 -> 2884
    //   2841: aload 12
    //   2843: aload 12
    //   2845: getfield 869	com/google/android/gms/internal/measurement/zzkl:zzate	[Lcom/google/android/gms/internal/measurement/zzkn;
    //   2848: aload 12
    //   2850: getfield 869	com/google/android/gms/internal/measurement/zzkl:zzate	[Lcom/google/android/gms/internal/measurement/zzkn;
    //   2853: arraylength
    //   2854: iconst_1
    //   2855: iadd
    //   2856: invokestatic 777	java/util/Arrays:copyOf	([Ljava/lang/Object;I)[Ljava/lang/Object;
    //   2859: checkcast 870	[Lcom/google/android/gms/internal/measurement/zzkn;
    //   2862: putfield 869	com/google/android/gms/internal/measurement/zzkl:zzate	[Lcom/google/android/gms/internal/measurement/zzkn;
    //   2865: aload 12
    //   2867: getfield 869	com/google/android/gms/internal/measurement/zzkl:zzate	[Lcom/google/android/gms/internal/measurement/zzkn;
    //   2870: aload 4
    //   2872: getfield 610	com/google/android/gms/internal/measurement/zzgl$zza:zzans	Lcom/google/android/gms/internal/measurement/zzkl;
    //   2875: getfield 869	com/google/android/gms/internal/measurement/zzkl:zzate	[Lcom/google/android/gms/internal/measurement/zzkn;
    //   2878: arraylength
    //   2879: iconst_1
    //   2880: isub
    //   2881: aload 11
    //   2883: aastore
    //   2884: lload_2
    //   2885: lconst_0
    //   2886: lcmp
    //   2887: ifle +29 -> 2916
    //   2890: aload_0
    //   2891: invokevirtual 566	com/google/android/gms/internal/measurement/zzgl:zzga	()Lcom/google/android/gms/internal/measurement/zzei;
    //   2894: aload_1
    //   2895: invokevirtual 873	com/google/android/gms/internal/measurement/zzei:zza	(Lcom/google/android/gms/internal/measurement/zzju;)Z
    //   2898: pop
    //   2899: aload_0
    //   2900: invokevirtual 254	com/google/android/gms/internal/measurement/zzgl:zzgg	()Lcom/google/android/gms/internal/measurement/zzfg;
    //   2903: invokevirtual 392	com/google/android/gms/internal/measurement/zzfg:zziq	()Lcom/google/android/gms/internal/measurement/zzfi;
    //   2906: ldc_w 875
    //   2909: aload_1
    //   2910: getfield 852	com/google/android/gms/internal/measurement/zzju:value	Ljava/lang/Object;
    //   2913: invokevirtual 374	com/google/android/gms/internal/measurement/zzfi:zzg	(Ljava/lang/String;Ljava/lang/Object;)V
    //   2916: aload 12
    //   2918: aload_0
    //   2919: aload 12
    //   2921: getfield 625	com/google/android/gms/internal/measurement/zzkl:zztd	Ljava/lang/String;
    //   2924: aload 12
    //   2926: getfield 869	com/google/android/gms/internal/measurement/zzkl:zzate	[Lcom/google/android/gms/internal/measurement/zzkn;
    //   2929: aload 12
    //   2931: getfield 621	com/google/android/gms/internal/measurement/zzkl:zzatd	[Lcom/google/android/gms/internal/measurement/zzki;
    //   2934: invokespecial 877	com/google/android/gms/internal/measurement/zzgl:zza	(Ljava/lang/String;[Lcom/google/android/gms/internal/measurement/zzkn;[Lcom/google/android/gms/internal/measurement/zzki;)[Lcom/google/android/gms/internal/measurement/zzkh;
    //   2937: putfield 881	com/google/android/gms/internal/measurement/zzkl:zzatv	[Lcom/google/android/gms/internal/measurement/zzkh;
    //   2940: getstatic 884	com/google/android/gms/internal/measurement/zzew:zzagk	Lcom/google/android/gms/internal/measurement/zzex;
    //   2943: invokevirtual 467	com/google/android/gms/internal/measurement/zzex:get	()Ljava/lang/Object;
    //   2946: checkcast 886	java/lang/Boolean
    //   2949: invokevirtual 889	java/lang/Boolean:booleanValue	()Z
    //   2952: ifeq +1174 -> 4126
    //   2955: aload_0
    //   2956: getfield 125	com/google/android/gms/internal/measurement/zzgl:zzamd	Lcom/google/android/gms/internal/measurement/zzeh;
    //   2959: astore 11
    //   2961: aload 4
    //   2963: getfield 610	com/google/android/gms/internal/measurement/zzgl$zza:zzans	Lcom/google/android/gms/internal/measurement/zzkl;
    //   2966: getfield 625	com/google/android/gms/internal/measurement/zzkl:zztd	Ljava/lang/String;
    //   2969: astore_1
    //   2970: ldc_w 891
    //   2973: aload 11
    //   2975: invokevirtual 892	com/google/android/gms/internal/measurement/zzhj:zzgd	()Lcom/google/android/gms/internal/measurement/zzgf;
    //   2978: aload_1
    //   2979: ldc_w 894
    //   2982: invokevirtual 897	com/google/android/gms/internal/measurement/zzgf:zzm	(Ljava/lang/String;Ljava/lang/String;)Ljava/lang/String;
    //   2985: invokevirtual 659	java/lang/String:equals	(Ljava/lang/Object;)Z
    //   2988: ifeq +1138 -> 4126
    //   2991: new 899	java/util/HashMap
    //   2994: astore 9
    //   2996: aload 9
    //   2998: invokespecial 900	java/util/HashMap:<init>	()V
    //   3001: aload 12
    //   3003: getfield 621	com/google/android/gms/internal/measurement/zzkl:zzatd	[Lcom/google/android/gms/internal/measurement/zzki;
    //   3006: arraylength
    //   3007: anewarray 615	com/google/android/gms/internal/measurement/zzki
    //   3010: astore 10
    //   3012: iconst_0
    //   3013: istore 21
    //   3015: aload_0
    //   3016: invokevirtual 383	com/google/android/gms/internal/measurement/zzgl:zzgc	()Lcom/google/android/gms/internal/measurement/zzjv;
    //   3019: invokevirtual 904	com/google/android/gms/internal/measurement/zzjv:zzku	()Ljava/security/SecureRandom;
    //   3022: astore 6
    //   3024: aload 12
    //   3026: getfield 621	com/google/android/gms/internal/measurement/zzkl:zzatd	[Lcom/google/android/gms/internal/measurement/zzki;
    //   3029: astore 15
    //   3031: aload 15
    //   3033: arraylength
    //   3034: istore 24
    //   3036: iconst_0
    //   3037: istore 20
    //   3039: iload 20
    //   3041: iload 24
    //   3043: if_icmpge +1003 -> 4046
    //   3046: aload 15
    //   3048: iload 20
    //   3050: aaload
    //   3051: astore 14
    //   3053: aload 14
    //   3055: getfield 634	com/google/android/gms/internal/measurement/zzki:name	Ljava/lang/String;
    //   3058: ldc_w 906
    //   3061: invokevirtual 659	java/lang/String:equals	(Ljava/lang/Object;)Z
    //   3064: ifeq +233 -> 3297
    //   3067: aload_0
    //   3068: invokevirtual 383	com/google/android/gms/internal/measurement/zzgl:zzgc	()Lcom/google/android/gms/internal/measurement/zzjv;
    //   3071: pop
    //   3072: aload 14
    //   3074: ldc_w 908
    //   3077: invokestatic 835	com/google/android/gms/internal/measurement/zzjv:zzb	(Lcom/google/android/gms/internal/measurement/zzki;Ljava/lang/String;)Ljava/lang/Object;
    //   3080: checkcast 280	java/lang/String
    //   3083: astore 5
    //   3085: aload 9
    //   3087: aload 5
    //   3089: invokeinterface 910 2 0
    //   3094: checkcast 912	com/google/android/gms/internal/measurement/zzeq
    //   3097: astore 11
    //   3099: aload 11
    //   3101: astore_1
    //   3102: aload 11
    //   3104: ifnonnull +32 -> 3136
    //   3107: aload_0
    //   3108: invokevirtual 566	com/google/android/gms/internal/measurement/zzgl:zzga	()Lcom/google/android/gms/internal/measurement/zzei;
    //   3111: aload 4
    //   3113: getfield 610	com/google/android/gms/internal/measurement/zzgl$zza:zzans	Lcom/google/android/gms/internal/measurement/zzkl;
    //   3116: getfield 625	com/google/android/gms/internal/measurement/zzkl:zztd	Ljava/lang/String;
    //   3119: aload 5
    //   3121: invokevirtual 915	com/google/android/gms/internal/measurement/zzei:zze	(Ljava/lang/String;Ljava/lang/String;)Lcom/google/android/gms/internal/measurement/zzeq;
    //   3124: astore_1
    //   3125: aload 9
    //   3127: aload 5
    //   3129: aload_1
    //   3130: invokeinterface 530 3 0
    //   3135: pop
    //   3136: aload_1
    //   3137: getfield 918	com/google/android/gms/internal/measurement/zzeq:zzaft	Ljava/lang/Long;
    //   3140: ifnonnull +899 -> 4039
    //   3143: aload_1
    //   3144: getfield 921	com/google/android/gms/internal/measurement/zzeq:zzafu	Ljava/lang/Long;
    //   3147: invokevirtual 840	java/lang/Long:longValue	()J
    //   3150: lconst_1
    //   3151: lcmp
    //   3152: ifle +28 -> 3180
    //   3155: aload_0
    //   3156: invokevirtual 383	com/google/android/gms/internal/measurement/zzgl:zzgc	()Lcom/google/android/gms/internal/measurement/zzjv;
    //   3159: pop
    //   3160: aload 14
    //   3162: aload 14
    //   3164: getfield 759	com/google/android/gms/internal/measurement/zzki:zzasv	[Lcom/google/android/gms/internal/measurement/zzkj;
    //   3167: ldc_w 923
    //   3170: aload_1
    //   3171: getfield 921	com/google/android/gms/internal/measurement/zzeq:zzafu	Ljava/lang/Long;
    //   3174: invokestatic 926	com/google/android/gms/internal/measurement/zzjv:zza	([Lcom/google/android/gms/internal/measurement/zzkj;Ljava/lang/String;Ljava/lang/Object;)[Lcom/google/android/gms/internal/measurement/zzkj;
    //   3177: putfield 759	com/google/android/gms/internal/measurement/zzki:zzasv	[Lcom/google/android/gms/internal/measurement/zzkj;
    //   3180: aload_1
    //   3181: getfield 929	com/google/android/gms/internal/measurement/zzeq:zzafv	Ljava/lang/Boolean;
    //   3184: ifnull +38 -> 3222
    //   3187: aload_1
    //   3188: getfield 929	com/google/android/gms/internal/measurement/zzeq:zzafv	Ljava/lang/Boolean;
    //   3191: invokevirtual 889	java/lang/Boolean:booleanValue	()Z
    //   3194: ifeq +28 -> 3222
    //   3197: aload_0
    //   3198: invokevirtual 383	com/google/android/gms/internal/measurement/zzgl:zzgc	()Lcom/google/android/gms/internal/measurement/zzjv;
    //   3201: pop
    //   3202: aload 14
    //   3204: aload 14
    //   3206: getfield 759	com/google/android/gms/internal/measurement/zzki:zzasv	[Lcom/google/android/gms/internal/measurement/zzkj;
    //   3209: ldc_w 931
    //   3212: lconst_1
    //   3213: invokestatic 370	java/lang/Long:valueOf	(J)Ljava/lang/Long;
    //   3216: invokestatic 926	com/google/android/gms/internal/measurement/zzjv:zza	([Lcom/google/android/gms/internal/measurement/zzkj;Ljava/lang/String;Ljava/lang/Object;)[Lcom/google/android/gms/internal/measurement/zzkj;
    //   3219: putfield 759	com/google/android/gms/internal/measurement/zzki:zzasv	[Lcom/google/android/gms/internal/measurement/zzkj;
    //   3222: iload 21
    //   3224: iconst_1
    //   3225: iadd
    //   3226: istore 16
    //   3228: aload 10
    //   3230: iload 21
    //   3232: aload 14
    //   3234: aastore
    //   3235: iinc 20 1
    //   3238: iload 16
    //   3240: istore 21
    //   3242: goto -203 -> 3039
    //   3245: new 848	com/google/android/gms/internal/measurement/zzju
    //   3248: dup
    //   3249: aload 12
    //   3251: getfield 625	com/google/android/gms/internal/measurement/zzkl:zztd	Ljava/lang/String;
    //   3254: ldc_w 854
    //   3257: ldc_w 843
    //   3260: aload_0
    //   3261: getfield 110	com/google/android/gms/internal/measurement/zzgl:zzrj	Lcom/google/android/gms/common/util/Clock;
    //   3264: invokeinterface 116 1 0
    //   3269: aload_1
    //   3270: getfield 852	com/google/android/gms/internal/measurement/zzju:value	Ljava/lang/Object;
    //   3273: checkcast 367	java/lang/Long
    //   3276: invokevirtual 840	java/lang/Long:longValue	()J
    //   3279: lload_2
    //   3280: ladd
    //   3281: invokestatic 370	java/lang/Long:valueOf	(J)Ljava/lang/Long;
    //   3284: invokespecial 857	com/google/android/gms/internal/measurement/zzju:<init>	(Ljava/lang/String;Ljava/lang/String;Ljava/lang/String;JLjava/lang/Object;)V
    //   3287: astore_1
    //   3288: goto -553 -> 2735
    //   3291: iinc 16 1
    //   3294: goto -506 -> 2788
    //   3297: lconst_1
    //   3298: invokestatic 370	java/lang/Long:valueOf	(J)Ljava/lang/Long;
    //   3301: astore 11
    //   3303: ldc_w 933
    //   3306: invokestatic 445	android/text/TextUtils:isEmpty	(Ljava/lang/CharSequence;)Z
    //   3309: ifne +8 -> 3317
    //   3312: aload 11
    //   3314: ifnonnull +77 -> 3391
    //   3317: iconst_0
    //   3318: istore 16
    //   3320: iload 16
    //   3322: ifne +1507 -> 4829
    //   3325: aload_0
    //   3326: invokevirtual 512	com/google/android/gms/internal/measurement/zzgl:zzgd	()Lcom/google/android/gms/internal/measurement/zzgf;
    //   3329: aload 4
    //   3331: getfield 610	com/google/android/gms/internal/measurement/zzgl$zza:zzans	Lcom/google/android/gms/internal/measurement/zzkl;
    //   3334: getfield 625	com/google/android/gms/internal/measurement/zzkl:zztd	Ljava/lang/String;
    //   3337: aload 14
    //   3339: getfield 634	com/google/android/gms/internal/measurement/zzki:name	Ljava/lang/String;
    //   3342: invokevirtual 937	com/google/android/gms/internal/measurement/zzgf:zzp	(Ljava/lang/String;Ljava/lang/String;)I
    //   3345: istore 16
    //   3347: iload 16
    //   3349: ifgt +167 -> 3516
    //   3352: aload_0
    //   3353: invokevirtual 254	com/google/android/gms/internal/measurement/zzgl:zzgg	()Lcom/google/android/gms/internal/measurement/zzfg;
    //   3356: invokevirtual 257	com/google/android/gms/internal/measurement/zzfg:zzin	()Lcom/google/android/gms/internal/measurement/zzfi;
    //   3359: ldc_w 939
    //   3362: aload 14
    //   3364: getfield 634	com/google/android/gms/internal/measurement/zzki:name	Ljava/lang/String;
    //   3367: iload 16
    //   3369: invokestatic 408	java/lang/Integer:valueOf	(I)Ljava/lang/Integer;
    //   3372: invokevirtual 412	com/google/android/gms/internal/measurement/zzfi:zze	(Ljava/lang/String;Ljava/lang/Object;Ljava/lang/Object;)V
    //   3375: iload 21
    //   3377: iconst_1
    //   3378: iadd
    //   3379: istore 16
    //   3381: aload 10
    //   3383: iload 21
    //   3385: aload 14
    //   3387: aastore
    //   3388: goto -153 -> 3235
    //   3391: aload 14
    //   3393: getfield 759	com/google/android/gms/internal/measurement/zzki:zzasv	[Lcom/google/android/gms/internal/measurement/zzkj;
    //   3396: astore 5
    //   3398: aload 5
    //   3400: arraylength
    //   3401: istore 26
    //   3403: iconst_0
    //   3404: istore 16
    //   3406: iload 16
    //   3408: iload 26
    //   3410: if_icmpge +100 -> 3510
    //   3413: aload 5
    //   3415: iload 16
    //   3417: aaload
    //   3418: astore_1
    //   3419: ldc_w 933
    //   3422: aload_1
    //   3423: getfield 764	com/google/android/gms/internal/measurement/zzkj:name	Ljava/lang/String;
    //   3426: invokevirtual 659	java/lang/String:equals	(Ljava/lang/Object;)Z
    //   3429: ifeq +75 -> 3504
    //   3432: aload 11
    //   3434: instanceof 367
    //   3437: ifeq +15 -> 3452
    //   3440: aload 11
    //   3442: aload_1
    //   3443: getfield 767	com/google/android/gms/internal/measurement/zzkj:zzasz	Ljava/lang/Long;
    //   3446: invokevirtual 940	java/lang/Object:equals	(Ljava/lang/Object;)Z
    //   3449: ifne +43 -> 3492
    //   3452: aload 11
    //   3454: instanceof 280
    //   3457: ifeq +15 -> 3472
    //   3460: aload 11
    //   3462: aload_1
    //   3463: getfield 943	com/google/android/gms/internal/measurement/zzkj:zzajf	Ljava/lang/String;
    //   3466: invokevirtual 940	java/lang/Object:equals	(Ljava/lang/Object;)Z
    //   3469: ifne +23 -> 3492
    //   3472: aload 11
    //   3474: instanceof 945
    //   3477: ifeq +21 -> 3498
    //   3480: aload 11
    //   3482: aload_1
    //   3483: getfield 949	com/google/android/gms/internal/measurement/zzkj:zzaqx	Ljava/lang/Double;
    //   3486: invokevirtual 940	java/lang/Object:equals	(Ljava/lang/Object;)Z
    //   3489: ifeq +9 -> 3498
    //   3492: iconst_1
    //   3493: istore 16
    //   3495: goto -175 -> 3320
    //   3498: iconst_0
    //   3499: istore 16
    //   3501: goto -181 -> 3320
    //   3504: iinc 16 1
    //   3507: goto -101 -> 3406
    //   3510: iconst_0
    //   3511: istore 16
    //   3513: goto -193 -> 3320
    //   3516: aload 9
    //   3518: aload 14
    //   3520: getfield 634	com/google/android/gms/internal/measurement/zzki:name	Ljava/lang/String;
    //   3523: invokeinterface 910 2 0
    //   3528: checkcast 912	com/google/android/gms/internal/measurement/zzeq
    //   3531: astore_1
    //   3532: aload_1
    //   3533: ifnonnull +1293 -> 4826
    //   3536: aload_0
    //   3537: invokevirtual 566	com/google/android/gms/internal/measurement/zzgl:zzga	()Lcom/google/android/gms/internal/measurement/zzei;
    //   3540: aload 4
    //   3542: getfield 610	com/google/android/gms/internal/measurement/zzgl$zza:zzans	Lcom/google/android/gms/internal/measurement/zzkl;
    //   3545: getfield 625	com/google/android/gms/internal/measurement/zzkl:zztd	Ljava/lang/String;
    //   3548: aload 14
    //   3550: getfield 634	com/google/android/gms/internal/measurement/zzki:name	Ljava/lang/String;
    //   3553: invokevirtual 915	com/google/android/gms/internal/measurement/zzei:zze	(Ljava/lang/String;Ljava/lang/String;)Lcom/google/android/gms/internal/measurement/zzeq;
    //   3556: astore 11
    //   3558: aload 11
    //   3560: astore_1
    //   3561: aload 11
    //   3563: ifnonnull +64 -> 3627
    //   3566: aload_0
    //   3567: invokevirtual 254	com/google/android/gms/internal/measurement/zzgl:zzgg	()Lcom/google/android/gms/internal/measurement/zzfg;
    //   3570: invokevirtual 257	com/google/android/gms/internal/measurement/zzfg:zzin	()Lcom/google/android/gms/internal/measurement/zzfi;
    //   3573: ldc_w 951
    //   3576: aload 4
    //   3578: getfield 610	com/google/android/gms/internal/measurement/zzgl$zza:zzans	Lcom/google/android/gms/internal/measurement/zzkl;
    //   3581: getfield 625	com/google/android/gms/internal/measurement/zzkl:zztd	Ljava/lang/String;
    //   3584: aload 14
    //   3586: getfield 634	com/google/android/gms/internal/measurement/zzki:name	Ljava/lang/String;
    //   3589: invokevirtual 412	com/google/android/gms/internal/measurement/zzfi:zze	(Ljava/lang/String;Ljava/lang/Object;Ljava/lang/Object;)V
    //   3592: new 912	com/google/android/gms/internal/measurement/zzeq
    //   3595: astore_1
    //   3596: aload_1
    //   3597: aload 4
    //   3599: getfield 610	com/google/android/gms/internal/measurement/zzgl$zza:zzans	Lcom/google/android/gms/internal/measurement/zzkl;
    //   3602: getfield 625	com/google/android/gms/internal/measurement/zzkl:zztd	Ljava/lang/String;
    //   3605: aload 14
    //   3607: getfield 634	com/google/android/gms/internal/measurement/zzki:name	Ljava/lang/String;
    //   3610: lconst_1
    //   3611: lconst_1
    //   3612: aload 14
    //   3614: getfield 744	com/google/android/gms/internal/measurement/zzki:zzasw	Ljava/lang/Long;
    //   3617: invokevirtual 840	java/lang/Long:longValue	()J
    //   3620: lconst_0
    //   3621: aconst_null
    //   3622: aconst_null
    //   3623: aconst_null
    //   3624: invokespecial 954	com/google/android/gms/internal/measurement/zzeq:<init>	(Ljava/lang/String;Ljava/lang/String;JJJJLjava/lang/Long;Ljava/lang/Long;Ljava/lang/Boolean;)V
    //   3627: aload_0
    //   3628: invokevirtual 383	com/google/android/gms/internal/measurement/zzgl:zzgc	()Lcom/google/android/gms/internal/measurement/zzjv;
    //   3631: pop
    //   3632: aload 14
    //   3634: ldc_w 956
    //   3637: invokestatic 835	com/google/android/gms/internal/measurement/zzjv:zzb	(Lcom/google/android/gms/internal/measurement/zzki;Ljava/lang/String;)Ljava/lang/Object;
    //   3640: checkcast 367	java/lang/Long
    //   3643: astore 11
    //   3645: aload 11
    //   3647: ifnull +98 -> 3745
    //   3650: iconst_1
    //   3651: istore 27
    //   3653: iload 27
    //   3655: invokestatic 959	java/lang/Boolean:valueOf	(Z)Ljava/lang/Boolean;
    //   3658: astore 5
    //   3660: iload 16
    //   3662: iconst_1
    //   3663: if_icmpne +88 -> 3751
    //   3666: iload 21
    //   3668: iconst_1
    //   3669: iadd
    //   3670: istore 26
    //   3672: aload 10
    //   3674: iload 21
    //   3676: aload 14
    //   3678: aastore
    //   3679: iload 26
    //   3681: istore 16
    //   3683: aload 5
    //   3685: invokevirtual 889	java/lang/Boolean:booleanValue	()Z
    //   3688: ifeq -453 -> 3235
    //   3691: aload_1
    //   3692: getfield 918	com/google/android/gms/internal/measurement/zzeq:zzaft	Ljava/lang/Long;
    //   3695: ifnonnull +21 -> 3716
    //   3698: aload_1
    //   3699: getfield 921	com/google/android/gms/internal/measurement/zzeq:zzafu	Ljava/lang/Long;
    //   3702: ifnonnull +14 -> 3716
    //   3705: iload 26
    //   3707: istore 16
    //   3709: aload_1
    //   3710: getfield 929	com/google/android/gms/internal/measurement/zzeq:zzafv	Ljava/lang/Boolean;
    //   3713: ifnull -478 -> 3235
    //   3716: aload_1
    //   3717: aconst_null
    //   3718: aconst_null
    //   3719: aconst_null
    //   3720: invokevirtual 962	com/google/android/gms/internal/measurement/zzeq:zza	(Ljava/lang/Long;Ljava/lang/Long;Ljava/lang/Boolean;)Lcom/google/android/gms/internal/measurement/zzeq;
    //   3723: astore_1
    //   3724: aload 9
    //   3726: aload 14
    //   3728: getfield 634	com/google/android/gms/internal/measurement/zzki:name	Ljava/lang/String;
    //   3731: aload_1
    //   3732: invokeinterface 530 3 0
    //   3737: pop
    //   3738: iload 26
    //   3740: istore 16
    //   3742: goto -507 -> 3235
    //   3745: iconst_0
    //   3746: istore 27
    //   3748: goto -95 -> 3653
    //   3751: aload 6
    //   3753: iload 16
    //   3755: invokevirtual 968	java/security/SecureRandom:nextInt	(I)I
    //   3758: ifne +101 -> 3859
    //   3761: aload_0
    //   3762: invokevirtual 383	com/google/android/gms/internal/measurement/zzgl:zzgc	()Lcom/google/android/gms/internal/measurement/zzjv;
    //   3765: pop
    //   3766: aload 14
    //   3768: aload 14
    //   3770: getfield 759	com/google/android/gms/internal/measurement/zzki:zzasv	[Lcom/google/android/gms/internal/measurement/zzkj;
    //   3773: ldc_w 923
    //   3776: iload 16
    //   3778: i2l
    //   3779: invokestatic 370	java/lang/Long:valueOf	(J)Ljava/lang/Long;
    //   3782: invokestatic 926	com/google/android/gms/internal/measurement/zzjv:zza	([Lcom/google/android/gms/internal/measurement/zzkj;Ljava/lang/String;Ljava/lang/Object;)[Lcom/google/android/gms/internal/measurement/zzkj;
    //   3785: putfield 759	com/google/android/gms/internal/measurement/zzki:zzasv	[Lcom/google/android/gms/internal/measurement/zzkj;
    //   3788: iload 21
    //   3790: iconst_1
    //   3791: iadd
    //   3792: istore 26
    //   3794: aload 10
    //   3796: iload 21
    //   3798: aload 14
    //   3800: aastore
    //   3801: aload_1
    //   3802: astore 11
    //   3804: aload 5
    //   3806: invokevirtual 889	java/lang/Boolean:booleanValue	()Z
    //   3809: ifeq +17 -> 3826
    //   3812: aload_1
    //   3813: aconst_null
    //   3814: iload 16
    //   3816: i2l
    //   3817: invokestatic 370	java/lang/Long:valueOf	(J)Ljava/lang/Long;
    //   3820: aconst_null
    //   3821: invokevirtual 962	com/google/android/gms/internal/measurement/zzeq:zza	(Ljava/lang/Long;Ljava/lang/Long;Ljava/lang/Boolean;)Lcom/google/android/gms/internal/measurement/zzeq;
    //   3824: astore 11
    //   3826: aload 9
    //   3828: aload 14
    //   3830: getfield 634	com/google/android/gms/internal/measurement/zzki:name	Ljava/lang/String;
    //   3833: aload 11
    //   3835: aload 14
    //   3837: getfield 744	com/google/android/gms/internal/measurement/zzki:zzasw	Ljava/lang/Long;
    //   3840: invokevirtual 840	java/lang/Long:longValue	()J
    //   3843: invokevirtual 972	com/google/android/gms/internal/measurement/zzeq:zzad	(J)Lcom/google/android/gms/internal/measurement/zzeq;
    //   3846: invokeinterface 530 3 0
    //   3851: pop
    //   3852: iload 26
    //   3854: istore 16
    //   3856: goto -621 -> 3235
    //   3859: aload_1
    //   3860: getfield 975	com/google/android/gms/internal/measurement/zzeq:zzafs	J
    //   3863: lstore_2
    //   3864: aload 14
    //   3866: getfield 744	com/google/android/gms/internal/measurement/zzki:zzasw	Ljava/lang/Long;
    //   3869: invokevirtual 840	java/lang/Long:longValue	()J
    //   3872: lload_2
    //   3873: lsub
    //   3874: invokestatic 981	java/lang/Math:abs	(J)J
    //   3877: ldc2_w 982
    //   3880: lcmp
    //   3881: iflt +129 -> 4010
    //   3884: aload_0
    //   3885: invokevirtual 383	com/google/android/gms/internal/measurement/zzgl:zzgc	()Lcom/google/android/gms/internal/measurement/zzjv;
    //   3888: pop
    //   3889: aload 14
    //   3891: aload 14
    //   3893: getfield 759	com/google/android/gms/internal/measurement/zzki:zzasv	[Lcom/google/android/gms/internal/measurement/zzkj;
    //   3896: ldc_w 931
    //   3899: lconst_1
    //   3900: invokestatic 370	java/lang/Long:valueOf	(J)Ljava/lang/Long;
    //   3903: invokestatic 926	com/google/android/gms/internal/measurement/zzjv:zza	([Lcom/google/android/gms/internal/measurement/zzkj;Ljava/lang/String;Ljava/lang/Object;)[Lcom/google/android/gms/internal/measurement/zzkj;
    //   3906: putfield 759	com/google/android/gms/internal/measurement/zzki:zzasv	[Lcom/google/android/gms/internal/measurement/zzkj;
    //   3909: aload_0
    //   3910: invokevirtual 383	com/google/android/gms/internal/measurement/zzgl:zzgc	()Lcom/google/android/gms/internal/measurement/zzjv;
    //   3913: pop
    //   3914: aload 14
    //   3916: aload 14
    //   3918: getfield 759	com/google/android/gms/internal/measurement/zzki:zzasv	[Lcom/google/android/gms/internal/measurement/zzkj;
    //   3921: ldc_w 923
    //   3924: iload 16
    //   3926: i2l
    //   3927: invokestatic 370	java/lang/Long:valueOf	(J)Ljava/lang/Long;
    //   3930: invokestatic 926	com/google/android/gms/internal/measurement/zzjv:zza	([Lcom/google/android/gms/internal/measurement/zzkj;Ljava/lang/String;Ljava/lang/Object;)[Lcom/google/android/gms/internal/measurement/zzkj;
    //   3933: putfield 759	com/google/android/gms/internal/measurement/zzki:zzasv	[Lcom/google/android/gms/internal/measurement/zzkj;
    //   3936: iload 21
    //   3938: iconst_1
    //   3939: iadd
    //   3940: istore 26
    //   3942: aload 10
    //   3944: iload 21
    //   3946: aload 14
    //   3948: aastore
    //   3949: aload_1
    //   3950: astore 11
    //   3952: aload 5
    //   3954: invokevirtual 889	java/lang/Boolean:booleanValue	()Z
    //   3957: ifeq +20 -> 3977
    //   3960: aload_1
    //   3961: aconst_null
    //   3962: iload 16
    //   3964: i2l
    //   3965: invokestatic 370	java/lang/Long:valueOf	(J)Ljava/lang/Long;
    //   3968: iconst_1
    //   3969: invokestatic 959	java/lang/Boolean:valueOf	(Z)Ljava/lang/Boolean;
    //   3972: invokevirtual 962	com/google/android/gms/internal/measurement/zzeq:zza	(Ljava/lang/Long;Ljava/lang/Long;Ljava/lang/Boolean;)Lcom/google/android/gms/internal/measurement/zzeq;
    //   3975: astore 11
    //   3977: aload 9
    //   3979: aload 14
    //   3981: getfield 634	com/google/android/gms/internal/measurement/zzki:name	Ljava/lang/String;
    //   3984: aload 11
    //   3986: aload 14
    //   3988: getfield 744	com/google/android/gms/internal/measurement/zzki:zzasw	Ljava/lang/Long;
    //   3991: invokevirtual 840	java/lang/Long:longValue	()J
    //   3994: invokevirtual 972	com/google/android/gms/internal/measurement/zzeq:zzad	(J)Lcom/google/android/gms/internal/measurement/zzeq;
    //   3997: invokeinterface 530 3 0
    //   4002: pop
    //   4003: iload 26
    //   4005: istore 16
    //   4007: goto -772 -> 3235
    //   4010: aload 5
    //   4012: invokevirtual 889	java/lang/Boolean:booleanValue	()Z
    //   4015: ifeq +24 -> 4039
    //   4018: aload 9
    //   4020: aload 14
    //   4022: getfield 634	com/google/android/gms/internal/measurement/zzki:name	Ljava/lang/String;
    //   4025: aload_1
    //   4026: aload 11
    //   4028: aconst_null
    //   4029: aconst_null
    //   4030: invokevirtual 962	com/google/android/gms/internal/measurement/zzeq:zza	(Ljava/lang/Long;Ljava/lang/Long;Ljava/lang/Boolean;)Lcom/google/android/gms/internal/measurement/zzeq;
    //   4033: invokeinterface 530 3 0
    //   4038: pop
    //   4039: iload 21
    //   4041: istore 16
    //   4043: goto -808 -> 3235
    //   4046: iload 21
    //   4048: aload 12
    //   4050: getfield 621	com/google/android/gms/internal/measurement/zzkl:zzatd	[Lcom/google/android/gms/internal/measurement/zzki;
    //   4053: arraylength
    //   4054: if_icmpge +18 -> 4072
    //   4057: aload 12
    //   4059: aload 10
    //   4061: iload 21
    //   4063: invokestatic 777	java/util/Arrays:copyOf	([Ljava/lang/Object;I)[Ljava/lang/Object;
    //   4066: checkcast 841	[Lcom/google/android/gms/internal/measurement/zzki;
    //   4069: putfield 621	com/google/android/gms/internal/measurement/zzkl:zzatd	[Lcom/google/android/gms/internal/measurement/zzki;
    //   4072: aload 9
    //   4074: invokeinterface 987 1 0
    //   4079: invokeinterface 993 1 0
    //   4084: astore 11
    //   4086: aload 11
    //   4088: invokeinterface 998 1 0
    //   4093: ifeq +33 -> 4126
    //   4096: aload 11
    //   4098: invokeinterface 1001 1 0
    //   4103: checkcast 1003	java/util/Map$Entry
    //   4106: astore_1
    //   4107: aload_0
    //   4108: invokevirtual 566	com/google/android/gms/internal/measurement/zzgl:zzga	()Lcom/google/android/gms/internal/measurement/zzei;
    //   4111: aload_1
    //   4112: invokeinterface 1006 1 0
    //   4117: checkcast 912	com/google/android/gms/internal/measurement/zzeq
    //   4120: invokevirtual 1009	com/google/android/gms/internal/measurement/zzei:zza	(Lcom/google/android/gms/internal/measurement/zzeq;)V
    //   4123: goto -37 -> 4086
    //   4126: aload 12
    //   4128: ldc2_w 1010
    //   4131: invokestatic 370	java/lang/Long:valueOf	(J)Ljava/lang/Long;
    //   4134: putfield 1014	com/google/android/gms/internal/measurement/zzkl:zzatg	Ljava/lang/Long;
    //   4137: aload 12
    //   4139: ldc2_w 1015
    //   4142: invokestatic 370	java/lang/Long:valueOf	(J)Ljava/lang/Long;
    //   4145: putfield 1019	com/google/android/gms/internal/measurement/zzkl:zzath	Ljava/lang/Long;
    //   4148: iconst_0
    //   4149: istore 16
    //   4151: iload 16
    //   4153: aload 12
    //   4155: getfield 621	com/google/android/gms/internal/measurement/zzkl:zzatd	[Lcom/google/android/gms/internal/measurement/zzki;
    //   4158: arraylength
    //   4159: if_icmpge +74 -> 4233
    //   4162: aload 12
    //   4164: getfield 621	com/google/android/gms/internal/measurement/zzkl:zzatd	[Lcom/google/android/gms/internal/measurement/zzki;
    //   4167: iload 16
    //   4169: aaload
    //   4170: astore_1
    //   4171: aload_1
    //   4172: getfield 744	com/google/android/gms/internal/measurement/zzki:zzasw	Ljava/lang/Long;
    //   4175: invokevirtual 840	java/lang/Long:longValue	()J
    //   4178: aload 12
    //   4180: getfield 1014	com/google/android/gms/internal/measurement/zzkl:zzatg	Ljava/lang/Long;
    //   4183: invokevirtual 840	java/lang/Long:longValue	()J
    //   4186: lcmp
    //   4187: ifge +12 -> 4199
    //   4190: aload 12
    //   4192: aload_1
    //   4193: getfield 744	com/google/android/gms/internal/measurement/zzki:zzasw	Ljava/lang/Long;
    //   4196: putfield 1014	com/google/android/gms/internal/measurement/zzkl:zzatg	Ljava/lang/Long;
    //   4199: aload_1
    //   4200: getfield 744	com/google/android/gms/internal/measurement/zzki:zzasw	Ljava/lang/Long;
    //   4203: invokevirtual 840	java/lang/Long:longValue	()J
    //   4206: aload 12
    //   4208: getfield 1019	com/google/android/gms/internal/measurement/zzkl:zzath	Ljava/lang/Long;
    //   4211: invokevirtual 840	java/lang/Long:longValue	()J
    //   4214: lcmp
    //   4215: ifle +12 -> 4227
    //   4218: aload 12
    //   4220: aload_1
    //   4221: getfield 744	com/google/android/gms/internal/measurement/zzki:zzasw	Ljava/lang/Long;
    //   4224: putfield 1019	com/google/android/gms/internal/measurement/zzkl:zzath	Ljava/lang/Long;
    //   4227: iinc 16 1
    //   4230: goto -79 -> 4151
    //   4233: aload 4
    //   4235: getfield 610	com/google/android/gms/internal/measurement/zzgl$zza:zzans	Lcom/google/android/gms/internal/measurement/zzkl;
    //   4238: getfield 625	com/google/android/gms/internal/measurement/zzkl:zztd	Ljava/lang/String;
    //   4241: astore 11
    //   4243: aload_0
    //   4244: invokevirtual 566	com/google/android/gms/internal/measurement/zzgl:zzga	()Lcom/google/android/gms/internal/measurement/zzei;
    //   4247: aload 11
    //   4249: invokevirtual 1023	com/google/android/gms/internal/measurement/zzei:zzax	(Ljava/lang/String;)Lcom/google/android/gms/internal/measurement/zzeb;
    //   4252: astore 14
    //   4254: aload 14
    //   4256: ifnonnull +195 -> 4451
    //   4259: aload_0
    //   4260: invokevirtual 254	com/google/android/gms/internal/measurement/zzgl:zzgg	()Lcom/google/android/gms/internal/measurement/zzfg;
    //   4263: invokevirtual 401	com/google/android/gms/internal/measurement/zzfg:zzil	()Lcom/google/android/gms/internal/measurement/zzfi;
    //   4266: ldc_w 1025
    //   4269: aload 4
    //   4271: getfield 610	com/google/android/gms/internal/measurement/zzgl$zza:zzans	Lcom/google/android/gms/internal/measurement/zzkl;
    //   4274: getfield 625	com/google/android/gms/internal/measurement/zzkl:zztd	Ljava/lang/String;
    //   4277: invokestatic 557	com/google/android/gms/internal/measurement/zzfg:zzbh	(Ljava/lang/String;)Ljava/lang/Object;
    //   4280: invokevirtual 374	com/google/android/gms/internal/measurement/zzfi:zzg	(Ljava/lang/String;Ljava/lang/Object;)V
    //   4283: aload 12
    //   4285: getfield 621	com/google/android/gms/internal/measurement/zzkl:zzatd	[Lcom/google/android/gms/internal/measurement/zzki;
    //   4288: arraylength
    //   4289: ifle +67 -> 4356
    //   4292: aload_0
    //   4293: invokevirtual 512	com/google/android/gms/internal/measurement/zzgl:zzgd	()Lcom/google/android/gms/internal/measurement/zzgf;
    //   4296: aload 4
    //   4298: getfield 610	com/google/android/gms/internal/measurement/zzgl$zza:zzans	Lcom/google/android/gms/internal/measurement/zzkl;
    //   4301: getfield 625	com/google/android/gms/internal/measurement/zzkl:zztd	Ljava/lang/String;
    //   4304: invokevirtual 516	com/google/android/gms/internal/measurement/zzgf:zzbp	(Ljava/lang/String;)Lcom/google/android/gms/internal/measurement/zzkf;
    //   4307: astore_1
    //   4308: aload_1
    //   4309: ifnull +10 -> 4319
    //   4312: aload_1
    //   4313: getfield 1030	com/google/android/gms/internal/measurement/zzkf:zzask	Ljava/lang/Long;
    //   4316: ifnonnull +302 -> 4618
    //   4319: aload 4
    //   4321: getfield 610	com/google/android/gms/internal/measurement/zzgl$zza:zzans	Lcom/google/android/gms/internal/measurement/zzkl;
    //   4324: getfield 1033	com/google/android/gms/internal/measurement/zzkl:zzadh	Ljava/lang/String;
    //   4327: invokestatic 445	android/text/TextUtils:isEmpty	(Ljava/lang/CharSequence;)Z
    //   4330: ifeq +261 -> 4591
    //   4333: aload 12
    //   4335: ldc2_w 99
    //   4338: invokestatic 370	java/lang/Long:valueOf	(J)Ljava/lang/Long;
    //   4341: putfield 1036	com/google/android/gms/internal/measurement/zzkl:zzaua	Ljava/lang/Long;
    //   4344: aload_0
    //   4345: invokevirtual 566	com/google/android/gms/internal/measurement/zzgl:zzga	()Lcom/google/android/gms/internal/measurement/zzei;
    //   4348: aload 12
    //   4350: iload 18
    //   4352: invokevirtual 1039	com/google/android/gms/internal/measurement/zzei:zza	(Lcom/google/android/gms/internal/measurement/zzkl;Z)Z
    //   4355: pop
    //   4356: aload_0
    //   4357: invokevirtual 566	com/google/android/gms/internal/measurement/zzgl:zzga	()Lcom/google/android/gms/internal/measurement/zzei;
    //   4360: astore_1
    //   4361: aload 4
    //   4363: getfield 1042	com/google/android/gms/internal/measurement/zzgl$zza:zzant	Ljava/util/List;
    //   4366: astore 12
    //   4368: aload 12
    //   4370: invokestatic 93	com/google/android/gms/common/internal/Preconditions:checkNotNull	(Ljava/lang/Object;)Ljava/lang/Object;
    //   4373: pop
    //   4374: aload_1
    //   4375: invokevirtual 310	com/google/android/gms/internal/measurement/zzhj:zzab	()V
    //   4378: aload_1
    //   4379: invokevirtual 542	com/google/android/gms/internal/measurement/zzhk:zzch	()V
    //   4382: new 286	java/lang/StringBuilder
    //   4385: astore 14
    //   4387: aload 14
    //   4389: ldc_w 1044
    //   4392: invokespecial 1045	java/lang/StringBuilder:<init>	(Ljava/lang/String;)V
    //   4395: iconst_0
    //   4396: istore 16
    //   4398: iload 16
    //   4400: aload 12
    //   4402: invokeinterface 613 1 0
    //   4407: if_icmpge +223 -> 4630
    //   4410: iload 16
    //   4412: ifeq +12 -> 4424
    //   4415: aload 14
    //   4417: ldc_w 1047
    //   4420: invokevirtual 299	java/lang/StringBuilder:append	(Ljava/lang/String;)Ljava/lang/StringBuilder;
    //   4423: pop
    //   4424: aload 14
    //   4426: aload 12
    //   4428: iload 16
    //   4430: invokeinterface 631 2 0
    //   4435: checkcast 367	java/lang/Long
    //   4438: invokevirtual 840	java/lang/Long:longValue	()J
    //   4441: invokevirtual 1050	java/lang/StringBuilder:append	(J)Ljava/lang/StringBuilder;
    //   4444: pop
    //   4445: iinc 16 1
    //   4448: goto -50 -> 4398
    //   4451: aload 12
    //   4453: getfield 621	com/google/android/gms/internal/measurement/zzkl:zzatd	[Lcom/google/android/gms/internal/measurement/zzki;
    //   4456: arraylength
    //   4457: ifle -174 -> 4283
    //   4460: aload 14
    //   4462: invokevirtual 1053	com/google/android/gms/internal/measurement/zzeb:zzgn	()J
    //   4465: lstore_2
    //   4466: lload_2
    //   4467: lconst_0
    //   4468: lcmp
    //   4469: ifeq +112 -> 4581
    //   4472: lload_2
    //   4473: invokestatic 370	java/lang/Long:valueOf	(J)Ljava/lang/Long;
    //   4476: astore_1
    //   4477: aload 12
    //   4479: aload_1
    //   4480: putfield 1056	com/google/android/gms/internal/measurement/zzkl:zzatj	Ljava/lang/Long;
    //   4483: aload 14
    //   4485: invokevirtual 1059	com/google/android/gms/internal/measurement/zzeb:zzgm	()J
    //   4488: lstore 7
    //   4490: lload 7
    //   4492: lconst_0
    //   4493: lcmp
    //   4494: ifne +326 -> 4820
    //   4497: lload_2
    //   4498: lconst_0
    //   4499: lcmp
    //   4500: ifeq +86 -> 4586
    //   4503: lload_2
    //   4504: invokestatic 370	java/lang/Long:valueOf	(J)Ljava/lang/Long;
    //   4507: astore_1
    //   4508: aload 12
    //   4510: aload_1
    //   4511: putfield 1062	com/google/android/gms/internal/measurement/zzkl:zzati	Ljava/lang/Long;
    //   4514: aload 14
    //   4516: invokevirtual 1065	com/google/android/gms/internal/measurement/zzeb:zzgv	()V
    //   4519: aload 12
    //   4521: aload 14
    //   4523: invokevirtual 1068	com/google/android/gms/internal/measurement/zzeb:zzgs	()J
    //   4526: l2i
    //   4527: invokestatic 408	java/lang/Integer:valueOf	(I)Ljava/lang/Integer;
    //   4530: putfield 1072	com/google/android/gms/internal/measurement/zzkl:zzatt	Ljava/lang/Integer;
    //   4533: aload 14
    //   4535: aload 12
    //   4537: getfield 1014	com/google/android/gms/internal/measurement/zzkl:zzatg	Ljava/lang/Long;
    //   4540: invokevirtual 840	java/lang/Long:longValue	()J
    //   4543: invokevirtual 1075	com/google/android/gms/internal/measurement/zzeb:zzm	(J)V
    //   4546: aload 14
    //   4548: aload 12
    //   4550: getfield 1019	com/google/android/gms/internal/measurement/zzkl:zzath	Ljava/lang/Long;
    //   4553: invokevirtual 840	java/lang/Long:longValue	()J
    //   4556: invokevirtual 1077	com/google/android/gms/internal/measurement/zzeb:zzn	(J)V
    //   4559: aload 12
    //   4561: aload 14
    //   4563: invokevirtual 1080	com/google/android/gms/internal/measurement/zzeb:zzhd	()Ljava/lang/String;
    //   4566: putfield 1083	com/google/android/gms/internal/measurement/zzkl:zzaef	Ljava/lang/String;
    //   4569: aload_0
    //   4570: invokevirtual 566	com/google/android/gms/internal/measurement/zzgl:zzga	()Lcom/google/android/gms/internal/measurement/zzei;
    //   4573: aload 14
    //   4575: invokevirtual 1085	com/google/android/gms/internal/measurement/zzei:zza	(Lcom/google/android/gms/internal/measurement/zzeb;)V
    //   4578: goto -295 -> 4283
    //   4581: aconst_null
    //   4582: astore_1
    //   4583: goto -106 -> 4477
    //   4586: aconst_null
    //   4587: astore_1
    //   4588: goto -80 -> 4508
    //   4591: aload_0
    //   4592: invokevirtual 254	com/google/android/gms/internal/measurement/zzgl:zzgg	()Lcom/google/android/gms/internal/measurement/zzfg;
    //   4595: invokevirtual 257	com/google/android/gms/internal/measurement/zzfg:zzin	()Lcom/google/android/gms/internal/measurement/zzfi;
    //   4598: ldc_w 1087
    //   4601: aload 4
    //   4603: getfield 610	com/google/android/gms/internal/measurement/zzgl$zza:zzans	Lcom/google/android/gms/internal/measurement/zzkl;
    //   4606: getfield 625	com/google/android/gms/internal/measurement/zzkl:zztd	Ljava/lang/String;
    //   4609: invokestatic 557	com/google/android/gms/internal/measurement/zzfg:zzbh	(Ljava/lang/String;)Ljava/lang/Object;
    //   4612: invokevirtual 374	com/google/android/gms/internal/measurement/zzfi:zzg	(Ljava/lang/String;Ljava/lang/Object;)V
    //   4615: goto -271 -> 4344
    //   4618: aload 12
    //   4620: aload_1
    //   4621: getfield 1030	com/google/android/gms/internal/measurement/zzkf:zzask	Ljava/lang/Long;
    //   4624: putfield 1036	com/google/android/gms/internal/measurement/zzkl:zzaua	Ljava/lang/Long;
    //   4627: goto -283 -> 4344
    //   4630: aload 14
    //   4632: ldc_w 1089
    //   4635: invokevirtual 299	java/lang/StringBuilder:append	(Ljava/lang/String;)Ljava/lang/StringBuilder;
    //   4638: pop
    //   4639: aload_1
    //   4640: invokevirtual 576	com/google/android/gms/internal/measurement/zzei:getWritableDatabase	()Landroid/database/sqlite/SQLiteDatabase;
    //   4643: ldc_w 724
    //   4646: aload 14
    //   4648: invokevirtual 303	java/lang/StringBuilder:toString	()Ljava/lang/String;
    //   4651: aconst_null
    //   4652: invokevirtual 1093	android/database/sqlite/SQLiteDatabase:delete	(Ljava/lang/String;Ljava/lang/String;[Ljava/lang/String;)I
    //   4655: istore 16
    //   4657: iload 16
    //   4659: aload 12
    //   4661: invokeinterface 613 1 0
    //   4666: if_icmpeq +31 -> 4697
    //   4669: aload_1
    //   4670: invokevirtual 232	com/google/android/gms/internal/measurement/zzhj:zzgg	()Lcom/google/android/gms/internal/measurement/zzfg;
    //   4673: invokevirtual 401	com/google/android/gms/internal/measurement/zzfg:zzil	()Lcom/google/android/gms/internal/measurement/zzfi;
    //   4676: ldc_w 1095
    //   4679: iload 16
    //   4681: invokestatic 408	java/lang/Integer:valueOf	(I)Ljava/lang/Integer;
    //   4684: aload 12
    //   4686: invokeinterface 613 1 0
    //   4691: invokestatic 408	java/lang/Integer:valueOf	(I)Ljava/lang/Integer;
    //   4694: invokevirtual 412	com/google/android/gms/internal/measurement/zzfi:zze	(Ljava/lang/String;Ljava/lang/Object;Ljava/lang/Object;)V
    //   4697: aload_0
    //   4698: invokevirtual 566	com/google/android/gms/internal/measurement/zzgl:zzga	()Lcom/google/android/gms/internal/measurement/zzei;
    //   4701: astore_1
    //   4702: aload_1
    //   4703: invokevirtual 576	com/google/android/gms/internal/measurement/zzei:getWritableDatabase	()Landroid/database/sqlite/SQLiteDatabase;
    //   4706: astore 12
    //   4708: aload 12
    //   4710: ldc_w 1097
    //   4713: iconst_2
    //   4714: anewarray 280	java/lang/String
    //   4717: dup
    //   4718: iconst_0
    //   4719: aload 11
    //   4721: aastore
    //   4722: dup
    //   4723: iconst_1
    //   4724: aload 11
    //   4726: aastore
    //   4727: invokevirtual 1101	android/database/sqlite/SQLiteDatabase:execSQL	(Ljava/lang/String;[Ljava/lang/Object;)V
    //   4730: aload_0
    //   4731: invokevirtual 566	com/google/android/gms/internal/measurement/zzgl:zzga	()Lcom/google/android/gms/internal/measurement/zzei;
    //   4734: invokevirtual 1104	com/google/android/gms/internal/measurement/zzei:setTransactionSuccessful	()V
    //   4737: aload_0
    //   4738: invokevirtual 566	com/google/android/gms/internal/measurement/zzgl:zzga	()Lcom/google/android/gms/internal/measurement/zzei;
    //   4741: invokevirtual 689	com/google/android/gms/internal/measurement/zzei:endTransaction	()V
    //   4744: iconst_1
    //   4745: istore 18
    //   4747: iload 18
    //   4749: ireturn
    //   4750: astore 12
    //   4752: aload_1
    //   4753: invokevirtual 232	com/google/android/gms/internal/measurement/zzhj:zzgg	()Lcom/google/android/gms/internal/measurement/zzfg;
    //   4756: invokevirtual 401	com/google/android/gms/internal/measurement/zzfg:zzil	()Lcom/google/android/gms/internal/measurement/zzfi;
    //   4759: ldc_w 1106
    //   4762: aload 11
    //   4764: invokestatic 557	com/google/android/gms/internal/measurement/zzfg:zzbh	(Ljava/lang/String;)Ljava/lang/Object;
    //   4767: aload 12
    //   4769: invokevirtual 412	com/google/android/gms/internal/measurement/zzfi:zze	(Ljava/lang/String;Ljava/lang/Object;Ljava/lang/Object;)V
    //   4772: goto -42 -> 4730
    //   4775: aload_0
    //   4776: invokevirtual 566	com/google/android/gms/internal/measurement/zzgl:zzga	()Lcom/google/android/gms/internal/measurement/zzei;
    //   4779: invokevirtual 1104	com/google/android/gms/internal/measurement/zzei:setTransactionSuccessful	()V
    //   4782: aload_0
    //   4783: invokevirtual 566	com/google/android/gms/internal/measurement/zzgl:zzga	()Lcom/google/android/gms/internal/measurement/zzei;
    //   4786: invokevirtual 689	com/google/android/gms/internal/measurement/zzei:endTransaction	()V
    //   4789: iconst_0
    //   4790: istore 18
    //   4792: goto -45 -> 4747
    //   4795: astore 11
    //   4797: goto -3106 -> 1691
    //   4800: astore 14
    //   4802: goto -3346 -> 1456
    //   4805: astore 14
    //   4807: aload 11
    //   4809: astore_1
    //   4810: aload 12
    //   4812: astore 11
    //   4814: aload_1
    //   4815: astore 12
    //   4817: goto -3361 -> 1456
    //   4820: lload 7
    //   4822: lstore_2
    //   4823: goto -326 -> 4497
    //   4826: goto -1199 -> 3627
    //   4829: iconst_1
    //   4830: istore 16
    //   4832: goto -1485 -> 3347
    //   4835: goto -2343 -> 2492
    //   4838: goto -2475 -> 2363
    //   4841: iconst_1
    //   4842: istore 27
    //   4844: goto -2634 -> 2210
    //   4847: goto -3009 -> 1838
    //   4850: goto -4311 -> 539
    // Local variable table:
    //   start	length	slot	name	signature
    //   0	4853	0	this	zzgl
    //   0	4853	1	paramString	String
    //   0	4853	2	paramLong	long
    //   10	4592	4	localzza	zza
    //   23	3988	5	localObject1	Object
    //   26	3726	6	localObject2	Object
    //   32	4789	7	l	long
    //   51	4022	9	localHashMap	java.util.HashMap
    //   54	4006	10	localObject3	Object
    //   61	1587	11	localObject4	Object
    //   1689	13	11	localObject5	Object
    //   1810	2953	11	localObject6	Object
    //   4795	13	11	localObject7	Object
    //   4812	1	11	localObject8	Object
    //   65	4644	12	localObject9	Object
    //   4750	61	12	localSQLiteException1	android.database.sqlite.SQLiteException
    //   4815	1	12	str	String
    //   72	1189	13	localSQLiteDatabase	android.database.sqlite.SQLiteDatabase
    //   131	1286	14	localObject10	Object
    //   1444	32	14	localSQLiteException2	android.database.sqlite.SQLiteException
    //   1518	85	14	localObject11	Object
    //   1631	955	14	localIOException1	java.io.IOException
    //   3051	1596	14	localObject12	Object
    //   4800	1	14	localSQLiteException3	android.database.sqlite.SQLiteException
    //   4805	1	14	localSQLiteException4	android.database.sqlite.SQLiteException
    //   145	1151	15	localObject13	Object
    //   1362	73	15	localIOException2	java.io.IOException
    //   1439	1608	15	localObject14	Object
    //   166	4665	16	i	int
    //   182	717	17	localStringBuilder	StringBuilder
    //   266	4525	18	bool1	boolean
    //   359	2313	19	bool2	boolean
    //   362	2874	20	j	int
    //   492	3570	21	k	int
    //   1736	494	22	bool3	boolean
    //   1750	824	23	bool4	boolean
    //   1764	1280	24	m	int
    //   1794	10	25	n	int
    //   1797	2207	26	i1	int
    //   2110	2733	27	bool5	boolean
    // Exception table:
    //   from	to	target	type
    //   7	25	765	finally
    //   28	50	765	finally
    //   278	285	765	finally
    //   285	306	765	finally
    //   317	342	765	finally
    //   347	361	765	finally
    //   364	491	765	finally
    //   499	539	765	finally
    //   755	762	765	finally
    //   957	964	765	finally
    //   1352	1359	765	finally
    //   1397	1404	765	finally
    //   1485	1492	765	finally
    //   1621	1628	765	finally
    //   1679	1686	765	finally
    //   1695	1701	765	finally
    //   1701	1704	765	finally
    //   1716	1738	765	finally
    //   1743	1748	765	finally
    //   1752	1763	765	finally
    //   1769	1786	765	finally
    //   1786	1796	765	finally
    //   1812	1835	765	finally
    //   1844	1867	765	finally
    //   1883	1968	765	finally
    //   1973	2058	765	finally
    //   2058	2105	765	finally
    //   2112	2155	765	finally
    //   2160	2173	765	finally
    //   2173	2200	765	finally
    //   2200	2206	765	finally
    //   2214	2225	765	finally
    //   2238	2312	765	finally
    //   2317	2329	765	finally
    //   2346	2360	765	finally
    //   2375	2389	765	finally
    //   2404	2428	765	finally
    //   2437	2468	765	finally
    //   2468	2492	765	finally
    //   2492	2498	765	finally
    //   2521	2538	765	finally
    //   2545	2569	765	finally
    //   2580	2597	765	finally
    //   2601	2625	765	finally
    //   2628	2635	765	finally
    //   2638	2671	765	finally
    //   2676	2692	765	finally
    //   2696	2703	765	finally
    //   2703	2735	765	finally
    //   2735	2782	765	finally
    //   2792	2833	765	finally
    //   2841	2884	765	finally
    //   2890	2916	765	finally
    //   2916	3012	765	finally
    //   3015	3036	765	finally
    //   3053	3099	765	finally
    //   3107	3136	765	finally
    //   3136	3180	765	finally
    //   3180	3222	765	finally
    //   3245	3288	765	finally
    //   3297	3312	765	finally
    //   3325	3347	765	finally
    //   3352	3375	765	finally
    //   3391	3403	765	finally
    //   3419	3452	765	finally
    //   3452	3472	765	finally
    //   3472	3492	765	finally
    //   3516	3532	765	finally
    //   3536	3558	765	finally
    //   3566	3627	765	finally
    //   3627	3645	765	finally
    //   3653	3660	765	finally
    //   3683	3705	765	finally
    //   3709	3716	765	finally
    //   3716	3738	765	finally
    //   3751	3788	765	finally
    //   3804	3826	765	finally
    //   3826	3852	765	finally
    //   3859	3936	765	finally
    //   3952	3977	765	finally
    //   3977	4003	765	finally
    //   4010	4039	765	finally
    //   4046	4072	765	finally
    //   4072	4086	765	finally
    //   4086	4123	765	finally
    //   4126	4148	765	finally
    //   4151	4199	765	finally
    //   4199	4227	765	finally
    //   4233	4254	765	finally
    //   4259	4283	765	finally
    //   4283	4308	765	finally
    //   4312	4319	765	finally
    //   4319	4344	765	finally
    //   4344	4356	765	finally
    //   4356	4395	765	finally
    //   4398	4410	765	finally
    //   4415	4424	765	finally
    //   4424	4445	765	finally
    //   4451	4466	765	finally
    //   4472	4477	765	finally
    //   4477	4490	765	finally
    //   4503	4508	765	finally
    //   4508	4578	765	finally
    //   4591	4615	765	finally
    //   4618	4627	765	finally
    //   4630	4697	765	finally
    //   4697	4708	765	finally
    //   4708	4730	765	finally
    //   4730	4737	765	finally
    //   4752	4772	765	finally
    //   4775	4782	765	finally
    //   1113	1121	1362	java/io/IOException
    //   662	707	1444	android/database/sqlite/SQLiteException
    //   714	724	1444	android/database/sqlite/SQLiteException
    //   731	750	1444	android/database/sqlite/SQLiteException
    //   1054	1064	1444	android/database/sqlite/SQLiteException
    //   1071	1082	1444	android/database/sqlite/SQLiteException
    //   1089	1094	1444	android/database/sqlite/SQLiteException
    //   1101	1106	1444	android/database/sqlite/SQLiteException
    //   1113	1121	1444	android/database/sqlite/SQLiteException
    //   1128	1138	1444	android/database/sqlite/SQLiteException
    //   1145	1164	1444	android/database/sqlite/SQLiteException
    //   1171	1178	1444	android/database/sqlite/SQLiteException
    //   1185	1194	1444	android/database/sqlite/SQLiteException
    //   1215	1221	1444	android/database/sqlite/SQLiteException
    //   1240	1249	1444	android/database/sqlite/SQLiteException
    //   1260	1308	1444	android/database/sqlite/SQLiteException
    //   1371	1392	1444	android/database/sqlite/SQLiteException
    //   1419	1425	1444	android/database/sqlite/SQLiteException
    //   1553	1561	1631	java/io/IOException
    //   67	74	1689	finally
    //   85	92	1689	finally
    //   112	133	1689	finally
    //   158	168	1689	finally
    //   179	184	1689	finally
    //   195	206	1689	finally
    //   217	248	1689	finally
    //   259	268	1689	finally
    //   556	569	1689	finally
    //   591	601	1689	finally
    //   612	622	1689	finally
    //   633	640	1689	finally
    //   795	813	1689	finally
    //   838	848	1689	finally
    //   859	864	1689	finally
    //   875	885	1689	finally
    //   896	927	1689	finally
    //   938	947	1689	finally
    //   978	988	1689	finally
    //   1010	1020	1689	finally
    //   1031	1038	1689	finally
    //   1315	1325	1689	finally
    //   1328	1347	1689	finally
    //   1459	1480	1689	finally
    //   1498	1507	1689	finally
    //   1510	1520	1689	finally
    //   1523	1534	1689	finally
    //   1537	1542	1689	finally
    //   1545	1550	1689	finally
    //   1553	1561	1689	finally
    //   1564	1577	1689	finally
    //   1580	1596	1689	finally
    //   1599	1611	1689	finally
    //   1636	1657	1689	finally
    //   1660	1669	1689	finally
    //   4708	4730	4750	android/database/sqlite/SQLiteException
    //   662	707	4795	finally
    //   714	724	4795	finally
    //   731	750	4795	finally
    //   1054	1064	4795	finally
    //   1071	1082	4795	finally
    //   1089	1094	4795	finally
    //   1101	1106	4795	finally
    //   1113	1121	4795	finally
    //   1128	1138	4795	finally
    //   1145	1164	4795	finally
    //   1171	1178	4795	finally
    //   1185	1194	4795	finally
    //   1215	1221	4795	finally
    //   1240	1249	4795	finally
    //   1260	1308	4795	finally
    //   1371	1392	4795	finally
    //   1419	1425	4795	finally
    //   67	74	4800	android/database/sqlite/SQLiteException
    //   85	92	4800	android/database/sqlite/SQLiteException
    //   112	133	4800	android/database/sqlite/SQLiteException
    //   158	168	4800	android/database/sqlite/SQLiteException
    //   179	184	4800	android/database/sqlite/SQLiteException
    //   195	206	4800	android/database/sqlite/SQLiteException
    //   217	248	4800	android/database/sqlite/SQLiteException
    //   259	268	4800	android/database/sqlite/SQLiteException
    //   556	569	4800	android/database/sqlite/SQLiteException
    //   591	601	4800	android/database/sqlite/SQLiteException
    //   612	622	4800	android/database/sqlite/SQLiteException
    //   633	640	4800	android/database/sqlite/SQLiteException
    //   795	813	4800	android/database/sqlite/SQLiteException
    //   838	848	4800	android/database/sqlite/SQLiteException
    //   859	864	4800	android/database/sqlite/SQLiteException
    //   875	885	4800	android/database/sqlite/SQLiteException
    //   896	927	4800	android/database/sqlite/SQLiteException
    //   938	947	4800	android/database/sqlite/SQLiteException
    //   978	988	4800	android/database/sqlite/SQLiteException
    //   1010	1020	4800	android/database/sqlite/SQLiteException
    //   1031	1038	4800	android/database/sqlite/SQLiteException
    //   1315	1325	4805	android/database/sqlite/SQLiteException
    //   1328	1347	4805	android/database/sqlite/SQLiteException
    //   1498	1507	4805	android/database/sqlite/SQLiteException
    //   1510	1520	4805	android/database/sqlite/SQLiteException
    //   1523	1534	4805	android/database/sqlite/SQLiteException
    //   1537	1542	4805	android/database/sqlite/SQLiteException
    //   1545	1550	4805	android/database/sqlite/SQLiteException
    //   1553	1561	4805	android/database/sqlite/SQLiteException
    //   1564	1577	4805	android/database/sqlite/SQLiteException
    //   1580	1596	4805	android/database/sqlite/SQLiteException
    //   1599	1611	4805	android/database/sqlite/SQLiteException
    //   1636	1657	4805	android/database/sqlite/SQLiteException
    //   1660	1669	4805	android/database/sqlite/SQLiteException
  }
  
  static void zzfq()
  {
    throw new IllegalStateException("Unexpected call on client side");
  }
  
  public static zzgl zzg(Context paramContext)
  {
    Preconditions.checkNotNull(paramContext);
    Preconditions.checkNotNull(paramContext.getApplicationContext());
    if (zzamc == null) {}
    try
    {
      if (zzamc == null)
      {
        zzhl localzzhl = new com/google/android/gms/internal/measurement/zzhl;
        localzzhl.<init>(paramContext);
        paramContext = new com/google/android/gms/internal/measurement/zzgl;
        paramContext.<init>(localzzhl);
        zzamc = paramContext;
      }
      return zzamc;
    }
    finally {}
  }
  
  private final zzfp zzjr()
  {
    if (this.zzamw == null) {
      throw new IllegalStateException("Network broadcast receiver not created");
    }
    return this.zzamw;
  }
  
  private final zzjq zzjs()
  {
    zza(this.zzamx);
    return this.zzamx;
  }
  
  private final long zzjv()
  {
    long l1 = this.zzrj.currentTimeMillis();
    zzfr localzzfr = zzgh();
    localzzfr.zzch();
    localzzfr.zzab();
    long l2 = localzzfr.zzajx.get();
    long l3 = l2;
    if (l2 == 0L)
    {
      l3 = 1L + localzzfr.zzgc().zzku().nextInt(86400000);
      localzzfr.zzajx.set(l3);
    }
    return (l3 + l1) / 1000L / 60L / 60L / 24L;
  }
  
  private final boolean zzjx()
  {
    zzgf().zzab();
    zzch();
    if ((zzga().zzhs()) || (!TextUtils.isEmpty(zzga().zzhn()))) {}
    for (boolean bool = true;; bool = false) {
      return bool;
    }
  }
  
  private final void zzjy()
  {
    zzgf().zzab();
    zzch();
    if (!zzkb()) {}
    long l1;
    for (;;)
    {
      return;
      if (this.zzank > 0L)
      {
        l1 = 3600000L - Math.abs(this.zzrj.elapsedRealtime() - this.zzank);
        if (l1 > 0L)
        {
          zzgg().zzir().zzg("Upload has been suspended. Will update scheduling later in approximately ms", Long.valueOf(l1));
          zzjr().unregister();
          zzjs().cancel();
        }
        else
        {
          this.zzank = 0L;
        }
      }
      else if ((!zzjk()) || (!zzjx()))
      {
        zzgg().zzir().log("Nothing to upload or uploading impossible");
        zzjr().unregister();
        zzjs().cancel();
      }
      else
      {
        l2 = this.zzrj.currentTimeMillis();
        l3 = Math.max(0L, ((Long)zzew.zzahl.get()).longValue());
        int i;
        label190:
        label240:
        long l4;
        long l5;
        long l6;
        if ((zzga().zzht()) || (zzga().zzho()))
        {
          i = 1;
          if (i == 0) {
            break label354;
          }
          String str = this.zzamd.zzhl();
          if ((TextUtils.isEmpty(str)) || (".none.".equals(str))) {
            break label334;
          }
          l1 = Math.max(0L, ((Long)zzew.zzahg.get()).longValue());
          l4 = zzgh().zzajt.get();
          l5 = zzgh().zzaju.get();
          l6 = Math.max(zzga().zzhq(), zzga().zzhr());
          if (l6 != 0L) {
            break label374;
          }
          l1 = 0L;
        }
        for (;;)
        {
          if (l1 != 0L) {
            break label568;
          }
          zzgg().zzir().log("Next upload time is 0");
          zzjr().unregister();
          zzjs().cancel();
          break;
          i = 0;
          break label190;
          label334:
          l1 = Math.max(0L, ((Long)zzew.zzahf.get()).longValue());
          break label240;
          label354:
          l1 = Math.max(0L, ((Long)zzew.zzahe.get()).longValue());
          break label240;
          label374:
          l6 = l2 - Math.abs(l6 - l2);
          l4 = Math.abs(l4 - l2);
          l5 = l2 - Math.abs(l5 - l2);
          l4 = Math.max(l2 - l4, l5);
          l2 = l6 + l3;
          l3 = l2;
          if (i != 0)
          {
            l3 = l2;
            if (l4 > 0L) {
              l3 = Math.min(l6, l4) + l1;
            }
          }
          if (!zzgc().zza(l4, l1)) {
            l3 = l4 + l1;
          }
          l1 = l3;
          if (l5 != 0L)
          {
            l1 = l3;
            if (l5 >= l6)
            {
              for (i = 0;; i++)
              {
                if (i >= Math.min(20, Math.max(0, ((Integer)zzew.zzahn.get()).intValue()))) {
                  break label563;
                }
                l3 += (1L << i) * Math.max(0L, ((Long)zzew.zzahm.get()).longValue());
                l1 = l3;
                if (l3 > l5) {
                  break;
                }
              }
              label563:
              l1 = 0L;
            }
          }
        }
        label568:
        if (zzjq().zzew()) {
          break;
        }
        zzgg().zzir().log("No network");
        zzjr().zzet();
        zzjs().cancel();
      }
    }
    long l2 = zzgh().zzajv.get();
    long l3 = Math.max(0L, ((Long)zzew.zzahc.get()).longValue());
    if (!zzgc().zza(l2, l3)) {
      l1 = Math.max(l1, l3 + l2);
    }
    for (;;)
    {
      zzjr().unregister();
      l3 = l1 - this.zzrj.currentTimeMillis();
      l1 = l3;
      if (l3 <= 0L)
      {
        l1 = Math.max(0L, ((Long)zzew.zzahh.get()).longValue());
        zzgh().zzajt.set(this.zzrj.currentTimeMillis());
      }
      zzgg().zzir().zzg("Upload scheduled in approximately ms", Long.valueOf(l1));
      zzjs().zzh(l1);
      break;
    }
  }
  
  private final boolean zzkb()
  {
    zzgf().zzab();
    zzch();
    if (this.zzana) {}
    for (boolean bool = true;; bool = false) {
      return bool;
    }
  }
  
  private final void zzkc()
  {
    zzgf().zzab();
    if ((this.zzanl) || (this.zzanm) || (this.zzann)) {
      zzgg().zzir().zzd("Not stopping services. fetch, network, upload", Boolean.valueOf(this.zzanl), Boolean.valueOf(this.zzanm), Boolean.valueOf(this.zzann));
    }
    for (;;)
    {
      return;
      zzgg().zzir().log("Stopping uploading service(s)");
      if (this.zzang != null)
      {
        Iterator localIterator = this.zzang.iterator();
        while (localIterator.hasNext()) {
          ((Runnable)localIterator.next()).run();
        }
        this.zzang.clear();
      }
    }
  }
  
  public final Context getContext()
  {
    return this.zzqs;
  }
  
  public final boolean isEnabled()
  {
    boolean bool1 = false;
    boolean bool2 = false;
    zzgf().zzab();
    zzch();
    if (this.zzamd.zzhi()) {
      return bool2;
    }
    Boolean localBoolean = this.zzamd.zzas("firebase_analytics_collection_enabled");
    if (localBoolean != null) {
      bool2 = localBoolean.booleanValue();
    }
    for (;;)
    {
      bool2 = zzgh().zzg(bool2);
      break;
      bool2 = bool1;
      if (!GoogleServices.isMeasurementExplicitlyDisabled()) {
        bool2 = true;
      }
    }
  }
  
  protected final void start()
  {
    boolean bool1 = false;
    zzgf().zzab();
    zzga().zzhp();
    if (zzgh().zzajt.get() == 0L) {
      zzgh().zzajt.set(this.zzrj.currentTimeMillis());
    }
    if (Long.valueOf(zzgh().zzajy.get()).longValue() == 0L)
    {
      zzgg().zzir().zzg("Persisting first open", Long.valueOf(this.zzaeh));
      zzgh().zzajy.set(this.zzaeh);
    }
    if (!zzjk())
    {
      if (isEnabled())
      {
        if (!zzgc().zzx("android.permission.INTERNET")) {
          zzgg().zzil().log("App is missing INTERNET permission");
        }
        if (!zzgc().zzx("android.permission.ACCESS_NETWORK_STATE")) {
          zzgg().zzil().log("App is missing ACCESS_NETWORK_STATE permission");
        }
        if (!Wrappers.packageManager(this.zzqs).isCallerInstantApp())
        {
          if (!zzgb.zza(this.zzqs)) {
            zzgg().zzil().log("AppMeasurementReceiver not registered/enabled");
          }
          if (!zzjf.zza(this.zzqs, false)) {
            zzgg().zzil().log("AppMeasurementService not registered/enabled");
          }
        }
        zzgg().zzil().log("Uploading is not possible. App measurement disabled");
      }
      zzjy();
      return;
    }
    Object localObject;
    if (!TextUtils.isEmpty(zzfv().getGmpAppId()))
    {
      localObject = zzgh().zziv();
      if (localObject != null) {
        break label404;
      }
      zzgh().zzbl(zzfv().getGmpAppId());
    }
    for (;;)
    {
      zzfu().zzbm(zzgh().zzaka.zzjc());
      if (TextUtils.isEmpty(zzfv().getGmpAppId())) {
        break;
      }
      boolean bool2 = isEnabled();
      if ((!zzgh().zzjb()) && (!this.zzamd.zzhi()))
      {
        localObject = zzgh();
        if (!bool2) {
          bool1 = true;
        }
        ((zzfr)localObject).zzh(bool1);
      }
      if ((!this.zzamd.zzav(zzfv().zzah())) || (bool2)) {
        zzfu().zzkj();
      }
      zzfx().zza(new AtomicReference());
      break;
      label404:
      if (!((String)localObject).equals(zzfv().getGmpAppId()))
      {
        zzgg().zzip().log("Rechecking which service to use due to a GMP App Id change");
        zzgh().zziy();
        this.zzamt.disconnect();
        this.zzamt.zzdf();
        zzgh().zzbl(zzfv().getGmpAppId());
        zzgh().zzajy.set(this.zzaeh);
        zzgh().zzaka.zzbn(null);
      }
    }
  }
  
  /* Error */
  protected final void zza(int paramInt, Throwable paramThrowable, byte[] paramArrayOfByte, String paramString)
  {
    // Byte code:
    //   0: aload_0
    //   1: invokevirtual 307	com/google/android/gms/internal/measurement/zzgl:zzgf	()Lcom/google/android/gms/internal/measurement/zzgg;
    //   4: invokevirtual 310	com/google/android/gms/internal/measurement/zzhj:zzab	()V
    //   7: aload_0
    //   8: invokevirtual 1150	com/google/android/gms/internal/measurement/zzgl:zzch	()V
    //   11: aload_3
    //   12: astore 5
    //   14: aload_3
    //   15: ifnonnull +8 -> 23
    //   18: iconst_0
    //   19: newarray <illegal type>
    //   21: astore 5
    //   23: aload_0
    //   24: getfield 1425	com/google/android/gms/internal/measurement/zzgl:zzanf	Ljava/util/List;
    //   27: astore_3
    //   28: aload_0
    //   29: aconst_null
    //   30: putfield 1425	com/google/android/gms/internal/measurement/zzgl:zzanf	Ljava/util/List;
    //   33: iload_1
    //   34: sipush 200
    //   37: if_icmpeq +10 -> 47
    //   40: iload_1
    //   41: sipush 204
    //   44: if_icmpne +318 -> 362
    //   47: aload_2
    //   48: ifnonnull +314 -> 362
    //   51: aload_0
    //   52: invokevirtual 1129	com/google/android/gms/internal/measurement/zzgl:zzgh	()Lcom/google/android/gms/internal/measurement/zzfr;
    //   55: getfield 1210	com/google/android/gms/internal/measurement/zzfr:zzajt	Lcom/google/android/gms/internal/measurement/zzfu;
    //   58: aload_0
    //   59: getfield 110	com/google/android/gms/internal/measurement/zzgl:zzrj	Lcom/google/android/gms/common/util/Clock;
    //   62: invokeinterface 116 1 0
    //   67: invokevirtual 1142	com/google/android/gms/internal/measurement/zzfu:set	(J)V
    //   70: aload_0
    //   71: invokevirtual 1129	com/google/android/gms/internal/measurement/zzgl:zzgh	()Lcom/google/android/gms/internal/measurement/zzfr;
    //   74: getfield 1213	com/google/android/gms/internal/measurement/zzfr:zzaju	Lcom/google/android/gms/internal/measurement/zzfu;
    //   77: lconst_0
    //   78: invokevirtual 1142	com/google/android/gms/internal/measurement/zzfu:set	(J)V
    //   81: aload_0
    //   82: invokespecial 1363	com/google/android/gms/internal/measurement/zzgl:zzjy	()V
    //   85: aload_0
    //   86: invokevirtual 254	com/google/android/gms/internal/measurement/zzgl:zzgg	()Lcom/google/android/gms/internal/measurement/zzfg;
    //   89: invokevirtual 236	com/google/android/gms/internal/measurement/zzfg:zzir	()Lcom/google/android/gms/internal/measurement/zzfi;
    //   92: ldc_w 1427
    //   95: iload_1
    //   96: invokestatic 408	java/lang/Integer:valueOf	(I)Ljava/lang/Integer;
    //   99: aload 5
    //   101: arraylength
    //   102: invokestatic 408	java/lang/Integer:valueOf	(I)Ljava/lang/Integer;
    //   105: invokevirtual 412	com/google/android/gms/internal/measurement/zzfi:zze	(Ljava/lang/String;Ljava/lang/Object;Ljava/lang/Object;)V
    //   108: aload_0
    //   109: invokevirtual 566	com/google/android/gms/internal/measurement/zzgl:zzga	()Lcom/google/android/gms/internal/measurement/zzei;
    //   112: invokevirtual 569	com/google/android/gms/internal/measurement/zzei:beginTransaction	()V
    //   115: aload_3
    //   116: invokeinterface 1286 1 0
    //   121: astore_3
    //   122: aload_3
    //   123: invokeinterface 998 1 0
    //   128: ifeq +165 -> 293
    //   131: aload_3
    //   132: invokeinterface 1001 1 0
    //   137: checkcast 367	java/lang/Long
    //   140: astore 4
    //   142: aload_0
    //   143: invokevirtual 566	com/google/android/gms/internal/measurement/zzgl:zzga	()Lcom/google/android/gms/internal/measurement/zzei;
    //   146: astore_2
    //   147: aload 4
    //   149: invokevirtual 840	java/lang/Long:longValue	()J
    //   152: lstore 6
    //   154: aload_2
    //   155: invokevirtual 310	com/google/android/gms/internal/measurement/zzhj:zzab	()V
    //   158: aload_2
    //   159: invokevirtual 542	com/google/android/gms/internal/measurement/zzhk:zzch	()V
    //   162: aload_2
    //   163: invokevirtual 576	com/google/android/gms/internal/measurement/zzei:getWritableDatabase	()Landroid/database/sqlite/SQLiteDatabase;
    //   166: astore 4
    //   168: aload 4
    //   170: ldc_w 1429
    //   173: ldc_w 1431
    //   176: iconst_1
    //   177: anewarray 280	java/lang/String
    //   180: dup
    //   181: iconst_0
    //   182: lload 6
    //   184: invokestatic 579	java/lang/String:valueOf	(J)Ljava/lang/String;
    //   187: aastore
    //   188: invokevirtual 1093	android/database/sqlite/SQLiteDatabase:delete	(Ljava/lang/String;Ljava/lang/String;[Ljava/lang/String;)I
    //   191: iconst_1
    //   192: if_icmpeq -70 -> 122
    //   195: new 560	android/database/sqlite/SQLiteException
    //   198: astore_3
    //   199: aload_3
    //   200: ldc_w 1433
    //   203: invokespecial 1434	android/database/sqlite/SQLiteException:<init>	(Ljava/lang/String;)V
    //   206: aload_3
    //   207: athrow
    //   208: astore_3
    //   209: aload_2
    //   210: invokevirtual 232	com/google/android/gms/internal/measurement/zzhj:zzgg	()Lcom/google/android/gms/internal/measurement/zzfg;
    //   213: invokevirtual 401	com/google/android/gms/internal/measurement/zzfg:zzil	()Lcom/google/android/gms/internal/measurement/zzfi;
    //   216: ldc_w 1436
    //   219: aload_3
    //   220: invokevirtual 374	com/google/android/gms/internal/measurement/zzfi:zzg	(Ljava/lang/String;Ljava/lang/Object;)V
    //   223: aload_3
    //   224: athrow
    //   225: astore_2
    //   226: aload_0
    //   227: invokevirtual 566	com/google/android/gms/internal/measurement/zzgl:zzga	()Lcom/google/android/gms/internal/measurement/zzei;
    //   230: invokevirtual 689	com/google/android/gms/internal/measurement/zzei:endTransaction	()V
    //   233: aload_2
    //   234: athrow
    //   235: astore_2
    //   236: aload_0
    //   237: invokevirtual 254	com/google/android/gms/internal/measurement/zzgl:zzgg	()Lcom/google/android/gms/internal/measurement/zzfg;
    //   240: invokevirtual 401	com/google/android/gms/internal/measurement/zzfg:zzil	()Lcom/google/android/gms/internal/measurement/zzfi;
    //   243: ldc_w 1438
    //   246: aload_2
    //   247: invokevirtual 374	com/google/android/gms/internal/measurement/zzfi:zzg	(Ljava/lang/String;Ljava/lang/Object;)V
    //   250: aload_0
    //   251: aload_0
    //   252: getfield 110	com/google/android/gms/internal/measurement/zzgl:zzrj	Lcom/google/android/gms/common/util/Clock;
    //   255: invokeinterface 1167 1 0
    //   260: putfield 1162	com/google/android/gms/internal/measurement/zzgl:zzank	J
    //   263: aload_0
    //   264: invokevirtual 254	com/google/android/gms/internal/measurement/zzgl:zzgg	()Lcom/google/android/gms/internal/measurement/zzfg;
    //   267: invokevirtual 236	com/google/android/gms/internal/measurement/zzfg:zzir	()Lcom/google/android/gms/internal/measurement/zzfi;
    //   270: ldc_w 1440
    //   273: aload_0
    //   274: getfield 1162	com/google/android/gms/internal/measurement/zzgl:zzank	J
    //   277: invokestatic 370	java/lang/Long:valueOf	(J)Ljava/lang/Long;
    //   280: invokevirtual 374	com/google/android/gms/internal/measurement/zzfi:zzg	(Ljava/lang/String;Ljava/lang/Object;)V
    //   283: aload_0
    //   284: iconst_0
    //   285: putfield 1274	com/google/android/gms/internal/measurement/zzgl:zzanm	Z
    //   288: aload_0
    //   289: invokespecial 1442	com/google/android/gms/internal/measurement/zzgl:zzkc	()V
    //   292: return
    //   293: aload_0
    //   294: invokevirtual 566	com/google/android/gms/internal/measurement/zzgl:zzga	()Lcom/google/android/gms/internal/measurement/zzei;
    //   297: invokevirtual 1104	com/google/android/gms/internal/measurement/zzei:setTransactionSuccessful	()V
    //   300: aload_0
    //   301: invokevirtual 566	com/google/android/gms/internal/measurement/zzgl:zzga	()Lcom/google/android/gms/internal/measurement/zzei;
    //   304: invokevirtual 689	com/google/android/gms/internal/measurement/zzei:endTransaction	()V
    //   307: aload_0
    //   308: invokevirtual 536	com/google/android/gms/internal/measurement/zzgl:zzjq	()Lcom/google/android/gms/internal/measurement/zzfk;
    //   311: invokevirtual 1250	com/google/android/gms/internal/measurement/zzfk:zzew	()Z
    //   314: ifeq +34 -> 348
    //   317: aload_0
    //   318: invokespecial 1184	com/google/android/gms/internal/measurement/zzgl:zzjx	()Z
    //   321: ifeq +27 -> 348
    //   324: aload_0
    //   325: invokevirtual 1445	com/google/android/gms/internal/measurement/zzgl:zzjw	()V
    //   328: aload_0
    //   329: lconst_0
    //   330: putfield 1162	com/google/android/gms/internal/measurement/zzgl:zzank	J
    //   333: goto -50 -> 283
    //   336: astore_2
    //   337: aload_0
    //   338: iconst_0
    //   339: putfield 1274	com/google/android/gms/internal/measurement/zzgl:zzanm	Z
    //   342: aload_0
    //   343: invokespecial 1442	com/google/android/gms/internal/measurement/zzgl:zzkc	()V
    //   346: aload_2
    //   347: athrow
    //   348: aload_0
    //   349: ldc2_w 99
    //   352: putfield 102	com/google/android/gms/internal/measurement/zzgl:zzanj	J
    //   355: aload_0
    //   356: invokespecial 1363	com/google/android/gms/internal/measurement/zzgl:zzjy	()V
    //   359: goto -31 -> 328
    //   362: aload_0
    //   363: invokevirtual 254	com/google/android/gms/internal/measurement/zzgl:zzgg	()Lcom/google/android/gms/internal/measurement/zzfg;
    //   366: invokevirtual 236	com/google/android/gms/internal/measurement/zzfg:zzir	()Lcom/google/android/gms/internal/measurement/zzfi;
    //   369: ldc_w 1447
    //   372: iload_1
    //   373: invokestatic 408	java/lang/Integer:valueOf	(I)Ljava/lang/Integer;
    //   376: aload_2
    //   377: invokevirtual 412	com/google/android/gms/internal/measurement/zzfi:zze	(Ljava/lang/String;Ljava/lang/Object;Ljava/lang/Object;)V
    //   380: aload_0
    //   381: invokevirtual 1129	com/google/android/gms/internal/measurement/zzgl:zzgh	()Lcom/google/android/gms/internal/measurement/zzfr;
    //   384: getfield 1213	com/google/android/gms/internal/measurement/zzfr:zzaju	Lcom/google/android/gms/internal/measurement/zzfu;
    //   387: aload_0
    //   388: getfield 110	com/google/android/gms/internal/measurement/zzgl:zzrj	Lcom/google/android/gms/common/util/Clock;
    //   391: invokeinterface 116 1 0
    //   396: invokevirtual 1142	com/google/android/gms/internal/measurement/zzfu:set	(J)V
    //   399: iload_1
    //   400: sipush 503
    //   403: if_icmpeq +10 -> 413
    //   406: iload_1
    //   407: sipush 429
    //   410: if_icmpne +58 -> 468
    //   413: iconst_1
    //   414: istore_1
    //   415: iload_1
    //   416: ifeq +22 -> 438
    //   419: aload_0
    //   420: invokevirtual 1129	com/google/android/gms/internal/measurement/zzgl:zzgh	()Lcom/google/android/gms/internal/measurement/zzfr;
    //   423: getfield 1258	com/google/android/gms/internal/measurement/zzfr:zzajv	Lcom/google/android/gms/internal/measurement/zzfu;
    //   426: aload_0
    //   427: getfield 110	com/google/android/gms/internal/measurement/zzgl:zzrj	Lcom/google/android/gms/common/util/Clock;
    //   430: invokeinterface 116 1 0
    //   435: invokevirtual 1142	com/google/android/gms/internal/measurement/zzfu:set	(J)V
    //   438: aload_0
    //   439: getfield 125	com/google/android/gms/internal/measurement/zzgl:zzamd	Lcom/google/android/gms/internal/measurement/zzeh;
    //   442: aload 4
    //   444: getstatic 1450	com/google/android/gms/internal/measurement/zzew:zzaia	Lcom/google/android/gms/internal/measurement/zzex;
    //   447: invokevirtual 1453	com/google/android/gms/internal/measurement/zzeh:zzd	(Ljava/lang/String;Lcom/google/android/gms/internal/measurement/zzex;)Z
    //   450: ifeq +11 -> 461
    //   453: aload_0
    //   454: invokevirtual 566	com/google/android/gms/internal/measurement/zzgl:zzga	()Lcom/google/android/gms/internal/measurement/zzei;
    //   457: aload_3
    //   458: invokevirtual 1456	com/google/android/gms/internal/measurement/zzei:zzc	(Ljava/util/List;)V
    //   461: aload_0
    //   462: invokespecial 1363	com/google/android/gms/internal/measurement/zzgl:zzjy	()V
    //   465: goto -182 -> 283
    //   468: iconst_0
    //   469: istore_1
    //   470: goto -55 -> 415
    // Local variable table:
    //   start	length	slot	name	signature
    //   0	473	0	this	zzgl
    //   0	473	1	paramInt	int
    //   0	473	2	paramThrowable	Throwable
    //   0	473	3	paramArrayOfByte	byte[]
    //   0	473	4	paramString	String
    //   12	88	5	arrayOfByte	byte[]
    //   152	31	6	l	long
    // Exception table:
    //   from	to	target	type
    //   168	208	208	android/database/sqlite/SQLiteException
    //   115	122	225	finally
    //   122	168	225	finally
    //   168	208	225	finally
    //   209	225	225	finally
    //   293	300	225	finally
    //   51	115	235	android/database/sqlite/SQLiteException
    //   226	235	235	android/database/sqlite/SQLiteException
    //   300	328	235	android/database/sqlite/SQLiteException
    //   328	333	235	android/database/sqlite/SQLiteException
    //   348	359	235	android/database/sqlite/SQLiteException
    //   18	23	336	finally
    //   23	33	336	finally
    //   51	115	336	finally
    //   226	235	336	finally
    //   236	283	336	finally
    //   300	328	336	finally
    //   328	333	336	finally
    //   348	359	336	finally
    //   362	399	336	finally
    //   419	438	336	finally
    //   438	461	336	finally
    //   461	465	336	finally
  }
  
  final void zzb(zzhk paramzzhk)
  {
    this.zzanh += 1;
  }
  
  final void zzb(String paramString, int paramInt, Throwable paramThrowable, byte[] paramArrayOfByte, Map<String, List<String>> paramMap)
  {
    int i = 1;
    zzgf().zzab();
    zzch();
    Preconditions.checkNotEmpty(paramString);
    byte[] arrayOfByte = paramArrayOfByte;
    if (paramArrayOfByte == null) {}
    for (;;)
    {
      try
      {
        arrayOfByte = new byte[0];
        zzgg().zzir().zzg("onConfigFetched. Response size", Integer.valueOf(arrayOfByte.length));
        zzga().beginTransaction();
        try
        {
          paramArrayOfByte = zzga().zzax(paramString);
          if (((paramInt == 200) || (paramInt == 204) || (paramInt == 304)) && (paramThrowable == null))
          {
            j = 1;
            if (paramArrayOfByte == null)
            {
              zzgg().zzin().zzg("App does not exist in onConfigFetched. appId", zzfg.zzbh(paramString));
              zzga().setTransactionSuccessful();
              zzga().endTransaction();
            }
          }
          else
          {
            j = 0;
            continue;
          }
          if ((j == 0) && (paramInt != 404)) {
            break;
          }
          if (paramMap != null)
          {
            paramThrowable = (List)paramMap.get("Last-Modified");
            if ((paramThrowable != null) && (paramThrowable.size() > 0))
            {
              paramThrowable = (String)paramThrowable.get(0);
              if ((paramInt != 404) && (paramInt != 304)) {
                continue;
              }
              if (zzgd().zzbp(paramString) != null) {
                continue;
              }
              bool = zzgd().zza(paramString, null, null);
              if (bool) {
                continue;
              }
              zzga().endTransaction();
              this.zzanl = false;
              zzkc();
            }
          }
          else
          {
            paramThrowable = null;
            continue;
          }
          paramThrowable = null;
          continue;
          boolean bool = zzgd().zza(paramString, arrayOfByte, paramThrowable);
          if (!bool)
          {
            zzga().endTransaction();
            this.zzanl = false;
            zzkc();
            continue;
          }
          paramArrayOfByte.zzs(this.zzrj.currentTimeMillis());
          zzga().zza(paramArrayOfByte);
          if (paramInt == 404)
          {
            zzgg().zzio().zzg("Config not found. Using empty config. appId", paramString);
            if ((!zzjq().zzew()) || (!zzjx())) {
              break label428;
            }
            zzjw();
            continue;
            paramString = finally;
          }
        }
        finally
        {
          zzga().endTransaction();
        }
        zzgg().zzir().zze("Successfully fetched config. Got network response. code, size", Integer.valueOf(paramInt), Integer.valueOf(arrayOfByte.length));
      }
      finally
      {
        this.zzanl = false;
        zzkc();
      }
      continue;
      label428:
      zzjy();
    }
    paramArrayOfByte.zzt(this.zzrj.currentTimeMillis());
    zzga().zza(paramArrayOfByte);
    zzgg().zzir().zze("Fetching config failed. code, error", Integer.valueOf(paramInt), paramThrowable);
    zzgd().zzbr(paramString);
    zzgh().zzaju.set(this.zzrj.currentTimeMillis());
    int j = i;
    if (paramInt != 503) {
      if (paramInt != 429) {
        break label556;
      }
    }
    label556:
    for (j = i;; j = 0)
    {
      if (j != 0) {
        zzgh().zzajv.set(this.zzrj.currentTimeMillis());
      }
      zzjy();
      break;
    }
  }
  
  public final Clock zzbt()
  {
    return this.zzrj;
  }
  
  final void zzch()
  {
    if (!this.zzvj) {
      throw new IllegalStateException("AppMeasurement is not initialized");
    }
  }
  
  public final zzdx zzfs()
  {
    zza(this.zzamq);
    return this.zzamq;
  }
  
  public final zzee zzft()
  {
    zza(this.zzamy);
    return this.zzamy;
  }
  
  public final zzhm zzfu()
  {
    zza(this.zzamp);
    return this.zzamp;
  }
  
  public final zzfb zzfv()
  {
    zza(this.zzamv);
    return this.zzamv;
  }
  
  public final zzeo zzfw()
  {
    zza(this.zzamu);
    return this.zzamu;
  }
  
  public final zzil zzfx()
  {
    zza(this.zzamt);
    return this.zzamt;
  }
  
  public final zzih zzfy()
  {
    zza(this.zzamo);
    return this.zzamo;
  }
  
  public final zzfc zzfz()
  {
    zza(this.zzams);
    return this.zzams;
  }
  
  public final zzei zzga()
  {
    zza(this.zzamr);
    return this.zzamr;
  }
  
  public final zzfe zzgb()
  {
    zza(this.zzamm);
    return this.zzamm;
  }
  
  public final zzjv zzgc()
  {
    zza(this.zzaml);
    return this.zzaml;
  }
  
  public final zzgf zzgd()
  {
    zza(this.zzami);
    return this.zzami;
  }
  
  public final zzjk zzge()
  {
    zza(this.zzamh);
    return this.zzamh;
  }
  
  public final zzgg zzgf()
  {
    zza(this.zzamg);
    return this.zzamg;
  }
  
  public final zzfg zzgg()
  {
    zza(this.zzamf);
    return this.zzamf;
  }
  
  public final zzfr zzgh()
  {
    zza(this.zzame);
    return this.zzame;
  }
  
  public final zzeh zzgi()
  {
    return this.zzamd;
  }
  
  public final void zzi(boolean paramBoolean)
  {
    zzjy();
  }
  
  protected final boolean zzjk()
  {
    boolean bool1 = false;
    zzch();
    zzgf().zzab();
    if ((this.zzanb == null) || (this.zzanc == 0L) || ((this.zzanb != null) && (!this.zzanb.booleanValue()) && (Math.abs(this.zzrj.elapsedRealtime() - this.zzanc) > 1000L)))
    {
      this.zzanc = this.zzrj.elapsedRealtime();
      boolean bool2 = bool1;
      if (zzgc().zzx("android.permission.INTERNET"))
      {
        bool2 = bool1;
        if (zzgc().zzx("android.permission.ACCESS_NETWORK_STATE")) {
          if (!Wrappers.packageManager(this.zzqs).isCallerInstantApp())
          {
            bool2 = bool1;
            if (zzgb.zza(this.zzqs))
            {
              bool2 = bool1;
              if (!zzjf.zza(this.zzqs, false)) {}
            }
          }
          else
          {
            bool2 = true;
          }
        }
      }
      this.zzanb = Boolean.valueOf(bool2);
      if (this.zzanb.booleanValue()) {
        this.zzanb = Boolean.valueOf(zzgc().zzbz(zzfv().getGmpAppId()));
      }
    }
    return this.zzanb.booleanValue();
  }
  
  public final zzfg zzjl()
  {
    if ((this.zzamf != null) && (this.zzamf.isInitialized())) {}
    for (zzfg localzzfg = this.zzamf;; localzzfg = null) {
      return localzzfg;
    }
  }
  
  final zzgg zzjn()
  {
    return this.zzamg;
  }
  
  public final AppMeasurement zzjo()
  {
    return this.zzamj;
  }
  
  public final FirebaseAnalytics zzjp()
  {
    return this.zzamk;
  }
  
  public final zzfk zzjq()
  {
    zza(this.zzamn);
    return this.zzamn;
  }
  
  final long zzju()
  {
    Long localLong = Long.valueOf(zzgh().zzajy.get());
    if (localLong.longValue() == 0L) {}
    for (long l = this.zzaeh;; l = Math.min(this.zzaeh, localLong.longValue())) {
      return l;
    }
  }
  
  public final void zzjw()
  {
    zzgf().zzab();
    zzch();
    this.zzann = true;
    for (;;)
    {
      long l1;
      Object localObject4;
      try
      {
        Object localObject1 = zzfx().zzkn();
        if (localObject1 == null)
        {
          zzgg().zzin().log("Upload data called on the client side before use of service was decided");
          return;
        }
        if (((Boolean)localObject1).booleanValue())
        {
          zzgg().zzil().log("Upload called in the client side when service should be used");
          this.zzann = false;
          zzkc();
          continue;
        }
        if (this.zzank > 0L)
        {
          zzjy();
          this.zzann = false;
          zzkc();
          continue;
        }
        zzgf().zzab();
        int i;
        if (this.zzanf != null)
        {
          i = 1;
          if (i != 0)
          {
            zzgg().zzir().log("Uploading requested multiple times");
            this.zzann = false;
            zzkc();
          }
        }
        else
        {
          i = 0;
          continue;
        }
        if (!zzjq().zzew())
        {
          zzgg().zzir().log("Network not connected, ignoring upload request");
          zzjy();
          this.zzann = false;
          zzkc();
          continue;
        }
        l1 = this.zzrj.currentTimeMillis();
        zzd(null, l1 - zzeh.zzhk());
        long l2 = zzgh().zzajt.get();
        if (l2 != 0L) {
          zzgg().zziq().zzg("Uploading events. Elapsed time since last upload attempt (ms)", Long.valueOf(Math.abs(l1 - l2)));
        }
        String str = zzga().zzhn();
        Object localObject5;
        if (!TextUtils.isEmpty(str))
        {
          if (this.zzanj == -1L) {
            this.zzanj = zzga().zzhu();
          }
          int j = this.zzamd.zzb(str, zzew.zzagr);
          i = Math.max(0, this.zzamd.zzb(str, zzew.zzags));
          localObject4 = zzga().zzb(str, j, i);
          Object localObject6;
          byte[] arrayOfByte;
          if (!((List)localObject4).isEmpty())
          {
            localObject5 = ((List)localObject4).iterator();
            if (!((Iterator)localObject5).hasNext()) {
              break label1048;
            }
            localObject1 = (zzkl)((Pair)((Iterator)localObject5).next()).first;
            if (TextUtils.isEmpty(((zzkl)localObject1).zzatq)) {
              continue;
            }
            localObject1 = ((zzkl)localObject1).zzatq;
            if (localObject1 == null) {
              break label1042;
            }
            i = 0;
            if (i >= ((List)localObject4).size()) {
              break label1042;
            }
            localObject5 = (zzkl)((Pair)((List)localObject4).get(i)).first;
            if ((!TextUtils.isEmpty(((zzkl)localObject5).zzatq)) && (!((zzkl)localObject5).zzatq.equals(localObject1)))
            {
              localObject1 = ((List)localObject4).subList(0, i);
              localObject6 = new com/google/android/gms/internal/measurement/zzkk;
              ((zzkk)localObject6).<init>();
              ((zzkk)localObject6).zzata = new zzkl[((List)localObject1).size()];
              localObject4 = new java/util/ArrayList;
              ((ArrayList)localObject4).<init>(((List)localObject1).size());
              if ((zzeh.zzhm()) && (this.zzamd.zzat(str)))
              {
                i = 1;
                j = 0;
                if (j >= ((zzkk)localObject6).zzata.length) {
                  continue;
                }
                ((zzkk)localObject6).zzata[j] = ((zzkl)((Pair)((List)localObject1).get(j)).first);
                ((List)localObject4).add((Long)((Pair)((List)localObject1).get(j)).second);
                localObject6.zzata[j].zzatp = Long.valueOf(12451L);
                localObject6.zzata[j].zzatf = Long.valueOf(l1);
                localObject6.zzata[j].zzatu = Boolean.valueOf(false);
                if (i == 0) {
                  localObject6.zzata[j].zzauc = null;
                }
                j++;
                continue;
              }
            }
            else
            {
              i++;
              continue;
            }
            i = 0;
            continue;
            if (!zzgg().isLoggable(2)) {
              break label1037;
            }
            localObject1 = zzgb().zza((zzkk)localObject6);
            arrayOfByte = zzgc().zzb((zzkk)localObject6);
            localObject5 = (String)zzew.zzahb.get();
          }
          try
          {
            URL localURL = new java/net/URL;
            localURL.<init>((String)localObject5);
            if (((List)localObject4).isEmpty()) {
              continue;
            }
            bool = true;
            Preconditions.checkArgument(bool);
            if (this.zzanf == null) {
              continue;
            }
            zzgg().zzil().log("Set uploading progress before finishing the previous upload");
            zzgh().zzaju.set(l1);
            localObject4 = "?";
            if (((zzkk)localObject6).zzata.length > 0) {
              localObject4 = localObject6.zzata[0].zztd;
            }
            zzgg().zzir().zzd("Uploading data. app, uncompressed size, data", localObject4, Integer.valueOf(arrayOfByte.length), localObject1);
            this.zzanm = true;
            localObject6 = zzjq();
            localObject4 = new com/google/android/gms/internal/measurement/zzgo;
            ((zzgo)localObject4).<init>(this, str);
            ((zzhj)localObject6).zzab();
            ((zzhk)localObject6).zzch();
            Preconditions.checkNotNull(localURL);
            Preconditions.checkNotNull(arrayOfByte);
            Preconditions.checkNotNull(localObject4);
            localObject7 = ((zzhj)localObject6).zzgf();
            localObject1 = new com/google/android/gms/internal/measurement/zzfo;
            ((zzfo)localObject1).<init>((zzfk)localObject6, str, localURL, arrayOfByte, null, (zzfm)localObject4);
            ((zzgg)localObject7).zzd((Runnable)localObject1);
          }
          catch (MalformedURLException localMalformedURLException)
          {
            boolean bool;
            Object localObject7;
            zzgg().zzil().zze("Failed to parse upload URL. Not uploading. appId", zzfg.zzbh(str), localObject5);
            continue;
          }
          this.zzann = false;
          zzkc();
          continue;
          bool = false;
          continue;
          localObject7 = new java/util/ArrayList;
          ((ArrayList)localObject7).<init>((Collection)localObject4);
          this.zzanf = ((List)localObject7);
          continue;
        }
        this.zzanj = -1L;
      }
      finally
      {
        this.zzann = false;
        zzkc();
      }
      Object localObject3 = zzga().zzab(l1 - zzeh.zzhk());
      if (!TextUtils.isEmpty((CharSequence)localObject3))
      {
        localObject3 = zzga().zzax((String)localObject3);
        if (localObject3 != null)
        {
          zzb((zzeb)localObject3);
          continue;
          label1037:
          localObject3 = null;
          continue;
          label1042:
          localObject3 = localObject4;
          continue;
          label1048:
          localObject3 = null;
        }
      }
    }
  }
  
  final void zzjz()
  {
    this.zzani += 1;
  }
  
  final class zza
    implements zzek
  {
    zzkl zzans;
    List<Long> zzant;
    List<zzki> zzanu;
    private long zzanv;
    
    private zza() {}
    
    private static long zza(zzki paramzzki)
    {
      return paramzzki.zzasw.longValue() / 1000L / 60L / 60L;
    }
    
    public final boolean zza(long paramLong, zzki paramzzki)
    {
      Preconditions.checkNotNull(paramzzki);
      if (this.zzanu == null) {
        this.zzanu = new ArrayList();
      }
      if (this.zzant == null) {
        this.zzant = new ArrayList();
      }
      boolean bool;
      if ((this.zzanu.size() > 0) && (zza((zzki)this.zzanu.get(0)) != zza(paramzzki))) {
        bool = false;
      }
      for (;;)
      {
        return bool;
        long l = this.zzanv + paramzzki.zzwg();
        if (l >= Math.max(0, ((Integer)zzew.zzagt.get()).intValue()))
        {
          bool = false;
        }
        else
        {
          this.zzanv = l;
          this.zzanu.add(paramzzki);
          this.zzant.add(Long.valueOf(paramLong));
          if (this.zzanu.size() >= Math.max(1, ((Integer)zzew.zzagu.get()).intValue())) {
            bool = false;
          } else {
            bool = true;
          }
        }
      }
    }
    
    public final void zzb(zzkl paramzzkl)
    {
      Preconditions.checkNotNull(paramzzkl);
      this.zzans = paramzzkl;
    }
  }
}


/* Location:              /home/fabian/Escritorio/Proyectos/Android/Dev/jardecompiler/TMessagesProj-fat-debug.jar!/com/google/android/gms/internal/measurement/zzgl.class
 * Java compiler version: 6 (50.0)
 * JD-Core Version:       0.7.1-SNAPSHOT-20140817
 */