package com.google.android.gms.internal.measurement;

import java.util.concurrent.atomic.AtomicReference;

final class zzhx
  implements Runnable
{
  zzhx(zzhm paramzzhm, AtomicReference paramAtomicReference) {}
  
  /* Error */
  public final void run()
  {
    // Byte code:
    //   0: aload_0
    //   1: getfield 16	com/google/android/gms/internal/measurement/zzhx:zzaoo	Ljava/util/concurrent/atomic/AtomicReference;
    //   4: astore_1
    //   5: aload_0
    //   6: getfield 14	com/google/android/gms/internal/measurement/zzhx:zzaop	Lcom/google/android/gms/internal/measurement/zzhm;
    //   9: invokevirtual 27	com/google/android/gms/internal/measurement/zzhj:zzgi	()Lcom/google/android/gms/internal/measurement/zzeh;
    //   12: astore_2
    //   13: aload_2
    //   14: invokevirtual 31	com/google/android/gms/internal/measurement/zzhj:zzfv	()Lcom/google/android/gms/internal/measurement/zzfb;
    //   17: invokevirtual 37	com/google/android/gms/internal/measurement/zzfb:zzah	()Ljava/lang/String;
    //   20: astore_3
    //   21: getstatic 43	com/google/android/gms/internal/measurement/zzew:zzaht	Lcom/google/android/gms/internal/measurement/zzex;
    //   24: astore 4
    //   26: aload_3
    //   27: ifnonnull +25 -> 52
    //   30: aload 4
    //   32: invokevirtual 49	com/google/android/gms/internal/measurement/zzex:get	()Ljava/lang/Object;
    //   35: checkcast 51	java/lang/String
    //   38: astore_3
    //   39: aload_1
    //   40: aload_3
    //   41: invokevirtual 57	java/util/concurrent/atomic/AtomicReference:set	(Ljava/lang/Object;)V
    //   44: aload_0
    //   45: getfield 16	com/google/android/gms/internal/measurement/zzhx:zzaoo	Ljava/util/concurrent/atomic/AtomicReference;
    //   48: invokevirtual 60	java/lang/Object:notify	()V
    //   51: return
    //   52: aload 4
    //   54: aload_2
    //   55: invokevirtual 64	com/google/android/gms/internal/measurement/zzhj:zzgd	()Lcom/google/android/gms/internal/measurement/zzgf;
    //   58: aload_3
    //   59: aload 4
    //   61: invokevirtual 67	com/google/android/gms/internal/measurement/zzex:getKey	()Ljava/lang/String;
    //   64: invokevirtual 73	com/google/android/gms/internal/measurement/zzgf:zzm	(Ljava/lang/String;Ljava/lang/String;)Ljava/lang/String;
    //   67: invokevirtual 76	com/google/android/gms/internal/measurement/zzex:get	(Ljava/lang/Object;)Ljava/lang/Object;
    //   70: checkcast 51	java/lang/String
    //   73: astore_3
    //   74: goto -35 -> 39
    //   77: astore_3
    //   78: aload_0
    //   79: getfield 16	com/google/android/gms/internal/measurement/zzhx:zzaoo	Ljava/util/concurrent/atomic/AtomicReference;
    //   82: invokevirtual 60	java/lang/Object:notify	()V
    //   85: aload_3
    //   86: athrow
    // Local variable table:
    //   start	length	slot	name	signature
    //   0	87	0	this	zzhx
    //   4	36	1	localAtomicReference	AtomicReference
    //   12	43	2	localzzeh	zzeh
    //   20	54	3	str	String
    //   77	9	3	localObject	Object
    //   24	36	4	localzzex	zzex
    // Exception table:
    //   from	to	target	type
    //   0	26	77	finally
    //   30	39	77	finally
    //   39	44	77	finally
    //   52	74	77	finally
  }
}


/* Location:              /home/fabian/Escritorio/Proyectos/Android/Dev/jardecompiler/TMessagesProj-fat-debug.jar!/com/google/android/gms/internal/measurement/zzhx.class
 * Java compiler version: 6 (50.0)
 * JD-Core Version:       0.7.1-SNAPSHOT-20140817
 */