package com.google.android.gms.common.data;

import android.graphics.Bitmap;
import android.graphics.Bitmap.Config;
import android.os.Parcel;
import android.os.ParcelFileDescriptor;
import android.os.ParcelFileDescriptor.AutoCloseInputStream;
import android.os.Parcelable.Creator;
import android.util.Log;
import com.google.android.gms.common.internal.ReflectedParcelable;
import com.google.android.gms.common.internal.safeparcel.zzd;
import java.io.Closeable;
import java.io.DataInputStream;
import java.io.DataOutputStream;
import java.io.File;
import java.io.IOException;
import java.nio.Buffer;
import java.nio.ByteBuffer;

public class BitmapTeleporter
  extends com.google.android.gms.common.internal.safeparcel.zza
  implements ReflectedParcelable
{
  public static final Parcelable.Creator<BitmapTeleporter> CREATOR = new zza();
  private ParcelFileDescriptor zzTP;
  private Bitmap zzaFr;
  private boolean zzaFs;
  private File zzaFt;
  private int zzaku;
  private int zzamr;
  
  BitmapTeleporter(int paramInt1, ParcelFileDescriptor paramParcelFileDescriptor, int paramInt2)
  {
    this.zzaku = paramInt1;
    this.zzTP = paramParcelFileDescriptor;
    this.zzamr = paramInt2;
    this.zzaFr = null;
    this.zzaFs = false;
  }
  
  public BitmapTeleporter(Bitmap paramBitmap)
  {
    this.zzaku = 1;
    this.zzTP = null;
    this.zzamr = 0;
    this.zzaFr = paramBitmap;
    this.zzaFs = true;
  }
  
  private static void zza(Closeable paramCloseable)
  {
    try
    {
      paramCloseable.close();
      return;
    }
    catch (IOException paramCloseable)
    {
      Log.w("BitmapTeleporter", "Could not close stream", paramCloseable);
    }
  }
  
  /* Error */
  private final java.io.FileOutputStream zzqP()
  {
    // Byte code:
    //   0: aload_0
    //   1: getfield 68	com/google/android/gms/common/data/BitmapTeleporter:zzaFt	Ljava/io/File;
    //   4: ifnonnull +13 -> 17
    //   7: new 70	java/lang/IllegalStateException
    //   10: dup
    //   11: ldc 72
    //   13: invokespecial 75	java/lang/IllegalStateException:<init>	(Ljava/lang/String;)V
    //   16: athrow
    //   17: ldc 77
    //   19: ldc 79
    //   21: aload_0
    //   22: getfield 68	com/google/android/gms/common/data/BitmapTeleporter:zzaFt	Ljava/io/File;
    //   25: invokestatic 85	java/io/File:createTempFile	(Ljava/lang/String;Ljava/lang/String;Ljava/io/File;)Ljava/io/File;
    //   28: astore_1
    //   29: new 87	java/io/FileOutputStream
    //   32: dup
    //   33: aload_1
    //   34: invokespecial 90	java/io/FileOutputStream:<init>	(Ljava/io/File;)V
    //   37: astore_2
    //   38: aload_0
    //   39: aload_1
    //   40: ldc 91
    //   42: invokestatic 97	android/os/ParcelFileDescriptor:open	(Ljava/io/File;I)Landroid/os/ParcelFileDescriptor;
    //   45: putfield 36	com/google/android/gms/common/data/BitmapTeleporter:zzTP	Landroid/os/ParcelFileDescriptor;
    //   48: aload_1
    //   49: invokevirtual 101	java/io/File:delete	()Z
    //   52: pop
    //   53: aload_2
    //   54: areturn
    //   55: astore_1
    //   56: new 70	java/lang/IllegalStateException
    //   59: dup
    //   60: ldc 103
    //   62: aload_1
    //   63: invokespecial 106	java/lang/IllegalStateException:<init>	(Ljava/lang/String;Ljava/lang/Throwable;)V
    //   66: athrow
    //   67: astore_1
    //   68: new 70	java/lang/IllegalStateException
    //   71: dup
    //   72: ldc 108
    //   74: invokespecial 75	java/lang/IllegalStateException:<init>	(Ljava/lang/String;)V
    //   77: athrow
    // Local variable table:
    //   start	length	slot	name	signature
    //   0	78	0	this	BitmapTeleporter
    //   28	21	1	localFile	File
    //   55	8	1	localIOException	IOException
    //   67	1	1	localFileNotFoundException	java.io.FileNotFoundException
    //   37	17	2	localFileOutputStream	java.io.FileOutputStream
    // Exception table:
    //   from	to	target	type
    //   17	29	55	java/io/IOException
    //   29	48	67	java/io/FileNotFoundException
  }
  
  public final void release()
  {
    if (!this.zzaFs) {}
    try
    {
      this.zzTP.close();
      return;
    }
    catch (IOException localIOException)
    {
      Log.w("BitmapTeleporter", "Could not close PFD", localIOException);
    }
  }
  
  public void writeToParcel(Parcel paramParcel, int paramInt)
  {
    Bitmap localBitmap;
    Object localObject;
    byte[] arrayOfByte;
    if (this.zzTP == null)
    {
      localBitmap = this.zzaFr;
      localObject = ByteBuffer.allocate(localBitmap.getRowBytes() * localBitmap.getHeight());
      localBitmap.copyPixelsToBuffer((Buffer)localObject);
      arrayOfByte = ((ByteBuffer)localObject).array();
      localObject = new DataOutputStream(zzqP());
    }
    try
    {
      ((DataOutputStream)localObject).writeInt(arrayOfByte.length);
      ((DataOutputStream)localObject).writeInt(localBitmap.getWidth());
      ((DataOutputStream)localObject).writeInt(localBitmap.getHeight());
      ((DataOutputStream)localObject).writeUTF(localBitmap.getConfig().toString());
      ((DataOutputStream)localObject).write(arrayOfByte);
      zza((Closeable)localObject);
      int i = zzd.zze(paramParcel);
      zzd.zzc(paramParcel, 1, this.zzaku);
      zzd.zza(paramParcel, 2, this.zzTP, paramInt | 0x1, false);
      zzd.zzc(paramParcel, 3, this.zzamr);
      zzd.zzI(paramParcel, i);
      this.zzTP = null;
      return;
    }
    catch (IOException paramParcel)
    {
      throw new IllegalStateException("Could not write into unlinked file", paramParcel);
    }
    finally
    {
      zza((Closeable)localObject);
    }
  }
  
  public final void zzc(File paramFile)
  {
    if (paramFile == null) {
      throw new NullPointerException("Cannot set null temp directory");
    }
    this.zzaFt = paramFile;
  }
  
  public final Bitmap zzqO()
  {
    Object localObject1;
    if (!this.zzaFs) {
      localObject1 = new DataInputStream(new ParcelFileDescriptor.AutoCloseInputStream(this.zzTP));
    }
    try
    {
      byte[] arrayOfByte = new byte[((DataInputStream)localObject1).readInt()];
      int i = ((DataInputStream)localObject1).readInt();
      int j = ((DataInputStream)localObject1).readInt();
      Object localObject2 = Bitmap.Config.valueOf(((DataInputStream)localObject1).readUTF());
      ((DataInputStream)localObject1).read(arrayOfByte);
      zza((Closeable)localObject1);
      localObject1 = ByteBuffer.wrap(arrayOfByte);
      localObject2 = Bitmap.createBitmap(i, j, (Bitmap.Config)localObject2);
      ((Bitmap)localObject2).copyPixelsFromBuffer((Buffer)localObject1);
      this.zzaFr = ((Bitmap)localObject2);
      this.zzaFs = true;
      return this.zzaFr;
    }
    catch (IOException localIOException)
    {
      throw new IllegalStateException("Could not read from parcel file descriptor", localIOException);
    }
    finally
    {
      zza((Closeable)localObject1);
    }
  }
}


/* Location:              /home/fabian/Escritorio/Proyectos/Android/Dev/jardecompiler/TMessagesProj-fat-debug.jar!/com/google/android/gms/common/data/BitmapTeleporter.class
 * Java compiler version: 6 (50.0)
 * JD-Core Version:       0.7.1-SNAPSHOT-20140817
 */