package com.google.android.gms.internal;

import android.os.Binder;
import android.os.Bundle;
import android.os.IBinder;
import android.os.IInterface;
import android.os.Parcel;
import android.os.Parcelable.Creator;
import android.os.RemoteException;
import com.google.android.gms.wallet.FullWalletRequest;
import com.google.android.gms.wallet.IsReadyToPayRequest;
import com.google.android.gms.wallet.MaskedWalletRequest;
import com.google.android.gms.wallet.NotifyTransactionStatusRequest;
import com.google.android.gms.wallet.firstparty.InitializeBuyFlowRequest;
import com.google.android.gms.wallet.firstparty.zza;
import com.google.android.gms.wallet.firstparty.zzd;
import com.google.android.gms.wallet.firstparty.zzh;
import com.google.android.gms.wallet.zze;
import com.google.android.gms.wallet.zzw;

public abstract interface zzbku
  extends IInterface
{
  public abstract void zzQ(Bundle paramBundle)
    throws RemoteException;
  
  public abstract void zzR(Bundle paramBundle)
    throws RemoteException;
  
  public abstract void zza(Bundle paramBundle, zzbkw paramzzbkw)
    throws RemoteException;
  
  public abstract void zza(FullWalletRequest paramFullWalletRequest, Bundle paramBundle, zzbkw paramzzbkw)
    throws RemoteException;
  
  public abstract void zza(IsReadyToPayRequest paramIsReadyToPayRequest, Bundle paramBundle, zzbkw paramzzbkw)
    throws RemoteException;
  
  public abstract void zza(MaskedWalletRequest paramMaskedWalletRequest, Bundle paramBundle, zzbkw paramzzbkw)
    throws RemoteException;
  
  public abstract void zza(NotifyTransactionStatusRequest paramNotifyTransactionStatusRequest, Bundle paramBundle)
    throws RemoteException;
  
  public abstract void zza(InitializeBuyFlowRequest paramInitializeBuyFlowRequest, Bundle paramBundle, zzbkw paramzzbkw)
    throws RemoteException;
  
  public abstract void zza(zza paramzza, Bundle paramBundle, zzbkw paramzzbkw)
    throws RemoteException;
  
  public abstract void zza(zzd paramzzd, Bundle paramBundle, zzbkw paramzzbkw)
    throws RemoteException;
  
  public abstract void zza(zzh paramzzh, Bundle paramBundle, zzbkw paramzzbkw)
    throws RemoteException;
  
  public abstract void zza(zze paramzze, Bundle paramBundle, zzbkw paramzzbkw)
    throws RemoteException;
  
  public abstract void zza(zzw paramzzw, Bundle paramBundle, zzbkw paramzzbkw)
    throws RemoteException;
  
  public abstract void zza(String paramString1, String paramString2, Bundle paramBundle, zzbkw paramzzbkw)
    throws RemoteException;
  
  public abstract void zzb(Bundle paramBundle, zzbkw paramzzbkw)
    throws RemoteException;
  
  public static abstract class zza
    extends Binder
    implements zzbku
  {
    public static zzbku zzfv(IBinder paramIBinder)
    {
      if (paramIBinder == null) {
        return null;
      }
      IInterface localIInterface = paramIBinder.queryLocalInterface("com.google.android.gms.wallet.internal.IOwService");
      if ((localIInterface != null) && ((localIInterface instanceof zzbku))) {
        return (zzbku)localIInterface;
      }
      return new zza(paramIBinder);
    }
    
    public boolean onTransact(int paramInt1, Parcel paramParcel1, Parcel paramParcel2, int paramInt2)
      throws RemoteException
    {
      switch (paramInt1)
      {
      default: 
        return super.onTransact(paramInt1, paramParcel1, paramParcel2, paramInt2);
      case 1598968902: 
        paramParcel2.writeString("com.google.android.gms.wallet.internal.IOwService");
        return true;
      case 1: 
        paramParcel1.enforceInterface("com.google.android.gms.wallet.internal.IOwService");
        if (paramParcel1.readInt() != 0)
        {
          paramParcel2 = (MaskedWalletRequest)MaskedWalletRequest.CREATOR.createFromParcel(paramParcel1);
          if (paramParcel1.readInt() == 0) {
            break label226;
          }
        }
        for (localObject = (Bundle)Bundle.CREATOR.createFromParcel(paramParcel1);; localObject = null)
        {
          zza(paramParcel2, (Bundle)localObject, zzbkw.zza.zzfx(paramParcel1.readStrongBinder()));
          return true;
          paramParcel2 = null;
          break;
        }
      case 2: 
        paramParcel1.enforceInterface("com.google.android.gms.wallet.internal.IOwService");
        if (paramParcel1.readInt() != 0)
        {
          paramParcel2 = (FullWalletRequest)FullWalletRequest.CREATOR.createFromParcel(paramParcel1);
          if (paramParcel1.readInt() == 0) {
            break label300;
          }
        }
        for (localObject = (Bundle)Bundle.CREATOR.createFromParcel(paramParcel1);; localObject = null)
        {
          zza(paramParcel2, (Bundle)localObject, zzbkw.zza.zzfx(paramParcel1.readStrongBinder()));
          return true;
          paramParcel2 = null;
          break;
        }
      case 3: 
        paramParcel1.enforceInterface("com.google.android.gms.wallet.internal.IOwService");
        localObject = paramParcel1.readString();
        String str = paramParcel1.readString();
        if (paramParcel1.readInt() != 0) {}
        for (paramParcel2 = (Bundle)Bundle.CREATOR.createFromParcel(paramParcel1);; paramParcel2 = null)
        {
          zza((String)localObject, str, paramParcel2, zzbkw.zza.zzfx(paramParcel1.readStrongBinder()));
          return true;
        }
      case 4: 
        paramParcel1.enforceInterface("com.google.android.gms.wallet.internal.IOwService");
        if (paramParcel1.readInt() != 0)
        {
          paramParcel2 = (NotifyTransactionStatusRequest)NotifyTransactionStatusRequest.CREATOR.createFromParcel(paramParcel1);
          if (paramParcel1.readInt() == 0) {
            break label426;
          }
        }
        for (paramParcel1 = (Bundle)Bundle.CREATOR.createFromParcel(paramParcel1);; paramParcel1 = null)
        {
          zza(paramParcel2, paramParcel1);
          return true;
          paramParcel2 = null;
          break;
        }
      case 5: 
        paramParcel1.enforceInterface("com.google.android.gms.wallet.internal.IOwService");
        if (paramParcel1.readInt() != 0) {}
        for (paramParcel2 = (Bundle)Bundle.CREATOR.createFromParcel(paramParcel1);; paramParcel2 = null)
        {
          zza(paramParcel2, zzbkw.zza.zzfx(paramParcel1.readStrongBinder()));
          return true;
        }
      case 6: 
        paramParcel1.enforceInterface("com.google.android.gms.wallet.internal.IOwService");
        if (paramParcel1.readInt() != 0)
        {
          paramParcel2 = (zze)zze.CREATOR.createFromParcel(paramParcel1);
          if (paramParcel1.readInt() == 0) {
            break label544;
          }
        }
        for (localObject = (Bundle)Bundle.CREATOR.createFromParcel(paramParcel1);; localObject = null)
        {
          zza(paramParcel2, (Bundle)localObject, zzbkw.zza.zzfx(paramParcel1.readStrongBinder()));
          return true;
          paramParcel2 = null;
          break;
        }
      case 9: 
        paramParcel1.enforceInterface("com.google.android.gms.wallet.internal.IOwService");
        if (paramParcel1.readInt() != 0) {}
        for (paramParcel1 = (Bundle)Bundle.CREATOR.createFromParcel(paramParcel1);; paramParcel1 = null)
        {
          zzQ(paramParcel1);
          return true;
        }
      case 10: 
        paramParcel1.enforceInterface("com.google.android.gms.wallet.internal.IOwService");
        if (paramParcel1.readInt() != 0) {}
        for (paramParcel1 = (Bundle)Bundle.CREATOR.createFromParcel(paramParcel1);; paramParcel1 = null)
        {
          zzR(paramParcel1);
          return true;
        }
      case 11: 
        paramParcel1.enforceInterface("com.google.android.gms.wallet.internal.IOwService");
        if (paramParcel1.readInt() != 0) {}
        for (paramParcel2 = (Bundle)Bundle.CREATOR.createFromParcel(paramParcel1);; paramParcel2 = null)
        {
          zzb(paramParcel2, zzbkw.zza.zzfx(paramParcel1.readStrongBinder()));
          return true;
        }
      case 12: 
        paramParcel1.enforceInterface("com.google.android.gms.wallet.internal.IOwService");
        if (paramParcel1.readInt() != 0)
        {
          paramParcel2 = (zzd)zzd.CREATOR.createFromParcel(paramParcel1);
          if (paramParcel1.readInt() == 0) {
            break label739;
          }
        }
        for (localObject = (Bundle)Bundle.CREATOR.createFromParcel(paramParcel1);; localObject = null)
        {
          zza(paramParcel2, (Bundle)localObject, zzbkw.zza.zzfx(paramParcel1.readStrongBinder()));
          return true;
          paramParcel2 = null;
          break;
        }
      case 13: 
        paramParcel1.enforceInterface("com.google.android.gms.wallet.internal.IOwService");
        if (paramParcel1.readInt() != 0)
        {
          paramParcel2 = (InitializeBuyFlowRequest)InitializeBuyFlowRequest.CREATOR.createFromParcel(paramParcel1);
          if (paramParcel1.readInt() == 0) {
            break label813;
          }
        }
        for (localObject = (Bundle)Bundle.CREATOR.createFromParcel(paramParcel1);; localObject = null)
        {
          zza(paramParcel2, (Bundle)localObject, zzbkw.zza.zzfx(paramParcel1.readStrongBinder()));
          return true;
          paramParcel2 = null;
          break;
        }
      case 14: 
        paramParcel1.enforceInterface("com.google.android.gms.wallet.internal.IOwService");
        if (paramParcel1.readInt() != 0)
        {
          paramParcel2 = (IsReadyToPayRequest)IsReadyToPayRequest.CREATOR.createFromParcel(paramParcel1);
          if (paramParcel1.readInt() == 0) {
            break label887;
          }
        }
        for (localObject = (Bundle)Bundle.CREATOR.createFromParcel(paramParcel1);; localObject = null)
        {
          zza(paramParcel2, (Bundle)localObject, zzbkw.zza.zzfx(paramParcel1.readStrongBinder()));
          return true;
          paramParcel2 = null;
          break;
        }
      case 15: 
        paramParcel1.enforceInterface("com.google.android.gms.wallet.internal.IOwService");
        if (paramParcel1.readInt() != 0)
        {
          paramParcel2 = (zzh)zzh.CREATOR.createFromParcel(paramParcel1);
          if (paramParcel1.readInt() == 0) {
            break label961;
          }
        }
        for (localObject = (Bundle)Bundle.CREATOR.createFromParcel(paramParcel1);; localObject = null)
        {
          zza(paramParcel2, (Bundle)localObject, zzbkw.zza.zzfx(paramParcel1.readStrongBinder()));
          return true;
          paramParcel2 = null;
          break;
        }
      case 16: 
        label226:
        label300:
        label426:
        label544:
        label739:
        label813:
        label887:
        label961:
        paramParcel1.enforceInterface("com.google.android.gms.wallet.internal.IOwService");
        if (paramParcel1.readInt() != 0)
        {
          paramParcel2 = (zza)zza.CREATOR.createFromParcel(paramParcel1);
          if (paramParcel1.readInt() == 0) {
            break label1035;
          }
        }
        label1035:
        for (localObject = (Bundle)Bundle.CREATOR.createFromParcel(paramParcel1);; localObject = null)
        {
          zza(paramParcel2, (Bundle)localObject, zzbkw.zza.zzfx(paramParcel1.readStrongBinder()));
          return true;
          paramParcel2 = null;
          break;
        }
      }
      paramParcel1.enforceInterface("com.google.android.gms.wallet.internal.IOwService");
      if (paramParcel1.readInt() != 0)
      {
        paramParcel2 = (zzw)zzw.CREATOR.createFromParcel(paramParcel1);
        if (paramParcel1.readInt() == 0) {
          break label1109;
        }
      }
      label1109:
      for (Object localObject = (Bundle)Bundle.CREATOR.createFromParcel(paramParcel1);; localObject = null)
      {
        zza(paramParcel2, (Bundle)localObject, zzbkw.zza.zzfx(paramParcel1.readStrongBinder()));
        return true;
        paramParcel2 = null;
        break;
      }
    }
    
    private static class zza
      implements zzbku
    {
      private IBinder zzrk;
      
      zza(IBinder paramIBinder)
      {
        this.zzrk = paramIBinder;
      }
      
      public IBinder asBinder()
      {
        return this.zzrk;
      }
      
      /* Error */
      public void zzQ(Bundle paramBundle)
        throws RemoteException
      {
        // Byte code:
        //   0: invokestatic 31	android/os/Parcel:obtain	()Landroid/os/Parcel;
        //   3: astore_2
        //   4: aload_2
        //   5: ldc 33
        //   7: invokevirtual 37	android/os/Parcel:writeInterfaceToken	(Ljava/lang/String;)V
        //   10: aload_1
        //   11: ifnull +34 -> 45
        //   14: aload_2
        //   15: iconst_1
        //   16: invokevirtual 41	android/os/Parcel:writeInt	(I)V
        //   19: aload_1
        //   20: aload_2
        //   21: iconst_0
        //   22: invokevirtual 47	android/os/Bundle:writeToParcel	(Landroid/os/Parcel;I)V
        //   25: aload_0
        //   26: getfield 18	com/google/android/gms/internal/zzbku$zza$zza:zzrk	Landroid/os/IBinder;
        //   29: bipush 9
        //   31: aload_2
        //   32: aconst_null
        //   33: iconst_1
        //   34: invokeinterface 53 5 0
        //   39: pop
        //   40: aload_2
        //   41: invokevirtual 56	android/os/Parcel:recycle	()V
        //   44: return
        //   45: aload_2
        //   46: iconst_0
        //   47: invokevirtual 41	android/os/Parcel:writeInt	(I)V
        //   50: goto -25 -> 25
        //   53: astore_1
        //   54: aload_2
        //   55: invokevirtual 56	android/os/Parcel:recycle	()V
        //   58: aload_1
        //   59: athrow
        // Local variable table:
        //   start	length	slot	name	signature
        //   0	60	0	this	zza
        //   0	60	1	paramBundle	Bundle
        //   3	52	2	localParcel	Parcel
        // Exception table:
        //   from	to	target	type
        //   4	10	53	finally
        //   14	25	53	finally
        //   25	40	53	finally
        //   45	50	53	finally
      }
      
      /* Error */
      public void zzR(Bundle paramBundle)
        throws RemoteException
      {
        // Byte code:
        //   0: invokestatic 31	android/os/Parcel:obtain	()Landroid/os/Parcel;
        //   3: astore_2
        //   4: aload_2
        //   5: ldc 33
        //   7: invokevirtual 37	android/os/Parcel:writeInterfaceToken	(Ljava/lang/String;)V
        //   10: aload_1
        //   11: ifnull +34 -> 45
        //   14: aload_2
        //   15: iconst_1
        //   16: invokevirtual 41	android/os/Parcel:writeInt	(I)V
        //   19: aload_1
        //   20: aload_2
        //   21: iconst_0
        //   22: invokevirtual 47	android/os/Bundle:writeToParcel	(Landroid/os/Parcel;I)V
        //   25: aload_0
        //   26: getfield 18	com/google/android/gms/internal/zzbku$zza$zza:zzrk	Landroid/os/IBinder;
        //   29: bipush 10
        //   31: aload_2
        //   32: aconst_null
        //   33: iconst_1
        //   34: invokeinterface 53 5 0
        //   39: pop
        //   40: aload_2
        //   41: invokevirtual 56	android/os/Parcel:recycle	()V
        //   44: return
        //   45: aload_2
        //   46: iconst_0
        //   47: invokevirtual 41	android/os/Parcel:writeInt	(I)V
        //   50: goto -25 -> 25
        //   53: astore_1
        //   54: aload_2
        //   55: invokevirtual 56	android/os/Parcel:recycle	()V
        //   58: aload_1
        //   59: athrow
        // Local variable table:
        //   start	length	slot	name	signature
        //   0	60	0	this	zza
        //   0	60	1	paramBundle	Bundle
        //   3	52	2	localParcel	Parcel
        // Exception table:
        //   from	to	target	type
        //   4	10	53	finally
        //   14	25	53	finally
        //   25	40	53	finally
        //   45	50	53	finally
      }
      
      /* Error */
      public void zza(Bundle paramBundle, zzbkw paramzzbkw)
        throws RemoteException
      {
        // Byte code:
        //   0: aconst_null
        //   1: astore_3
        //   2: invokestatic 31	android/os/Parcel:obtain	()Landroid/os/Parcel;
        //   5: astore 4
        //   7: aload 4
        //   9: ldc 33
        //   11: invokevirtual 37	android/os/Parcel:writeInterfaceToken	(Ljava/lang/String;)V
        //   14: aload_1
        //   15: ifnull +56 -> 71
        //   18: aload 4
        //   20: iconst_1
        //   21: invokevirtual 41	android/os/Parcel:writeInt	(I)V
        //   24: aload_1
        //   25: aload 4
        //   27: iconst_0
        //   28: invokevirtual 47	android/os/Bundle:writeToParcel	(Landroid/os/Parcel;I)V
        //   31: aload_3
        //   32: astore_1
        //   33: aload_2
        //   34: ifnull +10 -> 44
        //   37: aload_2
        //   38: invokeinterface 63 1 0
        //   43: astore_1
        //   44: aload 4
        //   46: aload_1
        //   47: invokevirtual 66	android/os/Parcel:writeStrongBinder	(Landroid/os/IBinder;)V
        //   50: aload_0
        //   51: getfield 18	com/google/android/gms/internal/zzbku$zza$zza:zzrk	Landroid/os/IBinder;
        //   54: iconst_5
        //   55: aload 4
        //   57: aconst_null
        //   58: iconst_1
        //   59: invokeinterface 53 5 0
        //   64: pop
        //   65: aload 4
        //   67: invokevirtual 56	android/os/Parcel:recycle	()V
        //   70: return
        //   71: aload 4
        //   73: iconst_0
        //   74: invokevirtual 41	android/os/Parcel:writeInt	(I)V
        //   77: goto -46 -> 31
        //   80: astore_1
        //   81: aload 4
        //   83: invokevirtual 56	android/os/Parcel:recycle	()V
        //   86: aload_1
        //   87: athrow
        // Local variable table:
        //   start	length	slot	name	signature
        //   0	88	0	this	zza
        //   0	88	1	paramBundle	Bundle
        //   0	88	2	paramzzbkw	zzbkw
        //   1	31	3	localObject	Object
        //   5	77	4	localParcel	Parcel
        // Exception table:
        //   from	to	target	type
        //   7	14	80	finally
        //   18	31	80	finally
        //   37	44	80	finally
        //   44	65	80	finally
        //   71	77	80	finally
      }
      
      public void zza(FullWalletRequest paramFullWalletRequest, Bundle paramBundle, zzbkw paramzzbkw)
        throws RemoteException
      {
        Object localObject = null;
        Parcel localParcel = Parcel.obtain();
        for (;;)
        {
          try
          {
            localParcel.writeInterfaceToken("com.google.android.gms.wallet.internal.IOwService");
            if (paramFullWalletRequest != null)
            {
              localParcel.writeInt(1);
              paramFullWalletRequest.writeToParcel(localParcel, 0);
              if (paramBundle != null)
              {
                localParcel.writeInt(1);
                paramBundle.writeToParcel(localParcel, 0);
                paramFullWalletRequest = (FullWalletRequest)localObject;
                if (paramzzbkw != null) {
                  paramFullWalletRequest = paramzzbkw.asBinder();
                }
                localParcel.writeStrongBinder(paramFullWalletRequest);
                this.zzrk.transact(2, localParcel, null, 1);
              }
            }
            else
            {
              localParcel.writeInt(0);
              continue;
            }
            localParcel.writeInt(0);
          }
          finally
          {
            localParcel.recycle();
          }
        }
      }
      
      public void zza(IsReadyToPayRequest paramIsReadyToPayRequest, Bundle paramBundle, zzbkw paramzzbkw)
        throws RemoteException
      {
        Object localObject = null;
        Parcel localParcel = Parcel.obtain();
        for (;;)
        {
          try
          {
            localParcel.writeInterfaceToken("com.google.android.gms.wallet.internal.IOwService");
            if (paramIsReadyToPayRequest != null)
            {
              localParcel.writeInt(1);
              paramIsReadyToPayRequest.writeToParcel(localParcel, 0);
              if (paramBundle != null)
              {
                localParcel.writeInt(1);
                paramBundle.writeToParcel(localParcel, 0);
                paramIsReadyToPayRequest = (IsReadyToPayRequest)localObject;
                if (paramzzbkw != null) {
                  paramIsReadyToPayRequest = paramzzbkw.asBinder();
                }
                localParcel.writeStrongBinder(paramIsReadyToPayRequest);
                this.zzrk.transact(14, localParcel, null, 1);
              }
            }
            else
            {
              localParcel.writeInt(0);
              continue;
            }
            localParcel.writeInt(0);
          }
          finally
          {
            localParcel.recycle();
          }
        }
      }
      
      public void zza(MaskedWalletRequest paramMaskedWalletRequest, Bundle paramBundle, zzbkw paramzzbkw)
        throws RemoteException
      {
        Object localObject = null;
        Parcel localParcel = Parcel.obtain();
        for (;;)
        {
          try
          {
            localParcel.writeInterfaceToken("com.google.android.gms.wallet.internal.IOwService");
            if (paramMaskedWalletRequest != null)
            {
              localParcel.writeInt(1);
              paramMaskedWalletRequest.writeToParcel(localParcel, 0);
              if (paramBundle != null)
              {
                localParcel.writeInt(1);
                paramBundle.writeToParcel(localParcel, 0);
                paramMaskedWalletRequest = (MaskedWalletRequest)localObject;
                if (paramzzbkw != null) {
                  paramMaskedWalletRequest = paramzzbkw.asBinder();
                }
                localParcel.writeStrongBinder(paramMaskedWalletRequest);
                this.zzrk.transact(1, localParcel, null, 1);
              }
            }
            else
            {
              localParcel.writeInt(0);
              continue;
            }
            localParcel.writeInt(0);
          }
          finally
          {
            localParcel.recycle();
          }
        }
      }
      
      public void zza(NotifyTransactionStatusRequest paramNotifyTransactionStatusRequest, Bundle paramBundle)
        throws RemoteException
      {
        Parcel localParcel = Parcel.obtain();
        for (;;)
        {
          try
          {
            localParcel.writeInterfaceToken("com.google.android.gms.wallet.internal.IOwService");
            if (paramNotifyTransactionStatusRequest != null)
            {
              localParcel.writeInt(1);
              paramNotifyTransactionStatusRequest.writeToParcel(localParcel, 0);
              if (paramBundle != null)
              {
                localParcel.writeInt(1);
                paramBundle.writeToParcel(localParcel, 0);
                this.zzrk.transact(4, localParcel, null, 1);
              }
            }
            else
            {
              localParcel.writeInt(0);
              continue;
            }
            localParcel.writeInt(0);
          }
          finally
          {
            localParcel.recycle();
          }
        }
      }
      
      public void zza(InitializeBuyFlowRequest paramInitializeBuyFlowRequest, Bundle paramBundle, zzbkw paramzzbkw)
        throws RemoteException
      {
        Object localObject = null;
        Parcel localParcel = Parcel.obtain();
        for (;;)
        {
          try
          {
            localParcel.writeInterfaceToken("com.google.android.gms.wallet.internal.IOwService");
            if (paramInitializeBuyFlowRequest != null)
            {
              localParcel.writeInt(1);
              paramInitializeBuyFlowRequest.writeToParcel(localParcel, 0);
              if (paramBundle != null)
              {
                localParcel.writeInt(1);
                paramBundle.writeToParcel(localParcel, 0);
                paramInitializeBuyFlowRequest = (InitializeBuyFlowRequest)localObject;
                if (paramzzbkw != null) {
                  paramInitializeBuyFlowRequest = paramzzbkw.asBinder();
                }
                localParcel.writeStrongBinder(paramInitializeBuyFlowRequest);
                this.zzrk.transact(13, localParcel, null, 1);
              }
            }
            else
            {
              localParcel.writeInt(0);
              continue;
            }
            localParcel.writeInt(0);
          }
          finally
          {
            localParcel.recycle();
          }
        }
      }
      
      public void zza(zza paramzza, Bundle paramBundle, zzbkw paramzzbkw)
        throws RemoteException
      {
        Object localObject = null;
        Parcel localParcel = Parcel.obtain();
        for (;;)
        {
          try
          {
            localParcel.writeInterfaceToken("com.google.android.gms.wallet.internal.IOwService");
            if (paramzza != null)
            {
              localParcel.writeInt(1);
              paramzza.writeToParcel(localParcel, 0);
              if (paramBundle != null)
              {
                localParcel.writeInt(1);
                paramBundle.writeToParcel(localParcel, 0);
                paramzza = (zza)localObject;
                if (paramzzbkw != null) {
                  paramzza = paramzzbkw.asBinder();
                }
                localParcel.writeStrongBinder(paramzza);
                this.zzrk.transact(16, localParcel, null, 1);
              }
            }
            else
            {
              localParcel.writeInt(0);
              continue;
            }
            localParcel.writeInt(0);
          }
          finally
          {
            localParcel.recycle();
          }
        }
      }
      
      public void zza(zzd paramzzd, Bundle paramBundle, zzbkw paramzzbkw)
        throws RemoteException
      {
        Object localObject = null;
        Parcel localParcel = Parcel.obtain();
        for (;;)
        {
          try
          {
            localParcel.writeInterfaceToken("com.google.android.gms.wallet.internal.IOwService");
            if (paramzzd != null)
            {
              localParcel.writeInt(1);
              paramzzd.writeToParcel(localParcel, 0);
              if (paramBundle != null)
              {
                localParcel.writeInt(1);
                paramBundle.writeToParcel(localParcel, 0);
                paramzzd = (zzd)localObject;
                if (paramzzbkw != null) {
                  paramzzd = paramzzbkw.asBinder();
                }
                localParcel.writeStrongBinder(paramzzd);
                this.zzrk.transact(12, localParcel, null, 1);
              }
            }
            else
            {
              localParcel.writeInt(0);
              continue;
            }
            localParcel.writeInt(0);
          }
          finally
          {
            localParcel.recycle();
          }
        }
      }
      
      public void zza(zzh paramzzh, Bundle paramBundle, zzbkw paramzzbkw)
        throws RemoteException
      {
        Object localObject = null;
        Parcel localParcel = Parcel.obtain();
        for (;;)
        {
          try
          {
            localParcel.writeInterfaceToken("com.google.android.gms.wallet.internal.IOwService");
            if (paramzzh != null)
            {
              localParcel.writeInt(1);
              paramzzh.writeToParcel(localParcel, 0);
              if (paramBundle != null)
              {
                localParcel.writeInt(1);
                paramBundle.writeToParcel(localParcel, 0);
                paramzzh = (zzh)localObject;
                if (paramzzbkw != null) {
                  paramzzh = paramzzbkw.asBinder();
                }
                localParcel.writeStrongBinder(paramzzh);
                this.zzrk.transact(15, localParcel, null, 1);
              }
            }
            else
            {
              localParcel.writeInt(0);
              continue;
            }
            localParcel.writeInt(0);
          }
          finally
          {
            localParcel.recycle();
          }
        }
      }
      
      public void zza(zze paramzze, Bundle paramBundle, zzbkw paramzzbkw)
        throws RemoteException
      {
        Object localObject = null;
        Parcel localParcel = Parcel.obtain();
        for (;;)
        {
          try
          {
            localParcel.writeInterfaceToken("com.google.android.gms.wallet.internal.IOwService");
            if (paramzze != null)
            {
              localParcel.writeInt(1);
              paramzze.writeToParcel(localParcel, 0);
              if (paramBundle != null)
              {
                localParcel.writeInt(1);
                paramBundle.writeToParcel(localParcel, 0);
                paramzze = (zze)localObject;
                if (paramzzbkw != null) {
                  paramzze = paramzzbkw.asBinder();
                }
                localParcel.writeStrongBinder(paramzze);
                this.zzrk.transact(6, localParcel, null, 1);
              }
            }
            else
            {
              localParcel.writeInt(0);
              continue;
            }
            localParcel.writeInt(0);
          }
          finally
          {
            localParcel.recycle();
          }
        }
      }
      
      public void zza(zzw paramzzw, Bundle paramBundle, zzbkw paramzzbkw)
        throws RemoteException
      {
        Object localObject = null;
        Parcel localParcel = Parcel.obtain();
        for (;;)
        {
          try
          {
            localParcel.writeInterfaceToken("com.google.android.gms.wallet.internal.IOwService");
            if (paramzzw != null)
            {
              localParcel.writeInt(1);
              paramzzw.writeToParcel(localParcel, 0);
              if (paramBundle != null)
              {
                localParcel.writeInt(1);
                paramBundle.writeToParcel(localParcel, 0);
                paramzzw = (zzw)localObject;
                if (paramzzbkw != null) {
                  paramzzw = paramzzbkw.asBinder();
                }
                localParcel.writeStrongBinder(paramzzw);
                this.zzrk.transact(17, localParcel, null, 1);
              }
            }
            else
            {
              localParcel.writeInt(0);
              continue;
            }
            localParcel.writeInt(0);
          }
          finally
          {
            localParcel.recycle();
          }
        }
      }
      
      /* Error */
      public void zza(String paramString1, String paramString2, Bundle paramBundle, zzbkw paramzzbkw)
        throws RemoteException
      {
        // Byte code:
        //   0: aconst_null
        //   1: astore 5
        //   3: invokestatic 31	android/os/Parcel:obtain	()Landroid/os/Parcel;
        //   6: astore 6
        //   8: aload 6
        //   10: ldc 33
        //   12: invokevirtual 37	android/os/Parcel:writeInterfaceToken	(Ljava/lang/String;)V
        //   15: aload 6
        //   17: aload_1
        //   18: invokevirtual 110	android/os/Parcel:writeString	(Ljava/lang/String;)V
        //   21: aload 6
        //   23: aload_2
        //   24: invokevirtual 110	android/os/Parcel:writeString	(Ljava/lang/String;)V
        //   27: aload_3
        //   28: ifnull +59 -> 87
        //   31: aload 6
        //   33: iconst_1
        //   34: invokevirtual 41	android/os/Parcel:writeInt	(I)V
        //   37: aload_3
        //   38: aload 6
        //   40: iconst_0
        //   41: invokevirtual 47	android/os/Bundle:writeToParcel	(Landroid/os/Parcel;I)V
        //   44: aload 5
        //   46: astore_1
        //   47: aload 4
        //   49: ifnull +11 -> 60
        //   52: aload 4
        //   54: invokeinterface 63 1 0
        //   59: astore_1
        //   60: aload 6
        //   62: aload_1
        //   63: invokevirtual 66	android/os/Parcel:writeStrongBinder	(Landroid/os/IBinder;)V
        //   66: aload_0
        //   67: getfield 18	com/google/android/gms/internal/zzbku$zza$zza:zzrk	Landroid/os/IBinder;
        //   70: iconst_3
        //   71: aload 6
        //   73: aconst_null
        //   74: iconst_1
        //   75: invokeinterface 53 5 0
        //   80: pop
        //   81: aload 6
        //   83: invokevirtual 56	android/os/Parcel:recycle	()V
        //   86: return
        //   87: aload 6
        //   89: iconst_0
        //   90: invokevirtual 41	android/os/Parcel:writeInt	(I)V
        //   93: goto -49 -> 44
        //   96: astore_1
        //   97: aload 6
        //   99: invokevirtual 56	android/os/Parcel:recycle	()V
        //   102: aload_1
        //   103: athrow
        // Local variable table:
        //   start	length	slot	name	signature
        //   0	104	0	this	zza
        //   0	104	1	paramString1	String
        //   0	104	2	paramString2	String
        //   0	104	3	paramBundle	Bundle
        //   0	104	4	paramzzbkw	zzbkw
        //   1	44	5	localObject	Object
        //   6	92	6	localParcel	Parcel
        // Exception table:
        //   from	to	target	type
        //   8	27	96	finally
        //   31	44	96	finally
        //   52	60	96	finally
        //   60	81	96	finally
        //   87	93	96	finally
      }
      
      /* Error */
      public void zzb(Bundle paramBundle, zzbkw paramzzbkw)
        throws RemoteException
      {
        // Byte code:
        //   0: aconst_null
        //   1: astore_3
        //   2: invokestatic 31	android/os/Parcel:obtain	()Landroid/os/Parcel;
        //   5: astore 4
        //   7: aload 4
        //   9: ldc 33
        //   11: invokevirtual 37	android/os/Parcel:writeInterfaceToken	(Ljava/lang/String;)V
        //   14: aload_1
        //   15: ifnull +57 -> 72
        //   18: aload 4
        //   20: iconst_1
        //   21: invokevirtual 41	android/os/Parcel:writeInt	(I)V
        //   24: aload_1
        //   25: aload 4
        //   27: iconst_0
        //   28: invokevirtual 47	android/os/Bundle:writeToParcel	(Landroid/os/Parcel;I)V
        //   31: aload_3
        //   32: astore_1
        //   33: aload_2
        //   34: ifnull +10 -> 44
        //   37: aload_2
        //   38: invokeinterface 63 1 0
        //   43: astore_1
        //   44: aload 4
        //   46: aload_1
        //   47: invokevirtual 66	android/os/Parcel:writeStrongBinder	(Landroid/os/IBinder;)V
        //   50: aload_0
        //   51: getfield 18	com/google/android/gms/internal/zzbku$zza$zza:zzrk	Landroid/os/IBinder;
        //   54: bipush 11
        //   56: aload 4
        //   58: aconst_null
        //   59: iconst_1
        //   60: invokeinterface 53 5 0
        //   65: pop
        //   66: aload 4
        //   68: invokevirtual 56	android/os/Parcel:recycle	()V
        //   71: return
        //   72: aload 4
        //   74: iconst_0
        //   75: invokevirtual 41	android/os/Parcel:writeInt	(I)V
        //   78: goto -47 -> 31
        //   81: astore_1
        //   82: aload 4
        //   84: invokevirtual 56	android/os/Parcel:recycle	()V
        //   87: aload_1
        //   88: athrow
        // Local variable table:
        //   start	length	slot	name	signature
        //   0	89	0	this	zza
        //   0	89	1	paramBundle	Bundle
        //   0	89	2	paramzzbkw	zzbkw
        //   1	31	3	localObject	Object
        //   5	78	4	localParcel	Parcel
        // Exception table:
        //   from	to	target	type
        //   7	14	81	finally
        //   18	31	81	finally
        //   37	44	81	finally
        //   44	66	81	finally
        //   72	78	81	finally
      }
    }
  }
}


/* Location:              /home/fabian/Escritorio/Proyectos/Android/Dev/jardecompiler/TMessagesProj-fat-debug.jar!/com/google/android/gms/internal/zzbku.class
 * Java compiler version: 6 (50.0)
 * JD-Core Version:       0.7.1-SNAPSHOT-20140817
 */