package com.google.android.gms.internal;

import android.support.annotation.WorkerThread;
import com.google.android.gms.common.internal.zzbo;
import java.net.URL;
import java.util.Map;

@WorkerThread
final class zzcft
  implements Runnable
{
  private final String mPackageName;
  private final URL zzJu;
  private final byte[] zzaKA;
  private final zzcfr zzbrd;
  private final Map<String, String> zzbre;
  
  public zzcft(String paramString, URL paramURL, byte[] paramArrayOfByte, Map<String, String> paramMap, zzcfr paramzzcfr)
  {
    zzbo.zzcF(paramURL);
    zzbo.zzu(paramArrayOfByte);
    Object localObject;
    zzbo.zzu(localObject);
    this.zzJu = paramArrayOfByte;
    this.zzaKA = paramMap;
    this.zzbrd = ((zzcfr)localObject);
    this.mPackageName = paramURL;
    this.zzbre = paramzzcfr;
  }
  
  /* Error */
  public final void run()
  {
    // Byte code:
    //   0: iconst_0
    //   1: istore 4
    //   3: iconst_0
    //   4: istore 5
    //   6: iconst_0
    //   7: istore_1
    //   8: aload_0
    //   9: getfield 24	com/google/android/gms/internal/zzcft:zzbrf	Lcom/google/android/gms/internal/zzcfp;
    //   12: invokevirtual 58	com/google/android/gms/internal/zzcfp:zzwq	()V
    //   15: aload_0
    //   16: getfield 39	com/google/android/gms/internal/zzcft:zzJu	Ljava/net/URL;
    //   19: invokevirtual 64	java/net/URL:openConnection	()Ljava/net/URLConnection;
    //   22: astore 6
    //   24: aload 6
    //   26: instanceof 66
    //   29: ifne +79 -> 108
    //   32: new 53	java/io/IOException
    //   35: dup
    //   36: ldc 68
    //   38: invokespecial 71	java/io/IOException:<init>	(Ljava/lang/String;)V
    //   41: athrow
    //   42: astore 8
    //   44: aconst_null
    //   45: astore 9
    //   47: iconst_0
    //   48: istore_1
    //   49: aconst_null
    //   50: astore 6
    //   52: aconst_null
    //   53: astore 7
    //   55: aload 6
    //   57: ifnull +8 -> 65
    //   60: aload 6
    //   62: invokevirtual 76	java/io/OutputStream:close	()V
    //   65: aload 7
    //   67: ifnull +8 -> 75
    //   70: aload 7
    //   72: invokevirtual 79	java/net/HttpURLConnection:disconnect	()V
    //   75: aload_0
    //   76: getfield 24	com/google/android/gms/internal/zzcft:zzbrf	Lcom/google/android/gms/internal/zzcfp;
    //   79: invokevirtual 83	com/google/android/gms/internal/zzcfp:zzwE	()Lcom/google/android/gms/internal/zzcgg;
    //   82: new 85	com/google/android/gms/internal/zzcfs
    //   85: dup
    //   86: aload_0
    //   87: getfield 45	com/google/android/gms/internal/zzcft:mPackageName	Ljava/lang/String;
    //   90: aload_0
    //   91: getfield 43	com/google/android/gms/internal/zzcft:zzbrd	Lcom/google/android/gms/internal/zzcfr;
    //   94: iload_1
    //   95: aload 8
    //   97: aconst_null
    //   98: aload 9
    //   100: aconst_null
    //   101: invokespecial 88	com/google/android/gms/internal/zzcfs:<init>	(Ljava/lang/String;Lcom/google/android/gms/internal/zzcfr;ILjava/lang/Throwable;[BLjava/util/Map;Lcom/google/android/gms/internal/zzcfq;)V
    //   104: invokevirtual 94	com/google/android/gms/internal/zzcgg:zzj	(Ljava/lang/Runnable;)V
    //   107: return
    //   108: aload 6
    //   110: checkcast 66	java/net/HttpURLConnection
    //   113: astore 6
    //   115: aload 6
    //   117: iconst_0
    //   118: invokevirtual 98	java/net/HttpURLConnection:setDefaultUseCaches	(Z)V
    //   121: invokestatic 104	com/google/android/gms/internal/zzcem:zzxz	()J
    //   124: pop2
    //   125: aload 6
    //   127: ldc 105
    //   129: invokevirtual 109	java/net/HttpURLConnection:setConnectTimeout	(I)V
    //   132: invokestatic 112	com/google/android/gms/internal/zzcem:zzxA	()J
    //   135: pop2
    //   136: aload 6
    //   138: ldc 113
    //   140: invokevirtual 116	java/net/HttpURLConnection:setReadTimeout	(I)V
    //   143: aload 6
    //   145: iconst_0
    //   146: invokevirtual 119	java/net/HttpURLConnection:setInstanceFollowRedirects	(Z)V
    //   149: aload 6
    //   151: iconst_1
    //   152: invokevirtual 122	java/net/HttpURLConnection:setDoInput	(Z)V
    //   155: iload 4
    //   157: istore_2
    //   158: iload 5
    //   160: istore_3
    //   161: aload_0
    //   162: getfield 47	com/google/android/gms/internal/zzcft:zzbre	Ljava/util/Map;
    //   165: ifnull +93 -> 258
    //   168: iload 4
    //   170: istore_2
    //   171: iload 5
    //   173: istore_3
    //   174: aload_0
    //   175: getfield 47	com/google/android/gms/internal/zzcft:zzbre	Ljava/util/Map;
    //   178: invokeinterface 128 1 0
    //   183: invokeinterface 134 1 0
    //   188: astore 7
    //   190: iload 4
    //   192: istore_2
    //   193: iload 5
    //   195: istore_3
    //   196: aload 7
    //   198: invokeinterface 140 1 0
    //   203: ifeq +55 -> 258
    //   206: iload 4
    //   208: istore_2
    //   209: iload 5
    //   211: istore_3
    //   212: aload 7
    //   214: invokeinterface 144 1 0
    //   219: checkcast 146	java/util/Map$Entry
    //   222: astore 8
    //   224: iload 4
    //   226: istore_2
    //   227: iload 5
    //   229: istore_3
    //   230: aload 6
    //   232: aload 8
    //   234: invokeinterface 149 1 0
    //   239: checkcast 151	java/lang/String
    //   242: aload 8
    //   244: invokeinterface 154 1 0
    //   249: checkcast 151	java/lang/String
    //   252: invokevirtual 158	java/net/HttpURLConnection:addRequestProperty	(Ljava/lang/String;Ljava/lang/String;)V
    //   255: goto -65 -> 190
    //   258: iload 4
    //   260: istore_2
    //   261: iload 5
    //   263: istore_3
    //   264: aload_0
    //   265: getfield 41	com/google/android/gms/internal/zzcft:zzaKA	[B
    //   268: ifnull +129 -> 397
    //   271: iload 4
    //   273: istore_2
    //   274: iload 5
    //   276: istore_3
    //   277: aload_0
    //   278: getfield 24	com/google/android/gms/internal/zzcft:zzbrf	Lcom/google/android/gms/internal/zzcfp;
    //   281: invokevirtual 162	com/google/android/gms/internal/zzcfp:zzwB	()Lcom/google/android/gms/internal/zzcjl;
    //   284: aload_0
    //   285: getfield 41	com/google/android/gms/internal/zzcft:zzaKA	[B
    //   288: invokevirtual 168	com/google/android/gms/internal/zzcjl:zzl	([B)[B
    //   291: astore 8
    //   293: iload 4
    //   295: istore_2
    //   296: iload 5
    //   298: istore_3
    //   299: aload_0
    //   300: getfield 24	com/google/android/gms/internal/zzcft:zzbrf	Lcom/google/android/gms/internal/zzcfp;
    //   303: invokevirtual 172	com/google/android/gms/internal/zzcfp:zzwF	()Lcom/google/android/gms/internal/zzcfl;
    //   306: invokevirtual 178	com/google/android/gms/internal/zzcfl:zzyD	()Lcom/google/android/gms/internal/zzcfn;
    //   309: ldc -76
    //   311: aload 8
    //   313: arraylength
    //   314: invokestatic 186	java/lang/Integer:valueOf	(I)Ljava/lang/Integer;
    //   317: invokevirtual 191	com/google/android/gms/internal/zzcfn:zzj	(Ljava/lang/String;Ljava/lang/Object;)V
    //   320: iload 4
    //   322: istore_2
    //   323: iload 5
    //   325: istore_3
    //   326: aload 6
    //   328: iconst_1
    //   329: invokevirtual 194	java/net/HttpURLConnection:setDoOutput	(Z)V
    //   332: iload 4
    //   334: istore_2
    //   335: iload 5
    //   337: istore_3
    //   338: aload 6
    //   340: ldc -60
    //   342: ldc -58
    //   344: invokevirtual 158	java/net/HttpURLConnection:addRequestProperty	(Ljava/lang/String;Ljava/lang/String;)V
    //   347: iload 4
    //   349: istore_2
    //   350: iload 5
    //   352: istore_3
    //   353: aload 6
    //   355: aload 8
    //   357: arraylength
    //   358: invokevirtual 201	java/net/HttpURLConnection:setFixedLengthStreamingMode	(I)V
    //   361: iload 4
    //   363: istore_2
    //   364: iload 5
    //   366: istore_3
    //   367: aload 6
    //   369: invokevirtual 204	java/net/HttpURLConnection:connect	()V
    //   372: iload 4
    //   374: istore_2
    //   375: iload 5
    //   377: istore_3
    //   378: aload 6
    //   380: invokevirtual 208	java/net/HttpURLConnection:getOutputStream	()Ljava/io/OutputStream;
    //   383: astore 7
    //   385: aload 7
    //   387: aload 8
    //   389: invokevirtual 212	java/io/OutputStream:write	([B)V
    //   392: aload 7
    //   394: invokevirtual 76	java/io/OutputStream:close	()V
    //   397: iload 4
    //   399: istore_2
    //   400: iload 5
    //   402: istore_3
    //   403: aload 6
    //   405: invokevirtual 216	java/net/HttpURLConnection:getResponseCode	()I
    //   408: istore_1
    //   409: iload_1
    //   410: istore_2
    //   411: iload_1
    //   412: istore_3
    //   413: aload 6
    //   415: invokevirtual 220	java/net/HttpURLConnection:getHeaderFields	()Ljava/util/Map;
    //   418: astore 7
    //   420: aload_0
    //   421: getfield 24	com/google/android/gms/internal/zzcft:zzbrf	Lcom/google/android/gms/internal/zzcfp;
    //   424: aload 6
    //   426: invokestatic 224	com/google/android/gms/internal/zzcfp:zza	(Lcom/google/android/gms/internal/zzcfp;Ljava/net/HttpURLConnection;)[B
    //   429: astore 8
    //   431: aload 6
    //   433: ifnull +8 -> 441
    //   436: aload 6
    //   438: invokevirtual 79	java/net/HttpURLConnection:disconnect	()V
    //   441: aload_0
    //   442: getfield 24	com/google/android/gms/internal/zzcft:zzbrf	Lcom/google/android/gms/internal/zzcfp;
    //   445: invokevirtual 83	com/google/android/gms/internal/zzcfp:zzwE	()Lcom/google/android/gms/internal/zzcgg;
    //   448: new 85	com/google/android/gms/internal/zzcfs
    //   451: dup
    //   452: aload_0
    //   453: getfield 45	com/google/android/gms/internal/zzcft:mPackageName	Ljava/lang/String;
    //   456: aload_0
    //   457: getfield 43	com/google/android/gms/internal/zzcft:zzbrd	Lcom/google/android/gms/internal/zzcfr;
    //   460: iload_1
    //   461: aconst_null
    //   462: aload 8
    //   464: aload 7
    //   466: aconst_null
    //   467: invokespecial 88	com/google/android/gms/internal/zzcfs:<init>	(Ljava/lang/String;Lcom/google/android/gms/internal/zzcfr;ILjava/lang/Throwable;[BLjava/util/Map;Lcom/google/android/gms/internal/zzcfq;)V
    //   470: invokevirtual 94	com/google/android/gms/internal/zzcgg:zzj	(Ljava/lang/Runnable;)V
    //   473: return
    //   474: astore 6
    //   476: aload_0
    //   477: getfield 24	com/google/android/gms/internal/zzcft:zzbrf	Lcom/google/android/gms/internal/zzcfp;
    //   480: invokevirtual 172	com/google/android/gms/internal/zzcfp:zzwF	()Lcom/google/android/gms/internal/zzcfl;
    //   483: invokevirtual 227	com/google/android/gms/internal/zzcfl:zzyx	()Lcom/google/android/gms/internal/zzcfn;
    //   486: ldc -27
    //   488: aload_0
    //   489: getfield 45	com/google/android/gms/internal/zzcft:mPackageName	Ljava/lang/String;
    //   492: invokestatic 233	com/google/android/gms/internal/zzcfl:zzdZ	(Ljava/lang/String;)Ljava/lang/Object;
    //   495: aload 6
    //   497: invokevirtual 237	com/google/android/gms/internal/zzcfn:zze	(Ljava/lang/String;Ljava/lang/Object;Ljava/lang/Object;)V
    //   500: goto -435 -> 65
    //   503: astore 8
    //   505: aconst_null
    //   506: astore 7
    //   508: aconst_null
    //   509: astore 6
    //   511: aconst_null
    //   512: astore 9
    //   514: aload 6
    //   516: ifnull +8 -> 524
    //   519: aload 6
    //   521: invokevirtual 76	java/io/OutputStream:close	()V
    //   524: aload 9
    //   526: ifnull +8 -> 534
    //   529: aload 9
    //   531: invokevirtual 79	java/net/HttpURLConnection:disconnect	()V
    //   534: aload_0
    //   535: getfield 24	com/google/android/gms/internal/zzcft:zzbrf	Lcom/google/android/gms/internal/zzcfp;
    //   538: invokevirtual 83	com/google/android/gms/internal/zzcfp:zzwE	()Lcom/google/android/gms/internal/zzcgg;
    //   541: new 85	com/google/android/gms/internal/zzcfs
    //   544: dup
    //   545: aload_0
    //   546: getfield 45	com/google/android/gms/internal/zzcft:mPackageName	Ljava/lang/String;
    //   549: aload_0
    //   550: getfield 43	com/google/android/gms/internal/zzcft:zzbrd	Lcom/google/android/gms/internal/zzcfr;
    //   553: iload_1
    //   554: aconst_null
    //   555: aconst_null
    //   556: aload 7
    //   558: aconst_null
    //   559: invokespecial 88	com/google/android/gms/internal/zzcfs:<init>	(Ljava/lang/String;Lcom/google/android/gms/internal/zzcfr;ILjava/lang/Throwable;[BLjava/util/Map;Lcom/google/android/gms/internal/zzcfq;)V
    //   562: invokevirtual 94	com/google/android/gms/internal/zzcgg:zzj	(Ljava/lang/Runnable;)V
    //   565: aload 8
    //   567: athrow
    //   568: astore 6
    //   570: aload_0
    //   571: getfield 24	com/google/android/gms/internal/zzcft:zzbrf	Lcom/google/android/gms/internal/zzcfp;
    //   574: invokevirtual 172	com/google/android/gms/internal/zzcfp:zzwF	()Lcom/google/android/gms/internal/zzcfl;
    //   577: invokevirtual 227	com/google/android/gms/internal/zzcfl:zzyx	()Lcom/google/android/gms/internal/zzcfn;
    //   580: ldc -27
    //   582: aload_0
    //   583: getfield 45	com/google/android/gms/internal/zzcft:mPackageName	Ljava/lang/String;
    //   586: invokestatic 233	com/google/android/gms/internal/zzcfl:zzdZ	(Ljava/lang/String;)Ljava/lang/Object;
    //   589: aload 6
    //   591: invokevirtual 237	com/google/android/gms/internal/zzcfn:zze	(Ljava/lang/String;Ljava/lang/Object;Ljava/lang/Object;)V
    //   594: goto -70 -> 524
    //   597: astore 8
    //   599: aconst_null
    //   600: astore 7
    //   602: aconst_null
    //   603: astore 10
    //   605: aload 6
    //   607: astore 9
    //   609: aload 10
    //   611: astore 6
    //   613: iload_2
    //   614: istore_1
    //   615: goto -101 -> 514
    //   618: astore 8
    //   620: aconst_null
    //   621: astore 10
    //   623: aload 6
    //   625: astore 9
    //   627: aload 7
    //   629: astore 6
    //   631: aload 10
    //   633: astore 7
    //   635: goto -121 -> 514
    //   638: astore 8
    //   640: aconst_null
    //   641: astore 10
    //   643: aload 6
    //   645: astore 9
    //   647: aload 10
    //   649: astore 6
    //   651: goto -137 -> 514
    //   654: astore 10
    //   656: aconst_null
    //   657: astore 9
    //   659: iconst_0
    //   660: istore_1
    //   661: aload 6
    //   663: astore 8
    //   665: aload 7
    //   667: astore 6
    //   669: aload 8
    //   671: astore 7
    //   673: aload 10
    //   675: astore 8
    //   677: goto -622 -> 55
    //   680: astore 8
    //   682: aload 7
    //   684: astore 9
    //   686: aload 6
    //   688: astore 7
    //   690: aconst_null
    //   691: astore 6
    //   693: goto -638 -> 55
    //   696: astore 8
    //   698: aconst_null
    //   699: astore 9
    //   701: iload_3
    //   702: istore_1
    //   703: aload 6
    //   705: astore 7
    //   707: aconst_null
    //   708: astore 6
    //   710: goto -655 -> 55
    // Local variable table:
    //   start	length	slot	name	signature
    //   0	713	0	this	zzcft
    //   7	696	1	i	int
    //   157	457	2	j	int
    //   160	542	3	k	int
    //   1	397	4	m	int
    //   4	397	5	n	int
    //   22	415	6	localObject1	Object
    //   474	22	6	localIOException1	java.io.IOException
    //   509	11	6	localObject2	Object
    //   568	38	6	localIOException2	java.io.IOException
    //   611	98	6	localObject3	Object
    //   53	653	7	localObject4	Object
    //   42	54	8	localIOException3	java.io.IOException
    //   222	241	8	localObject5	Object
    //   503	63	8	localObject6	Object
    //   597	1	8	localObject7	Object
    //   618	1	8	localObject8	Object
    //   638	1	8	localObject9	Object
    //   663	13	8	localObject10	Object
    //   680	1	8	localIOException4	java.io.IOException
    //   696	1	8	localIOException5	java.io.IOException
    //   45	655	9	localObject11	Object
    //   603	45	10	localObject12	Object
    //   654	20	10	localIOException6	java.io.IOException
    // Exception table:
    //   from	to	target	type
    //   15	42	42	java/io/IOException
    //   108	155	42	java/io/IOException
    //   60	65	474	java/io/IOException
    //   15	42	503	finally
    //   108	155	503	finally
    //   519	524	568	java/io/IOException
    //   161	168	597	finally
    //   174	190	597	finally
    //   196	206	597	finally
    //   212	224	597	finally
    //   230	255	597	finally
    //   264	271	597	finally
    //   277	293	597	finally
    //   299	320	597	finally
    //   326	332	597	finally
    //   338	347	597	finally
    //   353	361	597	finally
    //   367	372	597	finally
    //   378	385	597	finally
    //   403	409	597	finally
    //   413	420	597	finally
    //   385	397	618	finally
    //   420	431	638	finally
    //   385	397	654	java/io/IOException
    //   420	431	680	java/io/IOException
    //   161	168	696	java/io/IOException
    //   174	190	696	java/io/IOException
    //   196	206	696	java/io/IOException
    //   212	224	696	java/io/IOException
    //   230	255	696	java/io/IOException
    //   264	271	696	java/io/IOException
    //   277	293	696	java/io/IOException
    //   299	320	696	java/io/IOException
    //   326	332	696	java/io/IOException
    //   338	347	696	java/io/IOException
    //   353	361	696	java/io/IOException
    //   367	372	696	java/io/IOException
    //   378	385	696	java/io/IOException
    //   403	409	696	java/io/IOException
    //   413	420	696	java/io/IOException
  }
}


/* Location:              /home/fabian/Escritorio/Proyectos/Android/Dev/jardecompiler/TMessagesProj-fat-debug.jar!/com/google/android/gms/internal/zzcft.class
 * Java compiler version: 6 (50.0)
 * JD-Core Version:       0.7.1-SNAPSHOT-20140817
 */