package com.google.android.gms.internal;

import android.app.Application;
import android.content.Context;
import android.content.pm.ApplicationInfo;
import android.content.pm.PackageInfo;
import android.content.pm.PackageManager;
import android.content.pm.PackageManager.NameNotFoundException;
import android.database.sqlite.SQLiteDatabase;
import android.database.sqlite.SQLiteException;
import android.net.Uri;
import android.net.Uri.Builder;
import android.os.Build;
import android.os.Build.VERSION;
import android.os.Bundle;
import android.provider.Settings.Secure;
import android.support.v4.util.ArrayMap;
import android.text.TextUtils;
import android.util.Pair;
import com.google.android.gms.common.api.internal.zzbz;
import com.google.android.gms.common.internal.zzbq;
import com.google.android.gms.common.util.zzd;
import com.google.android.gms.common.util.zzh;
import com.google.android.gms.measurement.AppMeasurement;
import com.google.firebase.analytics.FirebaseAnalytics;
import java.io.File;
import java.io.FileNotFoundException;
import java.io.IOException;
import java.io.RandomAccessFile;
import java.net.MalformedURLException;
import java.net.URL;
import java.nio.ByteBuffer;
import java.nio.channels.FileChannel;
import java.nio.channels.FileLock;
import java.security.SecureRandom;
import java.util.ArrayList;
import java.util.Collection;
import java.util.Collections;
import java.util.Iterator;
import java.util.List;
import java.util.Locale;
import java.util.Map;
import java.util.concurrent.ExecutionException;
import java.util.concurrent.Future;
import java.util.concurrent.TimeUnit;
import java.util.concurrent.TimeoutException;
import java.util.concurrent.atomic.AtomicReference;

public class zzcim
{
  private static volatile zzcim zzjev;
  private final Context mContext;
  private final zzd zzata;
  private boolean zzdtb = false;
  private final zzcgn zzjew;
  private final zzchx zzjex;
  private final zzchm zzjey;
  private final zzcih zzjez;
  private final zzclf zzjfa;
  private final zzcig zzjfb;
  private final AppMeasurement zzjfc;
  private final FirebaseAnalytics zzjfd;
  private final zzclq zzjfe;
  private final zzchk zzjff;
  private final zzcgo zzjfg;
  private final zzchi zzjfh;
  private final zzchq zzjfi;
  private final zzckc zzjfj;
  private final zzckg zzjfk;
  private final zzcgu zzjfl;
  private final zzcjn zzjfm;
  private final zzchh zzjfn;
  private final zzchv zzjfo;
  private final zzcll zzjfp;
  private final zzcgk zzjfq;
  private final zzcgd zzjfr;
  private boolean zzjfs;
  private Boolean zzjft;
  private long zzjfu;
  private FileLock zzjfv;
  private FileChannel zzjfw;
  private List<Long> zzjfx;
  private List<Runnable> zzjfy;
  private int zzjfz;
  private int zzjga;
  private long zzjgb;
  private long zzjgc;
  private boolean zzjgd;
  private boolean zzjge;
  private boolean zzjgf;
  private final long zzjgg;
  
  private zzcim(zzcjm paramzzcjm)
  {
    zzbq.checkNotNull(paramzzcjm);
    this.mContext = paramzzcjm.mContext;
    this.zzjgb = -1L;
    this.zzata = zzh.zzamg();
    this.zzjgg = this.zzata.currentTimeMillis();
    this.zzjew = new zzcgn(this);
    paramzzcjm = new zzchx(this);
    paramzzcjm.initialize();
    this.zzjex = paramzzcjm;
    paramzzcjm = new zzchm(this);
    paramzzcjm.initialize();
    this.zzjey = paramzzcjm;
    paramzzcjm = new zzclq(this);
    paramzzcjm.initialize();
    this.zzjfe = paramzzcjm;
    paramzzcjm = new zzchk(this);
    paramzzcjm.initialize();
    this.zzjff = paramzzcjm;
    paramzzcjm = new zzcgu(this);
    paramzzcjm.initialize();
    this.zzjfl = paramzzcjm;
    paramzzcjm = new zzchh(this);
    paramzzcjm.initialize();
    this.zzjfn = paramzzcjm;
    paramzzcjm = new zzcgo(this);
    paramzzcjm.initialize();
    this.zzjfg = paramzzcjm;
    paramzzcjm = new zzchi(this);
    paramzzcjm.initialize();
    this.zzjfh = paramzzcjm;
    paramzzcjm = new zzcgk(this);
    paramzzcjm.initialize();
    this.zzjfq = paramzzcjm;
    this.zzjfr = new zzcgd(this);
    paramzzcjm = new zzchq(this);
    paramzzcjm.initialize();
    this.zzjfi = paramzzcjm;
    paramzzcjm = new zzckc(this);
    paramzzcjm.initialize();
    this.zzjfj = paramzzcjm;
    paramzzcjm = new zzckg(this);
    paramzzcjm.initialize();
    this.zzjfk = paramzzcjm;
    paramzzcjm = new zzcjn(this);
    paramzzcjm.initialize();
    this.zzjfm = paramzzcjm;
    paramzzcjm = new zzcll(this);
    paramzzcjm.initialize();
    this.zzjfp = paramzzcjm;
    this.zzjfo = new zzchv(this);
    this.zzjfc = new AppMeasurement(this);
    this.zzjfd = new FirebaseAnalytics(this);
    paramzzcjm = new zzclf(this);
    paramzzcjm.initialize();
    this.zzjfa = paramzzcjm;
    paramzzcjm = new zzcig(this);
    paramzzcjm.initialize();
    this.zzjfb = paramzzcjm;
    paramzzcjm = new zzcih(this);
    paramzzcjm.initialize();
    this.zzjez = paramzzcjm;
    if ((this.mContext.getApplicationContext() instanceof Application))
    {
      paramzzcjm = zzawm();
      if ((paramzzcjm.getContext().getApplicationContext() instanceof Application))
      {
        Application localApplication = (Application)paramzzcjm.getContext().getApplicationContext();
        if (paramzzcjm.zzjgx == null) {
          paramzzcjm.zzjgx = new zzckb(paramzzcjm, null);
        }
        localApplication.unregisterActivityLifecycleCallbacks(paramzzcjm.zzjgx);
        localApplication.registerActivityLifecycleCallbacks(paramzzcjm.zzjgx);
        paramzzcjm.zzawy().zzazj().log("Registered activity lifecycle callback");
      }
    }
    for (;;)
    {
      this.zzjez.zzg(new zzcin(this));
      return;
      zzawy().zzazf().log("Application context is not an Application");
    }
  }
  
  private final int zza(FileChannel paramFileChannel)
  {
    zzawx().zzve();
    if ((paramFileChannel == null) || (!paramFileChannel.isOpen())) {
      zzawy().zzazd().log("Bad chanel to read from");
    }
    ByteBuffer localByteBuffer;
    for (;;)
    {
      return 0;
      localByteBuffer = ByteBuffer.allocate(4);
      try
      {
        paramFileChannel.position(0L);
        i = paramFileChannel.read(localByteBuffer);
        if (i != 4)
        {
          if (i == -1) {
            continue;
          }
          zzawy().zzazf().zzj("Unexpected data length. Bytes read", Integer.valueOf(i));
          return 0;
        }
      }
      catch (IOException paramFileChannel)
      {
        zzawy().zzazd().zzj("Failed to read from channel", paramFileChannel);
        return 0;
      }
    }
    localByteBuffer.flip();
    int i = localByteBuffer.getInt();
    return i;
  }
  
  private final zzcgi zza(Context paramContext, String paramString1, String paramString2, boolean paramBoolean1, boolean paramBoolean2)
  {
    Object localObject3 = "Unknown";
    String str = "Unknown";
    int i = Integer.MIN_VALUE;
    Object localObject1 = paramContext.getPackageManager();
    if (localObject1 == null)
    {
      zzawy().zzazd().log("PackageManager is null, can not log app install information");
      return null;
    }
    try
    {
      localObject1 = ((PackageManager)localObject1).getInstallerPackageName(paramString1);
      localObject3 = localObject1;
    }
    catch (IllegalArgumentException localIllegalArgumentException)
    {
      for (;;)
      {
        try
        {
          localPackageInfo = zzbhf.zzdb(paramContext).getPackageInfo(paramString1, 0);
          localObject3 = str;
          if (localPackageInfo != null)
          {
            localObject3 = zzbhf.zzdb(paramContext).zzgt(paramString1);
            if (TextUtils.isEmpty((CharSequence)localObject3)) {
              break label245;
            }
            localObject3 = ((CharSequence)localObject3).toString();
          }
        }
        catch (PackageManager.NameNotFoundException paramContext)
        {
          localObject3 = "Unknown";
          zzawy().zzazd().zze("Error retrieving newly installed package info. appId, appName", zzchm.zzjk(paramString1), localObject3);
          return null;
        }
        try
        {
          str = localPackageInfo.versionName;
          i = localPackageInfo.versionCode;
          localObject3 = str;
          return new zzcgi(paramString1, paramString2, (String)localObject3, i, (String)localObject1, 11910L, zzawu().zzaf(paramContext, paramString1), null, paramBoolean1, false, "", 0L, 0L, 0, paramBoolean2);
        }
        catch (PackageManager.NameNotFoundException paramContext)
        {
          continue;
        }
        localIllegalArgumentException = localIllegalArgumentException;
        zzawy().zzazd().zzj("Error retrieving installer package name. appId", zzchm.zzjk(paramString1));
        continue;
        localObject2 = localObject3;
        if ("com.android.vending".equals(localObject3)) {
          localObject2 = "";
        }
      }
    }
    if (localObject3 == null) {
      localObject1 = "manual_install";
    }
    for (;;)
    {
      PackageInfo localPackageInfo;
      Object localObject2;
      label245:
      localObject3 = "Unknown";
    }
  }
  
  private static void zza(zzcjk paramzzcjk)
  {
    if (paramzzcjk == null) {
      throw new IllegalStateException("Component not created");
    }
  }
  
  private static void zza(zzcjl paramzzcjl)
  {
    if (paramzzcjl == null) {
      throw new IllegalStateException("Component not created");
    }
    if (!paramzzcjl.isInitialized()) {
      throw new IllegalStateException("Component not initialized");
    }
  }
  
  private final boolean zza(int paramInt, FileChannel paramFileChannel)
  {
    boolean bool = true;
    zzawx().zzve();
    if ((paramFileChannel == null) || (!paramFileChannel.isOpen()))
    {
      zzawy().zzazd().log("Bad chanel to read from");
      bool = false;
    }
    for (;;)
    {
      return bool;
      ByteBuffer localByteBuffer = ByteBuffer.allocate(4);
      localByteBuffer.putInt(paramInt);
      localByteBuffer.flip();
      try
      {
        paramFileChannel.truncate(0L);
        paramFileChannel.write(localByteBuffer);
        paramFileChannel.force(true);
        if (paramFileChannel.size() != 4L)
        {
          zzawy().zzazd().zzj("Error writing to channel. Bytes written", Long.valueOf(paramFileChannel.size()));
          return true;
        }
      }
      catch (IOException paramFileChannel)
      {
        zzawy().zzazd().zzj("Failed to write to channel", paramFileChannel);
      }
    }
    return false;
  }
  
  private static boolean zza(zzcmb paramzzcmb, String paramString, Object paramObject)
  {
    if ((TextUtils.isEmpty(paramString)) || (paramObject == null)) {}
    label111:
    for (;;)
    {
      return false;
      paramzzcmb = paramzzcmb.zzjlh;
      int j = paramzzcmb.length;
      int i = 0;
      for (;;)
      {
        if (i >= j) {
          break label111;
        }
        Object localObject = paramzzcmb[i];
        if (paramString.equals(((zzcmc)localObject).name))
        {
          if (((!(paramObject instanceof Long)) || (!paramObject.equals(((zzcmc)localObject).zzjll))) && ((!(paramObject instanceof String)) || (!paramObject.equals(((zzcmc)localObject).zzgcc))) && ((!(paramObject instanceof Double)) || (!paramObject.equals(((zzcmc)localObject).zzjjl)))) {
            break;
          }
          return true;
        }
        i += 1;
      }
    }
  }
  
  private final boolean zza(String paramString, zzcha paramzzcha)
  {
    String str = paramzzcha.zzizt.getString("currency");
    double d1;
    long l1;
    Object localObject;
    int i;
    if ("ecommerce_purchase".equals(paramzzcha.name))
    {
      double d2 = paramzzcha.zzizt.getDouble("value").doubleValue() * 1000000.0D;
      d1 = d2;
      if (d2 == 0.0D) {
        d1 = paramzzcha.zzizt.getLong("value").longValue() * 1000000.0D;
      }
      if ((d1 <= 9.223372036854776E18D) && (d1 >= -9.223372036854776E18D))
      {
        l1 = Math.round(d1);
        if (!TextUtils.isEmpty(str))
        {
          localObject = str.toUpperCase(Locale.US);
          if (((String)localObject).matches("[A-Z]{3}"))
          {
            str = String.valueOf("_ltv_");
            localObject = String.valueOf(localObject);
            if (((String)localObject).length() == 0) {
              break label379;
            }
            str = str.concat((String)localObject);
            localObject = zzaws().zzag(paramString, str);
            if ((localObject != null) && ((((zzclp)localObject).mValue instanceof Long))) {
              break label418;
            }
            localObject = zzaws();
            i = this.zzjew.zzb(paramString, zzchc.zzjbh);
            zzbq.zzgm(paramString);
            ((zzcjk)localObject).zzve();
            ((zzcjl)localObject).zzxf();
          }
        }
      }
    }
    for (;;)
    {
      try
      {
        ((zzcgo)localObject).getWritableDatabase().execSQL("delete from user_attributes where app_id=? and name in (select name from user_attributes where app_id=? and name like '_ltv_%' order by set_timestamp desc limit ?,10);", new String[] { paramString, paramString, String.valueOf(i - 1) });
        paramzzcha = new zzclp(paramString, paramzzcha.zziyf, str, this.zzata.currentTimeMillis(), Long.valueOf(l1));
        if (!zzaws().zza(paramzzcha))
        {
          zzawy().zzazd().zzd("Too many unique user properties are set. Ignoring user property. appId", zzchm.zzjk(paramString), zzawt().zzjj(paramzzcha.mName), paramzzcha.mValue);
          zzawu().zza(paramString, 9, null, null, 0);
        }
        return true;
        zzawy().zzazf().zze("Data lost. Currency value is too big. appId", zzchm.zzjk(paramString), Double.valueOf(d1));
        return false;
        l1 = paramzzcha.zzizt.getLong("value").longValue();
        break;
        label379:
        str = new String(str);
      }
      catch (SQLiteException localSQLiteException)
      {
        ((zzcjk)localObject).zzawy().zzazd().zze("Error pruning currencies. appId", zzchm.zzjk(paramString), localSQLiteException);
        continue;
      }
      label418:
      long l2 = ((Long)((zzclp)localObject).mValue).longValue();
      paramzzcha = new zzclp(paramString, paramzzcha.zziyf, str, this.zzata.currentTimeMillis(), Long.valueOf(l1 + l2));
    }
  }
  
  private final zzcma[] zza(String paramString, zzcmg[] paramArrayOfzzcmg, zzcmb[] paramArrayOfzzcmb)
  {
    zzbq.zzgm(paramString);
    return zzawl().zza(paramString, paramArrayOfzzcmb, paramArrayOfzzcmg);
  }
  
  static void zzawi()
  {
    throw new IllegalStateException("Unexpected call on client side");
  }
  
  private final void zzazw()
  {
    zzawx().zzve();
    this.zzjfe.zzazw();
    this.zzjex.zzazw();
    this.zzjfn.zzazw();
    zzawy().zzazh().zzj("App measurement is starting up, version", Long.valueOf(11910L));
    zzawy().zzazh().log("To enable debug logging run: adb shell setprop log.tag.FA VERBOSE");
    String str = this.zzjfn.getAppId();
    zzcho localzzcho;
    if (zzawu().zzkj(str))
    {
      localzzcho = zzawy().zzazh();
      str = "Faster debug mode event logging enabled. To disable, run:\n  adb shell setprop debug.firebase.analytics.app .none.";
    }
    for (;;)
    {
      localzzcho.log(str);
      zzawy().zzazi().log("Debug-level message logging enabled");
      if (this.zzjfz != this.zzjga) {
        zzawy().zzazd().zze("Not all components initialized", Integer.valueOf(this.zzjfz), Integer.valueOf(this.zzjga));
      }
      this.zzdtb = true;
      return;
      localzzcho = zzawy().zzazh();
      str = String.valueOf(str);
      if (str.length() != 0) {
        str = "To enable faster debug mode event logging run:\n  adb shell setprop debug.firebase.analytics.app ".concat(str);
      } else {
        str = new String("To enable faster debug mode event logging run:\n  adb shell setprop debug.firebase.analytics.app ");
      }
    }
  }
  
  private final void zzb(zzcgh paramzzcgh)
  {
    zzawx().zzve();
    if (TextUtils.isEmpty(paramzzcgh.getGmpAppId()))
    {
      zzb(paramzzcgh.getAppId(), 204, null, null, null);
      return;
    }
    Object localObject1 = paramzzcgh.getGmpAppId();
    String str2 = paramzzcgh.getAppInstanceId();
    Object localObject2 = new Uri.Builder();
    Object localObject3 = ((Uri.Builder)localObject2).scheme((String)zzchc.zzjah.get()).encodedAuthority((String)zzchc.zzjai.get());
    localObject1 = String.valueOf(localObject1);
    if (((String)localObject1).length() != 0)
    {
      localObject1 = "config/app/".concat((String)localObject1);
      ((Uri.Builder)localObject3).path((String)localObject1).appendQueryParameter("app_instance_id", str2).appendQueryParameter("platform", "android").appendQueryParameter("gmp_version", "11910");
      str2 = ((Uri.Builder)localObject2).build().toString();
    }
    for (;;)
    {
      try
      {
        localObject2 = new URL(str2);
        zzawy().zzazj().zzj("Fetching remote configuration", paramzzcgh.getAppId());
        localObject1 = zzawv().zzjs(paramzzcgh.getAppId());
        localObject3 = zzawv().zzjt(paramzzcgh.getAppId());
        if ((localObject1 == null) || (TextUtils.isEmpty((CharSequence)localObject3))) {
          break label336;
        }
        localObject1 = new ArrayMap();
        ((Map)localObject1).put("If-Modified-Since", localObject3);
        this.zzjgd = true;
        localObject3 = zzbab();
        String str3 = paramzzcgh.getAppId();
        zzciq localzzciq = new zzciq(this);
        ((zzcjk)localObject3).zzve();
        ((zzcjl)localObject3).zzxf();
        zzbq.checkNotNull(localObject2);
        zzbq.checkNotNull(localzzciq);
        ((zzcjk)localObject3).zzawx().zzh(new zzchu((zzchq)localObject3, str3, (URL)localObject2, null, (Map)localObject1, localzzciq));
        return;
      }
      catch (MalformedURLException localMalformedURLException)
      {
        zzawy().zzazd().zze("Failed to parse config URL. Not fetching. appId", zzchm.zzjk(paramzzcgh.getAppId()), str2);
        return;
      }
      String str1 = new String("config/app/");
      break;
      label336:
      str1 = null;
    }
  }
  
  private final zzchv zzbac()
  {
    if (this.zzjfo == null) {
      throw new IllegalStateException("Network broadcast receiver not created");
    }
    return this.zzjfo;
  }
  
  private final zzcll zzbad()
  {
    zza(this.zzjfp);
    return this.zzjfp;
  }
  
  private final boolean zzbae()
  {
    zzawx().zzve();
    File localFile = new File(this.mContext.getFilesDir(), "google_app_measurement.db");
    try
    {
      this.zzjfw = new RandomAccessFile(localFile, "rw").getChannel();
      this.zzjfv = this.zzjfw.tryLock();
      if (this.zzjfv != null)
      {
        zzawy().zzazj().log("Storage concurrent access okay");
        return true;
      }
      zzawy().zzazd().log("Storage concurrent data access panic");
    }
    catch (FileNotFoundException localFileNotFoundException)
    {
      for (;;)
      {
        zzawy().zzazd().zzj("Failed to acquire storage lock", localFileNotFoundException);
      }
    }
    catch (IOException localIOException)
    {
      for (;;)
      {
        zzawy().zzazd().zzj("Failed to access storage lock file", localIOException);
      }
    }
    return false;
  }
  
  private final long zzbag()
  {
    long l3 = this.zzata.currentTimeMillis();
    zzchx localzzchx = zzawz();
    localzzchx.zzxf();
    localzzchx.zzve();
    long l2 = localzzchx.zzjcv.get();
    long l1 = l2;
    if (l2 == 0L)
    {
      l1 = 1L + localzzchx.zzawu().zzbaz().nextInt(86400000);
      localzzchx.zzjcv.set(l1);
    }
    return (l1 + l3) / 1000L / 60L / 60L / 24L;
  }
  
  private final boolean zzbai()
  {
    zzawx().zzve();
    zzxf();
    return (zzaws().zzayk()) || (!TextUtils.isEmpty(zzaws().zzayf()));
  }
  
  private final void zzbaj()
  {
    zzawx().zzve();
    zzxf();
    if (!zzbam()) {
      return;
    }
    long l1;
    if (this.zzjgc > 0L)
    {
      l1 = 3600000L - Math.abs(this.zzata.elapsedRealtime() - this.zzjgc);
      if (l1 > 0L)
      {
        zzawy().zzazj().zzj("Upload has been suspended. Will update scheduling later in approximately ms", Long.valueOf(l1));
        zzbac().unregister();
        zzbad().cancel();
        return;
      }
      this.zzjgc = 0L;
    }
    if ((!zzazv()) || (!zzbai()))
    {
      zzawy().zzazj().log("Nothing to upload or uploading impossible");
      zzbac().unregister();
      zzbad().cancel();
      return;
    }
    long l3 = this.zzata.currentTimeMillis();
    long l2 = Math.max(0L, ((Long)zzchc.zzjbd.get()).longValue());
    int i;
    label235:
    long l6;
    long l5;
    long l4;
    if ((zzaws().zzayl()) || (zzaws().zzayg()))
    {
      i = 1;
      if (i == 0) {
        break label346;
      }
      String str = this.zzjew.zzayd();
      if ((TextUtils.isEmpty(str)) || (".none.".equals(str))) {
        break label326;
      }
      l1 = Math.max(0L, ((Long)zzchc.zzjay.get()).longValue());
      l6 = zzawz().zzjcr.get();
      l5 = zzawz().zzjcs.get();
      l4 = Math.max(zzaws().zzayi(), zzaws().zzayj());
      if (l4 != 0L) {
        break label366;
      }
      l1 = 0L;
    }
    for (;;)
    {
      if (l1 != 0L) {
        break label566;
      }
      zzawy().zzazj().log("Next upload time is 0");
      zzbac().unregister();
      zzbad().cancel();
      return;
      i = 0;
      break;
      label326:
      l1 = Math.max(0L, ((Long)zzchc.zzjax.get()).longValue());
      break label235;
      label346:
      l1 = Math.max(0L, ((Long)zzchc.zzjaw.get()).longValue());
      break label235;
      label366:
      l4 = l3 - Math.abs(l4 - l3);
      l6 = Math.abs(l6 - l3);
      l5 = l3 - Math.abs(l5 - l3);
      l6 = Math.max(l3 - l6, l5);
      l3 = l4 + l2;
      l2 = l3;
      if (i != 0)
      {
        l2 = l3;
        if (l6 > 0L) {
          l2 = Math.min(l4, l6) + l1;
        }
      }
      if (!zzawu().zzf(l6, l1)) {
        l2 = l6 + l1;
      }
      l1 = l2;
      if (l5 != 0L)
      {
        l1 = l2;
        if (l5 >= l4)
        {
          i = 0;
          for (;;)
          {
            if (i >= Math.min(20, Math.max(0, ((Integer)zzchc.zzjbf.get()).intValue()))) {
              break label561;
            }
            l2 += (1L << i) * Math.max(0L, ((Long)zzchc.zzjbe.get()).longValue());
            l1 = l2;
            if (l2 > l5) {
              break;
            }
            i += 1;
          }
          label561:
          l1 = 0L;
        }
      }
    }
    label566:
    if (!zzbab().zzzs())
    {
      zzawy().zzazj().log("No network");
      zzbac().zzzp();
      zzbad().cancel();
      return;
    }
    l2 = zzawz().zzjct.get();
    l3 = Math.max(0L, ((Long)zzchc.zzjau.get()).longValue());
    if (!zzawu().zzf(l2, l3)) {
      l1 = Math.max(l1, l3 + l2);
    }
    for (;;)
    {
      zzbac().unregister();
      l2 = l1 - this.zzata.currentTimeMillis();
      l1 = l2;
      if (l2 <= 0L)
      {
        l1 = Math.max(0L, ((Long)zzchc.zzjaz.get()).longValue());
        zzawz().zzjcr.set(this.zzata.currentTimeMillis());
      }
      zzawy().zzazj().zzj("Upload scheduled in approximately ms", Long.valueOf(l1));
      zzbad().zzs(l1);
      return;
    }
  }
  
  private final boolean zzbam()
  {
    zzawx().zzve();
    zzxf();
    return this.zzjfs;
  }
  
  private final void zzban()
  {
    zzawx().zzve();
    if ((this.zzjgd) || (this.zzjge) || (this.zzjgf)) {
      zzawy().zzazj().zzd("Not stopping services. fetch, network, upload", Boolean.valueOf(this.zzjgd), Boolean.valueOf(this.zzjge), Boolean.valueOf(this.zzjgf));
    }
    do
    {
      return;
      zzawy().zzazj().log("Stopping uploading service(s)");
    } while (this.zzjfy == null);
    Iterator localIterator = this.zzjfy.iterator();
    while (localIterator.hasNext()) {
      ((Runnable)localIterator.next()).run();
    }
    this.zzjfy.clear();
  }
  
  private final void zzc(zzcha paramzzcha, zzcgi paramzzcgi)
  {
    zzbq.checkNotNull(paramzzcgi);
    zzbq.zzgm(paramzzcgi.packageName);
    long l1 = System.nanoTime();
    zzawx().zzve();
    zzxf();
    localObject1 = paramzzcgi.packageName;
    zzawu();
    if (!zzclq.zzd(paramzzcha, paramzzcgi)) {
      return;
    }
    if (!paramzzcgi.zzixx)
    {
      zzg(paramzzcgi);
      return;
    }
    if (zzawv().zzan((String)localObject1, paramzzcha.name))
    {
      zzawy().zzazf().zze("Dropping blacklisted event. appId", zzchm.zzjk((String)localObject1), zzawt().zzjh(paramzzcha.name));
      if ((zzawu().zzkl((String)localObject1)) || (zzawu().zzkm((String)localObject1))) {}
      for (i = 1;; i = 0)
      {
        if ((i == 0) && (!"_err".equals(paramzzcha.name))) {
          zzawu().zza((String)localObject1, 11, "_ev", paramzzcha.name, 0);
        }
        if (i == 0) {
          break;
        }
        paramzzcha = zzaws().zzjb((String)localObject1);
        if (paramzzcha == null) {
          break;
        }
        l1 = Math.max(paramzzcha.zzaxn(), paramzzcha.zzaxm());
        if (Math.abs(this.zzata.currentTimeMillis() - l1) <= ((Long)zzchc.zzjbc.get()).longValue()) {
          break;
        }
        zzawy().zzazi().log("Fetching config for blacklisted app");
        zzb(paramzzcha);
        return;
      }
    }
    if (zzawy().zzae(2)) {
      zzawy().zzazj().zzj("Logging event", zzawt().zzb(paramzzcha));
    }
    zzaws().beginTransaction();
    long l2;
    for (;;)
    {
      Object localObject2;
      try
      {
        zzg(paramzzcgi);
        if ((("_iap".equals(paramzzcha.name)) || ("ecommerce_purchase".equals(paramzzcha.name))) && (!zza((String)localObject1, paramzzcha)))
        {
          zzaws().setTransactionSuccessful();
          return;
        }
        bool1 = zzclq.zzjz(paramzzcha.name);
        boolean bool2 = "_err".equals(paramzzcha.name);
        localObject2 = zzaws().zza(zzbag(), (String)localObject1, true, bool1, false, bool2, false);
        l2 = ((zzcgp)localObject2).zziyy - ((Integer)zzchc.zzjan.get()).intValue();
        if (l2 > 0L)
        {
          if (l2 % 1000L == 1L) {
            zzawy().zzazd().zze("Data loss. Too many events logged. appId, count", zzchm.zzjk((String)localObject1), Long.valueOf(((zzcgp)localObject2).zziyy));
          }
          zzaws().setTransactionSuccessful();
          return;
        }
        if (bool1)
        {
          l2 = ((zzcgp)localObject2).zziyx - ((Integer)zzchc.zzjap.get()).intValue();
          if (l2 > 0L)
          {
            if (l2 % 1000L == 1L) {
              zzawy().zzazd().zze("Data loss. Too many public events logged. appId, count", zzchm.zzjk((String)localObject1), Long.valueOf(((zzcgp)localObject2).zziyx));
            }
            zzawu().zza((String)localObject1, 16, "_ev", paramzzcha.name, 0);
            zzaws().setTransactionSuccessful();
            return;
          }
        }
        if (bool2)
        {
          l2 = ((zzcgp)localObject2).zziza - Math.max(0, Math.min(1000000, this.zzjew.zzb(paramzzcgi.packageName, zzchc.zzjao)));
          if (l2 > 0L)
          {
            if (l2 == 1L) {
              zzawy().zzazd().zze("Too many error events logged. appId, count", zzchm.zzjk((String)localObject1), Long.valueOf(((zzcgp)localObject2).zziza));
            }
            zzaws().setTransactionSuccessful();
            return;
          }
        }
        localObject2 = paramzzcha.zzizt.zzayx();
        zzawu().zza((Bundle)localObject2, "_o", paramzzcha.zziyf);
        if (zzawu().zzkj((String)localObject1))
        {
          zzawu().zza((Bundle)localObject2, "_dbg", Long.valueOf(1L));
          zzawu().zza((Bundle)localObject2, "_r", Long.valueOf(1L));
        }
        l2 = zzaws().zzjc((String)localObject1);
        if (l2 > 0L) {
          zzawy().zzazf().zze("Data lost. Too many events stored on disk, deleted. appId", zzchm.zzjk((String)localObject1), Long.valueOf(l2));
        }
        paramzzcha = new zzcgv(this, paramzzcha.zziyf, (String)localObject1, paramzzcha.name, paramzzcha.zzizu, 0L, (Bundle)localObject2);
        localObject2 = zzaws().zzae((String)localObject1, paramzzcha.mName);
        if (localObject2 == null)
        {
          if ((zzaws().zzjf((String)localObject1) >= 500L) && (bool1))
          {
            zzawy().zzazd().zzd("Too many event names used, ignoring event. appId, name, supported count", zzchm.zzjk((String)localObject1), zzawt().zzjh(paramzzcha.mName), Integer.valueOf(500));
            zzawu().zza((String)localObject1, 8, null, null, 0);
            return;
          }
          localObject1 = new zzcgw((String)localObject1, paramzzcha.mName, 0L, 0L, paramzzcha.zzfij, 0L, null, null, null);
          zzaws().zza((zzcgw)localObject1);
          zzawx().zzve();
          zzxf();
          zzbq.checkNotNull(paramzzcha);
          zzbq.checkNotNull(paramzzcgi);
          zzbq.zzgm(paramzzcha.mAppId);
          zzbq.checkArgument(paramzzcha.mAppId.equals(paramzzcgi.packageName));
          localzzcme = new zzcme();
          localzzcme.zzjlo = Integer.valueOf(1);
          localzzcme.zzjlw = "android";
          localzzcme.zzcn = paramzzcgi.packageName;
          localzzcme.zzixt = paramzzcgi.zzixt;
          localzzcme.zzifm = paramzzcgi.zzifm;
          if (paramzzcgi.zzixz == -2147483648L)
          {
            localObject1 = null;
            localzzcme.zzjmj = ((Integer)localObject1);
            localzzcme.zzjma = Long.valueOf(paramzzcgi.zzixu);
            localzzcme.zzixs = paramzzcgi.zzixs;
            if (paramzzcgi.zzixv != 0L) {
              continue;
            }
            localObject1 = null;
            localzzcme.zzjmf = ((Long)localObject1);
            localObject1 = zzawz().zzjm(paramzzcgi.packageName);
            if ((localObject1 == null) || (TextUtils.isEmpty((CharSequence)((Pair)localObject1).first))) {
              continue;
            }
            if (paramzzcgi.zziye)
            {
              localzzcme.zzjmc = ((String)((Pair)localObject1).first);
              localzzcme.zzjmd = ((Boolean)((Pair)localObject1).second);
            }
            zzawo().zzxf();
            localzzcme.zzjlx = Build.MODEL;
            zzawo().zzxf();
            localzzcme.zzdb = Build.VERSION.RELEASE;
            localzzcme.zzjlz = Integer.valueOf((int)zzawo().zzayu());
            localzzcme.zzjly = zzawo().zzayv();
            localzzcme.zzjmb = null;
            localzzcme.zzjlr = null;
            localzzcme.zzjls = null;
            localzzcme.zzjlt = null;
            localzzcme.zzfkk = Long.valueOf(paramzzcgi.zziyb);
            if ((isEnabled()) && (zzcgn.zzaye()))
            {
              zzawn();
              localzzcme.zzjmo = null;
            }
            localObject2 = zzaws().zzjb(paramzzcgi.packageName);
            localObject1 = localObject2;
            if (localObject2 == null)
            {
              localObject1 = new zzcgh(this, paramzzcgi.packageName);
              ((zzcgh)localObject1).zzir(zzawn().zzayz());
              ((zzcgh)localObject1).zziu(paramzzcgi.zziya);
              ((zzcgh)localObject1).zzis(paramzzcgi.zzixs);
              ((zzcgh)localObject1).zzit(zzawz().zzjn(paramzzcgi.packageName));
              ((zzcgh)localObject1).zzaq(0L);
              ((zzcgh)localObject1).zzal(0L);
              ((zzcgh)localObject1).zzam(0L);
              ((zzcgh)localObject1).setAppVersion(paramzzcgi.zzifm);
              ((zzcgh)localObject1).zzan(paramzzcgi.zzixz);
              ((zzcgh)localObject1).zziv(paramzzcgi.zzixt);
              ((zzcgh)localObject1).zzao(paramzzcgi.zzixu);
              ((zzcgh)localObject1).zzap(paramzzcgi.zzixv);
              ((zzcgh)localObject1).setMeasurementEnabled(paramzzcgi.zzixx);
              ((zzcgh)localObject1).zzaz(paramzzcgi.zziyb);
              zzaws().zza((zzcgh)localObject1);
            }
            localzzcme.zzjme = ((zzcgh)localObject1).getAppInstanceId();
            localzzcme.zziya = ((zzcgh)localObject1).zzaxd();
            paramzzcgi = zzaws().zzja(paramzzcgi.packageName);
            localzzcme.zzjlq = new zzcmg[paramzzcgi.size()];
            i = 0;
            if (i >= paramzzcgi.size()) {
              break;
            }
            localObject1 = new zzcmg();
            localzzcme.zzjlq[i] = localObject1;
            ((zzcmg)localObject1).name = ((zzclp)paramzzcgi.get(i)).mName;
            ((zzcmg)localObject1).zzjms = Long.valueOf(((zzclp)paramzzcgi.get(i)).zzjjm);
            zzawu().zza((zzcmg)localObject1, ((zzclp)paramzzcgi.get(i)).mValue);
            i += 1;
            continue;
          }
        }
        else
        {
          paramzzcha = paramzzcha.zza(this, ((zzcgw)localObject2).zzizm);
          localObject1 = ((zzcgw)localObject2).zzbb(paramzzcha.zzfij);
          continue;
        }
        localObject1 = Integer.valueOf((int)paramzzcgi.zzixz);
        continue;
        localObject1 = Long.valueOf(paramzzcgi.zzixv);
        continue;
        if (zzawo().zzdw(this.mContext)) {
          continue;
        }
        localObject2 = Settings.Secure.getString(this.mContext.getContentResolver(), "android_id");
        if (localObject2 == null)
        {
          zzawy().zzazf().zzj("null secure ID. appId", zzchm.zzjk(localzzcme.zzcn));
          localObject1 = "null";
          localzzcme.zzjmm = ((String)localObject1);
          continue;
        }
        localObject1 = localObject2;
      }
      finally
      {
        zzaws().endTransaction();
      }
      if (((String)localObject2).isEmpty())
      {
        zzawy().zzazf().zzj("empty secure ID. appId", zzchm.zzjk(localzzcme.zzcn));
        localObject1 = localObject2;
      }
    }
    try
    {
      l2 = zzaws().zza(localzzcme);
      paramzzcgi = zzaws();
      if (paramzzcha.zzizj == null) {
        break label2029;
      }
      localObject1 = paramzzcha.zzizj.iterator();
      do
      {
        if (!((Iterator)localObject1).hasNext()) {
          break;
        }
      } while (!"_r".equals((String)((Iterator)localObject1).next()));
      bool1 = true;
    }
    catch (IOException paramzzcgi)
    {
      for (;;)
      {
        zzawy().zzazd().zze("Data loss. Failed to insert raw event metadata. appId", zzchm.zzjk(localzzcme.zzcn), paramzzcgi);
        continue;
        bool1 = zzawv().zzao(paramzzcha.mAppId, paramzzcha.mName);
        localObject1 = zzaws().zza(zzbag(), paramzzcha.mAppId, false, false, false, false, false);
        if (bool1)
        {
          long l3 = ((zzcgp)localObject1).zzizb;
          i = this.zzjew.zzix(paramzzcha.mAppId);
          if (l3 < i)
          {
            bool1 = true;
            continue;
          }
        }
        bool1 = false;
      }
    }
    if (paramzzcgi.zza(paramzzcha, l2, bool1)) {
      this.zzjgc = 0L;
    }
    zzaws().setTransactionSuccessful();
    if (zzawy().zzae(2)) {
      zzawy().zzazj().zzj("Event recorded", zzawt().zza(paramzzcha));
    }
    zzaws().endTransaction();
    zzbaj();
    zzawy().zzazj().zzj("Background event processing time, ms", Long.valueOf((System.nanoTime() - l1 + 500000L) / 1000000L));
  }
  
  public static zzcim zzdx(Context paramContext)
  {
    zzbq.checkNotNull(paramContext);
    zzbq.checkNotNull(paramContext.getApplicationContext());
    if (zzjev == null) {}
    try
    {
      if (zzjev == null) {
        zzjev = new zzcim(new zzcjm(paramContext));
      }
      return zzjev;
    }
    finally {}
  }
  
  private final void zzg(zzcgi paramzzcgi)
  {
    int k = 1;
    zzawx().zzve();
    zzxf();
    zzbq.checkNotNull(paramzzcgi);
    zzbq.zzgm(paramzzcgi.packageName);
    zzcgh localzzcgh2 = zzaws().zzjb(paramzzcgi.packageName);
    String str = zzawz().zzjn(paramzzcgi.packageName);
    int i = 0;
    zzcgh localzzcgh1;
    int j;
    if (localzzcgh2 == null)
    {
      localzzcgh1 = new zzcgh(this, paramzzcgi.packageName);
      localzzcgh1.zzir(zzawn().zzayz());
      localzzcgh1.zzit(str);
      i = 1;
      j = i;
      if (!TextUtils.isEmpty(paramzzcgi.zzixs))
      {
        j = i;
        if (!paramzzcgi.zzixs.equals(localzzcgh1.getGmpAppId()))
        {
          localzzcgh1.zzis(paramzzcgi.zzixs);
          j = 1;
        }
      }
      i = j;
      if (!TextUtils.isEmpty(paramzzcgi.zziya))
      {
        i = j;
        if (!paramzzcgi.zziya.equals(localzzcgh1.zzaxd()))
        {
          localzzcgh1.zziu(paramzzcgi.zziya);
          i = 1;
        }
      }
      j = i;
      if (paramzzcgi.zzixu != 0L)
      {
        j = i;
        if (paramzzcgi.zzixu != localzzcgh1.zzaxi())
        {
          localzzcgh1.zzao(paramzzcgi.zzixu);
          j = 1;
        }
      }
      i = j;
      if (!TextUtils.isEmpty(paramzzcgi.zzifm))
      {
        i = j;
        if (!paramzzcgi.zzifm.equals(localzzcgh1.zzvj()))
        {
          localzzcgh1.setAppVersion(paramzzcgi.zzifm);
          i = 1;
        }
      }
      if (paramzzcgi.zzixz != localzzcgh1.zzaxg())
      {
        localzzcgh1.zzan(paramzzcgi.zzixz);
        i = 1;
      }
      j = i;
      if (paramzzcgi.zzixt != null)
      {
        j = i;
        if (!paramzzcgi.zzixt.equals(localzzcgh1.zzaxh()))
        {
          localzzcgh1.zziv(paramzzcgi.zzixt);
          j = 1;
        }
      }
      i = j;
      if (paramzzcgi.zzixv != localzzcgh1.zzaxj())
      {
        localzzcgh1.zzap(paramzzcgi.zzixv);
        i = 1;
      }
      if (paramzzcgi.zzixx != localzzcgh1.zzaxk())
      {
        localzzcgh1.setMeasurementEnabled(paramzzcgi.zzixx);
        i = 1;
      }
      j = i;
      if (!TextUtils.isEmpty(paramzzcgi.zzixw))
      {
        j = i;
        if (!paramzzcgi.zzixw.equals(localzzcgh1.zzaxv()))
        {
          localzzcgh1.zziw(paramzzcgi.zzixw);
          j = 1;
        }
      }
      if (paramzzcgi.zziyb != localzzcgh1.zzaxx())
      {
        localzzcgh1.zzaz(paramzzcgi.zziyb);
        j = 1;
      }
      if (paramzzcgi.zziye == localzzcgh1.zzaxy()) {
        break label509;
      }
      localzzcgh1.zzbl(paramzzcgi.zziye);
    }
    label509:
    for (i = k;; i = j)
    {
      if (i != 0) {
        zzaws().zza(localzzcgh1);
      }
      return;
      localzzcgh1 = localzzcgh2;
      if (str.equals(localzzcgh2.zzaxc())) {
        break;
      }
      localzzcgh2.zzit(str);
      localzzcgh2.zzir(zzawn().zzayz());
      i = 1;
      localzzcgh1 = localzzcgh2;
      break;
    }
  }
  
  /* Error */
  private final boolean zzg(String paramString, long paramLong)
  {
    // Byte code:
    //   0: aload_0
    //   1: invokevirtual 602	com/google/android/gms/internal/zzcim:zzaws	()Lcom/google/android/gms/internal/zzcgo;
    //   4: invokevirtual 1144	com/google/android/gms/internal/zzcgo:beginTransaction	()V
    //   7: new 6	com/google/android/gms/internal/zzcim$zza
    //   10: dup
    //   11: aload_0
    //   12: aconst_null
    //   13: invokespecial 1582	com/google/android/gms/internal/zzcim$zza:<init>	(Lcom/google/android/gms/internal/zzcim;Lcom/google/android/gms/internal/zzcin;)V
    //   16: astore 23
    //   18: aload_0
    //   19: invokevirtual 602	com/google/android/gms/internal/zzcim:zzaws	()Lcom/google/android/gms/internal/zzcgo;
    //   22: astore 24
    //   24: aconst_null
    //   25: astore 20
    //   27: aload_0
    //   28: getfield 104	com/google/android/gms/internal/zzcim:zzjgb	J
    //   31: lstore 10
    //   33: aload 23
    //   35: invokestatic 95	com/google/android/gms/common/internal/zzbq:checkNotNull	(Ljava/lang/Object;)Ljava/lang/Object;
    //   38: pop
    //   39: aload 24
    //   41: invokevirtual 310	com/google/android/gms/internal/zzcjk:zzve	()V
    //   44: aload 24
    //   46: invokevirtual 628	com/google/android/gms/internal/zzcjl:zzxf	()V
    //   49: aconst_null
    //   50: astore 22
    //   52: aconst_null
    //   53: astore 21
    //   55: aload 21
    //   57: astore 16
    //   59: aload 20
    //   61: astore 17
    //   63: aload 22
    //   65: astore_1
    //   66: aload 24
    //   68: invokevirtual 632	com/google/android/gms/internal/zzcgo:getWritableDatabase	()Landroid/database/sqlite/SQLiteDatabase;
    //   71: astore 25
    //   73: aload 21
    //   75: astore 16
    //   77: aload 20
    //   79: astore 17
    //   81: aload 22
    //   83: astore_1
    //   84: aconst_null
    //   85: invokestatic 401	android/text/TextUtils:isEmpty	(Ljava/lang/CharSequence;)Z
    //   88: ifeq +643 -> 731
    //   91: lload 10
    //   93: ldc2_w 101
    //   96: lcmp
    //   97: ifeq +416 -> 513
    //   100: aload 21
    //   102: astore 16
    //   104: aload 20
    //   106: astore 17
    //   108: aload 22
    //   110: astore_1
    //   111: iconst_2
    //   112: anewarray 443	java/lang/String
    //   115: dup
    //   116: iconst_0
    //   117: lload 10
    //   119: invokestatic 1585	java/lang/String:valueOf	(J)Ljava/lang/String;
    //   122: aastore
    //   123: dup
    //   124: iconst_1
    //   125: lload_2
    //   126: invokestatic 1585	java/lang/String:valueOf	(J)Ljava/lang/String;
    //   129: aastore
    //   130: astore 18
    //   132: goto +4055 -> 4187
    //   135: aload 21
    //   137: astore 16
    //   139: aload 20
    //   141: astore 17
    //   143: aload 22
    //   145: astore_1
    //   146: aload 25
    //   148: new 1587	java/lang/StringBuilder
    //   151: dup
    //   152: aload 19
    //   154: invokestatic 592	java/lang/String:valueOf	(Ljava/lang/Object;)Ljava/lang/String;
    //   157: invokevirtual 595	java/lang/String:length	()I
    //   160: sipush 148
    //   163: iadd
    //   164: invokespecial 1590	java/lang/StringBuilder:<init>	(I)V
    //   167: ldc_w 1592
    //   170: invokevirtual 1596	java/lang/StringBuilder:append	(Ljava/lang/String;)Ljava/lang/StringBuilder;
    //   173: aload 19
    //   175: invokevirtual 1596	java/lang/StringBuilder:append	(Ljava/lang/String;)Ljava/lang/StringBuilder;
    //   178: ldc_w 1598
    //   181: invokevirtual 1596	java/lang/StringBuilder:append	(Ljava/lang/String;)Ljava/lang/StringBuilder;
    //   184: invokevirtual 1599	java/lang/StringBuilder:toString	()Ljava/lang/String;
    //   187: aload 18
    //   189: invokevirtual 1603	android/database/sqlite/SQLiteDatabase:rawQuery	(Ljava/lang/String;[Ljava/lang/String;)Landroid/database/Cursor;
    //   192: astore 18
    //   194: aload 18
    //   196: astore 16
    //   198: aload 20
    //   200: astore 17
    //   202: aload 18
    //   204: astore_1
    //   205: aload 18
    //   207: invokeinterface 1608 1 0
    //   212: istore 12
    //   214: iload 12
    //   216: ifne +324 -> 540
    //   219: aload 18
    //   221: ifnull +10 -> 231
    //   224: aload 18
    //   226: invokeinterface 1611 1 0
    //   231: aload 23
    //   233: getfield 1614	com/google/android/gms/internal/zzcim$zza:zzapa	Ljava/util/List;
    //   236: ifnull +3968 -> 4204
    //   239: aload 23
    //   241: getfield 1614	com/google/android/gms/internal/zzcim$zza:zzapa	Ljava/util/List;
    //   244: invokeinterface 1615 1 0
    //   249: ifeq +4005 -> 4254
    //   252: goto +3952 -> 4204
    //   255: iload 4
    //   257: ifne +3859 -> 4116
    //   260: iconst_0
    //   261: istore 12
    //   263: aload 23
    //   265: getfield 1619	com/google/android/gms/internal/zzcim$zza:zzjgi	Lcom/google/android/gms/internal/zzcme;
    //   268: astore 17
    //   270: aload 17
    //   272: aload 23
    //   274: getfield 1614	com/google/android/gms/internal/zzcim$zza:zzapa	Ljava/util/List;
    //   277: invokeinterface 1440 1 0
    //   282: anewarray 500	com/google/android/gms/internal/zzcmb
    //   285: putfield 1623	com/google/android/gms/internal/zzcme:zzjlp	[Lcom/google/android/gms/internal/zzcmb;
    //   288: iconst_0
    //   289: istore 4
    //   291: iconst_0
    //   292: istore 6
    //   294: iload 6
    //   296: aload 23
    //   298: getfield 1614	com/google/android/gms/internal/zzcim$zza:zzapa	Ljava/util/List;
    //   301: invokeinterface 1440 1 0
    //   306: if_icmpge +2297 -> 2603
    //   309: aload_0
    //   310: invokevirtual 791	com/google/android/gms/internal/zzcim:zzawv	()Lcom/google/android/gms/internal/zzcig;
    //   313: aload 23
    //   315: getfield 1619	com/google/android/gms/internal/zzcim$zza:zzjgi	Lcom/google/android/gms/internal/zzcme;
    //   318: getfield 1257	com/google/android/gms/internal/zzcme:zzcn	Ljava/lang/String;
    //   321: aload 23
    //   323: getfield 1614	com/google/android/gms/internal/zzcim$zza:zzapa	Ljava/util/List;
    //   326: iload 6
    //   328: invokeinterface 1450 2 0
    //   333: checkcast 500	com/google/android/gms/internal/zzcmb
    //   336: getfield 1624	com/google/android/gms/internal/zzcmb:name	Ljava/lang/String;
    //   339: invokevirtual 1100	com/google/android/gms/internal/zzcig:zzan	(Ljava/lang/String;Ljava/lang/String;)Z
    //   342: ifeq +1251 -> 1593
    //   345: aload_0
    //   346: invokevirtual 294	com/google/android/gms/internal/zzcim:zzawy	()Lcom/google/android/gms/internal/zzchm;
    //   349: invokevirtual 297	com/google/android/gms/internal/zzchm:zzazf	()Lcom/google/android/gms/internal/zzcho;
    //   352: ldc_w 1626
    //   355: aload 23
    //   357: getfield 1619	com/google/android/gms/internal/zzcim$zza:zzjgi	Lcom/google/android/gms/internal/zzcme;
    //   360: getfield 1257	com/google/android/gms/internal/zzcme:zzcn	Ljava/lang/String;
    //   363: invokestatic 439	com/google/android/gms/internal/zzchm:zzjk	(Ljava/lang/String;)Ljava/lang/Object;
    //   366: aload_0
    //   367: invokevirtual 658	com/google/android/gms/internal/zzcim:zzawt	()Lcom/google/android/gms/internal/zzchk;
    //   370: aload 23
    //   372: getfield 1614	com/google/android/gms/internal/zzcim$zza:zzapa	Ljava/util/List;
    //   375: iload 6
    //   377: invokeinterface 1450 2 0
    //   382: checkcast 500	com/google/android/gms/internal/zzcmb
    //   385: getfield 1624	com/google/android/gms/internal/zzcmb:name	Ljava/lang/String;
    //   388: invokevirtual 1105	com/google/android/gms/internal/zzchk:zzjh	(Ljava/lang/String;)Ljava/lang/String;
    //   391: invokevirtual 453	com/google/android/gms/internal/zzcho:zze	(Ljava/lang/String;Ljava/lang/Object;Ljava/lang/Object;)V
    //   394: aload_0
    //   395: invokevirtual 424	com/google/android/gms/internal/zzcim:zzawu	()Lcom/google/android/gms/internal/zzclq;
    //   398: aload 23
    //   400: getfield 1619	com/google/android/gms/internal/zzcim$zza:zzjgi	Lcom/google/android/gms/internal/zzcme;
    //   403: getfield 1257	com/google/android/gms/internal/zzcme:zzcn	Ljava/lang/String;
    //   406: invokevirtual 1108	com/google/android/gms/internal/zzclq:zzkl	(Ljava/lang/String;)Z
    //   409: ifne +3801 -> 4210
    //   412: aload_0
    //   413: invokevirtual 424	com/google/android/gms/internal/zzcim:zzawu	()Lcom/google/android/gms/internal/zzclq;
    //   416: aload 23
    //   418: getfield 1619	com/google/android/gms/internal/zzcim$zza:zzjgi	Lcom/google/android/gms/internal/zzcme;
    //   421: getfield 1257	com/google/android/gms/internal/zzcme:zzcn	Ljava/lang/String;
    //   424: invokevirtual 1111	com/google/android/gms/internal/zzclq:zzkm	(Ljava/lang/String;)Z
    //   427: ifeq +3833 -> 4260
    //   430: goto +3780 -> 4210
    //   433: iload 5
    //   435: ifne +3749 -> 4184
    //   438: ldc_w 1113
    //   441: aload 23
    //   443: getfield 1614	com/google/android/gms/internal/zzcim$zza:zzapa	Ljava/util/List;
    //   446: iload 6
    //   448: invokeinterface 1450 2 0
    //   453: checkcast 500	com/google/android/gms/internal/zzcmb
    //   456: getfield 1624	com/google/android/gms/internal/zzcmb:name	Ljava/lang/String;
    //   459: invokevirtual 447	java/lang/String:equals	(Ljava/lang/Object;)Z
    //   462: ifne +3722 -> 4184
    //   465: aload_0
    //   466: invokevirtual 424	com/google/android/gms/internal/zzcim:zzawu	()Lcom/google/android/gms/internal/zzclq;
    //   469: aload 23
    //   471: getfield 1619	com/google/android/gms/internal/zzcim$zza:zzjgi	Lcom/google/android/gms/internal/zzcme;
    //   474: getfield 1257	com/google/android/gms/internal/zzcme:zzcn	Ljava/lang/String;
    //   477: bipush 11
    //   479: ldc_w 1115
    //   482: aload 23
    //   484: getfield 1614	com/google/android/gms/internal/zzcim$zza:zzapa	Ljava/util/List;
    //   487: iload 6
    //   489: invokeinterface 1450 2 0
    //   494: checkcast 500	com/google/android/gms/internal/zzcmb
    //   497: getfield 1624	com/google/android/gms/internal/zzcmb:name	Ljava/lang/String;
    //   500: iconst_0
    //   501: invokevirtual 671	com/google/android/gms/internal/zzclq:zza	(Ljava/lang/String;ILjava/lang/String;Ljava/lang/String;I)V
    //   504: iload 6
    //   506: iconst_1
    //   507: iadd
    //   508: istore 6
    //   510: goto -216 -> 294
    //   513: aload 21
    //   515: astore 16
    //   517: aload 20
    //   519: astore 17
    //   521: aload 22
    //   523: astore_1
    //   524: iconst_1
    //   525: anewarray 443	java/lang/String
    //   528: dup
    //   529: iconst_0
    //   530: lload_2
    //   531: invokestatic 1585	java/lang/String:valueOf	(J)Ljava/lang/String;
    //   534: aastore
    //   535: astore 18
    //   537: goto +3650 -> 4187
    //   540: aload 18
    //   542: astore 16
    //   544: aload 20
    //   546: astore 17
    //   548: aload 18
    //   550: astore_1
    //   551: aload 18
    //   553: iconst_0
    //   554: invokeinterface 1628 2 0
    //   559: astore 19
    //   561: aload 18
    //   563: astore 16
    //   565: aload 19
    //   567: astore 17
    //   569: aload 18
    //   571: astore_1
    //   572: aload 18
    //   574: iconst_1
    //   575: invokeinterface 1628 2 0
    //   580: astore 20
    //   582: aload 18
    //   584: astore 16
    //   586: aload 19
    //   588: astore 17
    //   590: aload 18
    //   592: astore_1
    //   593: aload 18
    //   595: invokeinterface 1611 1 0
    //   600: aload 20
    //   602: astore 16
    //   604: aload 18
    //   606: astore_1
    //   607: aload 16
    //   609: astore 18
    //   611: aload 19
    //   613: astore 16
    //   615: aload_1
    //   616: astore 17
    //   618: aload 25
    //   620: ldc_w 1630
    //   623: iconst_1
    //   624: anewarray 443	java/lang/String
    //   627: dup
    //   628: iconst_0
    //   629: ldc_w 1632
    //   632: aastore
    //   633: ldc_w 1634
    //   636: iconst_2
    //   637: anewarray 443	java/lang/String
    //   640: dup
    //   641: iconst_0
    //   642: aload 16
    //   644: aastore
    //   645: dup
    //   646: iconst_1
    //   647: aload 18
    //   649: aastore
    //   650: aconst_null
    //   651: aconst_null
    //   652: ldc_w 1636
    //   655: ldc_w 1638
    //   658: invokevirtual 1642	android/database/sqlite/SQLiteDatabase:query	(Ljava/lang/String;[Ljava/lang/String;Ljava/lang/String;[Ljava/lang/String;Ljava/lang/String;Ljava/lang/String;Ljava/lang/String;Ljava/lang/String;)Landroid/database/Cursor;
    //   661: astore 19
    //   663: aload 19
    //   665: astore 17
    //   667: aload 19
    //   669: astore_1
    //   670: aload 19
    //   672: invokeinterface 1608 1 0
    //   677: ifne +273 -> 950
    //   680: aload 19
    //   682: astore 17
    //   684: aload 19
    //   686: astore_1
    //   687: aload 24
    //   689: invokevirtual 274	com/google/android/gms/internal/zzcjk:zzawy	()Lcom/google/android/gms/internal/zzchm;
    //   692: invokevirtual 319	com/google/android/gms/internal/zzchm:zzazd	()Lcom/google/android/gms/internal/zzcho;
    //   695: ldc_w 1644
    //   698: aload 16
    //   700: invokestatic 439	com/google/android/gms/internal/zzchm:zzjk	(Ljava/lang/String;)Ljava/lang/Object;
    //   703: invokevirtual 347	com/google/android/gms/internal/zzcho:zzj	(Ljava/lang/String;Ljava/lang/Object;)V
    //   706: aload 19
    //   708: ifnull -477 -> 231
    //   711: aload 19
    //   713: invokeinterface 1611 1 0
    //   718: goto -487 -> 231
    //   721: astore_1
    //   722: aload_0
    //   723: invokevirtual 602	com/google/android/gms/internal/zzcim:zzaws	()Lcom/google/android/gms/internal/zzcgo;
    //   726: invokevirtual 1154	com/google/android/gms/internal/zzcgo:endTransaction	()V
    //   729: aload_1
    //   730: athrow
    //   731: lload 10
    //   733: ldc2_w 101
    //   736: lcmp
    //   737: ifeq +133 -> 870
    //   740: aload 21
    //   742: astore 16
    //   744: aload 20
    //   746: astore 17
    //   748: aload 22
    //   750: astore_1
    //   751: iconst_2
    //   752: anewarray 443	java/lang/String
    //   755: dup
    //   756: iconst_0
    //   757: aconst_null
    //   758: aastore
    //   759: dup
    //   760: iconst_1
    //   761: lload 10
    //   763: invokestatic 1585	java/lang/String:valueOf	(J)Ljava/lang/String;
    //   766: aastore
    //   767: astore 18
    //   769: goto +3455 -> 4224
    //   772: aload 21
    //   774: astore 16
    //   776: aload 20
    //   778: astore 17
    //   780: aload 22
    //   782: astore_1
    //   783: aload 25
    //   785: new 1587	java/lang/StringBuilder
    //   788: dup
    //   789: aload 19
    //   791: invokestatic 592	java/lang/String:valueOf	(Ljava/lang/Object;)Ljava/lang/String;
    //   794: invokevirtual 595	java/lang/String:length	()I
    //   797: bipush 84
    //   799: iadd
    //   800: invokespecial 1590	java/lang/StringBuilder:<init>	(I)V
    //   803: ldc_w 1646
    //   806: invokevirtual 1596	java/lang/StringBuilder:append	(Ljava/lang/String;)Ljava/lang/StringBuilder;
    //   809: aload 19
    //   811: invokevirtual 1596	java/lang/StringBuilder:append	(Ljava/lang/String;)Ljava/lang/StringBuilder;
    //   814: ldc_w 1648
    //   817: invokevirtual 1596	java/lang/StringBuilder:append	(Ljava/lang/String;)Ljava/lang/StringBuilder;
    //   820: invokevirtual 1599	java/lang/StringBuilder:toString	()Ljava/lang/String;
    //   823: aload 18
    //   825: invokevirtual 1603	android/database/sqlite/SQLiteDatabase:rawQuery	(Ljava/lang/String;[Ljava/lang/String;)Landroid/database/Cursor;
    //   828: astore 18
    //   830: aload 18
    //   832: astore 16
    //   834: aload 20
    //   836: astore 17
    //   838: aload 18
    //   840: astore_1
    //   841: aload 18
    //   843: invokeinterface 1608 1 0
    //   848: istore 12
    //   850: iload 12
    //   852: ifne +42 -> 894
    //   855: aload 18
    //   857: ifnull -626 -> 231
    //   860: aload 18
    //   862: invokeinterface 1611 1 0
    //   867: goto -636 -> 231
    //   870: aload 21
    //   872: astore 16
    //   874: aload 20
    //   876: astore 17
    //   878: aload 22
    //   880: astore_1
    //   881: iconst_1
    //   882: anewarray 443	java/lang/String
    //   885: dup
    //   886: iconst_0
    //   887: aconst_null
    //   888: aastore
    //   889: astore 18
    //   891: goto +3333 -> 4224
    //   894: aload 18
    //   896: astore 16
    //   898: aload 20
    //   900: astore 17
    //   902: aload 18
    //   904: astore_1
    //   905: aload 18
    //   907: iconst_0
    //   908: invokeinterface 1628 2 0
    //   913: astore 19
    //   915: aload 18
    //   917: astore 16
    //   919: aload 20
    //   921: astore 17
    //   923: aload 18
    //   925: astore_1
    //   926: aload 18
    //   928: invokeinterface 1611 1 0
    //   933: aload 19
    //   935: astore 17
    //   937: aload 18
    //   939: astore_1
    //   940: aconst_null
    //   941: astore 16
    //   943: aload 17
    //   945: astore 18
    //   947: goto -332 -> 615
    //   950: aload 19
    //   952: astore 17
    //   954: aload 19
    //   956: astore_1
    //   957: aload 19
    //   959: iconst_0
    //   960: invokeinterface 1652 2 0
    //   965: astore 20
    //   967: aload 19
    //   969: astore 17
    //   971: aload 19
    //   973: astore_1
    //   974: aload 20
    //   976: iconst_0
    //   977: aload 20
    //   979: arraylength
    //   980: invokestatic 1658	com/google/android/gms/internal/zzfjj:zzn	([BII)Lcom/google/android/gms/internal/zzfjj;
    //   983: astore 20
    //   985: aload 19
    //   987: astore 17
    //   989: aload 19
    //   991: astore_1
    //   992: new 1246	com/google/android/gms/internal/zzcme
    //   995: dup
    //   996: invokespecial 1247	com/google/android/gms/internal/zzcme:<init>	()V
    //   999: astore 21
    //   1001: aload 19
    //   1003: astore 17
    //   1005: aload 19
    //   1007: astore_1
    //   1008: aload 21
    //   1010: aload 20
    //   1012: invokevirtual 1663	com/google/android/gms/internal/zzfjs:zza	(Lcom/google/android/gms/internal/zzfjj;)Lcom/google/android/gms/internal/zzfjs;
    //   1015: pop
    //   1016: aload 19
    //   1018: astore 17
    //   1020: aload 19
    //   1022: astore_1
    //   1023: aload 19
    //   1025: invokeinterface 1666 1 0
    //   1030: ifeq +29 -> 1059
    //   1033: aload 19
    //   1035: astore 17
    //   1037: aload 19
    //   1039: astore_1
    //   1040: aload 24
    //   1042: invokevirtual 274	com/google/android/gms/internal/zzcjk:zzawy	()Lcom/google/android/gms/internal/zzchm;
    //   1045: invokevirtual 297	com/google/android/gms/internal/zzchm:zzazf	()Lcom/google/android/gms/internal/zzcho;
    //   1048: ldc_w 1668
    //   1051: aload 16
    //   1053: invokestatic 439	com/google/android/gms/internal/zzchm:zzjk	(Ljava/lang/String;)Ljava/lang/Object;
    //   1056: invokevirtual 347	com/google/android/gms/internal/zzcho:zzj	(Ljava/lang/String;Ljava/lang/Object;)V
    //   1059: aload 19
    //   1061: astore 17
    //   1063: aload 19
    //   1065: astore_1
    //   1066: aload 19
    //   1068: invokeinterface 1611 1 0
    //   1073: aload 19
    //   1075: astore 17
    //   1077: aload 19
    //   1079: astore_1
    //   1080: aload 23
    //   1082: aload 21
    //   1084: invokeinterface 1673 2 0
    //   1089: lload 10
    //   1091: ldc2_w 101
    //   1094: lcmp
    //   1095: ifeq +207 -> 1302
    //   1098: ldc_w 1675
    //   1101: astore 21
    //   1103: aload 19
    //   1105: astore 17
    //   1107: aload 19
    //   1109: astore_1
    //   1110: iconst_3
    //   1111: anewarray 443	java/lang/String
    //   1114: astore 20
    //   1116: aload 20
    //   1118: iconst_0
    //   1119: aload 16
    //   1121: aastore
    //   1122: aload 20
    //   1124: iconst_1
    //   1125: aload 18
    //   1127: aastore
    //   1128: aload 19
    //   1130: astore 17
    //   1132: aload 19
    //   1134: astore_1
    //   1135: aload 20
    //   1137: iconst_2
    //   1138: lload 10
    //   1140: invokestatic 1585	java/lang/String:valueOf	(J)Ljava/lang/String;
    //   1143: aastore
    //   1144: aload 21
    //   1146: astore 18
    //   1148: aload 19
    //   1150: astore 17
    //   1152: aload 19
    //   1154: astore_1
    //   1155: aload 25
    //   1157: ldc_w 1677
    //   1160: iconst_4
    //   1161: anewarray 443	java/lang/String
    //   1164: dup
    //   1165: iconst_0
    //   1166: ldc_w 1636
    //   1169: aastore
    //   1170: dup
    //   1171: iconst_1
    //   1172: ldc_w 1678
    //   1175: aastore
    //   1176: dup
    //   1177: iconst_2
    //   1178: ldc_w 1680
    //   1181: aastore
    //   1182: dup
    //   1183: iconst_3
    //   1184: ldc_w 1682
    //   1187: aastore
    //   1188: aload 18
    //   1190: aload 20
    //   1192: aconst_null
    //   1193: aconst_null
    //   1194: ldc_w 1636
    //   1197: aconst_null
    //   1198: invokevirtual 1642	android/database/sqlite/SQLiteDatabase:query	(Ljava/lang/String;[Ljava/lang/String;Ljava/lang/String;[Ljava/lang/String;Ljava/lang/String;Ljava/lang/String;Ljava/lang/String;Ljava/lang/String;)Landroid/database/Cursor;
    //   1201: astore 18
    //   1203: aload 18
    //   1205: astore 17
    //   1207: aload 17
    //   1209: astore_1
    //   1210: aload 17
    //   1212: invokeinterface 1608 1 0
    //   1217: ifne +173 -> 1390
    //   1220: aload 17
    //   1222: astore_1
    //   1223: aload 24
    //   1225: invokevirtual 274	com/google/android/gms/internal/zzcjk:zzawy	()Lcom/google/android/gms/internal/zzchm;
    //   1228: invokevirtual 297	com/google/android/gms/internal/zzchm:zzazf	()Lcom/google/android/gms/internal/zzcho;
    //   1231: ldc_w 1684
    //   1234: aload 16
    //   1236: invokestatic 439	com/google/android/gms/internal/zzchm:zzjk	(Ljava/lang/String;)Ljava/lang/Object;
    //   1239: invokevirtual 347	com/google/android/gms/internal/zzcho:zzj	(Ljava/lang/String;Ljava/lang/Object;)V
    //   1242: aload 17
    //   1244: ifnull -1013 -> 231
    //   1247: aload 17
    //   1249: invokeinterface 1611 1 0
    //   1254: goto -1023 -> 231
    //   1257: astore 18
    //   1259: aload 19
    //   1261: astore 17
    //   1263: aload 19
    //   1265: astore_1
    //   1266: aload 24
    //   1268: invokevirtual 274	com/google/android/gms/internal/zzcjk:zzawy	()Lcom/google/android/gms/internal/zzchm;
    //   1271: invokevirtual 319	com/google/android/gms/internal/zzchm:zzazd	()Lcom/google/android/gms/internal/zzcho;
    //   1274: ldc_w 1686
    //   1277: aload 16
    //   1279: invokestatic 439	com/google/android/gms/internal/zzchm:zzjk	(Ljava/lang/String;)Ljava/lang/Object;
    //   1282: aload 18
    //   1284: invokevirtual 453	com/google/android/gms/internal/zzcho:zze	(Ljava/lang/String;Ljava/lang/Object;Ljava/lang/Object;)V
    //   1287: aload 19
    //   1289: ifnull -1058 -> 231
    //   1292: aload 19
    //   1294: invokeinterface 1611 1 0
    //   1299: goto -1068 -> 231
    //   1302: ldc_w 1634
    //   1305: astore 21
    //   1307: aload 19
    //   1309: astore 17
    //   1311: aload 19
    //   1313: astore_1
    //   1314: iconst_2
    //   1315: anewarray 443	java/lang/String
    //   1318: astore 20
    //   1320: aload 20
    //   1322: iconst_0
    //   1323: aload 16
    //   1325: aastore
    //   1326: aload 20
    //   1328: iconst_1
    //   1329: aload 18
    //   1331: aastore
    //   1332: aload 21
    //   1334: astore 18
    //   1336: goto -188 -> 1148
    //   1339: astore 18
    //   1341: aload 17
    //   1343: astore_1
    //   1344: aload 16
    //   1346: astore 17
    //   1348: aload_1
    //   1349: astore 16
    //   1351: aload 16
    //   1353: astore_1
    //   1354: aload 24
    //   1356: invokevirtual 274	com/google/android/gms/internal/zzcjk:zzawy	()Lcom/google/android/gms/internal/zzchm;
    //   1359: invokevirtual 319	com/google/android/gms/internal/zzchm:zzazd	()Lcom/google/android/gms/internal/zzcho;
    //   1362: ldc_w 1688
    //   1365: aload 17
    //   1367: invokestatic 439	com/google/android/gms/internal/zzchm:zzjk	(Ljava/lang/String;)Ljava/lang/Object;
    //   1370: aload 18
    //   1372: invokevirtual 453	com/google/android/gms/internal/zzcho:zze	(Ljava/lang/String;Ljava/lang/Object;Ljava/lang/Object;)V
    //   1375: aload 16
    //   1377: ifnull -1146 -> 231
    //   1380: aload 16
    //   1382: invokeinterface 1611 1 0
    //   1387: goto -1156 -> 231
    //   1390: aload 17
    //   1392: astore_1
    //   1393: aload 17
    //   1395: iconst_0
    //   1396: invokeinterface 1691 2 0
    //   1401: lstore_2
    //   1402: aload 17
    //   1404: astore_1
    //   1405: aload 17
    //   1407: iconst_3
    //   1408: invokeinterface 1652 2 0
    //   1413: astore 18
    //   1415: aload 17
    //   1417: astore_1
    //   1418: aload 18
    //   1420: iconst_0
    //   1421: aload 18
    //   1423: arraylength
    //   1424: invokestatic 1658	com/google/android/gms/internal/zzfjj:zzn	([BII)Lcom/google/android/gms/internal/zzfjj;
    //   1427: astore 18
    //   1429: aload 17
    //   1431: astore_1
    //   1432: new 500	com/google/android/gms/internal/zzcmb
    //   1435: dup
    //   1436: invokespecial 1692	com/google/android/gms/internal/zzcmb:<init>	()V
    //   1439: astore 19
    //   1441: aload 17
    //   1443: astore_1
    //   1444: aload 19
    //   1446: aload 18
    //   1448: invokevirtual 1663	com/google/android/gms/internal/zzfjs:zza	(Lcom/google/android/gms/internal/zzfjj;)Lcom/google/android/gms/internal/zzfjs;
    //   1451: pop
    //   1452: aload 17
    //   1454: astore_1
    //   1455: aload 19
    //   1457: aload 17
    //   1459: iconst_1
    //   1460: invokeinterface 1628 2 0
    //   1465: putfield 1624	com/google/android/gms/internal/zzcmb:name	Ljava/lang/String;
    //   1468: aload 17
    //   1470: astore_1
    //   1471: aload 19
    //   1473: aload 17
    //   1475: iconst_2
    //   1476: invokeinterface 1691 2 0
    //   1481: invokestatic 495	java/lang/Long:valueOf	(J)Ljava/lang/Long;
    //   1484: putfield 1695	com/google/android/gms/internal/zzcmb:zzjli	Ljava/lang/Long;
    //   1487: aload 17
    //   1489: astore_1
    //   1490: aload 23
    //   1492: lload_2
    //   1493: aload 19
    //   1495: invokeinterface 1698 4 0
    //   1500: istore 12
    //   1502: iload 12
    //   1504: ifne +44 -> 1548
    //   1507: aload 17
    //   1509: ifnull -1278 -> 231
    //   1512: aload 17
    //   1514: invokeinterface 1611 1 0
    //   1519: goto -1288 -> 231
    //   1522: astore 18
    //   1524: aload 17
    //   1526: astore_1
    //   1527: aload 24
    //   1529: invokevirtual 274	com/google/android/gms/internal/zzcjk:zzawy	()Lcom/google/android/gms/internal/zzchm;
    //   1532: invokevirtual 319	com/google/android/gms/internal/zzchm:zzazd	()Lcom/google/android/gms/internal/zzcho;
    //   1535: ldc_w 1700
    //   1538: aload 16
    //   1540: invokestatic 439	com/google/android/gms/internal/zzchm:zzjk	(Ljava/lang/String;)Ljava/lang/Object;
    //   1543: aload 18
    //   1545: invokevirtual 453	com/google/android/gms/internal/zzcho:zze	(Ljava/lang/String;Ljava/lang/Object;Ljava/lang/Object;)V
    //   1548: aload 17
    //   1550: astore_1
    //   1551: aload 17
    //   1553: invokeinterface 1666 1 0
    //   1558: istore 12
    //   1560: iload 12
    //   1562: ifne -172 -> 1390
    //   1565: aload 17
    //   1567: ifnull -1336 -> 231
    //   1570: aload 17
    //   1572: invokeinterface 1611 1 0
    //   1577: goto -1346 -> 231
    //   1580: aload_1
    //   1581: ifnull +9 -> 1590
    //   1584: aload_1
    //   1585: invokeinterface 1611 1 0
    //   1590: aload 16
    //   1592: athrow
    //   1593: aload_0
    //   1594: invokevirtual 791	com/google/android/gms/internal/zzcim:zzawv	()Lcom/google/android/gms/internal/zzcig;
    //   1597: aload 23
    //   1599: getfield 1619	com/google/android/gms/internal/zzcim$zza:zzjgi	Lcom/google/android/gms/internal/zzcme;
    //   1602: getfield 1257	com/google/android/gms/internal/zzcme:zzcn	Ljava/lang/String;
    //   1605: aload 23
    //   1607: getfield 1614	com/google/android/gms/internal/zzcim$zza:zzapa	Ljava/util/List;
    //   1610: iload 6
    //   1612: invokeinterface 1450 2 0
    //   1617: checkcast 500	com/google/android/gms/internal/zzcmb
    //   1620: getfield 1624	com/google/android/gms/internal/zzcmb:name	Ljava/lang/String;
    //   1623: invokevirtual 1523	com/google/android/gms/internal/zzcig:zzao	(Ljava/lang/String;Ljava/lang/String;)Z
    //   1626: istore 15
    //   1628: iload 15
    //   1630: ifne +36 -> 1666
    //   1633: aload_0
    //   1634: invokevirtual 424	com/google/android/gms/internal/zzcim:zzawu	()Lcom/google/android/gms/internal/zzclq;
    //   1637: pop
    //   1638: iload 12
    //   1640: istore 14
    //   1642: aload 23
    //   1644: getfield 1614	com/google/android/gms/internal/zzcim$zza:zzapa	Ljava/util/List;
    //   1647: iload 6
    //   1649: invokeinterface 1450 2 0
    //   1654: checkcast 500	com/google/android/gms/internal/zzcmb
    //   1657: getfield 1624	com/google/android/gms/internal/zzcmb:name	Ljava/lang/String;
    //   1660: invokestatic 1703	com/google/android/gms/internal/zzclq:zzkn	(Ljava/lang/String;)Z
    //   1663: ifeq +2630 -> 4293
    //   1666: iconst_0
    //   1667: istore 8
    //   1669: iconst_0
    //   1670: istore 5
    //   1672: aload 23
    //   1674: getfield 1614	com/google/android/gms/internal/zzcim$zza:zzapa	Ljava/util/List;
    //   1677: iload 6
    //   1679: invokeinterface 1450 2 0
    //   1684: checkcast 500	com/google/android/gms/internal/zzcmb
    //   1687: getfield 504	com/google/android/gms/internal/zzcmb:zzjlh	[Lcom/google/android/gms/internal/zzcmc;
    //   1690: ifnonnull +25 -> 1715
    //   1693: aload 23
    //   1695: getfield 1614	com/google/android/gms/internal/zzcim$zza:zzapa	Ljava/util/List;
    //   1698: iload 6
    //   1700: invokeinterface 1450 2 0
    //   1705: checkcast 500	com/google/android/gms/internal/zzcmb
    //   1708: iconst_0
    //   1709: anewarray 506	com/google/android/gms/internal/zzcmc
    //   1712: putfield 504	com/google/android/gms/internal/zzcmb:zzjlh	[Lcom/google/android/gms/internal/zzcmc;
    //   1715: aload 23
    //   1717: getfield 1614	com/google/android/gms/internal/zzcim$zza:zzapa	Ljava/util/List;
    //   1720: iload 6
    //   1722: invokeinterface 1450 2 0
    //   1727: checkcast 500	com/google/android/gms/internal/zzcmb
    //   1730: getfield 504	com/google/android/gms/internal/zzcmb:zzjlh	[Lcom/google/android/gms/internal/zzcmc;
    //   1733: astore_1
    //   1734: aload_1
    //   1735: arraylength
    //   1736: istore 9
    //   1738: iconst_0
    //   1739: istore 7
    //   1741: iload 7
    //   1743: iload 9
    //   1745: if_icmpge +67 -> 1812
    //   1748: aload_1
    //   1749: iload 7
    //   1751: aaload
    //   1752: astore 16
    //   1754: ldc_w 1705
    //   1757: aload 16
    //   1759: getfield 509	com/google/android/gms/internal/zzcmc:name	Ljava/lang/String;
    //   1762: invokevirtual 447	java/lang/String:equals	(Ljava/lang/Object;)Z
    //   1765: ifeq +18 -> 1783
    //   1768: aload 16
    //   1770: lconst_1
    //   1771: invokestatic 495	java/lang/Long:valueOf	(J)Ljava/lang/Long;
    //   1774: putfield 513	com/google/android/gms/internal/zzcmc:zzjll	Ljava/lang/Long;
    //   1777: iconst_1
    //   1778: istore 8
    //   1780: goto +2486 -> 4266
    //   1783: ldc_w 1202
    //   1786: aload 16
    //   1788: getfield 509	com/google/android/gms/internal/zzcmc:name	Ljava/lang/String;
    //   1791: invokevirtual 447	java/lang/String:equals	(Ljava/lang/Object;)Z
    //   1794: ifeq +2387 -> 4181
    //   1797: aload 16
    //   1799: lconst_1
    //   1800: invokestatic 495	java/lang/Long:valueOf	(J)Ljava/lang/Long;
    //   1803: putfield 513	com/google/android/gms/internal/zzcmc:zzjll	Ljava/lang/Long;
    //   1806: iconst_1
    //   1807: istore 5
    //   1809: goto +2457 -> 4266
    //   1812: iload 8
    //   1814: ifne +145 -> 1959
    //   1817: iload 15
    //   1819: ifeq +140 -> 1959
    //   1822: aload_0
    //   1823: invokevirtual 294	com/google/android/gms/internal/zzcim:zzawy	()Lcom/google/android/gms/internal/zzchm;
    //   1826: invokevirtual 278	com/google/android/gms/internal/zzchm:zzazj	()Lcom/google/android/gms/internal/zzcho;
    //   1829: ldc_w 1707
    //   1832: aload_0
    //   1833: invokevirtual 658	com/google/android/gms/internal/zzcim:zzawt	()Lcom/google/android/gms/internal/zzchk;
    //   1836: aload 23
    //   1838: getfield 1614	com/google/android/gms/internal/zzcim$zza:zzapa	Ljava/util/List;
    //   1841: iload 6
    //   1843: invokeinterface 1450 2 0
    //   1848: checkcast 500	com/google/android/gms/internal/zzcmb
    //   1851: getfield 1624	com/google/android/gms/internal/zzcmb:name	Ljava/lang/String;
    //   1854: invokevirtual 1105	com/google/android/gms/internal/zzchk:zzjh	(Ljava/lang/String;)Ljava/lang/String;
    //   1857: invokevirtual 347	com/google/android/gms/internal/zzcho:zzj	(Ljava/lang/String;Ljava/lang/Object;)V
    //   1860: aload 23
    //   1862: getfield 1614	com/google/android/gms/internal/zzcim$zza:zzapa	Ljava/util/List;
    //   1865: iload 6
    //   1867: invokeinterface 1450 2 0
    //   1872: checkcast 500	com/google/android/gms/internal/zzcmb
    //   1875: getfield 504	com/google/android/gms/internal/zzcmb:zzjlh	[Lcom/google/android/gms/internal/zzcmc;
    //   1878: aload 23
    //   1880: getfield 1614	com/google/android/gms/internal/zzcim$zza:zzapa	Ljava/util/List;
    //   1883: iload 6
    //   1885: invokeinterface 1450 2 0
    //   1890: checkcast 500	com/google/android/gms/internal/zzcmb
    //   1893: getfield 504	com/google/android/gms/internal/zzcmb:zzjlh	[Lcom/google/android/gms/internal/zzcmc;
    //   1896: arraylength
    //   1897: iconst_1
    //   1898: iadd
    //   1899: invokestatic 1713	java/util/Arrays:copyOf	([Ljava/lang/Object;I)[Ljava/lang/Object;
    //   1902: checkcast 1714	[Lcom/google/android/gms/internal/zzcmc;
    //   1905: astore_1
    //   1906: new 506	com/google/android/gms/internal/zzcmc
    //   1909: dup
    //   1910: invokespecial 1715	com/google/android/gms/internal/zzcmc:<init>	()V
    //   1913: astore 16
    //   1915: aload 16
    //   1917: ldc_w 1705
    //   1920: putfield 509	com/google/android/gms/internal/zzcmc:name	Ljava/lang/String;
    //   1923: aload 16
    //   1925: lconst_1
    //   1926: invokestatic 495	java/lang/Long:valueOf	(J)Ljava/lang/Long;
    //   1929: putfield 513	com/google/android/gms/internal/zzcmc:zzjll	Ljava/lang/Long;
    //   1932: aload_1
    //   1933: aload_1
    //   1934: arraylength
    //   1935: iconst_1
    //   1936: isub
    //   1937: aload 16
    //   1939: aastore
    //   1940: aload 23
    //   1942: getfield 1614	com/google/android/gms/internal/zzcim$zza:zzapa	Ljava/util/List;
    //   1945: iload 6
    //   1947: invokeinterface 1450 2 0
    //   1952: checkcast 500	com/google/android/gms/internal/zzcmb
    //   1955: aload_1
    //   1956: putfield 504	com/google/android/gms/internal/zzcmb:zzjlh	[Lcom/google/android/gms/internal/zzcmc;
    //   1959: iload 5
    //   1961: ifne +140 -> 2101
    //   1964: aload_0
    //   1965: invokevirtual 294	com/google/android/gms/internal/zzcim:zzawy	()Lcom/google/android/gms/internal/zzchm;
    //   1968: invokevirtual 278	com/google/android/gms/internal/zzchm:zzazj	()Lcom/google/android/gms/internal/zzcho;
    //   1971: ldc_w 1717
    //   1974: aload_0
    //   1975: invokevirtual 658	com/google/android/gms/internal/zzcim:zzawt	()Lcom/google/android/gms/internal/zzchk;
    //   1978: aload 23
    //   1980: getfield 1614	com/google/android/gms/internal/zzcim$zza:zzapa	Ljava/util/List;
    //   1983: iload 6
    //   1985: invokeinterface 1450 2 0
    //   1990: checkcast 500	com/google/android/gms/internal/zzcmb
    //   1993: getfield 1624	com/google/android/gms/internal/zzcmb:name	Ljava/lang/String;
    //   1996: invokevirtual 1105	com/google/android/gms/internal/zzchk:zzjh	(Ljava/lang/String;)Ljava/lang/String;
    //   1999: invokevirtual 347	com/google/android/gms/internal/zzcho:zzj	(Ljava/lang/String;Ljava/lang/Object;)V
    //   2002: aload 23
    //   2004: getfield 1614	com/google/android/gms/internal/zzcim$zza:zzapa	Ljava/util/List;
    //   2007: iload 6
    //   2009: invokeinterface 1450 2 0
    //   2014: checkcast 500	com/google/android/gms/internal/zzcmb
    //   2017: getfield 504	com/google/android/gms/internal/zzcmb:zzjlh	[Lcom/google/android/gms/internal/zzcmc;
    //   2020: aload 23
    //   2022: getfield 1614	com/google/android/gms/internal/zzcim$zza:zzapa	Ljava/util/List;
    //   2025: iload 6
    //   2027: invokeinterface 1450 2 0
    //   2032: checkcast 500	com/google/android/gms/internal/zzcmb
    //   2035: getfield 504	com/google/android/gms/internal/zzcmb:zzjlh	[Lcom/google/android/gms/internal/zzcmc;
    //   2038: arraylength
    //   2039: iconst_1
    //   2040: iadd
    //   2041: invokestatic 1713	java/util/Arrays:copyOf	([Ljava/lang/Object;I)[Ljava/lang/Object;
    //   2044: checkcast 1714	[Lcom/google/android/gms/internal/zzcmc;
    //   2047: astore_1
    //   2048: new 506	com/google/android/gms/internal/zzcmc
    //   2051: dup
    //   2052: invokespecial 1715	com/google/android/gms/internal/zzcmc:<init>	()V
    //   2055: astore 16
    //   2057: aload 16
    //   2059: ldc_w 1202
    //   2062: putfield 509	com/google/android/gms/internal/zzcmc:name	Ljava/lang/String;
    //   2065: aload 16
    //   2067: lconst_1
    //   2068: invokestatic 495	java/lang/Long:valueOf	(J)Ljava/lang/Long;
    //   2071: putfield 513	com/google/android/gms/internal/zzcmc:zzjll	Ljava/lang/Long;
    //   2074: aload_1
    //   2075: aload_1
    //   2076: arraylength
    //   2077: iconst_1
    //   2078: isub
    //   2079: aload 16
    //   2081: aastore
    //   2082: aload 23
    //   2084: getfield 1614	com/google/android/gms/internal/zzcim$zza:zzapa	Ljava/util/List;
    //   2087: iload 6
    //   2089: invokeinterface 1450 2 0
    //   2094: checkcast 500	com/google/android/gms/internal/zzcmb
    //   2097: aload_1
    //   2098: putfield 504	com/google/android/gms/internal/zzcmb:zzjlh	[Lcom/google/android/gms/internal/zzcmc;
    //   2101: aload_0
    //   2102: invokevirtual 602	com/google/android/gms/internal/zzcim:zzaws	()Lcom/google/android/gms/internal/zzcgo;
    //   2105: aload_0
    //   2106: invokespecial 1159	com/google/android/gms/internal/zzcim:zzbag	()J
    //   2109: aload 23
    //   2111: getfield 1619	com/google/android/gms/internal/zzcim$zza:zzjgi	Lcom/google/android/gms/internal/zzcme;
    //   2114: getfield 1257	com/google/android/gms/internal/zzcme:zzcn	Ljava/lang/String;
    //   2117: iconst_0
    //   2118: iconst_0
    //   2119: iconst_0
    //   2120: iconst_0
    //   2121: iconst_1
    //   2122: invokevirtual 1162	com/google/android/gms/internal/zzcgo:zza	(JLjava/lang/String;ZZZZZ)Lcom/google/android/gms/internal/zzcgp;
    //   2125: getfield 1526	com/google/android/gms/internal/zzcgp:zzizb	J
    //   2128: aload_0
    //   2129: getfield 127	com/google/android/gms/internal/zzcim:zzjew	Lcom/google/android/gms/internal/zzcgn;
    //   2132: aload 23
    //   2134: getfield 1619	com/google/android/gms/internal/zzcim$zza:zzjgi	Lcom/google/android/gms/internal/zzcme;
    //   2137: getfield 1257	com/google/android/gms/internal/zzcme:zzcn	Ljava/lang/String;
    //   2140: invokevirtual 1530	com/google/android/gms/internal/zzcgn:zzix	(Ljava/lang/String;)I
    //   2143: i2l
    //   2144: lcmp
    //   2145: ifle +2030 -> 4175
    //   2148: aload 23
    //   2150: getfield 1614	com/google/android/gms/internal/zzcim$zza:zzapa	Ljava/util/List;
    //   2153: iload 6
    //   2155: invokeinterface 1450 2 0
    //   2160: checkcast 500	com/google/android/gms/internal/zzcmb
    //   2163: astore_1
    //   2164: iconst_0
    //   2165: istore 5
    //   2167: iload 12
    //   2169: istore 13
    //   2171: iload 5
    //   2173: aload_1
    //   2174: getfield 504	com/google/android/gms/internal/zzcmb:zzjlh	[Lcom/google/android/gms/internal/zzcmc;
    //   2177: arraylength
    //   2178: if_icmpge +91 -> 2269
    //   2181: ldc_w 1202
    //   2184: aload_1
    //   2185: getfield 504	com/google/android/gms/internal/zzcmb:zzjlh	[Lcom/google/android/gms/internal/zzcmc;
    //   2188: iload 5
    //   2190: aaload
    //   2191: getfield 509	com/google/android/gms/internal/zzcmc:name	Ljava/lang/String;
    //   2194: invokevirtual 447	java/lang/String:equals	(Ljava/lang/Object;)Z
    //   2197: ifeq +2087 -> 4284
    //   2200: aload_1
    //   2201: getfield 504	com/google/android/gms/internal/zzcmb:zzjlh	[Lcom/google/android/gms/internal/zzcmc;
    //   2204: arraylength
    //   2205: iconst_1
    //   2206: isub
    //   2207: anewarray 506	com/google/android/gms/internal/zzcmc
    //   2210: astore 16
    //   2212: iload 5
    //   2214: ifle +16 -> 2230
    //   2217: aload_1
    //   2218: getfield 504	com/google/android/gms/internal/zzcmb:zzjlh	[Lcom/google/android/gms/internal/zzcmc;
    //   2221: iconst_0
    //   2222: aload 16
    //   2224: iconst_0
    //   2225: iload 5
    //   2227: invokestatic 1721	java/lang/System:arraycopy	(Ljava/lang/Object;ILjava/lang/Object;II)V
    //   2230: iload 5
    //   2232: aload 16
    //   2234: arraylength
    //   2235: if_icmpge +24 -> 2259
    //   2238: aload_1
    //   2239: getfield 504	com/google/android/gms/internal/zzcmb:zzjlh	[Lcom/google/android/gms/internal/zzcmc;
    //   2242: iload 5
    //   2244: iconst_1
    //   2245: iadd
    //   2246: aload 16
    //   2248: iload 5
    //   2250: aload 16
    //   2252: arraylength
    //   2253: iload 5
    //   2255: isub
    //   2256: invokestatic 1721	java/lang/System:arraycopy	(Ljava/lang/Object;ILjava/lang/Object;II)V
    //   2259: aload_1
    //   2260: aload 16
    //   2262: putfield 504	com/google/android/gms/internal/zzcmb:zzjlh	[Lcom/google/android/gms/internal/zzcmc;
    //   2265: iload 12
    //   2267: istore 13
    //   2269: iload 13
    //   2271: istore 14
    //   2273: aload 23
    //   2275: getfield 1614	com/google/android/gms/internal/zzcim$zza:zzapa	Ljava/util/List;
    //   2278: iload 6
    //   2280: invokeinterface 1450 2 0
    //   2285: checkcast 500	com/google/android/gms/internal/zzcmb
    //   2288: getfield 1624	com/google/android/gms/internal/zzcmb:name	Ljava/lang/String;
    //   2291: invokestatic 1157	com/google/android/gms/internal/zzclq:zzjz	(Ljava/lang/String;)Z
    //   2294: ifeq +1999 -> 4293
    //   2297: iload 13
    //   2299: istore 14
    //   2301: iload 15
    //   2303: ifeq +1990 -> 4293
    //   2306: iload 13
    //   2308: istore 14
    //   2310: aload_0
    //   2311: invokevirtual 602	com/google/android/gms/internal/zzcim:zzaws	()Lcom/google/android/gms/internal/zzcgo;
    //   2314: aload_0
    //   2315: invokespecial 1159	com/google/android/gms/internal/zzcim:zzbag	()J
    //   2318: aload 23
    //   2320: getfield 1619	com/google/android/gms/internal/zzcim$zza:zzjgi	Lcom/google/android/gms/internal/zzcme;
    //   2323: getfield 1257	com/google/android/gms/internal/zzcme:zzcn	Ljava/lang/String;
    //   2326: iconst_0
    //   2327: iconst_0
    //   2328: iconst_1
    //   2329: iconst_0
    //   2330: iconst_0
    //   2331: invokevirtual 1162	com/google/android/gms/internal/zzcgo:zza	(JLjava/lang/String;ZZZZZ)Lcom/google/android/gms/internal/zzcgp;
    //   2334: getfield 1724	com/google/android/gms/internal/zzcgp:zziyz	J
    //   2337: aload_0
    //   2338: getfield 127	com/google/android/gms/internal/zzcim:zzjew	Lcom/google/android/gms/internal/zzcgn;
    //   2341: aload 23
    //   2343: getfield 1619	com/google/android/gms/internal/zzcim$zza:zzjgi	Lcom/google/android/gms/internal/zzcme;
    //   2346: getfield 1257	com/google/android/gms/internal/zzcme:zzcn	Ljava/lang/String;
    //   2349: getstatic 1727	com/google/android/gms/internal/zzchc:zzjaq	Lcom/google/android/gms/internal/zzchd;
    //   2352: invokevirtual 622	com/google/android/gms/internal/zzcgn:zzb	(Ljava/lang/String;Lcom/google/android/gms/internal/zzchd;)I
    //   2355: i2l
    //   2356: lcmp
    //   2357: ifle +1936 -> 4293
    //   2360: aload_0
    //   2361: invokevirtual 294	com/google/android/gms/internal/zzcim:zzawy	()Lcom/google/android/gms/internal/zzchm;
    //   2364: invokevirtual 297	com/google/android/gms/internal/zzchm:zzazf	()Lcom/google/android/gms/internal/zzcho;
    //   2367: ldc_w 1729
    //   2370: aload 23
    //   2372: getfield 1619	com/google/android/gms/internal/zzcim$zza:zzjgi	Lcom/google/android/gms/internal/zzcme;
    //   2375: getfield 1257	com/google/android/gms/internal/zzcme:zzcn	Ljava/lang/String;
    //   2378: invokestatic 439	com/google/android/gms/internal/zzchm:zzjk	(Ljava/lang/String;)Ljava/lang/Object;
    //   2381: invokevirtual 347	com/google/android/gms/internal/zzcho:zzj	(Ljava/lang/String;Ljava/lang/Object;)V
    //   2384: aload 23
    //   2386: getfield 1614	com/google/android/gms/internal/zzcim$zza:zzapa	Ljava/util/List;
    //   2389: iload 6
    //   2391: invokeinterface 1450 2 0
    //   2396: checkcast 500	com/google/android/gms/internal/zzcmb
    //   2399: astore 18
    //   2401: iconst_0
    //   2402: istore 5
    //   2404: aconst_null
    //   2405: astore_1
    //   2406: aload 18
    //   2408: getfield 504	com/google/android/gms/internal/zzcmb:zzjlh	[Lcom/google/android/gms/internal/zzcmc;
    //   2411: astore 19
    //   2413: aload 19
    //   2415: arraylength
    //   2416: istore 8
    //   2418: iconst_0
    //   2419: istore 7
    //   2421: iload 7
    //   2423: iload 8
    //   2425: if_icmpge +50 -> 2475
    //   2428: aload 19
    //   2430: iload 7
    //   2432: aaload
    //   2433: astore 16
    //   2435: ldc_w 1705
    //   2438: aload 16
    //   2440: getfield 509	com/google/android/gms/internal/zzcmc:name	Ljava/lang/String;
    //   2443: invokevirtual 447	java/lang/String:equals	(Ljava/lang/Object;)Z
    //   2446: ifeq +9 -> 2455
    //   2449: aload 16
    //   2451: astore_1
    //   2452: goto +1823 -> 4275
    //   2455: ldc_w 1113
    //   2458: aload 16
    //   2460: getfield 509	com/google/android/gms/internal/zzcmc:name	Ljava/lang/String;
    //   2463: invokevirtual 447	java/lang/String:equals	(Ljava/lang/Object;)Z
    //   2466: ifeq +1706 -> 4172
    //   2469: iconst_1
    //   2470: istore 5
    //   2472: goto +1803 -> 4275
    //   2475: iload 5
    //   2477: ifeq +67 -> 2544
    //   2480: aload_1
    //   2481: ifnull +63 -> 2544
    //   2484: aload 18
    //   2486: aload 18
    //   2488: getfield 504	com/google/android/gms/internal/zzcmb:zzjlh	[Lcom/google/android/gms/internal/zzcmc;
    //   2491: iconst_1
    //   2492: anewarray 506	com/google/android/gms/internal/zzcmc
    //   2495: dup
    //   2496: iconst_0
    //   2497: aload_1
    //   2498: aastore
    //   2499: invokestatic 1734	com/google/android/gms/common/util/zza:zza	([Ljava/lang/Object;[Ljava/lang/Object;)[Ljava/lang/Object;
    //   2502: checkcast 1714	[Lcom/google/android/gms/internal/zzcmc;
    //   2505: putfield 504	com/google/android/gms/internal/zzcmb:zzjlh	[Lcom/google/android/gms/internal/zzcmc;
    //   2508: iload 13
    //   2510: istore 12
    //   2512: aload 17
    //   2514: getfield 1623	com/google/android/gms/internal/zzcme:zzjlp	[Lcom/google/android/gms/internal/zzcmb;
    //   2517: iload 4
    //   2519: aload 23
    //   2521: getfield 1614	com/google/android/gms/internal/zzcim$zza:zzapa	Ljava/util/List;
    //   2524: iload 6
    //   2526: invokeinterface 1450 2 0
    //   2531: checkcast 500	com/google/android/gms/internal/zzcmb
    //   2534: aastore
    //   2535: iload 4
    //   2537: iconst_1
    //   2538: iadd
    //   2539: istore 4
    //   2541: goto -2037 -> 504
    //   2544: aload_1
    //   2545: ifnull +27 -> 2572
    //   2548: aload_1
    //   2549: ldc_w 1113
    //   2552: putfield 509	com/google/android/gms/internal/zzcmc:name	Ljava/lang/String;
    //   2555: aload_1
    //   2556: ldc2_w 1735
    //   2559: invokestatic 495	java/lang/Long:valueOf	(J)Ljava/lang/Long;
    //   2562: putfield 513	com/google/android/gms/internal/zzcmc:zzjll	Ljava/lang/Long;
    //   2565: iload 13
    //   2567: istore 12
    //   2569: goto -57 -> 2512
    //   2572: aload_0
    //   2573: invokevirtual 294	com/google/android/gms/internal/zzcim:zzawy	()Lcom/google/android/gms/internal/zzchm;
    //   2576: invokevirtual 319	com/google/android/gms/internal/zzchm:zzazd	()Lcom/google/android/gms/internal/zzcho;
    //   2579: ldc_w 1738
    //   2582: aload 23
    //   2584: getfield 1619	com/google/android/gms/internal/zzcim$zza:zzjgi	Lcom/google/android/gms/internal/zzcme;
    //   2587: getfield 1257	com/google/android/gms/internal/zzcme:zzcn	Ljava/lang/String;
    //   2590: invokestatic 439	com/google/android/gms/internal/zzchm:zzjk	(Ljava/lang/String;)Ljava/lang/Object;
    //   2593: invokevirtual 347	com/google/android/gms/internal/zzcho:zzj	(Ljava/lang/String;Ljava/lang/Object;)V
    //   2596: iload 13
    //   2598: istore 14
    //   2600: goto +1693 -> 4293
    //   2603: iload 4
    //   2605: aload 23
    //   2607: getfield 1614	com/google/android/gms/internal/zzcim$zza:zzapa	Ljava/util/List;
    //   2610: invokeinterface 1440 1 0
    //   2615: if_icmpge +21 -> 2636
    //   2618: aload 17
    //   2620: aload 17
    //   2622: getfield 1623	com/google/android/gms/internal/zzcme:zzjlp	[Lcom/google/android/gms/internal/zzcmb;
    //   2625: iload 4
    //   2627: invokestatic 1713	java/util/Arrays:copyOf	([Ljava/lang/Object;I)[Ljava/lang/Object;
    //   2630: checkcast 1739	[Lcom/google/android/gms/internal/zzcmb;
    //   2633: putfield 1623	com/google/android/gms/internal/zzcme:zzjlp	[Lcom/google/android/gms/internal/zzcmb;
    //   2636: aload 17
    //   2638: aload_0
    //   2639: aload 23
    //   2641: getfield 1619	com/google/android/gms/internal/zzcim$zza:zzjgi	Lcom/google/android/gms/internal/zzcme;
    //   2644: getfield 1257	com/google/android/gms/internal/zzcme:zzcn	Ljava/lang/String;
    //   2647: aload 23
    //   2649: getfield 1619	com/google/android/gms/internal/zzcim$zza:zzjgi	Lcom/google/android/gms/internal/zzcme;
    //   2652: getfield 1446	com/google/android/gms/internal/zzcme:zzjlq	[Lcom/google/android/gms/internal/zzcmg;
    //   2655: aload 17
    //   2657: getfield 1623	com/google/android/gms/internal/zzcme:zzjlp	[Lcom/google/android/gms/internal/zzcmb;
    //   2660: invokespecial 1741	com/google/android/gms/internal/zzcim:zza	(Ljava/lang/String;[Lcom/google/android/gms/internal/zzcmg;[Lcom/google/android/gms/internal/zzcmb;)[Lcom/google/android/gms/internal/zzcma;
    //   2663: putfield 1745	com/google/android/gms/internal/zzcme:zzjmi	[Lcom/google/android/gms/internal/zzcma;
    //   2666: getstatic 1748	com/google/android/gms/internal/zzchc:zzjac	Lcom/google/android/gms/internal/zzchd;
    //   2669: invokevirtual 746	com/google/android/gms/internal/zzchd:get	()Ljava/lang/Object;
    //   2672: checkcast 1048	java/lang/Boolean
    //   2675: invokevirtual 1751	java/lang/Boolean:booleanValue	()Z
    //   2678: ifeq +956 -> 3634
    //   2681: aload_0
    //   2682: getfield 127	com/google/android/gms/internal/zzcim:zzjew	Lcom/google/android/gms/internal/zzcgn;
    //   2685: astore_1
    //   2686: aload 23
    //   2688: getfield 1619	com/google/android/gms/internal/zzcim$zza:zzjgi	Lcom/google/android/gms/internal/zzcme;
    //   2691: getfield 1257	com/google/android/gms/internal/zzcme:zzcn	Ljava/lang/String;
    //   2694: astore 16
    //   2696: ldc_w 1753
    //   2699: aload_1
    //   2700: invokevirtual 1754	com/google/android/gms/internal/zzcjk:zzawv	()Lcom/google/android/gms/internal/zzcig;
    //   2703: aload 16
    //   2705: ldc_w 1756
    //   2708: invokevirtual 1759	com/google/android/gms/internal/zzcig:zzam	(Ljava/lang/String;Ljava/lang/String;)Ljava/lang/String;
    //   2711: invokevirtual 447	java/lang/String:equals	(Ljava/lang/Object;)Z
    //   2714: ifeq +920 -> 3634
    //   2717: new 1761	java/util/HashMap
    //   2720: dup
    //   2721: invokespecial 1762	java/util/HashMap:<init>	()V
    //   2724: astore 18
    //   2726: aload 17
    //   2728: getfield 1623	com/google/android/gms/internal/zzcme:zzjlp	[Lcom/google/android/gms/internal/zzcmb;
    //   2731: arraylength
    //   2732: anewarray 500	com/google/android/gms/internal/zzcmb
    //   2735: astore 19
    //   2737: iconst_0
    //   2738: istore 4
    //   2740: aload_0
    //   2741: invokevirtual 424	com/google/android/gms/internal/zzcim:zzawu	()Lcom/google/android/gms/internal/zzclq;
    //   2744: invokevirtual 894	com/google/android/gms/internal/zzclq:zzbaz	()Ljava/security/SecureRandom;
    //   2747: astore 20
    //   2749: aload 17
    //   2751: getfield 1623	com/google/android/gms/internal/zzcme:zzjlp	[Lcom/google/android/gms/internal/zzcmb;
    //   2754: astore 21
    //   2756: aload 21
    //   2758: arraylength
    //   2759: istore 8
    //   2761: iconst_0
    //   2762: istore 5
    //   2764: iload 5
    //   2766: iload 8
    //   2768: if_icmpge +787 -> 3555
    //   2771: aload 21
    //   2773: iload 5
    //   2775: aaload
    //   2776: astore 22
    //   2778: aload 22
    //   2780: getfield 1624	com/google/android/gms/internal/zzcmb:name	Ljava/lang/String;
    //   2783: ldc_w 1764
    //   2786: invokevirtual 447	java/lang/String:equals	(Ljava/lang/Object;)Z
    //   2789: ifeq +161 -> 2950
    //   2792: aload_0
    //   2793: invokevirtual 424	com/google/android/gms/internal/zzcim:zzawu	()Lcom/google/android/gms/internal/zzclq;
    //   2796: pop
    //   2797: aload 22
    //   2799: ldc_w 1766
    //   2802: invokestatic 1769	com/google/android/gms/internal/zzclq:zza	(Lcom/google/android/gms/internal/zzcmb;Ljava/lang/String;)Ljava/lang/Object;
    //   2805: checkcast 443	java/lang/String
    //   2808: astore 24
    //   2810: aload 18
    //   2812: aload 24
    //   2814: invokeinterface 1771 2 0
    //   2819: checkcast 1229	com/google/android/gms/internal/zzcgw
    //   2822: astore 16
    //   2824: aload 16
    //   2826: astore_1
    //   2827: aload 16
    //   2829: ifnonnull +32 -> 2861
    //   2832: aload_0
    //   2833: invokevirtual 602	com/google/android/gms/internal/zzcim:zzaws	()Lcom/google/android/gms/internal/zzcgo;
    //   2836: aload 23
    //   2838: getfield 1619	com/google/android/gms/internal/zzcim$zza:zzjgi	Lcom/google/android/gms/internal/zzcme;
    //   2841: getfield 1257	com/google/android/gms/internal/zzcme:zzcn	Ljava/lang/String;
    //   2844: aload 24
    //   2846: invokevirtual 1220	com/google/android/gms/internal/zzcgo:zzae	(Ljava/lang/String;Ljava/lang/String;)Lcom/google/android/gms/internal/zzcgw;
    //   2849: astore_1
    //   2850: aload 18
    //   2852: aload 24
    //   2854: aload_1
    //   2855: invokeinterface 809 3 0
    //   2860: pop
    //   2861: aload_1
    //   2862: getfield 1774	com/google/android/gms/internal/zzcgw:zzizo	Ljava/lang/Long;
    //   2865: ifnonnull +1467 -> 4332
    //   2868: aload_1
    //   2869: getfield 1777	com/google/android/gms/internal/zzcgw:zzizp	Ljava/lang/Long;
    //   2872: invokevirtual 561	java/lang/Long:longValue	()J
    //   2875: lconst_1
    //   2876: lcmp
    //   2877: ifle +28 -> 2905
    //   2880: aload_0
    //   2881: invokevirtual 424	com/google/android/gms/internal/zzcim:zzawu	()Lcom/google/android/gms/internal/zzclq;
    //   2884: pop
    //   2885: aload 22
    //   2887: aload 22
    //   2889: getfield 504	com/google/android/gms/internal/zzcmb:zzjlh	[Lcom/google/android/gms/internal/zzcmc;
    //   2892: ldc_w 1779
    //   2895: aload_1
    //   2896: getfield 1777	com/google/android/gms/internal/zzcgw:zzizp	Ljava/lang/Long;
    //   2899: invokestatic 1782	com/google/android/gms/internal/zzclq:zza	([Lcom/google/android/gms/internal/zzcmc;Ljava/lang/String;Ljava/lang/Object;)[Lcom/google/android/gms/internal/zzcmc;
    //   2902: putfield 504	com/google/android/gms/internal/zzcmb:zzjlh	[Lcom/google/android/gms/internal/zzcmc;
    //   2905: aload_1
    //   2906: getfield 1785	com/google/android/gms/internal/zzcgw:zzizq	Ljava/lang/Boolean;
    //   2909: ifnull +1391 -> 4300
    //   2912: aload_1
    //   2913: getfield 1785	com/google/android/gms/internal/zzcgw:zzizq	Ljava/lang/Boolean;
    //   2916: invokevirtual 1751	java/lang/Boolean:booleanValue	()Z
    //   2919: ifeq +1381 -> 4300
    //   2922: aload_0
    //   2923: invokevirtual 424	com/google/android/gms/internal/zzcim:zzawu	()Lcom/google/android/gms/internal/zzclq;
    //   2926: pop
    //   2927: aload 22
    //   2929: aload 22
    //   2931: getfield 504	com/google/android/gms/internal/zzcmb:zzjlh	[Lcom/google/android/gms/internal/zzcmc;
    //   2934: ldc_w 1787
    //   2937: lconst_1
    //   2938: invokestatic 495	java/lang/Long:valueOf	(J)Ljava/lang/Long;
    //   2941: invokestatic 1782	com/google/android/gms/internal/zzclq:zza	([Lcom/google/android/gms/internal/zzcmc;Ljava/lang/String;Ljava/lang/Object;)[Lcom/google/android/gms/internal/zzcmc;
    //   2944: putfield 504	com/google/android/gms/internal/zzcmb:zzjlh	[Lcom/google/android/gms/internal/zzcmc;
    //   2947: goto +1353 -> 4300
    //   2950: aload 22
    //   2952: ldc_w 1200
    //   2955: lconst_1
    //   2956: invokestatic 495	java/lang/Long:valueOf	(J)Ljava/lang/Long;
    //   2959: invokestatic 1789	com/google/android/gms/internal/zzcim:zza	(Lcom/google/android/gms/internal/zzcmb;Ljava/lang/String;Ljava/lang/Object;)Z
    //   2962: ifne +1204 -> 4166
    //   2965: aload_0
    //   2966: invokevirtual 791	com/google/android/gms/internal/zzcim:zzawv	()Lcom/google/android/gms/internal/zzcig;
    //   2969: aload 23
    //   2971: getfield 1619	com/google/android/gms/internal/zzcim$zza:zzjgi	Lcom/google/android/gms/internal/zzcme;
    //   2974: getfield 1257	com/google/android/gms/internal/zzcme:zzcn	Ljava/lang/String;
    //   2977: aload 22
    //   2979: getfield 1624	com/google/android/gms/internal/zzcmb:name	Ljava/lang/String;
    //   2982: invokevirtual 1792	com/google/android/gms/internal/zzcig:zzap	(Ljava/lang/String;Ljava/lang/String;)I
    //   2985: istore 6
    //   2987: iload 6
    //   2989: ifgt +46 -> 3035
    //   2992: aload_0
    //   2993: invokevirtual 294	com/google/android/gms/internal/zzcim:zzawy	()Lcom/google/android/gms/internal/zzchm;
    //   2996: invokevirtual 297	com/google/android/gms/internal/zzchm:zzazf	()Lcom/google/android/gms/internal/zzcho;
    //   2999: ldc_w 1794
    //   3002: aload 22
    //   3004: getfield 1624	com/google/android/gms/internal/zzcmb:name	Ljava/lang/String;
    //   3007: iload 6
    //   3009: invokestatic 343	java/lang/Integer:valueOf	(I)Ljava/lang/Integer;
    //   3012: invokevirtual 453	com/google/android/gms/internal/zzcho:zze	(Ljava/lang/String;Ljava/lang/Object;Ljava/lang/Object;)V
    //   3015: iload 4
    //   3017: iconst_1
    //   3018: iadd
    //   3019: istore 6
    //   3021: aload 19
    //   3023: iload 4
    //   3025: aload 22
    //   3027: aastore
    //   3028: iload 6
    //   3030: istore 4
    //   3032: goto +1285 -> 4317
    //   3035: aload 18
    //   3037: aload 22
    //   3039: getfield 1624	com/google/android/gms/internal/zzcmb:name	Ljava/lang/String;
    //   3042: invokeinterface 1771 2 0
    //   3047: checkcast 1229	com/google/android/gms/internal/zzcgw
    //   3050: astore_1
    //   3051: aload_1
    //   3052: ifnonnull +1111 -> 4163
    //   3055: aload_0
    //   3056: invokevirtual 602	com/google/android/gms/internal/zzcim:zzaws	()Lcom/google/android/gms/internal/zzcgo;
    //   3059: aload 23
    //   3061: getfield 1619	com/google/android/gms/internal/zzcim$zza:zzjgi	Lcom/google/android/gms/internal/zzcme;
    //   3064: getfield 1257	com/google/android/gms/internal/zzcme:zzcn	Ljava/lang/String;
    //   3067: aload 22
    //   3069: getfield 1624	com/google/android/gms/internal/zzcmb:name	Ljava/lang/String;
    //   3072: invokevirtual 1220	com/google/android/gms/internal/zzcgo:zzae	(Ljava/lang/String;Ljava/lang/String;)Lcom/google/android/gms/internal/zzcgw;
    //   3075: astore 16
    //   3077: aload 16
    //   3079: astore_1
    //   3080: aload 16
    //   3082: ifnonnull +64 -> 3146
    //   3085: aload_0
    //   3086: invokevirtual 294	com/google/android/gms/internal/zzcim:zzawy	()Lcom/google/android/gms/internal/zzchm;
    //   3089: invokevirtual 297	com/google/android/gms/internal/zzchm:zzazf	()Lcom/google/android/gms/internal/zzcho;
    //   3092: ldc_w 1796
    //   3095: aload 23
    //   3097: getfield 1619	com/google/android/gms/internal/zzcim$zza:zzjgi	Lcom/google/android/gms/internal/zzcme;
    //   3100: getfield 1257	com/google/android/gms/internal/zzcme:zzcn	Ljava/lang/String;
    //   3103: aload 22
    //   3105: getfield 1624	com/google/android/gms/internal/zzcmb:name	Ljava/lang/String;
    //   3108: invokevirtual 453	com/google/android/gms/internal/zzcho:zze	(Ljava/lang/String;Ljava/lang/Object;Ljava/lang/Object;)V
    //   3111: new 1229	com/google/android/gms/internal/zzcgw
    //   3114: dup
    //   3115: aload 23
    //   3117: getfield 1619	com/google/android/gms/internal/zzcim$zza:zzjgi	Lcom/google/android/gms/internal/zzcme;
    //   3120: getfield 1257	com/google/android/gms/internal/zzcme:zzcn	Ljava/lang/String;
    //   3123: aload 22
    //   3125: getfield 1624	com/google/android/gms/internal/zzcmb:name	Ljava/lang/String;
    //   3128: lconst_1
    //   3129: lconst_1
    //   3130: aload 22
    //   3132: getfield 1695	com/google/android/gms/internal/zzcmb:zzjli	Ljava/lang/Long;
    //   3135: invokevirtual 561	java/lang/Long:longValue	()J
    //   3138: lconst_0
    //   3139: aconst_null
    //   3140: aconst_null
    //   3141: aconst_null
    //   3142: invokespecial 1235	com/google/android/gms/internal/zzcgw:<init>	(Ljava/lang/String;Ljava/lang/String;JJJJLjava/lang/Long;Ljava/lang/Long;Ljava/lang/Boolean;)V
    //   3145: astore_1
    //   3146: aload_0
    //   3147: invokevirtual 424	com/google/android/gms/internal/zzcim:zzawu	()Lcom/google/android/gms/internal/zzclq;
    //   3150: pop
    //   3151: aload 22
    //   3153: ldc_w 1798
    //   3156: invokestatic 1769	com/google/android/gms/internal/zzclq:zza	(Lcom/google/android/gms/internal/zzcmb;Ljava/lang/String;)Ljava/lang/Object;
    //   3159: checkcast 492	java/lang/Long
    //   3162: astore 16
    //   3164: aload 16
    //   3166: ifnull +1160 -> 4326
    //   3169: iconst_1
    //   3170: istore 13
    //   3172: iload 13
    //   3174: invokestatic 1051	java/lang/Boolean:valueOf	(Z)Ljava/lang/Boolean;
    //   3177: astore 24
    //   3179: iload 6
    //   3181: iconst_1
    //   3182: if_icmpne +82 -> 3264
    //   3185: iload 4
    //   3187: iconst_1
    //   3188: iadd
    //   3189: istore 6
    //   3191: aload 19
    //   3193: iload 4
    //   3195: aload 22
    //   3197: aastore
    //   3198: iload 6
    //   3200: istore 4
    //   3202: aload 24
    //   3204: invokevirtual 1751	java/lang/Boolean:booleanValue	()Z
    //   3207: ifeq +1110 -> 4317
    //   3210: aload_1
    //   3211: getfield 1774	com/google/android/gms/internal/zzcgw:zzizo	Ljava/lang/Long;
    //   3214: ifnonnull +21 -> 3235
    //   3217: aload_1
    //   3218: getfield 1777	com/google/android/gms/internal/zzcgw:zzizp	Ljava/lang/Long;
    //   3221: ifnonnull +14 -> 3235
    //   3224: iload 6
    //   3226: istore 4
    //   3228: aload_1
    //   3229: getfield 1785	com/google/android/gms/internal/zzcgw:zzizq	Ljava/lang/Boolean;
    //   3232: ifnull +1085 -> 4317
    //   3235: aload_1
    //   3236: aconst_null
    //   3237: aconst_null
    //   3238: aconst_null
    //   3239: invokevirtual 1801	com/google/android/gms/internal/zzcgw:zza	(Ljava/lang/Long;Ljava/lang/Long;Ljava/lang/Boolean;)Lcom/google/android/gms/internal/zzcgw;
    //   3242: astore_1
    //   3243: aload 18
    //   3245: aload 22
    //   3247: getfield 1624	com/google/android/gms/internal/zzcmb:name	Ljava/lang/String;
    //   3250: aload_1
    //   3251: invokeinterface 809 3 0
    //   3256: pop
    //   3257: iload 6
    //   3259: istore 4
    //   3261: goto +1056 -> 4317
    //   3264: aload 20
    //   3266: iload 6
    //   3268: invokevirtual 901	java/security/SecureRandom:nextInt	(I)I
    //   3271: ifne +101 -> 3372
    //   3274: aload_0
    //   3275: invokevirtual 424	com/google/android/gms/internal/zzcim:zzawu	()Lcom/google/android/gms/internal/zzclq;
    //   3278: pop
    //   3279: aload 22
    //   3281: aload 22
    //   3283: getfield 504	com/google/android/gms/internal/zzcmb:zzjlh	[Lcom/google/android/gms/internal/zzcmc;
    //   3286: ldc_w 1779
    //   3289: iload 6
    //   3291: i2l
    //   3292: invokestatic 495	java/lang/Long:valueOf	(J)Ljava/lang/Long;
    //   3295: invokestatic 1782	com/google/android/gms/internal/zzclq:zza	([Lcom/google/android/gms/internal/zzcmc;Ljava/lang/String;Ljava/lang/Object;)[Lcom/google/android/gms/internal/zzcmc;
    //   3298: putfield 504	com/google/android/gms/internal/zzcmb:zzjlh	[Lcom/google/android/gms/internal/zzcmc;
    //   3301: iload 4
    //   3303: iconst_1
    //   3304: iadd
    //   3305: istore 7
    //   3307: aload 19
    //   3309: iload 4
    //   3311: aload 22
    //   3313: aastore
    //   3314: aload_1
    //   3315: astore 16
    //   3317: aload 24
    //   3319: invokevirtual 1751	java/lang/Boolean:booleanValue	()Z
    //   3322: ifeq +17 -> 3339
    //   3325: aload_1
    //   3326: aconst_null
    //   3327: iload 6
    //   3329: i2l
    //   3330: invokestatic 495	java/lang/Long:valueOf	(J)Ljava/lang/Long;
    //   3333: aconst_null
    //   3334: invokevirtual 1801	com/google/android/gms/internal/zzcgw:zza	(Ljava/lang/Long;Ljava/lang/Long;Ljava/lang/Boolean;)Lcom/google/android/gms/internal/zzcgw;
    //   3337: astore 16
    //   3339: aload 18
    //   3341: aload 22
    //   3343: getfield 1624	com/google/android/gms/internal/zzcmb:name	Ljava/lang/String;
    //   3346: aload 16
    //   3348: aload 22
    //   3350: getfield 1695	com/google/android/gms/internal/zzcmb:zzjli	Ljava/lang/Long;
    //   3353: invokevirtual 561	java/lang/Long:longValue	()J
    //   3356: invokevirtual 1804	com/google/android/gms/internal/zzcgw:zzbc	(J)Lcom/google/android/gms/internal/zzcgw;
    //   3359: invokeinterface 809 3 0
    //   3364: pop
    //   3365: iload 7
    //   3367: istore 4
    //   3369: goto +948 -> 4317
    //   3372: aload_1
    //   3373: getfield 1807	com/google/android/gms/internal/zzcgw:zzizn	J
    //   3376: lstore_2
    //   3377: aload 22
    //   3379: getfield 1695	com/google/android/gms/internal/zzcmb:zzjli	Ljava/lang/Long;
    //   3382: invokevirtual 561	java/lang/Long:longValue	()J
    //   3385: lload_2
    //   3386: lsub
    //   3387: invokestatic 934	java/lang/Math:abs	(J)J
    //   3390: ldc2_w 1808
    //   3393: lcmp
    //   3394: iflt +129 -> 3523
    //   3397: aload_0
    //   3398: invokevirtual 424	com/google/android/gms/internal/zzcim:zzawu	()Lcom/google/android/gms/internal/zzclq;
    //   3401: pop
    //   3402: aload 22
    //   3404: aload 22
    //   3406: getfield 504	com/google/android/gms/internal/zzcmb:zzjlh	[Lcom/google/android/gms/internal/zzcmc;
    //   3409: ldc_w 1787
    //   3412: lconst_1
    //   3413: invokestatic 495	java/lang/Long:valueOf	(J)Ljava/lang/Long;
    //   3416: invokestatic 1782	com/google/android/gms/internal/zzclq:zza	([Lcom/google/android/gms/internal/zzcmc;Ljava/lang/String;Ljava/lang/Object;)[Lcom/google/android/gms/internal/zzcmc;
    //   3419: putfield 504	com/google/android/gms/internal/zzcmb:zzjlh	[Lcom/google/android/gms/internal/zzcmc;
    //   3422: aload_0
    //   3423: invokevirtual 424	com/google/android/gms/internal/zzcim:zzawu	()Lcom/google/android/gms/internal/zzclq;
    //   3426: pop
    //   3427: aload 22
    //   3429: aload 22
    //   3431: getfield 504	com/google/android/gms/internal/zzcmb:zzjlh	[Lcom/google/android/gms/internal/zzcmc;
    //   3434: ldc_w 1779
    //   3437: iload 6
    //   3439: i2l
    //   3440: invokestatic 495	java/lang/Long:valueOf	(J)Ljava/lang/Long;
    //   3443: invokestatic 1782	com/google/android/gms/internal/zzclq:zza	([Lcom/google/android/gms/internal/zzcmc;Ljava/lang/String;Ljava/lang/Object;)[Lcom/google/android/gms/internal/zzcmc;
    //   3446: putfield 504	com/google/android/gms/internal/zzcmb:zzjlh	[Lcom/google/android/gms/internal/zzcmc;
    //   3449: iload 4
    //   3451: iconst_1
    //   3452: iadd
    //   3453: istore 7
    //   3455: aload 19
    //   3457: iload 4
    //   3459: aload 22
    //   3461: aastore
    //   3462: aload_1
    //   3463: astore 16
    //   3465: aload 24
    //   3467: invokevirtual 1751	java/lang/Boolean:booleanValue	()Z
    //   3470: ifeq +20 -> 3490
    //   3473: aload_1
    //   3474: aconst_null
    //   3475: iload 6
    //   3477: i2l
    //   3478: invokestatic 495	java/lang/Long:valueOf	(J)Ljava/lang/Long;
    //   3481: iconst_1
    //   3482: invokestatic 1051	java/lang/Boolean:valueOf	(Z)Ljava/lang/Boolean;
    //   3485: invokevirtual 1801	com/google/android/gms/internal/zzcgw:zza	(Ljava/lang/Long;Ljava/lang/Long;Ljava/lang/Boolean;)Lcom/google/android/gms/internal/zzcgw;
    //   3488: astore 16
    //   3490: aload 18
    //   3492: aload 22
    //   3494: getfield 1624	com/google/android/gms/internal/zzcmb:name	Ljava/lang/String;
    //   3497: aload 16
    //   3499: aload 22
    //   3501: getfield 1695	com/google/android/gms/internal/zzcmb:zzjli	Ljava/lang/Long;
    //   3504: invokevirtual 561	java/lang/Long:longValue	()J
    //   3507: invokevirtual 1804	com/google/android/gms/internal/zzcgw:zzbc	(J)Lcom/google/android/gms/internal/zzcgw;
    //   3510: invokeinterface 809 3 0
    //   3515: pop
    //   3516: iload 7
    //   3518: istore 4
    //   3520: goto +797 -> 4317
    //   3523: aload 24
    //   3525: invokevirtual 1751	java/lang/Boolean:booleanValue	()Z
    //   3528: ifeq +804 -> 4332
    //   3531: aload 18
    //   3533: aload 22
    //   3535: getfield 1624	com/google/android/gms/internal/zzcmb:name	Ljava/lang/String;
    //   3538: aload_1
    //   3539: aload 16
    //   3541: aconst_null
    //   3542: aconst_null
    //   3543: invokevirtual 1801	com/google/android/gms/internal/zzcgw:zza	(Ljava/lang/Long;Ljava/lang/Long;Ljava/lang/Boolean;)Lcom/google/android/gms/internal/zzcgw;
    //   3546: invokeinterface 809 3 0
    //   3551: pop
    //   3552: goto +780 -> 4332
    //   3555: iload 4
    //   3557: aload 17
    //   3559: getfield 1623	com/google/android/gms/internal/zzcme:zzjlp	[Lcom/google/android/gms/internal/zzcmb;
    //   3562: arraylength
    //   3563: if_icmpge +18 -> 3581
    //   3566: aload 17
    //   3568: aload 19
    //   3570: iload 4
    //   3572: invokestatic 1713	java/util/Arrays:copyOf	([Ljava/lang/Object;I)[Ljava/lang/Object;
    //   3575: checkcast 1739	[Lcom/google/android/gms/internal/zzcmb;
    //   3578: putfield 1623	com/google/android/gms/internal/zzcme:zzjlp	[Lcom/google/android/gms/internal/zzcmb;
    //   3581: aload 18
    //   3583: invokeinterface 1813 1 0
    //   3588: invokeinterface 1816 1 0
    //   3593: astore_1
    //   3594: aload_1
    //   3595: invokeinterface 1066 1 0
    //   3600: ifeq +34 -> 3634
    //   3603: aload_1
    //   3604: invokeinterface 1069 1 0
    //   3609: checkcast 1818	java/util/Map$Entry
    //   3612: astore 16
    //   3614: aload_0
    //   3615: invokevirtual 602	com/google/android/gms/internal/zzcim:zzaws	()Lcom/google/android/gms/internal/zzcgo;
    //   3618: aload 16
    //   3620: invokeinterface 1821 1 0
    //   3625: checkcast 1229	com/google/android/gms/internal/zzcgw
    //   3628: invokevirtual 1238	com/google/android/gms/internal/zzcgo:zza	(Lcom/google/android/gms/internal/zzcgw;)V
    //   3631: goto -37 -> 3594
    //   3634: aload 17
    //   3636: ldc2_w 1822
    //   3639: invokestatic 495	java/lang/Long:valueOf	(J)Ljava/lang/Long;
    //   3642: putfield 1350	com/google/android/gms/internal/zzcme:zzjls	Ljava/lang/Long;
    //   3645: aload 17
    //   3647: ldc2_w 1824
    //   3650: invokestatic 495	java/lang/Long:valueOf	(J)Ljava/lang/Long;
    //   3653: putfield 1353	com/google/android/gms/internal/zzcme:zzjlt	Ljava/lang/Long;
    //   3656: iconst_0
    //   3657: istore 4
    //   3659: iload 4
    //   3661: aload 17
    //   3663: getfield 1623	com/google/android/gms/internal/zzcme:zzjlp	[Lcom/google/android/gms/internal/zzcmb;
    //   3666: arraylength
    //   3667: if_icmpge +71 -> 3738
    //   3670: aload 17
    //   3672: getfield 1623	com/google/android/gms/internal/zzcme:zzjlp	[Lcom/google/android/gms/internal/zzcmb;
    //   3675: iload 4
    //   3677: aaload
    //   3678: astore_1
    //   3679: aload_1
    //   3680: getfield 1695	com/google/android/gms/internal/zzcmb:zzjli	Ljava/lang/Long;
    //   3683: invokevirtual 561	java/lang/Long:longValue	()J
    //   3686: aload 17
    //   3688: getfield 1350	com/google/android/gms/internal/zzcme:zzjls	Ljava/lang/Long;
    //   3691: invokevirtual 561	java/lang/Long:longValue	()J
    //   3694: lcmp
    //   3695: ifge +12 -> 3707
    //   3698: aload 17
    //   3700: aload_1
    //   3701: getfield 1695	com/google/android/gms/internal/zzcmb:zzjli	Ljava/lang/Long;
    //   3704: putfield 1350	com/google/android/gms/internal/zzcme:zzjls	Ljava/lang/Long;
    //   3707: aload_1
    //   3708: getfield 1695	com/google/android/gms/internal/zzcmb:zzjli	Ljava/lang/Long;
    //   3711: invokevirtual 561	java/lang/Long:longValue	()J
    //   3714: aload 17
    //   3716: getfield 1353	com/google/android/gms/internal/zzcme:zzjlt	Ljava/lang/Long;
    //   3719: invokevirtual 561	java/lang/Long:longValue	()J
    //   3722: lcmp
    //   3723: ifle +612 -> 4335
    //   3726: aload 17
    //   3728: aload_1
    //   3729: getfield 1695	com/google/android/gms/internal/zzcmb:zzjli	Ljava/lang/Long;
    //   3732: putfield 1353	com/google/android/gms/internal/zzcme:zzjlt	Ljava/lang/Long;
    //   3735: goto +600 -> 4335
    //   3738: aload 23
    //   3740: getfield 1619	com/google/android/gms/internal/zzcim$zza:zzjgi	Lcom/google/android/gms/internal/zzcme;
    //   3743: getfield 1257	com/google/android/gms/internal/zzcme:zzcn	Ljava/lang/String;
    //   3746: astore 16
    //   3748: aload_0
    //   3749: invokevirtual 602	com/google/android/gms/internal/zzcim:zzaws	()Lcom/google/android/gms/internal/zzcgo;
    //   3752: aload 16
    //   3754: invokevirtual 1119	com/google/android/gms/internal/zzcgo:zzjb	(Ljava/lang/String;)Lcom/google/android/gms/internal/zzcgh;
    //   3757: astore 18
    //   3759: aload 18
    //   3761: ifnonnull +161 -> 3922
    //   3764: aload_0
    //   3765: invokevirtual 294	com/google/android/gms/internal/zzcim:zzawy	()Lcom/google/android/gms/internal/zzchm;
    //   3768: invokevirtual 319	com/google/android/gms/internal/zzchm:zzazd	()Lcom/google/android/gms/internal/zzcho;
    //   3771: ldc_w 1827
    //   3774: aload 23
    //   3776: getfield 1619	com/google/android/gms/internal/zzcim$zza:zzjgi	Lcom/google/android/gms/internal/zzcme;
    //   3779: getfield 1257	com/google/android/gms/internal/zzcme:zzcn	Ljava/lang/String;
    //   3782: invokestatic 439	com/google/android/gms/internal/zzchm:zzjk	(Ljava/lang/String;)Ljava/lang/Object;
    //   3785: invokevirtual 347	com/google/android/gms/internal/zzcho:zzj	(Ljava/lang/String;Ljava/lang/Object;)V
    //   3788: aload 17
    //   3790: getfield 1623	com/google/android/gms/internal/zzcme:zzjlp	[Lcom/google/android/gms/internal/zzcmb;
    //   3793: arraylength
    //   3794: ifle +67 -> 3861
    //   3797: aload_0
    //   3798: invokevirtual 791	com/google/android/gms/internal/zzcim:zzawv	()Lcom/google/android/gms/internal/zzcig;
    //   3801: aload 23
    //   3803: getfield 1619	com/google/android/gms/internal/zzcim$zza:zzjgi	Lcom/google/android/gms/internal/zzcme;
    //   3806: getfield 1257	com/google/android/gms/internal/zzcme:zzcn	Ljava/lang/String;
    //   3809: invokevirtual 795	com/google/android/gms/internal/zzcig:zzjs	(Ljava/lang/String;)Lcom/google/android/gms/internal/zzcly;
    //   3812: astore_1
    //   3813: aload_1
    //   3814: ifnull +10 -> 3824
    //   3817: aload_1
    //   3818: getfield 1832	com/google/android/gms/internal/zzcly:zzjkw	Ljava/lang/Long;
    //   3821: ifnonnull +258 -> 4079
    //   3824: aload 23
    //   3826: getfield 1619	com/google/android/gms/internal/zzcim$zza:zzjgi	Lcom/google/android/gms/internal/zzcme;
    //   3829: getfield 1283	com/google/android/gms/internal/zzcme:zzixs	Ljava/lang/String;
    //   3832: invokestatic 401	android/text/TextUtils:isEmpty	(Ljava/lang/CharSequence;)Z
    //   3835: ifeq +217 -> 4052
    //   3838: aload 17
    //   3840: ldc2_w 101
    //   3843: invokestatic 495	java/lang/Long:valueOf	(J)Ljava/lang/Long;
    //   3846: putfield 1835	com/google/android/gms/internal/zzcme:zzjmn	Ljava/lang/Long;
    //   3849: aload_0
    //   3850: invokevirtual 602	com/google/android/gms/internal/zzcim:zzaws	()Lcom/google/android/gms/internal/zzcgo;
    //   3853: aload 17
    //   3855: iload 12
    //   3857: invokevirtual 1838	com/google/android/gms/internal/zzcgo:zza	(Lcom/google/android/gms/internal/zzcme;Z)Z
    //   3860: pop
    //   3861: aload_0
    //   3862: invokevirtual 602	com/google/android/gms/internal/zzcim:zzaws	()Lcom/google/android/gms/internal/zzcgo;
    //   3865: aload 23
    //   3867: getfield 1841	com/google/android/gms/internal/zzcim$zza:zzjgj	Ljava/util/List;
    //   3870: invokevirtual 1845	com/google/android/gms/internal/zzcgo:zzah	(Ljava/util/List;)V
    //   3873: aload_0
    //   3874: invokevirtual 602	com/google/android/gms/internal/zzcim:zzaws	()Lcom/google/android/gms/internal/zzcgo;
    //   3877: astore_1
    //   3878: aload_1
    //   3879: invokevirtual 632	com/google/android/gms/internal/zzcgo:getWritableDatabase	()Landroid/database/sqlite/SQLiteDatabase;
    //   3882: astore 17
    //   3884: aload 17
    //   3886: ldc_w 1847
    //   3889: iconst_2
    //   3890: anewarray 443	java/lang/String
    //   3893: dup
    //   3894: iconst_0
    //   3895: aload 16
    //   3897: aastore
    //   3898: dup
    //   3899: iconst_1
    //   3900: aload 16
    //   3902: aastore
    //   3903: invokevirtual 643	android/database/sqlite/SQLiteDatabase:execSQL	(Ljava/lang/String;[Ljava/lang/Object;)V
    //   3906: aload_0
    //   3907: invokevirtual 602	com/google/android/gms/internal/zzcim:zzaws	()Lcom/google/android/gms/internal/zzcgo;
    //   3910: invokevirtual 1151	com/google/android/gms/internal/zzcgo:setTransactionSuccessful	()V
    //   3913: aload_0
    //   3914: invokevirtual 602	com/google/android/gms/internal/zzcim:zzaws	()Lcom/google/android/gms/internal/zzcgo;
    //   3917: invokevirtual 1154	com/google/android/gms/internal/zzcgo:endTransaction	()V
    //   3920: iconst_1
    //   3921: ireturn
    //   3922: aload 17
    //   3924: getfield 1623	com/google/android/gms/internal/zzcme:zzjlp	[Lcom/google/android/gms/internal/zzcmb;
    //   3927: arraylength
    //   3928: ifle -140 -> 3788
    //   3931: aload 18
    //   3933: invokevirtual 1850	com/google/android/gms/internal/zzcgh:zzaxf	()J
    //   3936: lstore_2
    //   3937: lload_2
    //   3938: lconst_0
    //   3939: lcmp
    //   3940: ifeq +404 -> 4344
    //   3943: lload_2
    //   3944: invokestatic 495	java/lang/Long:valueOf	(J)Ljava/lang/Long;
    //   3947: astore_1
    //   3948: aload 17
    //   3950: aload_1
    //   3951: putfield 1853	com/google/android/gms/internal/zzcme:zzjlv	Ljava/lang/Long;
    //   3954: aload 18
    //   3956: invokevirtual 1856	com/google/android/gms/internal/zzcgh:zzaxe	()J
    //   3959: lstore 10
    //   3961: lload 10
    //   3963: lconst_0
    //   3964: lcmp
    //   3965: ifne +192 -> 4157
    //   3968: lload_2
    //   3969: lconst_0
    //   3970: lcmp
    //   3971: ifeq +378 -> 4349
    //   3974: lload_2
    //   3975: invokestatic 495	java/lang/Long:valueOf	(J)Ljava/lang/Long;
    //   3978: astore_1
    //   3979: aload 17
    //   3981: aload_1
    //   3982: putfield 1859	com/google/android/gms/internal/zzcme:zzjlu	Ljava/lang/Long;
    //   3985: aload 18
    //   3987: invokevirtual 1862	com/google/android/gms/internal/zzcgh:zzaxo	()V
    //   3990: aload 17
    //   3992: aload 18
    //   3994: invokevirtual 1865	com/google/android/gms/internal/zzcgh:zzaxl	()J
    //   3997: l2i
    //   3998: invokestatic 343	java/lang/Integer:valueOf	(I)Ljava/lang/Integer;
    //   4001: putfield 1868	com/google/android/gms/internal/zzcme:zzjmg	Ljava/lang/Integer;
    //   4004: aload 18
    //   4006: aload 17
    //   4008: getfield 1350	com/google/android/gms/internal/zzcme:zzjls	Ljava/lang/Long;
    //   4011: invokevirtual 561	java/lang/Long:longValue	()J
    //   4014: invokevirtual 1402	com/google/android/gms/internal/zzcgh:zzal	(J)V
    //   4017: aload 18
    //   4019: aload 17
    //   4021: getfield 1353	com/google/android/gms/internal/zzcme:zzjlt	Ljava/lang/Long;
    //   4024: invokevirtual 561	java/lang/Long:longValue	()J
    //   4027: invokevirtual 1405	com/google/android/gms/internal/zzcgh:zzam	(J)V
    //   4030: aload 17
    //   4032: aload 18
    //   4034: invokevirtual 1871	com/google/android/gms/internal/zzcgh:zzaxw	()Ljava/lang/String;
    //   4037: putfield 1872	com/google/android/gms/internal/zzcme:zzixw	Ljava/lang/String;
    //   4040: aload_0
    //   4041: invokevirtual 602	com/google/android/gms/internal/zzcim:zzaws	()Lcom/google/android/gms/internal/zzcgo;
    //   4044: aload 18
    //   4046: invokevirtual 1427	com/google/android/gms/internal/zzcgo:zza	(Lcom/google/android/gms/internal/zzcgh;)V
    //   4049: goto -261 -> 3788
    //   4052: aload_0
    //   4053: invokevirtual 294	com/google/android/gms/internal/zzcim:zzawy	()Lcom/google/android/gms/internal/zzchm;
    //   4056: invokevirtual 297	com/google/android/gms/internal/zzchm:zzazf	()Lcom/google/android/gms/internal/zzcho;
    //   4059: ldc_w 1874
    //   4062: aload 23
    //   4064: getfield 1619	com/google/android/gms/internal/zzcim$zza:zzjgi	Lcom/google/android/gms/internal/zzcme;
    //   4067: getfield 1257	com/google/android/gms/internal/zzcme:zzcn	Ljava/lang/String;
    //   4070: invokestatic 439	com/google/android/gms/internal/zzchm:zzjk	(Ljava/lang/String;)Ljava/lang/Object;
    //   4073: invokevirtual 347	com/google/android/gms/internal/zzcho:zzj	(Ljava/lang/String;Ljava/lang/Object;)V
    //   4076: goto -227 -> 3849
    //   4079: aload 17
    //   4081: aload_1
    //   4082: getfield 1832	com/google/android/gms/internal/zzcly:zzjkw	Ljava/lang/Long;
    //   4085: putfield 1835	com/google/android/gms/internal/zzcme:zzjmn	Ljava/lang/Long;
    //   4088: goto -239 -> 3849
    //   4091: astore 17
    //   4093: aload_1
    //   4094: invokevirtual 274	com/google/android/gms/internal/zzcjk:zzawy	()Lcom/google/android/gms/internal/zzchm;
    //   4097: invokevirtual 319	com/google/android/gms/internal/zzchm:zzazd	()Lcom/google/android/gms/internal/zzcho;
    //   4100: ldc_w 1876
    //   4103: aload 16
    //   4105: invokestatic 439	com/google/android/gms/internal/zzchm:zzjk	(Ljava/lang/String;)Ljava/lang/Object;
    //   4108: aload 17
    //   4110: invokevirtual 453	com/google/android/gms/internal/zzcho:zze	(Ljava/lang/String;Ljava/lang/Object;Ljava/lang/Object;)V
    //   4113: goto -207 -> 3906
    //   4116: aload_0
    //   4117: invokevirtual 602	com/google/android/gms/internal/zzcim:zzaws	()Lcom/google/android/gms/internal/zzcgo;
    //   4120: invokevirtual 1151	com/google/android/gms/internal/zzcgo:setTransactionSuccessful	()V
    //   4123: aload_0
    //   4124: invokevirtual 602	com/google/android/gms/internal/zzcim:zzaws	()Lcom/google/android/gms/internal/zzcgo;
    //   4127: invokevirtual 1154	com/google/android/gms/internal/zzcgo:endTransaction	()V
    //   4130: iconst_0
    //   4131: ireturn
    //   4132: astore 16
    //   4134: goto -2554 -> 1580
    //   4137: astore 18
    //   4139: goto -2788 -> 1351
    //   4142: astore 18
    //   4144: aload 16
    //   4146: astore_1
    //   4147: aload 17
    //   4149: astore 16
    //   4151: aload_1
    //   4152: astore 17
    //   4154: goto -2803 -> 1351
    //   4157: lload 10
    //   4159: lstore_2
    //   4160: goto -192 -> 3968
    //   4163: goto -1017 -> 3146
    //   4166: iconst_1
    //   4167: istore 6
    //   4169: goto -1182 -> 2987
    //   4172: goto +103 -> 4275
    //   4175: iconst_1
    //   4176: istore 13
    //   4178: goto -1909 -> 2269
    //   4181: goto +85 -> 4266
    //   4184: goto -3680 -> 504
    //   4187: lload 10
    //   4189: ldc2_w 101
    //   4192: lcmp
    //   4193: ifeq +23 -> 4216
    //   4196: ldc_w 1878
    //   4199: astore 19
    //   4201: goto -4066 -> 135
    //   4204: iconst_1
    //   4205: istore 4
    //   4207: goto -3952 -> 255
    //   4210: iconst_1
    //   4211: istore 5
    //   4213: goto -3780 -> 433
    //   4216: ldc_w 430
    //   4219: astore 19
    //   4221: goto -4086 -> 135
    //   4224: lload 10
    //   4226: ldc2_w 101
    //   4229: lcmp
    //   4230: ifeq +11 -> 4241
    //   4233: ldc_w 1880
    //   4236: astore 19
    //   4238: goto -3466 -> 772
    //   4241: ldc_w 430
    //   4244: astore 19
    //   4246: goto -3474 -> 772
    //   4249: astore 16
    //   4251: goto -2671 -> 1580
    //   4254: iconst_0
    //   4255: istore 4
    //   4257: goto -4002 -> 255
    //   4260: iconst_0
    //   4261: istore 5
    //   4263: goto -3830 -> 433
    //   4266: iload 7
    //   4268: iconst_1
    //   4269: iadd
    //   4270: istore 7
    //   4272: goto -2531 -> 1741
    //   4275: iload 7
    //   4277: iconst_1
    //   4278: iadd
    //   4279: istore 7
    //   4281: goto -1860 -> 2421
    //   4284: iload 5
    //   4286: iconst_1
    //   4287: iadd
    //   4288: istore 5
    //   4290: goto -2123 -> 2167
    //   4293: iload 14
    //   4295: istore 12
    //   4297: goto -1785 -> 2512
    //   4300: iload 4
    //   4302: iconst_1
    //   4303: iadd
    //   4304: istore 6
    //   4306: aload 19
    //   4308: iload 4
    //   4310: aload 22
    //   4312: aastore
    //   4313: iload 6
    //   4315: istore 4
    //   4317: iload 5
    //   4319: iconst_1
    //   4320: iadd
    //   4321: istore 5
    //   4323: goto -1559 -> 2764
    //   4326: iconst_0
    //   4327: istore 13
    //   4329: goto -1157 -> 3172
    //   4332: goto -15 -> 4317
    //   4335: iload 4
    //   4337: iconst_1
    //   4338: iadd
    //   4339: istore 4
    //   4341: goto -682 -> 3659
    //   4344: aconst_null
    //   4345: astore_1
    //   4346: goto -398 -> 3948
    //   4349: aconst_null
    //   4350: astore_1
    //   4351: goto -372 -> 3979
    // Local variable table:
    //   start	length	slot	name	signature
    //   0	4354	0	this	zzcim
    //   0	4354	1	paramString	String
    //   0	4354	2	paramLong	long
    //   255	4085	4	i	int
    //   433	3889	5	j	int
    //   292	4022	6	k	int
    //   1739	2541	7	m	int
    //   1667	1102	8	n	int
    //   1736	10	9	i1	int
    //   31	4194	10	l	long
    //   212	4084	12	bool1	boolean
    //   2169	2159	13	bool2	boolean
    //   1640	2654	14	bool3	boolean
    //   1626	676	15	bool4	boolean
    //   57	4047	16	localObject1	Object
    //   4132	13	16	localObject2	Object
    //   4149	1	16	localObject3	Object
    //   4249	1	16	localObject4	Object
    //   61	4019	17	localObject5	Object
    //   4091	57	17	localSQLiteException1	SQLiteException
    //   4152	1	17	str	String
    //   130	1074	18	localObject6	Object
    //   1257	73	18	localIOException1	IOException
    //   1334	1	18	localObject7	Object
    //   1339	32	18	localSQLiteException2	SQLiteException
    //   1413	34	18	localObject8	Object
    //   1522	22	18	localIOException2	IOException
    //   2399	1646	18	localObject9	Object
    //   4137	1	18	localSQLiteException3	SQLiteException
    //   4142	1	18	localSQLiteException4	SQLiteException
    //   152	4155	19	localObject10	Object
    //   25	3240	20	localObject11	Object
    //   53	2719	21	localObject12	Object
    //   50	4261	22	localzzcmb	zzcmb
    //   16	4047	23	localzza	zza
    //   22	3502	24	localObject13	Object
    //   71	1085	25	localSQLiteDatabase	SQLiteDatabase
    // Exception table:
    //   from	to	target	type
    //   7	24	721	finally
    //   27	49	721	finally
    //   224	231	721	finally
    //   231	252	721	finally
    //   263	288	721	finally
    //   294	430	721	finally
    //   438	504	721	finally
    //   711	718	721	finally
    //   860	867	721	finally
    //   1247	1254	721	finally
    //   1292	1299	721	finally
    //   1380	1387	721	finally
    //   1512	1519	721	finally
    //   1570	1577	721	finally
    //   1584	1590	721	finally
    //   1590	1593	721	finally
    //   1593	1628	721	finally
    //   1633	1638	721	finally
    //   1642	1666	721	finally
    //   1672	1715	721	finally
    //   1715	1738	721	finally
    //   1754	1777	721	finally
    //   1783	1806	721	finally
    //   1822	1959	721	finally
    //   1964	2101	721	finally
    //   2101	2164	721	finally
    //   2171	2212	721	finally
    //   2217	2230	721	finally
    //   2230	2259	721	finally
    //   2259	2265	721	finally
    //   2273	2297	721	finally
    //   2310	2401	721	finally
    //   2406	2418	721	finally
    //   2435	2449	721	finally
    //   2455	2469	721	finally
    //   2484	2508	721	finally
    //   2512	2535	721	finally
    //   2548	2565	721	finally
    //   2572	2596	721	finally
    //   2603	2636	721	finally
    //   2636	2737	721	finally
    //   2740	2761	721	finally
    //   2778	2824	721	finally
    //   2832	2861	721	finally
    //   2861	2905	721	finally
    //   2905	2947	721	finally
    //   2950	2987	721	finally
    //   2992	3015	721	finally
    //   3035	3051	721	finally
    //   3055	3077	721	finally
    //   3085	3146	721	finally
    //   3146	3164	721	finally
    //   3172	3179	721	finally
    //   3202	3224	721	finally
    //   3228	3235	721	finally
    //   3235	3257	721	finally
    //   3264	3301	721	finally
    //   3317	3339	721	finally
    //   3339	3365	721	finally
    //   3372	3449	721	finally
    //   3465	3490	721	finally
    //   3490	3516	721	finally
    //   3523	3552	721	finally
    //   3555	3581	721	finally
    //   3581	3594	721	finally
    //   3594	3631	721	finally
    //   3634	3656	721	finally
    //   3659	3707	721	finally
    //   3707	3735	721	finally
    //   3738	3759	721	finally
    //   3764	3788	721	finally
    //   3788	3813	721	finally
    //   3817	3824	721	finally
    //   3824	3849	721	finally
    //   3849	3861	721	finally
    //   3861	3884	721	finally
    //   3884	3906	721	finally
    //   3906	3913	721	finally
    //   3922	3937	721	finally
    //   3943	3948	721	finally
    //   3948	3961	721	finally
    //   3974	3979	721	finally
    //   3979	4049	721	finally
    //   4052	4076	721	finally
    //   4079	4088	721	finally
    //   4093	4113	721	finally
    //   4116	4123	721	finally
    //   1008	1016	1257	java/io/IOException
    //   618	663	1339	android/database/sqlite/SQLiteException
    //   670	680	1339	android/database/sqlite/SQLiteException
    //   687	706	1339	android/database/sqlite/SQLiteException
    //   957	967	1339	android/database/sqlite/SQLiteException
    //   974	985	1339	android/database/sqlite/SQLiteException
    //   992	1001	1339	android/database/sqlite/SQLiteException
    //   1008	1016	1339	android/database/sqlite/SQLiteException
    //   1023	1033	1339	android/database/sqlite/SQLiteException
    //   1040	1059	1339	android/database/sqlite/SQLiteException
    //   1066	1073	1339	android/database/sqlite/SQLiteException
    //   1080	1089	1339	android/database/sqlite/SQLiteException
    //   1110	1116	1339	android/database/sqlite/SQLiteException
    //   1135	1144	1339	android/database/sqlite/SQLiteException
    //   1155	1203	1339	android/database/sqlite/SQLiteException
    //   1266	1287	1339	android/database/sqlite/SQLiteException
    //   1314	1320	1339	android/database/sqlite/SQLiteException
    //   1444	1452	1522	java/io/IOException
    //   3884	3906	4091	android/database/sqlite/SQLiteException
    //   618	663	4132	finally
    //   670	680	4132	finally
    //   687	706	4132	finally
    //   957	967	4132	finally
    //   974	985	4132	finally
    //   992	1001	4132	finally
    //   1008	1016	4132	finally
    //   1023	1033	4132	finally
    //   1040	1059	4132	finally
    //   1066	1073	4132	finally
    //   1080	1089	4132	finally
    //   1110	1116	4132	finally
    //   1135	1144	4132	finally
    //   1155	1203	4132	finally
    //   1266	1287	4132	finally
    //   1314	1320	4132	finally
    //   66	73	4137	android/database/sqlite/SQLiteException
    //   84	91	4137	android/database/sqlite/SQLiteException
    //   111	132	4137	android/database/sqlite/SQLiteException
    //   146	194	4137	android/database/sqlite/SQLiteException
    //   205	214	4137	android/database/sqlite/SQLiteException
    //   524	537	4137	android/database/sqlite/SQLiteException
    //   551	561	4137	android/database/sqlite/SQLiteException
    //   572	582	4137	android/database/sqlite/SQLiteException
    //   593	600	4137	android/database/sqlite/SQLiteException
    //   751	769	4137	android/database/sqlite/SQLiteException
    //   783	830	4137	android/database/sqlite/SQLiteException
    //   841	850	4137	android/database/sqlite/SQLiteException
    //   881	891	4137	android/database/sqlite/SQLiteException
    //   905	915	4137	android/database/sqlite/SQLiteException
    //   926	933	4137	android/database/sqlite/SQLiteException
    //   1210	1220	4142	android/database/sqlite/SQLiteException
    //   1223	1242	4142	android/database/sqlite/SQLiteException
    //   1393	1402	4142	android/database/sqlite/SQLiteException
    //   1405	1415	4142	android/database/sqlite/SQLiteException
    //   1418	1429	4142	android/database/sqlite/SQLiteException
    //   1432	1441	4142	android/database/sqlite/SQLiteException
    //   1444	1452	4142	android/database/sqlite/SQLiteException
    //   1455	1468	4142	android/database/sqlite/SQLiteException
    //   1471	1487	4142	android/database/sqlite/SQLiteException
    //   1490	1502	4142	android/database/sqlite/SQLiteException
    //   1527	1548	4142	android/database/sqlite/SQLiteException
    //   1551	1560	4142	android/database/sqlite/SQLiteException
    //   66	73	4249	finally
    //   84	91	4249	finally
    //   111	132	4249	finally
    //   146	194	4249	finally
    //   205	214	4249	finally
    //   524	537	4249	finally
    //   551	561	4249	finally
    //   572	582	4249	finally
    //   593	600	4249	finally
    //   751	769	4249	finally
    //   783	830	4249	finally
    //   841	850	4249	finally
    //   881	891	4249	finally
    //   905	915	4249	finally
    //   926	933	4249	finally
    //   1210	1220	4249	finally
    //   1223	1242	4249	finally
    //   1354	1375	4249	finally
    //   1393	1402	4249	finally
    //   1405	1415	4249	finally
    //   1418	1429	4249	finally
    //   1432	1441	4249	finally
    //   1444	1452	4249	finally
    //   1455	1468	4249	finally
    //   1471	1487	4249	finally
    //   1490	1502	4249	finally
    //   1527	1548	4249	finally
    //   1551	1560	4249	finally
  }
  
  private final zzcgi zzjw(String paramString)
  {
    zzcgh localzzcgh = zzaws().zzjb(paramString);
    if ((localzzcgh == null) || (TextUtils.isEmpty(localzzcgh.zzvj())))
    {
      zzawy().zzazi().zzj("No app data available; dropping", paramString);
      return null;
    }
    try
    {
      String str = zzbhf.zzdb(this.mContext).getPackageInfo(paramString, 0).versionName;
      if ((localzzcgh.zzvj() != null) && (!localzzcgh.zzvj().equals(str)))
      {
        zzawy().zzazf().zzj("App version does not match; dropping. appId", zzchm.zzjk(paramString));
        return null;
      }
    }
    catch (PackageManager.NameNotFoundException localNameNotFoundException) {}
    return new zzcgi(paramString, localzzcgh.getGmpAppId(), localzzcgh.zzvj(), localzzcgh.zzaxg(), localzzcgh.zzaxh(), localzzcgh.zzaxi(), localzzcgh.zzaxj(), null, localzzcgh.zzaxk(), false, localzzcgh.zzaxd(), localzzcgh.zzaxx(), 0L, 0, localzzcgh.zzaxy());
  }
  
  public final Context getContext()
  {
    return this.mContext;
  }
  
  public final boolean isEnabled()
  {
    boolean bool = false;
    zzawx().zzve();
    zzxf();
    if (this.zzjew.zzaya()) {
      return false;
    }
    Boolean localBoolean = this.zzjew.zziy("firebase_analytics_collection_enabled");
    if (localBoolean != null) {
      bool = localBoolean.booleanValue();
    }
    for (;;)
    {
      return zzawz().zzbn(bool);
      if (!zzbz.zzaji()) {
        bool = true;
      }
    }
  }
  
  protected final void start()
  {
    zzawx().zzve();
    zzaws().zzayh();
    if (zzawz().zzjcr.get() == 0L) {
      zzawz().zzjcr.set(this.zzata.currentTimeMillis());
    }
    if (Long.valueOf(zzawz().zzjcw.get()).longValue() == 0L)
    {
      zzawy().zzazj().zzj("Persisting first open", Long.valueOf(this.zzjgg));
      zzawz().zzjcw.set(this.zzjgg);
    }
    if (!zzazv())
    {
      if (isEnabled())
      {
        if (!zzawu().zzeb("android.permission.INTERNET")) {
          zzawy().zzazd().log("App is missing INTERNET permission");
        }
        if (!zzawu().zzeb("android.permission.ACCESS_NETWORK_STATE")) {
          zzawy().zzazd().log("App is missing ACCESS_NETWORK_STATE permission");
        }
        if (!zzbhf.zzdb(this.mContext).zzamu())
        {
          if (!zzcid.zzbk(this.mContext)) {
            zzawy().zzazd().log("AppMeasurementReceiver not registered/enabled");
          }
          if (!zzcla.zzk(this.mContext, false)) {
            zzawy().zzazd().log("AppMeasurementService not registered/enabled");
          }
        }
        zzawy().zzazd().log("Uploading is not possible. App measurement disabled");
      }
      zzbaj();
      return;
    }
    Object localObject;
    if (!TextUtils.isEmpty(zzawn().getGmpAppId()))
    {
      localObject = zzawz().zzazm();
      if (localObject != null) {
        break label422;
      }
      zzawz().zzjo(zzawn().getGmpAppId());
    }
    for (;;)
    {
      zzawm().zzjp(zzawz().zzjcx.zzazr());
      if (TextUtils.isEmpty(zzawn().getGmpAppId())) {
        break;
      }
      localObject = zzawm();
      ((zzcjk)localObject).zzve();
      ((zzcjl)localObject).zzxf();
      if (((zzcjn)localObject).zziwf.zzazv())
      {
        ((zzcjk)localObject).zzawp().zzbar();
        String str = ((zzcjk)localObject).zzawz().zzazq();
        if (!TextUtils.isEmpty(str))
        {
          ((zzcjk)localObject).zzawo().zzxf();
          if (!str.equals(Build.VERSION.RELEASE))
          {
            Bundle localBundle = new Bundle();
            localBundle.putString("_po", str);
            ((zzcjn)localObject).zzc("auto", "_ou", localBundle);
          }
        }
      }
      zzawp().zza(new AtomicReference());
      break;
      label422:
      if (!((String)localObject).equals(zzawn().getGmpAppId()))
      {
        zzawy().zzazh().log("Rechecking which service to use due to a GMP App Id change");
        zzawz().zzazp();
        this.zzjfk.disconnect();
        this.zzjfk.zzyc();
        zzawz().zzjo(zzawn().getGmpAppId());
        zzawz().zzjcw.set(this.zzjgg);
        zzawz().zzjcx.zzjq(null);
      }
    }
  }
  
  /* Error */
  protected final void zza(int paramInt, Throwable paramThrowable, byte[] paramArrayOfByte)
  {
    // Byte code:
    //   0: aload_0
    //   1: invokevirtual 307	com/google/android/gms/internal/zzcim:zzawx	()Lcom/google/android/gms/internal/zzcih;
    //   4: invokevirtual 310	com/google/android/gms/internal/zzcjk:zzve	()V
    //   7: aload_0
    //   8: invokevirtual 913	com/google/android/gms/internal/zzcim:zzxf	()V
    //   11: aload_3
    //   12: astore 6
    //   14: aload_3
    //   15: ifnonnull +8 -> 23
    //   18: iconst_0
    //   19: newarray <illegal type>
    //   21: astore 6
    //   23: aload_0
    //   24: getfield 2018	com/google/android/gms/internal/zzcim:zzjfx	Ljava/util/List;
    //   27: astore_3
    //   28: aload_0
    //   29: aconst_null
    //   30: putfield 2018	com/google/android/gms/internal/zzcim:zzjfx	Ljava/util/List;
    //   33: iload_1
    //   34: sipush 200
    //   37: if_icmpeq +10 -> 47
    //   40: iload_1
    //   41: sipush 204
    //   44: if_icmpne +316 -> 360
    //   47: aload_2
    //   48: ifnonnull +312 -> 360
    //   51: aload_0
    //   52: invokevirtual 881	com/google/android/gms/internal/zzcim:zzawz	()Lcom/google/android/gms/internal/zzchx;
    //   55: getfield 977	com/google/android/gms/internal/zzchx:zzjcr	Lcom/google/android/gms/internal/zzcia;
    //   58: aload_0
    //   59: getfield 112	com/google/android/gms/internal/zzcim:zzata	Lcom/google/android/gms/common/util/zzd;
    //   62: invokeinterface 118 1 0
    //   67: invokevirtual 905	com/google/android/gms/internal/zzcia:set	(J)V
    //   70: aload_0
    //   71: invokevirtual 881	com/google/android/gms/internal/zzcim:zzawz	()Lcom/google/android/gms/internal/zzchx;
    //   74: getfield 980	com/google/android/gms/internal/zzchx:zzjcs	Lcom/google/android/gms/internal/zzcia;
    //   77: lconst_0
    //   78: invokevirtual 905	com/google/android/gms/internal/zzcia:set	(J)V
    //   81: aload_0
    //   82: invokespecial 1513	com/google/android/gms/internal/zzcim:zzbaj	()V
    //   85: aload_0
    //   86: invokevirtual 294	com/google/android/gms/internal/zzcim:zzawy	()Lcom/google/android/gms/internal/zzchm;
    //   89: invokevirtual 278	com/google/android/gms/internal/zzchm:zzazj	()Lcom/google/android/gms/internal/zzcho;
    //   92: ldc_w 2020
    //   95: iload_1
    //   96: invokestatic 343	java/lang/Integer:valueOf	(I)Ljava/lang/Integer;
    //   99: aload 6
    //   101: arraylength
    //   102: invokestatic 343	java/lang/Integer:valueOf	(I)Ljava/lang/Integer;
    //   105: invokevirtual 453	com/google/android/gms/internal/zzcho:zze	(Ljava/lang/String;Ljava/lang/Object;Ljava/lang/Object;)V
    //   108: aload_0
    //   109: invokevirtual 602	com/google/android/gms/internal/zzcim:zzaws	()Lcom/google/android/gms/internal/zzcgo;
    //   112: invokevirtual 1144	com/google/android/gms/internal/zzcgo:beginTransaction	()V
    //   115: aload_3
    //   116: invokeinterface 1061 1 0
    //   121: astore_3
    //   122: aload_3
    //   123: invokeinterface 1066 1 0
    //   128: ifeq +163 -> 291
    //   131: aload_3
    //   132: invokeinterface 1069 1 0
    //   137: checkcast 492	java/lang/Long
    //   140: astore 6
    //   142: aload_0
    //   143: invokevirtual 602	com/google/android/gms/internal/zzcim:zzaws	()Lcom/google/android/gms/internal/zzcgo;
    //   146: astore_2
    //   147: aload 6
    //   149: invokevirtual 561	java/lang/Long:longValue	()J
    //   152: lstore 4
    //   154: aload_2
    //   155: invokevirtual 310	com/google/android/gms/internal/zzcjk:zzve	()V
    //   158: aload_2
    //   159: invokevirtual 628	com/google/android/gms/internal/zzcjl:zzxf	()V
    //   162: aload_2
    //   163: invokevirtual 632	com/google/android/gms/internal/zzcgo:getWritableDatabase	()Landroid/database/sqlite/SQLiteDatabase;
    //   166: astore 6
    //   168: aload 6
    //   170: ldc_w 2022
    //   173: ldc_w 2024
    //   176: iconst_1
    //   177: anewarray 443	java/lang/String
    //   180: dup
    //   181: iconst_0
    //   182: lload 4
    //   184: invokestatic 1585	java/lang/String:valueOf	(J)Ljava/lang/String;
    //   187: aastore
    //   188: invokevirtual 2028	android/database/sqlite/SQLiteDatabase:delete	(Ljava/lang/String;Ljava/lang/String;[Ljava/lang/String;)I
    //   191: iconst_1
    //   192: if_icmpeq -70 -> 122
    //   195: new 526	android/database/sqlite/SQLiteException
    //   198: dup
    //   199: ldc_w 2030
    //   202: invokespecial 2031	android/database/sqlite/SQLiteException:<init>	(Ljava/lang/String;)V
    //   205: athrow
    //   206: astore_3
    //   207: aload_2
    //   208: invokevirtual 274	com/google/android/gms/internal/zzcjk:zzawy	()Lcom/google/android/gms/internal/zzchm;
    //   211: invokevirtual 319	com/google/android/gms/internal/zzchm:zzazd	()Lcom/google/android/gms/internal/zzcho;
    //   214: ldc_w 2033
    //   217: aload_3
    //   218: invokevirtual 347	com/google/android/gms/internal/zzcho:zzj	(Ljava/lang/String;Ljava/lang/Object;)V
    //   221: aload_3
    //   222: athrow
    //   223: astore_2
    //   224: aload_0
    //   225: invokevirtual 602	com/google/android/gms/internal/zzcim:zzaws	()Lcom/google/android/gms/internal/zzcgo;
    //   228: invokevirtual 1154	com/google/android/gms/internal/zzcgo:endTransaction	()V
    //   231: aload_2
    //   232: athrow
    //   233: astore_2
    //   234: aload_0
    //   235: invokevirtual 294	com/google/android/gms/internal/zzcim:zzawy	()Lcom/google/android/gms/internal/zzchm;
    //   238: invokevirtual 319	com/google/android/gms/internal/zzchm:zzazd	()Lcom/google/android/gms/internal/zzcho;
    //   241: ldc_w 2035
    //   244: aload_2
    //   245: invokevirtual 347	com/google/android/gms/internal/zzcho:zzj	(Ljava/lang/String;Ljava/lang/Object;)V
    //   248: aload_0
    //   249: aload_0
    //   250: getfield 112	com/google/android/gms/internal/zzcim:zzata	Lcom/google/android/gms/common/util/zzd;
    //   253: invokeinterface 930 1 0
    //   258: putfield 925	com/google/android/gms/internal/zzcim:zzjgc	J
    //   261: aload_0
    //   262: invokevirtual 294	com/google/android/gms/internal/zzcim:zzawy	()Lcom/google/android/gms/internal/zzchm;
    //   265: invokevirtual 278	com/google/android/gms/internal/zzchm:zzazj	()Lcom/google/android/gms/internal/zzcho;
    //   268: ldc_w 2037
    //   271: aload_0
    //   272: getfield 925	com/google/android/gms/internal/zzcim:zzjgc	J
    //   275: invokestatic 495	java/lang/Long:valueOf	(J)Ljava/lang/Long;
    //   278: invokevirtual 347	com/google/android/gms/internal/zzcho:zzj	(Ljava/lang/String;Ljava/lang/Object;)V
    //   281: aload_0
    //   282: iconst_0
    //   283: putfield 1042	com/google/android/gms/internal/zzcim:zzjge	Z
    //   286: aload_0
    //   287: invokespecial 2039	com/google/android/gms/internal/zzcim:zzban	()V
    //   290: return
    //   291: aload_0
    //   292: invokevirtual 602	com/google/android/gms/internal/zzcim:zzaws	()Lcom/google/android/gms/internal/zzcgo;
    //   295: invokevirtual 1151	com/google/android/gms/internal/zzcgo:setTransactionSuccessful	()V
    //   298: aload_0
    //   299: invokevirtual 602	com/google/android/gms/internal/zzcim:zzaws	()Lcom/google/android/gms/internal/zzcgo;
    //   302: invokevirtual 1154	com/google/android/gms/internal/zzcgo:endTransaction	()V
    //   305: aload_0
    //   306: invokevirtual 815	com/google/android/gms/internal/zzcim:zzbab	()Lcom/google/android/gms/internal/zzchq;
    //   309: invokevirtual 1018	com/google/android/gms/internal/zzchq:zzzs	()Z
    //   312: ifeq +34 -> 346
    //   315: aload_0
    //   316: invokespecial 951	com/google/android/gms/internal/zzcim:zzbai	()Z
    //   319: ifeq +27 -> 346
    //   322: aload_0
    //   323: invokevirtual 2042	com/google/android/gms/internal/zzcim:zzbah	()V
    //   326: aload_0
    //   327: lconst_0
    //   328: putfield 925	com/google/android/gms/internal/zzcim:zzjgc	J
    //   331: goto -50 -> 281
    //   334: astore_2
    //   335: aload_0
    //   336: iconst_0
    //   337: putfield 1042	com/google/android/gms/internal/zzcim:zzjge	Z
    //   340: aload_0
    //   341: invokespecial 2039	com/google/android/gms/internal/zzcim:zzban	()V
    //   344: aload_2
    //   345: athrow
    //   346: aload_0
    //   347: ldc2_w 101
    //   350: putfield 104	com/google/android/gms/internal/zzcim:zzjgb	J
    //   353: aload_0
    //   354: invokespecial 1513	com/google/android/gms/internal/zzcim:zzbaj	()V
    //   357: goto -31 -> 326
    //   360: aload_0
    //   361: invokevirtual 294	com/google/android/gms/internal/zzcim:zzawy	()Lcom/google/android/gms/internal/zzchm;
    //   364: invokevirtual 278	com/google/android/gms/internal/zzchm:zzazj	()Lcom/google/android/gms/internal/zzcho;
    //   367: ldc_w 2044
    //   370: iload_1
    //   371: invokestatic 343	java/lang/Integer:valueOf	(I)Ljava/lang/Integer;
    //   374: aload_2
    //   375: invokevirtual 453	com/google/android/gms/internal/zzcho:zze	(Ljava/lang/String;Ljava/lang/Object;Ljava/lang/Object;)V
    //   378: aload_0
    //   379: invokevirtual 881	com/google/android/gms/internal/zzcim:zzawz	()Lcom/google/android/gms/internal/zzchx;
    //   382: getfield 980	com/google/android/gms/internal/zzchx:zzjcs	Lcom/google/android/gms/internal/zzcia;
    //   385: aload_0
    //   386: getfield 112	com/google/android/gms/internal/zzcim:zzata	Lcom/google/android/gms/common/util/zzd;
    //   389: invokeinterface 118 1 0
    //   394: invokevirtual 905	com/google/android/gms/internal/zzcia:set	(J)V
    //   397: iload_1
    //   398: sipush 503
    //   401: if_icmpeq +48 -> 449
    //   404: iload_1
    //   405: sipush 429
    //   408: if_icmpne +36 -> 444
    //   411: goto +38 -> 449
    //   414: iload_1
    //   415: ifeq +22 -> 437
    //   418: aload_0
    //   419: invokevirtual 881	com/google/android/gms/internal/zzcim:zzawz	()Lcom/google/android/gms/internal/zzchx;
    //   422: getfield 1026	com/google/android/gms/internal/zzchx:zzjct	Lcom/google/android/gms/internal/zzcia;
    //   425: aload_0
    //   426: getfield 112	com/google/android/gms/internal/zzcim:zzata	Lcom/google/android/gms/common/util/zzd;
    //   429: invokeinterface 118 1 0
    //   434: invokevirtual 905	com/google/android/gms/internal/zzcia:set	(J)V
    //   437: aload_0
    //   438: invokespecial 1513	com/google/android/gms/internal/zzcim:zzbaj	()V
    //   441: goto -160 -> 281
    //   444: iconst_0
    //   445: istore_1
    //   446: goto -32 -> 414
    //   449: iconst_1
    //   450: istore_1
    //   451: goto -37 -> 414
    // Local variable table:
    //   start	length	slot	name	signature
    //   0	454	0	this	zzcim
    //   0	454	1	paramInt	int
    //   0	454	2	paramThrowable	Throwable
    //   0	454	3	paramArrayOfByte	byte[]
    //   152	31	4	l	long
    //   12	157	6	localObject	Object
    // Exception table:
    //   from	to	target	type
    //   168	206	206	android/database/sqlite/SQLiteException
    //   115	122	223	finally
    //   122	168	223	finally
    //   168	206	223	finally
    //   207	223	223	finally
    //   291	298	223	finally
    //   51	115	233	android/database/sqlite/SQLiteException
    //   224	233	233	android/database/sqlite/SQLiteException
    //   298	326	233	android/database/sqlite/SQLiteException
    //   326	331	233	android/database/sqlite/SQLiteException
    //   346	357	233	android/database/sqlite/SQLiteException
    //   18	23	334	finally
    //   23	33	334	finally
    //   51	115	334	finally
    //   224	233	334	finally
    //   234	281	334	finally
    //   298	326	334	finally
    //   326	331	334	finally
    //   346	357	334	finally
    //   360	397	334	finally
    //   418	437	334	finally
    //   437	441	334	finally
  }
  
  public final byte[] zza(zzcha paramzzcha, String paramString)
  {
    zzxf();
    zzawx().zzve();
    zzawi();
    zzbq.checkNotNull(paramzzcha);
    zzbq.zzgm(paramString);
    zzcmd localzzcmd = new zzcmd();
    zzaws().beginTransaction();
    zzcgh localzzcgh;
    zzcme localzzcme;
    Object localObject1;
    try
    {
      localzzcgh = zzaws().zzjb(paramString);
      if (localzzcgh == null)
      {
        zzawy().zzazi().zzj("Log and bundle not available. package_name", paramString);
        return new byte[0];
      }
      if (!localzzcgh.zzaxk())
      {
        zzawy().zzazi().zzj("Log and bundle disabled. package_name", paramString);
        return new byte[0];
      }
      if ((("_iap".equals(paramzzcha.name)) || ("ecommerce_purchase".equals(paramzzcha.name))) && (!zza(paramString, paramzzcha))) {
        zzawy().zzazf().zzj("Failed to handle purchase event at single event bundle creation. appId", zzchm.zzjk(paramString));
      }
      localzzcme = new zzcme();
      localzzcmd.zzjlm = new zzcme[] { localzzcme };
      localzzcme.zzjlo = Integer.valueOf(1);
      localzzcme.zzjlw = "android";
      localzzcme.zzcn = localzzcgh.getAppId();
      localzzcme.zzixt = localzzcgh.zzaxh();
      localzzcme.zzifm = localzzcgh.zzvj();
      l1 = localzzcgh.zzaxg();
      if (l1 == -2147483648L) {}
      int i;
      for (localObject1 = null;; localObject1 = Integer.valueOf((int)l1))
      {
        localzzcme.zzjmj = ((Integer)localObject1);
        localzzcme.zzjma = Long.valueOf(localzzcgh.zzaxi());
        localzzcme.zzixs = localzzcgh.getGmpAppId();
        localzzcme.zzjmf = Long.valueOf(localzzcgh.zzaxj());
        if ((isEnabled()) && (zzcgn.zzaye()) && (this.zzjew.zziz(localzzcme.zzcn)))
        {
          zzawn();
          localzzcme.zzjmo = null;
        }
        localObject1 = zzawz().zzjm(localzzcgh.getAppId());
        if ((localzzcgh.zzaxy()) && (localObject1 != null) && (!TextUtils.isEmpty((CharSequence)((Pair)localObject1).first)))
        {
          localzzcme.zzjmc = ((String)((Pair)localObject1).first);
          localzzcme.zzjmd = ((Boolean)((Pair)localObject1).second);
        }
        zzawo().zzxf();
        localzzcme.zzjlx = Build.MODEL;
        zzawo().zzxf();
        localzzcme.zzdb = Build.VERSION.RELEASE;
        localzzcme.zzjlz = Integer.valueOf((int)zzawo().zzayu());
        localzzcme.zzjly = zzawo().zzayv();
        localzzcme.zzjme = localzzcgh.getAppInstanceId();
        localzzcme.zziya = localzzcgh.zzaxd();
        localObject1 = zzaws().zzja(localzzcgh.getAppId());
        localzzcme.zzjlq = new zzcmg[((List)localObject1).size()];
        i = 0;
        while (i < ((List)localObject1).size())
        {
          localObject2 = new zzcmg();
          localzzcme.zzjlq[i] = localObject2;
          ((zzcmg)localObject2).name = ((zzclp)((List)localObject1).get(i)).mName;
          ((zzcmg)localObject2).zzjms = Long.valueOf(((zzclp)((List)localObject1).get(i)).zzjjm);
          zzawu().zza((zzcmg)localObject2, ((zzclp)((List)localObject1).get(i)).mValue);
          i += 1;
        }
      }
      localObject1 = paramzzcha.zzizt.zzayx();
      if ("_iap".equals(paramzzcha.name))
      {
        ((Bundle)localObject1).putLong("_c", 1L);
        zzawy().zzazi().log("Marking in-app purchase as real-time");
        ((Bundle)localObject1).putLong("_r", 1L);
      }
      ((Bundle)localObject1).putString("_o", paramzzcha.zziyf);
      if (zzawu().zzkj(localzzcme.zzcn))
      {
        zzawu().zza((Bundle)localObject1, "_dbg", Long.valueOf(1L));
        zzawu().zza((Bundle)localObject1, "_r", Long.valueOf(1L));
      }
      Object localObject2 = zzaws().zzae(paramString, paramzzcha.name);
      if (localObject2 == null)
      {
        localObject2 = new zzcgw(paramString, paramzzcha.name, 1L, 0L, paramzzcha.zzizu, 0L, null, null, null);
        zzaws().zza((zzcgw)localObject2);
        l1 = 0L;
      }
      for (;;)
      {
        paramzzcha = new zzcgv(this, paramzzcha.zziyf, paramString, paramzzcha.name, paramzzcha.zzizu, l1, (Bundle)localObject1);
        localObject1 = new zzcmb();
        localzzcme.zzjlp = new zzcmb[] { localObject1 };
        ((zzcmb)localObject1).zzjli = Long.valueOf(paramzzcha.zzfij);
        ((zzcmb)localObject1).name = paramzzcha.mName;
        ((zzcmb)localObject1).zzjlj = Long.valueOf(paramzzcha.zzizi);
        ((zzcmb)localObject1).zzjlh = new zzcmc[paramzzcha.zzizj.size()];
        localObject2 = paramzzcha.zzizj.iterator();
        i = 0;
        while (((Iterator)localObject2).hasNext())
        {
          Object localObject3 = (String)((Iterator)localObject2).next();
          zzcmc localzzcmc = new zzcmc();
          ((zzcmb)localObject1).zzjlh[i] = localzzcmc;
          localzzcmc.name = ((String)localObject3);
          localObject3 = paramzzcha.zzizj.get((String)localObject3);
          zzawu().zza(localzzcmc, localObject3);
          i += 1;
        }
        l1 = ((zzcgw)localObject2).zzizm;
        localObject2 = ((zzcgw)localObject2).zzbb(paramzzcha.zzizu).zzayw();
        zzaws().zza((zzcgw)localObject2);
      }
      localzzcme.zzjmi = zza(localzzcgh.getAppId(), localzzcme.zzjlq, localzzcme.zzjlp);
    }
    finally
    {
      zzaws().endTransaction();
    }
    localzzcme.zzjls = ((zzcmb)localObject1).zzjli;
    localzzcme.zzjlt = ((zzcmb)localObject1).zzjli;
    long l1 = localzzcgh.zzaxf();
    long l2;
    if (l1 != 0L)
    {
      paramzzcha = Long.valueOf(l1);
      localzzcme.zzjlv = paramzzcha;
      l2 = localzzcgh.zzaxe();
      if (l2 != 0L) {
        break label1295;
      }
    }
    for (;;)
    {
      if (l1 != 0L) {}
      for (paramzzcha = Long.valueOf(l1);; paramzzcha = null)
      {
        localzzcme.zzjlu = paramzzcha;
        localzzcgh.zzaxo();
        localzzcme.zzjmg = Integer.valueOf((int)localzzcgh.zzaxl());
        localzzcme.zzjmb = Long.valueOf(11910L);
        localzzcme.zzjlr = Long.valueOf(this.zzata.currentTimeMillis());
        localzzcme.zzjmh = Boolean.TRUE;
        localzzcgh.zzal(localzzcme.zzjls.longValue());
        localzzcgh.zzam(localzzcme.zzjlt.longValue());
        zzaws().zza(localzzcgh);
        zzaws().setTransactionSuccessful();
        zzaws().endTransaction();
        try
        {
          paramzzcha = new byte[localzzcmd.zzho()];
          localObject1 = zzfjk.zzo(paramzzcha, 0, paramzzcha.length);
          localzzcmd.zza((zzfjk)localObject1);
          ((zzfjk)localObject1).zzcwt();
          paramzzcha = zzawu().zzq(paramzzcha);
          return paramzzcha;
        }
        catch (IOException paramzzcha)
        {
          zzawy().zzazd().zze("Data loss. Failed to bundle and serialize. appId", zzchm.zzjk(paramString), paramzzcha);
          return null;
        }
        paramzzcha = null;
        break;
      }
      label1295:
      l1 = l2;
    }
  }
  
  public final zzcgd zzawk()
  {
    zza(this.zzjfr);
    return this.zzjfr;
  }
  
  public final zzcgk zzawl()
  {
    zza(this.zzjfq);
    return this.zzjfq;
  }
  
  public final zzcjn zzawm()
  {
    zza(this.zzjfm);
    return this.zzjfm;
  }
  
  public final zzchh zzawn()
  {
    zza(this.zzjfn);
    return this.zzjfn;
  }
  
  public final zzcgu zzawo()
  {
    zza(this.zzjfl);
    return this.zzjfl;
  }
  
  public final zzckg zzawp()
  {
    zza(this.zzjfk);
    return this.zzjfk;
  }
  
  public final zzckc zzawq()
  {
    zza(this.zzjfj);
    return this.zzjfj;
  }
  
  public final zzchi zzawr()
  {
    zza(this.zzjfh);
    return this.zzjfh;
  }
  
  public final zzcgo zzaws()
  {
    zza(this.zzjfg);
    return this.zzjfg;
  }
  
  public final zzchk zzawt()
  {
    zza(this.zzjff);
    return this.zzjff;
  }
  
  public final zzclq zzawu()
  {
    zza(this.zzjfe);
    return this.zzjfe;
  }
  
  public final zzcig zzawv()
  {
    zza(this.zzjfb);
    return this.zzjfb;
  }
  
  public final zzclf zzaww()
  {
    zza(this.zzjfa);
    return this.zzjfa;
  }
  
  public final zzcih zzawx()
  {
    zza(this.zzjez);
    return this.zzjez;
  }
  
  public final zzchm zzawy()
  {
    zza(this.zzjey);
    return this.zzjey;
  }
  
  public final zzchx zzawz()
  {
    zza(this.zzjex);
    return this.zzjex;
  }
  
  public final zzcgn zzaxa()
  {
    return this.zzjew;
  }
  
  protected final boolean zzazv()
  {
    boolean bool2 = false;
    zzxf();
    zzawx().zzve();
    if ((this.zzjft == null) || (this.zzjfu == 0L) || ((this.zzjft != null) && (!this.zzjft.booleanValue()) && (Math.abs(this.zzata.elapsedRealtime() - this.zzjfu) > 1000L)))
    {
      this.zzjfu = this.zzata.elapsedRealtime();
      boolean bool1 = bool2;
      if (zzawu().zzeb("android.permission.INTERNET"))
      {
        bool1 = bool2;
        if (zzawu().zzeb("android.permission.ACCESS_NETWORK_STATE")) {
          if (!zzbhf.zzdb(this.mContext).zzamu())
          {
            bool1 = bool2;
            if (zzcid.zzbk(this.mContext))
            {
              bool1 = bool2;
              if (!zzcla.zzk(this.mContext, false)) {}
            }
          }
          else
          {
            bool1 = true;
          }
        }
      }
      this.zzjft = Boolean.valueOf(bool1);
      if (this.zzjft.booleanValue()) {
        this.zzjft = Boolean.valueOf(zzawu().zzkg(zzawn().getGmpAppId()));
      }
    }
    return this.zzjft.booleanValue();
  }
  
  public final zzchm zzazx()
  {
    if ((this.zzjey != null) && (this.zzjey.isInitialized())) {
      return this.zzjey;
    }
    return null;
  }
  
  final zzcih zzazy()
  {
    return this.zzjez;
  }
  
  public final AppMeasurement zzazz()
  {
    return this.zzjfc;
  }
  
  final void zzb(zzcgl paramzzcgl, zzcgi paramzzcgi)
  {
    int i = 1;
    zzbq.checkNotNull(paramzzcgl);
    zzbq.zzgm(paramzzcgl.packageName);
    zzbq.checkNotNull(paramzzcgl.zziyf);
    zzbq.checkNotNull(paramzzcgl.zziyg);
    zzbq.zzgm(paramzzcgl.zziyg.name);
    zzawx().zzve();
    zzxf();
    if (TextUtils.isEmpty(paramzzcgi.zzixs)) {
      return;
    }
    if (!paramzzcgi.zzixx)
    {
      zzg(paramzzcgi);
      return;
    }
    paramzzcgl = new zzcgl(paramzzcgl);
    paramzzcgl.zziyi = false;
    zzaws().beginTransaction();
    for (;;)
    {
      try
      {
        Object localObject = zzaws().zzah(paramzzcgl.packageName, paramzzcgl.zziyg.name);
        if ((localObject != null) && (!((zzcgl)localObject).zziyf.equals(paramzzcgl.zziyf))) {
          zzawy().zzazf().zzd("Updating a conditional user property with different origin. name, origin, origin (from DB)", zzawt().zzjj(paramzzcgl.zziyg.name), paramzzcgl.zziyf, ((zzcgl)localObject).zziyf);
        }
        if ((localObject != null) && (((zzcgl)localObject).zziyi))
        {
          paramzzcgl.zziyf = ((zzcgl)localObject).zziyf;
          paramzzcgl.zziyh = ((zzcgl)localObject).zziyh;
          paramzzcgl.zziyl = ((zzcgl)localObject).zziyl;
          paramzzcgl.zziyj = ((zzcgl)localObject).zziyj;
          paramzzcgl.zziym = ((zzcgl)localObject).zziym;
          paramzzcgl.zziyi = ((zzcgl)localObject).zziyi;
          paramzzcgl.zziyg = new zzcln(paramzzcgl.zziyg.name, ((zzcgl)localObject).zziyg.zzjji, paramzzcgl.zziyg.getValue(), ((zzcgl)localObject).zziyg.zziyf);
          i = 0;
          if (paramzzcgl.zziyi)
          {
            localObject = paramzzcgl.zziyg;
            localObject = new zzclp(paramzzcgl.packageName, paramzzcgl.zziyf, ((zzcln)localObject).name, ((zzcln)localObject).zzjji, ((zzcln)localObject).getValue());
            if (!zzaws().zza((zzclp)localObject)) {
              break label534;
            }
            zzawy().zzazi().zzd("User property updated immediately", paramzzcgl.packageName, zzawt().zzjj(((zzclp)localObject).mName), ((zzclp)localObject).mValue);
            if ((i != 0) && (paramzzcgl.zziym != null)) {
              zzc(new zzcha(paramzzcgl.zziym, paramzzcgl.zziyh), paramzzcgi);
            }
          }
          if (!zzaws().zza(paramzzcgl)) {
            break label574;
          }
          zzawy().zzazi().zzd("Conditional property added", paramzzcgl.packageName, zzawt().zzjj(paramzzcgl.zziyg.name), paramzzcgl.zziyg.getValue());
          zzaws().setTransactionSuccessful();
        }
        else
        {
          if (!TextUtils.isEmpty(paramzzcgl.zziyj)) {
            break label618;
          }
          paramzzcgl.zziyg = new zzcln(paramzzcgl.zziyg.name, paramzzcgl.zziyh, paramzzcgl.zziyg.getValue(), paramzzcgl.zziyg.zziyf);
          paramzzcgl.zziyi = true;
          continue;
        }
        zzawy().zzazd().zzd("(2)Too many active user properties, ignoring", zzchm.zzjk(paramzzcgl.packageName), zzawt().zzjj(((zzclp)localObject).mName), ((zzclp)localObject).mValue);
      }
      finally
      {
        zzaws().endTransaction();
      }
      label534:
      continue;
      label574:
      zzawy().zzazd().zzd("Too many conditional properties, ignoring", zzchm.zzjk(paramzzcgl.packageName), zzawt().zzjj(paramzzcgl.zziyg.name), paramzzcgl.zziyg.getValue());
      continue;
      label618:
      i = 0;
    }
  }
  
  final void zzb(zzcha paramzzcha, zzcgi paramzzcgi)
  {
    zzbq.checkNotNull(paramzzcgi);
    zzbq.zzgm(paramzzcgi.packageName);
    zzawx().zzve();
    zzxf();
    Object localObject2 = paramzzcgi.packageName;
    long l = paramzzcha.zzizu;
    zzawu();
    if (!zzclq.zzd(paramzzcha, paramzzcgi)) {
      return;
    }
    if (!paramzzcgi.zzixx)
    {
      zzg(paramzzcgi);
      return;
    }
    zzaws().beginTransaction();
    for (;;)
    {
      try
      {
        localObject1 = zzaws();
        zzbq.zzgm((String)localObject2);
        ((zzcjk)localObject1).zzve();
        ((zzcjl)localObject1).zzxf();
        if (l < 0L)
        {
          ((zzcjk)localObject1).zzawy().zzazf().zze("Invalid time querying timed out conditional properties", zzchm.zzjk((String)localObject2), Long.valueOf(l));
          localObject1 = Collections.emptyList();
          localObject1 = ((List)localObject1).iterator();
          if (!((Iterator)localObject1).hasNext()) {
            break;
          }
          localObject3 = (zzcgl)((Iterator)localObject1).next();
          if (localObject3 == null) {
            continue;
          }
          zzawy().zzazi().zzd("User property timed out", ((zzcgl)localObject3).packageName, zzawt().zzjj(((zzcgl)localObject3).zziyg.name), ((zzcgl)localObject3).zziyg.getValue());
          if (((zzcgl)localObject3).zziyk != null) {
            zzc(new zzcha(((zzcgl)localObject3).zziyk, l), paramzzcgi);
          }
          zzaws().zzai((String)localObject2, ((zzcgl)localObject3).zziyg.name);
          continue;
        }
      }
      finally
      {
        zzaws().endTransaction();
      }
      tmp272_269[0] = localObject2;
      String[] tmp277_272 = tmp272_269;
      tmp277_272[1] = String.valueOf(l);
      localObject1 = ((zzcgo)localObject1).zzc("active=0 and app_id=? and abs(? - creation_timestamp) > trigger_timeout", tmp277_272);
    }
    Object localObject1 = zzaws();
    zzbq.zzgm((String)localObject2);
    ((zzcjk)localObject1).zzve();
    ((zzcjl)localObject1).zzxf();
    if (l < 0L) {
      ((zzcjk)localObject1).zzawy().zzazf().zze("Invalid time querying expired conditional properties", zzchm.zzjk((String)localObject2), Long.valueOf(l));
    }
    Object localObject4;
    for (localObject1 = Collections.emptyList();; localObject1 = ((zzcgo)localObject1).zzc("active<>0 and app_id=? and abs(? - triggered_timestamp) > time_to_live", new String[] { localObject2, String.valueOf(l) }))
    {
      localObject3 = new ArrayList(((List)localObject1).size());
      localObject1 = ((List)localObject1).iterator();
      while (((Iterator)localObject1).hasNext())
      {
        localObject4 = (zzcgl)((Iterator)localObject1).next();
        if (localObject4 != null)
        {
          zzawy().zzazi().zzd("User property expired", ((zzcgl)localObject4).packageName, zzawt().zzjj(((zzcgl)localObject4).zziyg.name), ((zzcgl)localObject4).zziyg.getValue());
          zzaws().zzaf((String)localObject2, ((zzcgl)localObject4).zziyg.name);
          if (((zzcgl)localObject4).zziyo != null) {
            ((List)localObject3).add(((zzcgl)localObject4).zziyo);
          }
          zzaws().zzai((String)localObject2, ((zzcgl)localObject4).zziyg.name);
        }
      }
    }
    localObject1 = (ArrayList)localObject3;
    int j = ((ArrayList)localObject1).size();
    int i = 0;
    while (i < j)
    {
      localObject3 = ((ArrayList)localObject1).get(i);
      i += 1;
      zzc(new zzcha((zzcha)localObject3, l), paramzzcgi);
    }
    localObject1 = zzaws();
    Object localObject3 = paramzzcha.name;
    zzbq.zzgm((String)localObject2);
    zzbq.zzgm((String)localObject3);
    ((zzcjk)localObject1).zzve();
    ((zzcjl)localObject1).zzxf();
    if (l < 0L)
    {
      ((zzcjk)localObject1).zzawy().zzazf().zzd("Invalid time querying triggered conditional properties", zzchm.zzjk((String)localObject2), ((zzcjk)localObject1).zzawt().zzjh((String)localObject3), Long.valueOf(l));
      localObject1 = Collections.emptyList();
      localObject2 = new ArrayList(((List)localObject1).size());
      localObject1 = ((List)localObject1).iterator();
      label694:
      do
      {
        if (!((Iterator)localObject1).hasNext()) {
          break;
        }
        localObject3 = (zzcgl)((Iterator)localObject1).next();
      } while (localObject3 == null);
      localObject4 = ((zzcgl)localObject3).zziyg;
      localObject4 = new zzclp(((zzcgl)localObject3).packageName, ((zzcgl)localObject3).zziyf, ((zzcln)localObject4).name, l, ((zzcln)localObject4).getValue());
      if (!zzaws().zza((zzclp)localObject4)) {
        break label895;
      }
      zzawy().zzazi().zzd("User property triggered", ((zzcgl)localObject3).packageName, zzawt().zzjj(((zzclp)localObject4).mName), ((zzclp)localObject4).mValue);
    }
    for (;;)
    {
      if (((zzcgl)localObject3).zziym != null) {
        ((List)localObject2).add(((zzcgl)localObject3).zziym);
      }
      ((zzcgl)localObject3).zziyg = new zzcln((zzclp)localObject4);
      ((zzcgl)localObject3).zziyi = true;
      zzaws().zza((zzcgl)localObject3);
      break label694;
      localObject1 = ((zzcgo)localObject1).zzc("active=0 and app_id=? and trigger_event_name=? and abs(? - creation_timestamp) <= trigger_timeout", new String[] { localObject2, localObject3, String.valueOf(l) });
      break;
      label895:
      zzawy().zzazd().zzd("Too many active user properties, ignoring", zzchm.zzjk(((zzcgl)localObject3).packageName), zzawt().zzjj(((zzclp)localObject4).mName), ((zzclp)localObject4).mValue);
    }
    zzc(paramzzcha, paramzzcgi);
    paramzzcha = (ArrayList)localObject2;
    j = paramzzcha.size();
    i = 0;
    while (i < j)
    {
      localObject1 = paramzzcha.get(i);
      i += 1;
      zzc(new zzcha((zzcha)localObject1, l), paramzzcgi);
    }
    zzaws().setTransactionSuccessful();
    zzaws().endTransaction();
  }
  
  final void zzb(zzcha paramzzcha, String paramString)
  {
    zzcgh localzzcgh = zzaws().zzjb(paramString);
    if ((localzzcgh == null) || (TextUtils.isEmpty(localzzcgh.zzvj())))
    {
      zzawy().zzazi().zzj("No app data available; dropping event", paramString);
      return;
    }
    try
    {
      String str = zzbhf.zzdb(this.mContext).getPackageInfo(paramString, 0).versionName;
      if ((localzzcgh.zzvj() != null) && (!localzzcgh.zzvj().equals(str)))
      {
        zzawy().zzazf().zzj("App version does not match; dropping event. appId", zzchm.zzjk(paramString));
        return;
      }
    }
    catch (PackageManager.NameNotFoundException localNameNotFoundException)
    {
      if (!"_ui".equals(paramzzcha.name)) {
        zzawy().zzazf().zzj("Could not find package. appId", zzchm.zzjk(paramString));
      }
      zzb(paramzzcha, new zzcgi(paramString, localzzcgh.getGmpAppId(), localzzcgh.zzvj(), localzzcgh.zzaxg(), localzzcgh.zzaxh(), localzzcgh.zzaxi(), localzzcgh.zzaxj(), null, localzzcgh.zzaxk(), false, localzzcgh.zzaxd(), localzzcgh.zzaxx(), 0L, 0, localzzcgh.zzaxy()));
    }
  }
  
  final void zzb(zzcjl paramzzcjl)
  {
    this.zzjfz += 1;
  }
  
  /* Error */
  final void zzb(zzcln paramzzcln, zzcgi paramzzcgi)
  {
    // Byte code:
    //   0: iconst_0
    //   1: istore 4
    //   3: iconst_0
    //   4: istore_3
    //   5: aload_0
    //   6: invokevirtual 307	com/google/android/gms/internal/zzcim:zzawx	()Lcom/google/android/gms/internal/zzcih;
    //   9: invokevirtual 310	com/google/android/gms/internal/zzcjk:zzve	()V
    //   12: aload_0
    //   13: invokevirtual 913	com/google/android/gms/internal/zzcim:zzxf	()V
    //   16: aload_2
    //   17: getfield 1282	com/google/android/gms/internal/zzcgi:zzixs	Ljava/lang/String;
    //   20: invokestatic 401	android/text/TextUtils:isEmpty	(Ljava/lang/CharSequence;)Z
    //   23: ifeq +4 -> 27
    //   26: return
    //   27: aload_2
    //   28: getfield 1093	com/google/android/gms/internal/zzcgi:zzixx	Z
    //   31: ifne +9 -> 40
    //   34: aload_0
    //   35: aload_2
    //   36: invokespecial 1096	com/google/android/gms/internal/zzcim:zzg	(Lcom/google/android/gms/internal/zzcgi;)V
    //   39: return
    //   40: aload_0
    //   41: invokevirtual 424	com/google/android/gms/internal/zzcim:zzawu	()Lcom/google/android/gms/internal/zzclq;
    //   44: aload_1
    //   45: getfield 2147	com/google/android/gms/internal/zzcln:name	Ljava/lang/String;
    //   48: invokevirtual 2262	com/google/android/gms/internal/zzclq:zzkd	(Ljava/lang/String;)I
    //   51: istore 5
    //   53: iload 5
    //   55: ifeq +55 -> 110
    //   58: aload_0
    //   59: invokevirtual 424	com/google/android/gms/internal/zzcim:zzawu	()Lcom/google/android/gms/internal/zzclq;
    //   62: pop
    //   63: aload_1
    //   64: getfield 2147	com/google/android/gms/internal/zzcln:name	Ljava/lang/String;
    //   67: bipush 24
    //   69: iconst_1
    //   70: invokestatic 2265	com/google/android/gms/internal/zzclq:zza	(Ljava/lang/String;IZ)Ljava/lang/String;
    //   73: astore 7
    //   75: aload_1
    //   76: getfield 2147	com/google/android/gms/internal/zzcln:name	Ljava/lang/String;
    //   79: ifnull +11 -> 90
    //   82: aload_1
    //   83: getfield 2147	com/google/android/gms/internal/zzcln:name	Ljava/lang/String;
    //   86: invokevirtual 595	java/lang/String:length	()I
    //   89: istore_3
    //   90: aload_0
    //   91: invokevirtual 424	com/google/android/gms/internal/zzcim:zzawu	()Lcom/google/android/gms/internal/zzclq;
    //   94: aload_2
    //   95: getfield 1082	com/google/android/gms/internal/zzcgi:packageName	Ljava/lang/String;
    //   98: iload 5
    //   100: ldc_w 1115
    //   103: aload 7
    //   105: iload_3
    //   106: invokevirtual 671	com/google/android/gms/internal/zzclq:zza	(Ljava/lang/String;ILjava/lang/String;Ljava/lang/String;I)V
    //   109: return
    //   110: aload_0
    //   111: invokevirtual 424	com/google/android/gms/internal/zzcim:zzawu	()Lcom/google/android/gms/internal/zzclq;
    //   114: aload_1
    //   115: getfield 2147	com/google/android/gms/internal/zzcln:name	Ljava/lang/String;
    //   118: aload_1
    //   119: invokevirtual 2175	com/google/android/gms/internal/zzcln:getValue	()Ljava/lang/Object;
    //   122: invokevirtual 2269	com/google/android/gms/internal/zzclq:zzl	(Ljava/lang/String;Ljava/lang/Object;)I
    //   125: istore 5
    //   127: iload 5
    //   129: ifeq +77 -> 206
    //   132: aload_0
    //   133: invokevirtual 424	com/google/android/gms/internal/zzcim:zzawu	()Lcom/google/android/gms/internal/zzclq;
    //   136: pop
    //   137: aload_1
    //   138: getfield 2147	com/google/android/gms/internal/zzcln:name	Ljava/lang/String;
    //   141: bipush 24
    //   143: iconst_1
    //   144: invokestatic 2265	com/google/android/gms/internal/zzclq:zza	(Ljava/lang/String;IZ)Ljava/lang/String;
    //   147: astore 7
    //   149: aload_1
    //   150: invokevirtual 2175	com/google/android/gms/internal/zzcln:getValue	()Ljava/lang/Object;
    //   153: astore_1
    //   154: iload 4
    //   156: istore_3
    //   157: aload_1
    //   158: ifnull +28 -> 186
    //   161: aload_1
    //   162: instanceof 443
    //   165: ifne +13 -> 178
    //   168: iload 4
    //   170: istore_3
    //   171: aload_1
    //   172: instanceof 403
    //   175: ifeq +11 -> 186
    //   178: aload_1
    //   179: invokestatic 592	java/lang/String:valueOf	(Ljava/lang/Object;)Ljava/lang/String;
    //   182: invokevirtual 595	java/lang/String:length	()I
    //   185: istore_3
    //   186: aload_0
    //   187: invokevirtual 424	com/google/android/gms/internal/zzcim:zzawu	()Lcom/google/android/gms/internal/zzclq;
    //   190: aload_2
    //   191: getfield 1082	com/google/android/gms/internal/zzcgi:packageName	Ljava/lang/String;
    //   194: iload 5
    //   196: ldc_w 1115
    //   199: aload 7
    //   201: iload_3
    //   202: invokevirtual 671	com/google/android/gms/internal/zzclq:zza	(Ljava/lang/String;ILjava/lang/String;Ljava/lang/String;I)V
    //   205: return
    //   206: aload_0
    //   207: invokevirtual 424	com/google/android/gms/internal/zzcim:zzawu	()Lcom/google/android/gms/internal/zzclq;
    //   210: aload_1
    //   211: getfield 2147	com/google/android/gms/internal/zzcln:name	Ljava/lang/String;
    //   214: aload_1
    //   215: invokevirtual 2175	com/google/android/gms/internal/zzcln:getValue	()Ljava/lang/Object;
    //   218: invokevirtual 2273	com/google/android/gms/internal/zzclq:zzm	(Ljava/lang/String;Ljava/lang/Object;)Ljava/lang/Object;
    //   221: astore 7
    //   223: aload 7
    //   225: ifnull -199 -> 26
    //   228: new 608	com/google/android/gms/internal/zzclp
    //   231: dup
    //   232: aload_2
    //   233: getfield 1082	com/google/android/gms/internal/zzcgi:packageName	Ljava/lang/String;
    //   236: aload_1
    //   237: getfield 2176	com/google/android/gms/internal/zzcln:zziyf	Ljava/lang/String;
    //   240: aload_1
    //   241: getfield 2147	com/google/android/gms/internal/zzcln:name	Ljava/lang/String;
    //   244: aload_1
    //   245: getfield 2174	com/google/android/gms/internal/zzcln:zzjji	J
    //   248: aload 7
    //   250: invokespecial 649	com/google/android/gms/internal/zzclp:<init>	(Ljava/lang/String;Ljava/lang/String;Ljava/lang/String;JLjava/lang/Object;)V
    //   253: astore_1
    //   254: aload_0
    //   255: invokevirtual 294	com/google/android/gms/internal/zzcim:zzawy	()Lcom/google/android/gms/internal/zzchm;
    //   258: invokevirtual 709	com/google/android/gms/internal/zzchm:zzazi	()Lcom/google/android/gms/internal/zzcho;
    //   261: ldc_w 2275
    //   264: aload_0
    //   265: invokevirtual 658	com/google/android/gms/internal/zzcim:zzawt	()Lcom/google/android/gms/internal/zzchk;
    //   268: aload_1
    //   269: getfield 661	com/google/android/gms/internal/zzclp:mName	Ljava/lang/String;
    //   272: invokevirtual 664	com/google/android/gms/internal/zzchk:zzjj	(Ljava/lang/String;)Ljava/lang/String;
    //   275: aload 7
    //   277: invokevirtual 453	com/google/android/gms/internal/zzcho:zze	(Ljava/lang/String;Ljava/lang/Object;Ljava/lang/Object;)V
    //   280: aload_0
    //   281: invokevirtual 602	com/google/android/gms/internal/zzcim:zzaws	()Lcom/google/android/gms/internal/zzcgo;
    //   284: invokevirtual 1144	com/google/android/gms/internal/zzcgo:beginTransaction	()V
    //   287: aload_0
    //   288: aload_2
    //   289: invokespecial 1096	com/google/android/gms/internal/zzcim:zzg	(Lcom/google/android/gms/internal/zzcgi;)V
    //   292: aload_0
    //   293: invokevirtual 602	com/google/android/gms/internal/zzcim:zzaws	()Lcom/google/android/gms/internal/zzcgo;
    //   296: aload_1
    //   297: invokevirtual 652	com/google/android/gms/internal/zzcgo:zza	(Lcom/google/android/gms/internal/zzclp;)Z
    //   300: istore 6
    //   302: aload_0
    //   303: invokevirtual 602	com/google/android/gms/internal/zzcim:zzaws	()Lcom/google/android/gms/internal/zzcgo;
    //   306: invokevirtual 1151	com/google/android/gms/internal/zzcgo:setTransactionSuccessful	()V
    //   309: iload 6
    //   311: ifeq +39 -> 350
    //   314: aload_0
    //   315: invokevirtual 294	com/google/android/gms/internal/zzcim:zzawy	()Lcom/google/android/gms/internal/zzchm;
    //   318: invokevirtual 709	com/google/android/gms/internal/zzchm:zzazi	()Lcom/google/android/gms/internal/zzcho;
    //   321: ldc_w 2277
    //   324: aload_0
    //   325: invokevirtual 658	com/google/android/gms/internal/zzcim:zzawt	()Lcom/google/android/gms/internal/zzchk;
    //   328: aload_1
    //   329: getfield 661	com/google/android/gms/internal/zzclp:mName	Ljava/lang/String;
    //   332: invokevirtual 664	com/google/android/gms/internal/zzchk:zzjj	(Ljava/lang/String;)Ljava/lang/String;
    //   335: aload_1
    //   336: getfield 612	com/google/android/gms/internal/zzclp:mValue	Ljava/lang/Object;
    //   339: invokevirtual 453	com/google/android/gms/internal/zzcho:zze	(Ljava/lang/String;Ljava/lang/Object;Ljava/lang/Object;)V
    //   342: aload_0
    //   343: invokevirtual 602	com/google/android/gms/internal/zzcim:zzaws	()Lcom/google/android/gms/internal/zzcgo;
    //   346: invokevirtual 1154	com/google/android/gms/internal/zzcgo:endTransaction	()V
    //   349: return
    //   350: aload_0
    //   351: invokevirtual 294	com/google/android/gms/internal/zzcim:zzawy	()Lcom/google/android/gms/internal/zzchm;
    //   354: invokevirtual 319	com/google/android/gms/internal/zzchm:zzazd	()Lcom/google/android/gms/internal/zzcho;
    //   357: ldc_w 2279
    //   360: aload_0
    //   361: invokevirtual 658	com/google/android/gms/internal/zzcim:zzawt	()Lcom/google/android/gms/internal/zzchk;
    //   364: aload_1
    //   365: getfield 661	com/google/android/gms/internal/zzclp:mName	Ljava/lang/String;
    //   368: invokevirtual 664	com/google/android/gms/internal/zzchk:zzjj	(Ljava/lang/String;)Ljava/lang/String;
    //   371: aload_1
    //   372: getfield 612	com/google/android/gms/internal/zzclp:mValue	Ljava/lang/Object;
    //   375: invokevirtual 453	com/google/android/gms/internal/zzcho:zze	(Ljava/lang/String;Ljava/lang/Object;Ljava/lang/Object;)V
    //   378: aload_0
    //   379: invokevirtual 424	com/google/android/gms/internal/zzcim:zzawu	()Lcom/google/android/gms/internal/zzclq;
    //   382: aload_2
    //   383: getfield 1082	com/google/android/gms/internal/zzcgi:packageName	Ljava/lang/String;
    //   386: bipush 9
    //   388: aconst_null
    //   389: aconst_null
    //   390: iconst_0
    //   391: invokevirtual 671	com/google/android/gms/internal/zzclq:zza	(Ljava/lang/String;ILjava/lang/String;Ljava/lang/String;I)V
    //   394: goto -52 -> 342
    //   397: astore_1
    //   398: aload_0
    //   399: invokevirtual 602	com/google/android/gms/internal/zzcim:zzaws	()Lcom/google/android/gms/internal/zzcgo;
    //   402: invokevirtual 1154	com/google/android/gms/internal/zzcgo:endTransaction	()V
    //   405: aload_1
    //   406: athrow
    // Local variable table:
    //   start	length	slot	name	signature
    //   0	407	0	this	zzcim
    //   0	407	1	paramzzcln	zzcln
    //   0	407	2	paramzzcgi	zzcgi
    //   4	198	3	i	int
    //   1	168	4	j	int
    //   51	144	5	k	int
    //   300	10	6	bool	boolean
    //   73	203	7	localObject	Object
    // Exception table:
    //   from	to	target	type
    //   287	309	397	finally
    //   314	342	397	finally
    //   350	394	397	finally
  }
  
  final void zzb(String paramString, int paramInt, Throwable paramThrowable, byte[] paramArrayOfByte, Map<String, List<String>> paramMap)
  {
    int j = 1;
    zzawx().zzve();
    zzxf();
    zzbq.zzgm(paramString);
    byte[] arrayOfByte = paramArrayOfByte;
    if (paramArrayOfByte == null) {}
    for (;;)
    {
      try
      {
        arrayOfByte = new byte[0];
        zzawy().zzazj().zzj("onConfigFetched. Response size", Integer.valueOf(arrayOfByte.length));
        zzaws().beginTransaction();
        try
        {
          paramArrayOfByte = zzaws().zzjb(paramString);
          if ((paramInt == 200) || (paramInt == 204)) {
            break label543;
          }
          if (paramInt == 304)
          {
            break label543;
            if (paramArrayOfByte == null)
            {
              zzawy().zzazf().zzj("App does not exist in onConfigFetched. appId", zzchm.zzjk(paramString));
              zzaws().setTransactionSuccessful();
              zzaws().endTransaction();
            }
          }
          else
          {
            i = 0;
            continue;
          }
          if ((i == 0) && (paramInt != 404)) {
            break label416;
          }
          if (paramMap != null)
          {
            paramThrowable = (List)paramMap.get("Last-Modified");
            if ((paramThrowable != null) && (paramThrowable.size() > 0))
            {
              paramThrowable = (String)paramThrowable.get(0);
              break label553;
              if (zzawv().zzjs(paramString) != null) {
                continue;
              }
              bool = zzawv().zzb(paramString, null, null);
              if (bool) {
                continue;
              }
              zzaws().endTransaction();
            }
          }
          else
          {
            paramThrowable = null;
            continue;
          }
          paramThrowable = null;
          break label553;
          boolean bool = zzawv().zzb(paramString, arrayOfByte, paramThrowable);
          if (!bool)
          {
            zzaws().endTransaction();
            return;
          }
          paramArrayOfByte.zzar(this.zzata.currentTimeMillis());
          zzaws().zza(paramArrayOfByte);
          if (paramInt == 404)
          {
            zzawy().zzazg().zzj("Config not found. Using empty config. appId", paramString);
            if ((!zzbab().zzzs()) || (!zzbai())) {
              break label409;
            }
            zzbah();
            continue;
            paramString = finally;
          }
        }
        finally
        {
          zzaws().endTransaction();
        }
        zzawy().zzazj().zze("Successfully fetched config. Got network response. code, size", Integer.valueOf(paramInt), Integer.valueOf(arrayOfByte.length));
      }
      finally
      {
        this.zzjgd = false;
        zzban();
      }
      continue;
      label409:
      zzbaj();
      continue;
      label416:
      paramArrayOfByte.zzas(this.zzata.currentTimeMillis());
      zzaws().zza(paramArrayOfByte);
      zzawy().zzazj().zze("Fetching config failed. code, error", Integer.valueOf(paramInt), paramThrowable);
      zzawv().zzju(paramString);
      zzawz().zzjcs.set(this.zzata.currentTimeMillis());
      int i = j;
      if (paramInt != 503) {
        if (paramInt != 429) {
          break label537;
        }
      }
      label537:
      for (i = j;; i = 0)
      {
        if (i != 0) {
          zzawz().zzjct.set(this.zzata.currentTimeMillis());
        }
        zzbaj();
        break;
      }
      label543:
      if (paramThrowable == null)
      {
        i = 1;
        continue;
        label553:
        if (paramInt != 404) {
          if (paramInt != 304) {}
        }
      }
    }
  }
  
  public final FirebaseAnalytics zzbaa()
  {
    return this.zzjfd;
  }
  
  public final zzchq zzbab()
  {
    zza(this.zzjfi);
    return this.zzjfi;
  }
  
  final long zzbaf()
  {
    Long localLong = Long.valueOf(zzawz().zzjcw.get());
    if (localLong.longValue() == 0L) {
      return this.zzjgg;
    }
    return Math.min(this.zzjgg, localLong.longValue());
  }
  
  public final void zzbah()
  {
    zzawx().zzve();
    zzxf();
    this.zzjgf = true;
    int i;
    int j;
    for (;;)
    {
      long l1;
      Object localObject4;
      try
      {
        Object localObject1 = zzawp().zzbas();
        if (localObject1 == null)
        {
          zzawy().zzazf().log("Upload data called on the client side before use of service was decided");
          return;
        }
        if (((Boolean)localObject1).booleanValue())
        {
          zzawy().zzazd().log("Upload called in the client side when service should be used");
          return;
        }
        if (this.zzjgc > 0L)
        {
          zzbaj();
          return;
        }
        zzawx().zzve();
        if (this.zzjfx != null)
        {
          i = 1;
          if (i != 0) {
            zzawy().zzazj().log("Uploading requested multiple times");
          }
        }
        else
        {
          i = 0;
          continue;
        }
        if (!zzbab().zzzs())
        {
          zzawy().zzazj().log("Network not connected, ignoring upload request");
          zzbaj();
          return;
        }
        l1 = this.zzata.currentTimeMillis();
        zzg(null, l1 - zzcgn.zzayc());
        long l2 = zzawz().zzjcr.get();
        if (l2 != 0L) {
          zzawy().zzazi().zzj("Uploading events. Elapsed time since last upload attempt (ms)", Long.valueOf(Math.abs(l1 - l2)));
        }
        str = zzaws().zzayf();
        if (TextUtils.isEmpty(str)) {
          break label953;
        }
        if (this.zzjgb == -1L) {
          this.zzjgb = zzaws().zzaym();
        }
        i = this.zzjew.zzb(str, zzchc.zzjaj);
        j = Math.max(0, this.zzjew.zzb(str, zzchc.zzjak));
        localObject4 = zzaws().zzl(str, i, j);
        zzcmd localzzcmd;
        label533:
        byte[] arrayOfByte;
        if (!((List)localObject4).isEmpty())
        {
          localObject1 = ((List)localObject4).iterator();
          if (!((Iterator)localObject1).hasNext()) {
            break label1020;
          }
          localObject5 = (zzcme)((Pair)((Iterator)localObject1).next()).first;
          if (TextUtils.isEmpty(((zzcme)localObject5).zzjmc)) {
            continue;
          }
          localObject1 = ((zzcme)localObject5).zzjmc;
          break label1023;
          if (i >= ((List)localObject4).size()) {
            break label1013;
          }
          localObject5 = (zzcme)((Pair)((List)localObject4).get(i)).first;
          if ((TextUtils.isEmpty(((zzcme)localObject5).zzjmc)) || (((zzcme)localObject5).zzjmc.equals(localObject1))) {
            break label1045;
          }
          localObject1 = ((List)localObject4).subList(0, i);
          localzzcmd = new zzcmd();
          localzzcmd.zzjlm = new zzcme[((List)localObject1).size()];
          localObject4 = new ArrayList(((List)localObject1).size());
          if ((!zzcgn.zzaye()) || (!this.zzjew.zziz(str))) {
            break label1052;
          }
          i = 1;
          break;
          if (j < localzzcmd.zzjlm.length)
          {
            localzzcmd.zzjlm[j] = ((zzcme)((Pair)((List)localObject1).get(j)).first);
            ((List)localObject4).add((Long)((Pair)((List)localObject1).get(j)).second);
            localzzcmd.zzjlm[j].zzjmb = Long.valueOf(11910L);
            localzzcmd.zzjlm[j].zzjlr = Long.valueOf(l1);
            localzzcmd.zzjlm[j].zzjmh = Boolean.valueOf(false);
            if (i != 0) {
              break label1038;
            }
            localzzcmd.zzjlm[j].zzjmo = null;
            break label1038;
          }
          if (!zzawy().zzae(2)) {
            break label1007;
          }
          localObject1 = zzawt().zza(localzzcmd);
          arrayOfByte = zzawu().zzb(localzzcmd);
          localObject5 = (String)zzchc.zzjat.get();
        }
        try
        {
          URL localURL = new URL((String)localObject5);
          if (((List)localObject4).isEmpty()) {
            continue;
          }
          bool = true;
          zzbq.checkArgument(bool);
          if (this.zzjfx == null) {
            continue;
          }
          zzawy().zzazd().log("Set uploading progress before finishing the previous upload");
          zzawz().zzjcs.set(l1);
          localObject4 = "?";
          if (localzzcmd.zzjlm.length > 0) {
            localObject4 = localzzcmd.zzjlm[0].zzcn;
          }
          zzawy().zzazj().zzd("Uploading data. app, uncompressed size, data", localObject4, Integer.valueOf(arrayOfByte.length), localObject1);
          this.zzjge = true;
          localObject1 = zzbab();
          localObject4 = new zzcip(this);
          ((zzcjk)localObject1).zzve();
          ((zzcjl)localObject1).zzxf();
          zzbq.checkNotNull(localURL);
          zzbq.checkNotNull(arrayOfByte);
          zzbq.checkNotNull(localObject4);
          ((zzcjk)localObject1).zzawx().zzh(new zzchu((zzchq)localObject1, str, localURL, arrayOfByte, null, (zzchs)localObject4));
        }
        catch (MalformedURLException localMalformedURLException)
        {
          boolean bool;
          zzawy().zzazd().zze("Failed to parse upload URL. Not uploading. appId", zzchm.zzjk(str), localObject5);
          continue;
        }
        return;
      }
      finally
      {
        String str;
        Object localObject5;
        this.zzjgf = false;
        zzban();
      }
      bool = false;
      continue;
      this.zzjfx = new ArrayList((Collection)localObject4);
      continue;
      label953:
      this.zzjgb = -1L;
      Object localObject3 = zzaws().zzba(l1 - zzcgn.zzayc());
      if (!TextUtils.isEmpty((CharSequence)localObject3))
      {
        localObject3 = zzaws().zzjb((String)localObject3);
        if (localObject3 != null)
        {
          zzb((zzcgh)localObject3);
          continue;
          label1007:
          localObject3 = null;
          continue;
          label1013:
          label1020:
          label1023:
          do
          {
            localObject3 = localObject4;
            break;
            localObject3 = null;
          } while (localObject3 == null);
          i = 0;
        }
      }
    }
    for (;;)
    {
      j = 0;
      break label533;
      label1038:
      j += 1;
      break label533;
      label1045:
      i += 1;
      break;
      label1052:
      i = 0;
    }
  }
  
  final void zzbak()
  {
    this.zzjga += 1;
  }
  
  final void zzbal()
  {
    zzawx().zzve();
    zzxf();
    int i;
    int j;
    if (!this.zzjfs)
    {
      zzawy().zzazh().log("This instance being marked as an uploader");
      zzawx().zzve();
      zzxf();
      if ((zzbam()) && (zzbae()))
      {
        i = zza(this.zzjfw);
        j = zzawn().zzaza();
        zzawx().zzve();
        if (i <= j) {
          break label116;
        }
        zzawy().zzazd().zze("Panic: can't downgrade version. Previous, current version", Integer.valueOf(i), Integer.valueOf(j));
      }
    }
    for (;;)
    {
      this.zzjfs = true;
      zzbaj();
      return;
      label116:
      if (i < j) {
        if (zza(j, this.zzjfw)) {
          zzawy().zzazj().zze("Storage version upgraded. Previous, current version", Integer.valueOf(i), Integer.valueOf(j));
        } else {
          zzawy().zzazd().zze("Storage version upgrade failed. Previous, current version", Integer.valueOf(i), Integer.valueOf(j));
        }
      }
    }
  }
  
  public final void zzbo(boolean paramBoolean)
  {
    zzbaj();
  }
  
  /* Error */
  final void zzc(zzcgl paramzzcgl, zzcgi paramzzcgi)
  {
    // Byte code:
    //   0: aload_1
    //   1: invokestatic 95	com/google/android/gms/common/internal/zzbq:checkNotNull	(Ljava/lang/Object;)Ljava/lang/Object;
    //   4: pop
    //   5: aload_1
    //   6: getfield 2139	com/google/android/gms/internal/zzcgl:packageName	Ljava/lang/String;
    //   9: invokestatic 625	com/google/android/gms/common/internal/zzbq:zzgm	(Ljava/lang/String;)Ljava/lang/String;
    //   12: pop
    //   13: aload_1
    //   14: getfield 2144	com/google/android/gms/internal/zzcgl:zziyg	Lcom/google/android/gms/internal/zzcln;
    //   17: invokestatic 95	com/google/android/gms/common/internal/zzbq:checkNotNull	(Ljava/lang/Object;)Ljava/lang/Object;
    //   20: pop
    //   21: aload_1
    //   22: getfield 2144	com/google/android/gms/internal/zzcgl:zziyg	Lcom/google/android/gms/internal/zzcln;
    //   25: getfield 2147	com/google/android/gms/internal/zzcln:name	Ljava/lang/String;
    //   28: invokestatic 625	com/google/android/gms/common/internal/zzbq:zzgm	(Ljava/lang/String;)Ljava/lang/String;
    //   31: pop
    //   32: aload_0
    //   33: invokevirtual 307	com/google/android/gms/internal/zzcim:zzawx	()Lcom/google/android/gms/internal/zzcih;
    //   36: invokevirtual 310	com/google/android/gms/internal/zzcjk:zzve	()V
    //   39: aload_0
    //   40: invokevirtual 913	com/google/android/gms/internal/zzcim:zzxf	()V
    //   43: aload_2
    //   44: getfield 1282	com/google/android/gms/internal/zzcgi:zzixs	Ljava/lang/String;
    //   47: invokestatic 401	android/text/TextUtils:isEmpty	(Ljava/lang/CharSequence;)Z
    //   50: ifeq +4 -> 54
    //   53: return
    //   54: aload_2
    //   55: getfield 1093	com/google/android/gms/internal/zzcgi:zzixx	Z
    //   58: ifne +9 -> 67
    //   61: aload_0
    //   62: aload_2
    //   63: invokespecial 1096	com/google/android/gms/internal/zzcim:zzg	(Lcom/google/android/gms/internal/zzcgi;)V
    //   66: return
    //   67: aload_0
    //   68: invokevirtual 602	com/google/android/gms/internal/zzcim:zzaws	()Lcom/google/android/gms/internal/zzcgo;
    //   71: invokevirtual 1144	com/google/android/gms/internal/zzcgo:beginTransaction	()V
    //   74: aload_0
    //   75: aload_2
    //   76: invokespecial 1096	com/google/android/gms/internal/zzcim:zzg	(Lcom/google/android/gms/internal/zzcgi;)V
    //   79: aload_0
    //   80: invokevirtual 602	com/google/android/gms/internal/zzcim:zzaws	()Lcom/google/android/gms/internal/zzcgo;
    //   83: aload_1
    //   84: getfield 2139	com/google/android/gms/internal/zzcgl:packageName	Ljava/lang/String;
    //   87: aload_1
    //   88: getfield 2144	com/google/android/gms/internal/zzcgl:zziyg	Lcom/google/android/gms/internal/zzcln;
    //   91: getfield 2147	com/google/android/gms/internal/zzcln:name	Ljava/lang/String;
    //   94: invokevirtual 2156	com/google/android/gms/internal/zzcgo:zzah	(Ljava/lang/String;Ljava/lang/String;)Lcom/google/android/gms/internal/zzcgl;
    //   97: astore 4
    //   99: aload 4
    //   101: ifnull +158 -> 259
    //   104: aload_0
    //   105: invokevirtual 294	com/google/android/gms/internal/zzcim:zzawy	()Lcom/google/android/gms/internal/zzchm;
    //   108: invokevirtual 709	com/google/android/gms/internal/zzchm:zzazi	()Lcom/google/android/gms/internal/zzcho;
    //   111: ldc_w 2394
    //   114: aload_1
    //   115: getfield 2139	com/google/android/gms/internal/zzcgl:packageName	Ljava/lang/String;
    //   118: aload_0
    //   119: invokevirtual 658	com/google/android/gms/internal/zzcim:zzawt	()Lcom/google/android/gms/internal/zzchk;
    //   122: aload_1
    //   123: getfield 2144	com/google/android/gms/internal/zzcgl:zziyg	Lcom/google/android/gms/internal/zzcln;
    //   126: getfield 2147	com/google/android/gms/internal/zzcln:name	Ljava/lang/String;
    //   129: invokevirtual 664	com/google/android/gms/internal/zzchk:zzjj	(Ljava/lang/String;)Ljava/lang/String;
    //   132: invokevirtual 453	com/google/android/gms/internal/zzcho:zze	(Ljava/lang/String;Ljava/lang/Object;Ljava/lang/Object;)V
    //   135: aload_0
    //   136: invokevirtual 602	com/google/android/gms/internal/zzcim:zzaws	()Lcom/google/android/gms/internal/zzcgo;
    //   139: aload_1
    //   140: getfield 2139	com/google/android/gms/internal/zzcgl:packageName	Ljava/lang/String;
    //   143: aload_1
    //   144: getfield 2144	com/google/android/gms/internal/zzcgl:zziyg	Lcom/google/android/gms/internal/zzcln;
    //   147: getfield 2147	com/google/android/gms/internal/zzcln:name	Ljava/lang/String;
    //   150: invokevirtual 2211	com/google/android/gms/internal/zzcgo:zzai	(Ljava/lang/String;Ljava/lang/String;)I
    //   153: pop
    //   154: aload 4
    //   156: getfield 2153	com/google/android/gms/internal/zzcgl:zziyi	Z
    //   159: ifeq +21 -> 180
    //   162: aload_0
    //   163: invokevirtual 602	com/google/android/gms/internal/zzcim:zzaws	()Lcom/google/android/gms/internal/zzcgo;
    //   166: aload_1
    //   167: getfield 2139	com/google/android/gms/internal/zzcgl:packageName	Ljava/lang/String;
    //   170: aload_1
    //   171: getfield 2144	com/google/android/gms/internal/zzcgl:zziyg	Lcom/google/android/gms/internal/zzcln;
    //   174: getfield 2147	com/google/android/gms/internal/zzcln:name	Ljava/lang/String;
    //   177: invokevirtual 2225	com/google/android/gms/internal/zzcgo:zzaf	(Ljava/lang/String;Ljava/lang/String;)V
    //   180: aload_1
    //   181: getfield 2228	com/google/android/gms/internal/zzcgl:zziyo	Lcom/google/android/gms/internal/zzcha;
    //   184: ifnull +60 -> 244
    //   187: aconst_null
    //   188: astore_3
    //   189: aload_1
    //   190: getfield 2228	com/google/android/gms/internal/zzcgl:zziyo	Lcom/google/android/gms/internal/zzcha;
    //   193: getfield 532	com/google/android/gms/internal/zzcha:zzizt	Lcom/google/android/gms/internal/zzcgx;
    //   196: ifnull +14 -> 210
    //   199: aload_1
    //   200: getfield 2228	com/google/android/gms/internal/zzcgl:zziyo	Lcom/google/android/gms/internal/zzcha;
    //   203: getfield 532	com/google/android/gms/internal/zzcha:zzizt	Lcom/google/android/gms/internal/zzcgx;
    //   206: invokevirtual 1193	com/google/android/gms/internal/zzcgx:zzayx	()Landroid/os/Bundle;
    //   209: astore_3
    //   210: aload_0
    //   211: aload_0
    //   212: invokevirtual 424	com/google/android/gms/internal/zzcim:zzawu	()Lcom/google/android/gms/internal/zzclq;
    //   215: aload_1
    //   216: getfield 2228	com/google/android/gms/internal/zzcgl:zziyo	Lcom/google/android/gms/internal/zzcha;
    //   219: getfield 542	com/google/android/gms/internal/zzcha:name	Ljava/lang/String;
    //   222: aload_3
    //   223: aload 4
    //   225: getfield 2140	com/google/android/gms/internal/zzcgl:zziyf	Ljava/lang/String;
    //   228: aload_1
    //   229: getfield 2228	com/google/android/gms/internal/zzcgl:zziyo	Lcom/google/android/gms/internal/zzcha;
    //   232: getfield 1213	com/google/android/gms/internal/zzcha:zzizu	J
    //   235: iconst_1
    //   236: iconst_0
    //   237: invokevirtual 2397	com/google/android/gms/internal/zzclq:zza	(Ljava/lang/String;Landroid/os/Bundle;Ljava/lang/String;JZZ)Lcom/google/android/gms/internal/zzcha;
    //   240: aload_2
    //   241: invokespecial 2186	com/google/android/gms/internal/zzcim:zzc	(Lcom/google/android/gms/internal/zzcha;Lcom/google/android/gms/internal/zzcgi;)V
    //   244: aload_0
    //   245: invokevirtual 602	com/google/android/gms/internal/zzcim:zzaws	()Lcom/google/android/gms/internal/zzcgo;
    //   248: invokevirtual 1151	com/google/android/gms/internal/zzcgo:setTransactionSuccessful	()V
    //   251: aload_0
    //   252: invokevirtual 602	com/google/android/gms/internal/zzcim:zzaws	()Lcom/google/android/gms/internal/zzcgo;
    //   255: invokevirtual 1154	com/google/android/gms/internal/zzcgo:endTransaction	()V
    //   258: return
    //   259: aload_0
    //   260: invokevirtual 294	com/google/android/gms/internal/zzcim:zzawy	()Lcom/google/android/gms/internal/zzchm;
    //   263: invokevirtual 297	com/google/android/gms/internal/zzchm:zzazf	()Lcom/google/android/gms/internal/zzcho;
    //   266: ldc_w 2399
    //   269: aload_1
    //   270: getfield 2139	com/google/android/gms/internal/zzcgl:packageName	Ljava/lang/String;
    //   273: invokestatic 439	com/google/android/gms/internal/zzchm:zzjk	(Ljava/lang/String;)Ljava/lang/Object;
    //   276: aload_0
    //   277: invokevirtual 658	com/google/android/gms/internal/zzcim:zzawt	()Lcom/google/android/gms/internal/zzchk;
    //   280: aload_1
    //   281: getfield 2144	com/google/android/gms/internal/zzcgl:zziyg	Lcom/google/android/gms/internal/zzcln;
    //   284: getfield 2147	com/google/android/gms/internal/zzcln:name	Ljava/lang/String;
    //   287: invokevirtual 664	com/google/android/gms/internal/zzchk:zzjj	(Ljava/lang/String;)Ljava/lang/String;
    //   290: invokevirtual 453	com/google/android/gms/internal/zzcho:zze	(Ljava/lang/String;Ljava/lang/Object;Ljava/lang/Object;)V
    //   293: goto -49 -> 244
    //   296: astore_1
    //   297: aload_0
    //   298: invokevirtual 602	com/google/android/gms/internal/zzcim:zzaws	()Lcom/google/android/gms/internal/zzcgo;
    //   301: invokevirtual 1154	com/google/android/gms/internal/zzcgo:endTransaction	()V
    //   304: aload_1
    //   305: athrow
    // Local variable table:
    //   start	length	slot	name	signature
    //   0	306	0	this	zzcim
    //   0	306	1	paramzzcgl	zzcgl
    //   0	306	2	paramzzcgi	zzcgi
    //   188	35	3	localBundle	Bundle
    //   97	127	4	localzzcgl	zzcgl
    // Exception table:
    //   from	to	target	type
    //   74	99	296	finally
    //   104	180	296	finally
    //   180	187	296	finally
    //   189	210	296	finally
    //   210	244	296	finally
    //   244	251	296	finally
    //   259	293	296	finally
  }
  
  final void zzc(zzcln paramzzcln, zzcgi paramzzcgi)
  {
    zzawx().zzve();
    zzxf();
    if (TextUtils.isEmpty(paramzzcgi.zzixs)) {
      return;
    }
    if (!paramzzcgi.zzixx)
    {
      zzg(paramzzcgi);
      return;
    }
    zzawy().zzazi().zzj("Removing user property", zzawt().zzjj(paramzzcln.name));
    zzaws().beginTransaction();
    try
    {
      zzg(paramzzcgi);
      zzaws().zzaf(paramzzcgi.packageName, paramzzcln.name);
      zzaws().setTransactionSuccessful();
      zzawy().zzazi().zzj("User property removed", zzawt().zzjj(paramzzcln.name));
      return;
    }
    finally
    {
      zzaws().endTransaction();
    }
  }
  
  final void zzd(zzcgi paramzzcgi)
  {
    zzaws().zzjb(paramzzcgi.packageName);
    localzzcgo = zzaws();
    str = paramzzcgi.packageName;
    zzbq.zzgm(str);
    localzzcgo.zzve();
    localzzcgo.zzxf();
    try
    {
      SQLiteDatabase localSQLiteDatabase = localzzcgo.getWritableDatabase();
      String[] arrayOfString = new String[1];
      arrayOfString[0] = str;
      int i = localSQLiteDatabase.delete("apps", "app_id=?", arrayOfString);
      int j = localSQLiteDatabase.delete("events", "app_id=?", arrayOfString);
      int k = localSQLiteDatabase.delete("user_attributes", "app_id=?", arrayOfString);
      int m = localSQLiteDatabase.delete("conditional_properties", "app_id=?", arrayOfString);
      int n = localSQLiteDatabase.delete("raw_events", "app_id=?", arrayOfString);
      int i1 = localSQLiteDatabase.delete("raw_events_metadata", "app_id=?", arrayOfString);
      int i2 = localSQLiteDatabase.delete("queue", "app_id=?", arrayOfString);
      i = localSQLiteDatabase.delete("audience_filter_values", "app_id=?", arrayOfString) + (i + 0 + j + k + m + n + i1 + i2);
      if (i > 0) {
        localzzcgo.zzawy().zzazj().zze("Reset analytics data. app, records", str, Integer.valueOf(i));
      }
    }
    catch (SQLiteException localSQLiteException)
    {
      for (;;)
      {
        localzzcgo.zzawy().zzazd().zze("Error resetting analytics data. appId, error", zzchm.zzjk(str), localSQLiteException);
      }
    }
    zzf(zza(this.mContext, paramzzcgi.packageName, paramzzcgi.zzixs, paramzzcgi.zzixx, paramzzcgi.zziye));
  }
  
  final void zzd(zzcgl paramzzcgl)
  {
    zzcgi localzzcgi = zzjw(paramzzcgl.packageName);
    if (localzzcgi != null) {
      zzb(paramzzcgl, localzzcgi);
    }
  }
  
  final void zze(zzcgi paramzzcgi)
  {
    zzawx().zzve();
    zzxf();
    zzbq.zzgm(paramzzcgi.packageName);
    zzg(paramzzcgi);
  }
  
  final void zze(zzcgl paramzzcgl)
  {
    zzcgi localzzcgi = zzjw(paramzzcgl.packageName);
    if (localzzcgi != null) {
      zzc(paramzzcgl, localzzcgi);
    }
  }
  
  public final void zzf(zzcgi paramzzcgi)
  {
    zzawx().zzve();
    zzxf();
    zzbq.checkNotNull(paramzzcgi);
    zzbq.zzgm(paramzzcgi.packageName);
    if (TextUtils.isEmpty(paramzzcgi.zzixs)) {
      return;
    }
    Object localObject1 = zzaws().zzjb(paramzzcgi.packageName);
    if ((localObject1 != null) && (TextUtils.isEmpty(((zzcgh)localObject1).getGmpAppId())) && (!TextUtils.isEmpty(paramzzcgi.zzixs)))
    {
      ((zzcgh)localObject1).zzar(0L);
      zzaws().zza((zzcgh)localObject1);
      zzawv().zzjv(paramzzcgi.packageName);
    }
    if (!paramzzcgi.zzixx)
    {
      zzg(paramzzcgi);
      return;
    }
    long l2 = paramzzcgi.zziyc;
    long l1 = l2;
    if (l2 == 0L) {
      l1 = this.zzata.currentTimeMillis();
    }
    int i = paramzzcgi.zziyd;
    Object localObject2;
    if ((i != 0) && (i != 1))
    {
      zzawy().zzazf().zze("Incorrect app type, assuming installed app. appId, appType", zzchm.zzjk(paramzzcgi.packageName), Integer.valueOf(i));
      i = 0;
      zzaws().beginTransaction();
      for (;;)
      {
        try
        {
          localObject2 = zzaws().zzjb(paramzzcgi.packageName);
          localObject1 = localObject2;
          if (localObject2 != null)
          {
            localObject1 = localObject2;
            if (((zzcgh)localObject2).getGmpAppId() != null)
            {
              localObject1 = localObject2;
              if (!((zzcgh)localObject2).getGmpAppId().equals(paramzzcgi.zzixs))
              {
                zzawy().zzazf().zzj("New GMP App Id passed in. Removing cached database data. appId", zzchm.zzjk(((zzcgh)localObject2).getAppId()));
                localObject1 = zzaws();
                localObject2 = ((zzcgh)localObject2).getAppId();
                ((zzcjl)localObject1).zzxf();
                ((zzcjk)localObject1).zzve();
                zzbq.zzgm((String)localObject2);
              }
            }
          }
          try
          {
            localObject3 = ((zzcgo)localObject1).getWritableDatabase();
            String[] arrayOfString = new String[1];
            arrayOfString[0] = localObject2;
            int j = ((SQLiteDatabase)localObject3).delete("events", "app_id=?", arrayOfString);
            int k = ((SQLiteDatabase)localObject3).delete("user_attributes", "app_id=?", arrayOfString);
            int m = ((SQLiteDatabase)localObject3).delete("conditional_properties", "app_id=?", arrayOfString);
            int n = ((SQLiteDatabase)localObject3).delete("apps", "app_id=?", arrayOfString);
            int i1 = ((SQLiteDatabase)localObject3).delete("raw_events", "app_id=?", arrayOfString);
            int i2 = ((SQLiteDatabase)localObject3).delete("raw_events_metadata", "app_id=?", arrayOfString);
            int i3 = ((SQLiteDatabase)localObject3).delete("event_filters", "app_id=?", arrayOfString);
            int i4 = ((SQLiteDatabase)localObject3).delete("property_filters", "app_id=?", arrayOfString);
            j = ((SQLiteDatabase)localObject3).delete("audience_filter_values", "app_id=?", arrayOfString) + (j + 0 + k + m + n + i1 + i2 + i3 + i4);
            if (j > 0) {
              ((zzcjk)localObject1).zzawy().zzazj().zze("Deleted application data. app, records", localObject2, Integer.valueOf(j));
            }
          }
          catch (SQLiteException localSQLiteException)
          {
            Object localObject3;
            ((zzcjk)localObject1).zzawy().zzazd().zze("Error deleting application data. appId, error", zzchm.zzjk((String)localObject2), localSQLiteException);
            continue;
          }
          localObject1 = null;
          if ((localObject1 != null) && (((zzcgh)localObject1).zzvj() != null) && (!((zzcgh)localObject1).zzvj().equals(paramzzcgi.zzifm)))
          {
            localObject2 = new Bundle();
            ((Bundle)localObject2).putString("_pv", ((zzcgh)localObject1).zzvj());
            zzb(new zzcha("_au", new zzcgx((Bundle)localObject2), "auto", l1), paramzzcgi);
          }
          zzg(paramzzcgi);
          localObject1 = null;
          if (i == 0)
          {
            localObject1 = zzaws().zzae(paramzzcgi.packageName, "_f");
            if (localObject1 != null) {
              break label1280;
            }
            l2 = (1L + l1 / 3600000L) * 3600000L;
            if (i != 0) {
              break label1180;
            }
            zzb(new zzcln("_fot", l1, Long.valueOf(l2), "auto"), paramzzcgi);
            zzawx().zzve();
            zzxf();
            localObject3 = new Bundle();
            ((Bundle)localObject3).putLong("_c", 1L);
            ((Bundle)localObject3).putLong("_r", 1L);
            ((Bundle)localObject3).putLong("_uwa", 0L);
            ((Bundle)localObject3).putLong("_pfo", 0L);
            ((Bundle)localObject3).putLong("_sys", 0L);
            ((Bundle)localObject3).putLong("_sysu", 0L);
            if (this.mContext.getPackageManager() != null) {
              break;
            }
            zzawy().zzazd().zzj("PackageManager is null, first open report might be inaccurate. appId", zzchm.zzjk(paramzzcgi.packageName));
            label754:
            localObject1 = zzaws();
            localObject2 = paramzzcgi.packageName;
            zzbq.zzgm((String)localObject2);
            ((zzcjk)localObject1).zzve();
            ((zzcjl)localObject1).zzxf();
            l2 = ((zzcgo)localObject1).zzal((String)localObject2, "first_open_count");
            if (l2 >= 0L) {
              ((Bundle)localObject3).putLong("_pfo", l2);
            }
            zzb(new zzcha("_f", new zzcgx((Bundle)localObject3), "auto", l1), paramzzcgi);
            label840:
            localObject1 = new Bundle();
            ((Bundle)localObject1).putLong("_et", 1L);
            zzb(new zzcha("_e", new zzcgx((Bundle)localObject1), "auto", l1), paramzzcgi);
            label887:
            zzaws().setTransactionSuccessful();
            return;
          }
        }
        finally
        {
          zzaws().endTransaction();
        }
        if (i == 1) {
          localObject1 = zzaws().zzae(paramzzcgi.packageName, "_v");
        }
      }
      localObject1 = null;
    }
    for (;;)
    {
      try
      {
        localObject2 = zzbhf.zzdb(this.mContext).getPackageInfo(paramzzcgi.packageName, 0);
        localObject1 = localObject2;
        if ((localObject1 != null) && (((PackageInfo)localObject1).firstInstallTime != 0L))
        {
          i = 0;
          if (((PackageInfo)localObject1).firstInstallTime == ((PackageInfo)localObject1).lastUpdateTime) {
            break label1327;
          }
          localSQLiteException.putLong("_uwa", 1L);
          if (i == 0) {
            break label1332;
          }
          l2 = 1L;
          zzb(new zzcln("_fi", l1, Long.valueOf(l2), "auto"), paramzzcgi);
        }
      }
      catch (PackageManager.NameNotFoundException localNameNotFoundException2)
      {
        try
        {
          localObject1 = zzbhf.zzdb(this.mContext).getApplicationInfo(paramzzcgi.packageName, 0);
          if (localObject1 == null) {
            break label754;
          }
          if ((((ApplicationInfo)localObject1).flags & 0x1) != 0) {
            localSQLiteException.putLong("_sys", 1L);
          }
          if ((((ApplicationInfo)localObject1).flags & 0x80) == 0) {
            break label754;
          }
          localSQLiteException.putLong("_sysu", 1L);
          break label754;
          localNameNotFoundException2 = localNameNotFoundException2;
          zzawy().zzazd().zze("Package info is null, first open report might be inaccurate. appId", zzchm.zzjk(paramzzcgi.packageName), localNameNotFoundException2);
        }
        catch (PackageManager.NameNotFoundException localNameNotFoundException1)
        {
          zzawy().zzazd().zze("Application info is null, first open report might be inaccurate. appId", zzchm.zzjk(paramzzcgi.packageName), localNameNotFoundException1);
          localBundle = null;
          continue;
        }
      }
      label1180:
      if (i != 1) {
        break label840;
      }
      zzb(new zzcln("_fvt", l1, Long.valueOf(l2), "auto"), paramzzcgi);
      zzawx().zzve();
      zzxf();
      Bundle localBundle = new Bundle();
      localBundle.putLong("_c", 1L);
      localBundle.putLong("_r", 1L);
      zzb(new zzcha("_v", new zzcgx(localBundle), "auto", l1), paramzzcgi);
      break label840;
      label1280:
      if (!paramzzcgi.zzixy) {
        break label887;
      }
      zzb(new zzcha("_cd", new zzcgx(new Bundle()), "auto", l1), paramzzcgi);
      break label887;
      break;
      label1327:
      i = 1;
      continue;
      label1332:
      l2 = 0L;
    }
  }
  
  final void zzi(Runnable paramRunnable)
  {
    zzawx().zzve();
    if (this.zzjfy == null) {
      this.zzjfy = new ArrayList();
    }
    this.zzjfy.add(paramRunnable);
  }
  
  public final String zzjx(String paramString)
  {
    Object localObject = zzawx().zzc(new zzcio(this, paramString));
    try
    {
      localObject = (String)((Future)localObject).get(30000L, TimeUnit.MILLISECONDS);
      return (String)localObject;
    }
    catch (InterruptedException localInterruptedException)
    {
      zzawy().zzazd().zze("Failed to get app instance id. appId", zzchm.zzjk(paramString), localInterruptedException);
      return null;
    }
    catch (ExecutionException localExecutionException)
    {
      for (;;) {}
    }
    catch (TimeoutException localTimeoutException)
    {
      for (;;) {}
    }
  }
  
  public final zzd zzws()
  {
    return this.zzata;
  }
  
  final void zzxf()
  {
    if (!this.zzdtb) {
      throw new IllegalStateException("AppMeasurement is not initialized");
    }
  }
  
  final class zza
    implements zzcgq
  {
    List<zzcmb> zzapa;
    zzcme zzjgi;
    List<Long> zzjgj;
    private long zzjgk;
    
    private zza() {}
    
    private static long zza(zzcmb paramzzcmb)
    {
      return paramzzcmb.zzjli.longValue() / 1000L / 60L / 60L;
    }
    
    public final boolean zza(long paramLong, zzcmb paramzzcmb)
    {
      zzbq.checkNotNull(paramzzcmb);
      if (this.zzapa == null) {
        this.zzapa = new ArrayList();
      }
      if (this.zzjgj == null) {
        this.zzjgj = new ArrayList();
      }
      if ((this.zzapa.size() > 0) && (zza((zzcmb)this.zzapa.get(0)) != zza(paramzzcmb))) {
        return false;
      }
      long l = this.zzjgk + paramzzcmb.zzho();
      if (l >= Math.max(0, ((Integer)zzchc.zzjal.get()).intValue())) {
        return false;
      }
      this.zzjgk = l;
      this.zzapa.add(paramzzcmb);
      this.zzjgj.add(Long.valueOf(paramLong));
      return this.zzapa.size() < Math.max(1, ((Integer)zzchc.zzjam.get()).intValue());
    }
    
    public final void zzb(zzcme paramzzcme)
    {
      zzbq.checkNotNull(paramzzcme);
      this.zzjgi = paramzzcme;
    }
  }
}


/* Location:              /home/fabian/Escritorio/Proyectos/Android/Dev/jardecompiler/TMessagesProj-fat-debug.jar!/com/google/android/gms/internal/zzcim.class
 * Java compiler version: 6 (50.0)
 * JD-Core Version:       0.7.1-SNAPSHOT-20140817
 */