package com.google.android.gms.wearable.internal;

import android.os.ParcelFileDescriptor;
import java.util.concurrent.Callable;

final class zzfx
  implements Callable<Boolean>
{
  zzfx(zzfw paramzzfw, ParcelFileDescriptor paramParcelFileDescriptor, byte[] paramArrayOfByte) {}
  
  /* Error */
  private final Boolean zzDX()
  {
    // Byte code:
    //   0: ldc 27
    //   2: iconst_3
    //   3: invokestatic 33	android/util/Log:isLoggable	(Ljava/lang/String;I)Z
    //   6: ifeq +46 -> 52
    //   9: aload_0
    //   10: getfield 15	com/google/android/gms/wearable/internal/zzfx:zzbTp	Landroid/os/ParcelFileDescriptor;
    //   13: invokestatic 39	java/lang/String:valueOf	(Ljava/lang/Object;)Ljava/lang/String;
    //   16: astore_1
    //   17: ldc 27
    //   19: new 41	java/lang/StringBuilder
    //   22: dup
    //   23: aload_1
    //   24: invokestatic 39	java/lang/String:valueOf	(Ljava/lang/Object;)Ljava/lang/String;
    //   27: invokevirtual 45	java/lang/String:length	()I
    //   30: bipush 36
    //   32: iadd
    //   33: invokespecial 48	java/lang/StringBuilder:<init>	(I)V
    //   36: ldc 50
    //   38: invokevirtual 54	java/lang/StringBuilder:append	(Ljava/lang/String;)Ljava/lang/StringBuilder;
    //   41: aload_1
    //   42: invokevirtual 54	java/lang/StringBuilder:append	(Ljava/lang/String;)Ljava/lang/StringBuilder;
    //   45: invokevirtual 58	java/lang/StringBuilder:toString	()Ljava/lang/String;
    //   48: invokestatic 62	android/util/Log:d	(Ljava/lang/String;Ljava/lang/String;)I
    //   51: pop
    //   52: new 64	android/os/ParcelFileDescriptor$AutoCloseOutputStream
    //   55: dup
    //   56: aload_0
    //   57: getfield 15	com/google/android/gms/wearable/internal/zzfx:zzbTp	Landroid/os/ParcelFileDescriptor;
    //   60: invokespecial 67	android/os/ParcelFileDescriptor$AutoCloseOutputStream:<init>	(Landroid/os/ParcelFileDescriptor;)V
    //   63: astore_1
    //   64: aload_1
    //   65: aload_0
    //   66: getfield 17	com/google/android/gms/wearable/internal/zzfx:zzbKQ	[B
    //   69: invokevirtual 71	android/os/ParcelFileDescriptor$AutoCloseOutputStream:write	([B)V
    //   72: aload_1
    //   73: invokevirtual 74	android/os/ParcelFileDescriptor$AutoCloseOutputStream:flush	()V
    //   76: ldc 27
    //   78: iconst_3
    //   79: invokestatic 33	android/util/Log:isLoggable	(Ljava/lang/String;I)Z
    //   82: ifeq +46 -> 128
    //   85: aload_0
    //   86: getfield 15	com/google/android/gms/wearable/internal/zzfx:zzbTp	Landroid/os/ParcelFileDescriptor;
    //   89: invokestatic 39	java/lang/String:valueOf	(Ljava/lang/Object;)Ljava/lang/String;
    //   92: astore_2
    //   93: ldc 27
    //   95: new 41	java/lang/StringBuilder
    //   98: dup
    //   99: aload_2
    //   100: invokestatic 39	java/lang/String:valueOf	(Ljava/lang/Object;)Ljava/lang/String;
    //   103: invokevirtual 45	java/lang/String:length	()I
    //   106: bipush 27
    //   108: iadd
    //   109: invokespecial 48	java/lang/StringBuilder:<init>	(I)V
    //   112: ldc 76
    //   114: invokevirtual 54	java/lang/StringBuilder:append	(Ljava/lang/String;)Ljava/lang/StringBuilder;
    //   117: aload_2
    //   118: invokevirtual 54	java/lang/StringBuilder:append	(Ljava/lang/String;)Ljava/lang/StringBuilder;
    //   121: invokevirtual 58	java/lang/StringBuilder:toString	()Ljava/lang/String;
    //   124: invokestatic 62	android/util/Log:d	(Ljava/lang/String;Ljava/lang/String;)I
    //   127: pop
    //   128: iconst_1
    //   129: invokestatic 81	java/lang/Boolean:valueOf	(Z)Ljava/lang/Boolean;
    //   132: astore_2
    //   133: ldc 27
    //   135: iconst_3
    //   136: invokestatic 33	android/util/Log:isLoggable	(Ljava/lang/String;I)Z
    //   139: ifeq +46 -> 185
    //   142: aload_0
    //   143: getfield 15	com/google/android/gms/wearable/internal/zzfx:zzbTp	Landroid/os/ParcelFileDescriptor;
    //   146: invokestatic 39	java/lang/String:valueOf	(Ljava/lang/Object;)Ljava/lang/String;
    //   149: astore_3
    //   150: ldc 27
    //   152: new 41	java/lang/StringBuilder
    //   155: dup
    //   156: aload_3
    //   157: invokestatic 39	java/lang/String:valueOf	(Ljava/lang/Object;)Ljava/lang/String;
    //   160: invokevirtual 45	java/lang/String:length	()I
    //   163: bipush 24
    //   165: iadd
    //   166: invokespecial 48	java/lang/StringBuilder:<init>	(I)V
    //   169: ldc 83
    //   171: invokevirtual 54	java/lang/StringBuilder:append	(Ljava/lang/String;)Ljava/lang/StringBuilder;
    //   174: aload_3
    //   175: invokevirtual 54	java/lang/StringBuilder:append	(Ljava/lang/String;)Ljava/lang/StringBuilder;
    //   178: invokevirtual 58	java/lang/StringBuilder:toString	()Ljava/lang/String;
    //   181: invokestatic 62	android/util/Log:d	(Ljava/lang/String;Ljava/lang/String;)I
    //   184: pop
    //   185: aload_1
    //   186: invokevirtual 86	android/os/ParcelFileDescriptor$AutoCloseOutputStream:close	()V
    //   189: aload_2
    //   190: areturn
    //   191: astore_2
    //   192: aload_0
    //   193: getfield 15	com/google/android/gms/wearable/internal/zzfx:zzbTp	Landroid/os/ParcelFileDescriptor;
    //   196: invokestatic 39	java/lang/String:valueOf	(Ljava/lang/Object;)Ljava/lang/String;
    //   199: astore_2
    //   200: ldc 27
    //   202: new 41	java/lang/StringBuilder
    //   205: dup
    //   206: aload_2
    //   207: invokestatic 39	java/lang/String:valueOf	(Ljava/lang/Object;)Ljava/lang/String;
    //   210: invokevirtual 45	java/lang/String:length	()I
    //   213: bipush 36
    //   215: iadd
    //   216: invokespecial 48	java/lang/StringBuilder:<init>	(I)V
    //   219: ldc 88
    //   221: invokevirtual 54	java/lang/StringBuilder:append	(Ljava/lang/String;)Ljava/lang/StringBuilder;
    //   224: aload_2
    //   225: invokevirtual 54	java/lang/StringBuilder:append	(Ljava/lang/String;)Ljava/lang/StringBuilder;
    //   228: invokevirtual 58	java/lang/StringBuilder:toString	()Ljava/lang/String;
    //   231: invokestatic 91	android/util/Log:w	(Ljava/lang/String;Ljava/lang/String;)I
    //   234: pop
    //   235: ldc 27
    //   237: iconst_3
    //   238: invokestatic 33	android/util/Log:isLoggable	(Ljava/lang/String;I)Z
    //   241: ifeq +46 -> 287
    //   244: aload_0
    //   245: getfield 15	com/google/android/gms/wearable/internal/zzfx:zzbTp	Landroid/os/ParcelFileDescriptor;
    //   248: invokestatic 39	java/lang/String:valueOf	(Ljava/lang/Object;)Ljava/lang/String;
    //   251: astore_2
    //   252: ldc 27
    //   254: new 41	java/lang/StringBuilder
    //   257: dup
    //   258: aload_2
    //   259: invokestatic 39	java/lang/String:valueOf	(Ljava/lang/Object;)Ljava/lang/String;
    //   262: invokevirtual 45	java/lang/String:length	()I
    //   265: bipush 24
    //   267: iadd
    //   268: invokespecial 48	java/lang/StringBuilder:<init>	(I)V
    //   271: ldc 83
    //   273: invokevirtual 54	java/lang/StringBuilder:append	(Ljava/lang/String;)Ljava/lang/StringBuilder;
    //   276: aload_2
    //   277: invokevirtual 54	java/lang/StringBuilder:append	(Ljava/lang/String;)Ljava/lang/StringBuilder;
    //   280: invokevirtual 58	java/lang/StringBuilder:toString	()Ljava/lang/String;
    //   283: invokestatic 62	android/util/Log:d	(Ljava/lang/String;Ljava/lang/String;)I
    //   286: pop
    //   287: aload_1
    //   288: invokevirtual 86	android/os/ParcelFileDescriptor$AutoCloseOutputStream:close	()V
    //   291: iconst_0
    //   292: invokestatic 81	java/lang/Boolean:valueOf	(Z)Ljava/lang/Boolean;
    //   295: areturn
    //   296: astore_2
    //   297: ldc 27
    //   299: iconst_3
    //   300: invokestatic 33	android/util/Log:isLoggable	(Ljava/lang/String;I)Z
    //   303: ifeq +46 -> 349
    //   306: aload_0
    //   307: getfield 15	com/google/android/gms/wearable/internal/zzfx:zzbTp	Landroid/os/ParcelFileDescriptor;
    //   310: invokestatic 39	java/lang/String:valueOf	(Ljava/lang/Object;)Ljava/lang/String;
    //   313: astore_3
    //   314: ldc 27
    //   316: new 41	java/lang/StringBuilder
    //   319: dup
    //   320: aload_3
    //   321: invokestatic 39	java/lang/String:valueOf	(Ljava/lang/Object;)Ljava/lang/String;
    //   324: invokevirtual 45	java/lang/String:length	()I
    //   327: bipush 24
    //   329: iadd
    //   330: invokespecial 48	java/lang/StringBuilder:<init>	(I)V
    //   333: ldc 83
    //   335: invokevirtual 54	java/lang/StringBuilder:append	(Ljava/lang/String;)Ljava/lang/StringBuilder;
    //   338: aload_3
    //   339: invokevirtual 54	java/lang/StringBuilder:append	(Ljava/lang/String;)Ljava/lang/StringBuilder;
    //   342: invokevirtual 58	java/lang/StringBuilder:toString	()Ljava/lang/String;
    //   345: invokestatic 62	android/util/Log:d	(Ljava/lang/String;Ljava/lang/String;)I
    //   348: pop
    //   349: aload_1
    //   350: invokevirtual 86	android/os/ParcelFileDescriptor$AutoCloseOutputStream:close	()V
    //   353: aload_2
    //   354: athrow
    //   355: astore_1
    //   356: goto -3 -> 353
    //   359: astore_1
    //   360: goto -69 -> 291
    //   363: astore_1
    //   364: aload_2
    //   365: areturn
    // Local variable table:
    //   start	length	slot	name	signature
    //   0	366	0	this	zzfx
    //   16	334	1	localObject1	Object
    //   355	1	1	localIOException1	java.io.IOException
    //   359	1	1	localIOException2	java.io.IOException
    //   363	1	1	localIOException3	java.io.IOException
    //   92	98	2	localObject2	Object
    //   191	1	2	localIOException4	java.io.IOException
    //   199	78	2	str1	String
    //   296	69	2	localBoolean	Boolean
    //   149	190	3	str2	String
    // Exception table:
    //   from	to	target	type
    //   64	128	191	java/io/IOException
    //   128	133	191	java/io/IOException
    //   64	128	296	finally
    //   128	133	296	finally
    //   192	235	296	finally
    //   297	349	355	java/io/IOException
    //   349	353	355	java/io/IOException
    //   235	287	359	java/io/IOException
    //   287	291	359	java/io/IOException
    //   133	185	363	java/io/IOException
    //   185	189	363	java/io/IOException
  }
}


/* Location:              /home/fabian/Escritorio/Proyectos/Android/Dev/jardecompiler/TMessagesProj-fat-debug.jar!/com/google/android/gms/wearable/internal/zzfx.class
 * Java compiler version: 6 (50.0)
 * JD-Core Version:       0.7.1-SNAPSHOT-20140817
 */