package com.google.android.gms.maps.model.internal;

import android.os.Binder;
import android.os.IBinder;
import android.os.IInterface;
import android.os.Parcel;
import android.os.RemoteException;
import com.google.android.gms.maps.model.LatLng;
import com.google.android.gms.maps.model.zze;

public abstract interface zzb
  extends IInterface
{
  public abstract LatLng getCenter()
    throws RemoteException;
  
  public abstract int getFillColor()
    throws RemoteException;
  
  public abstract String getId()
    throws RemoteException;
  
  public abstract double getRadius()
    throws RemoteException;
  
  public abstract int getStrokeColor()
    throws RemoteException;
  
  public abstract float getStrokeWidth()
    throws RemoteException;
  
  public abstract float getZIndex()
    throws RemoteException;
  
  public abstract int hashCodeRemote()
    throws RemoteException;
  
  public abstract boolean isClickable()
    throws RemoteException;
  
  public abstract boolean isVisible()
    throws RemoteException;
  
  public abstract void remove()
    throws RemoteException;
  
  public abstract void setCenter(LatLng paramLatLng)
    throws RemoteException;
  
  public abstract void setClickable(boolean paramBoolean)
    throws RemoteException;
  
  public abstract void setFillColor(int paramInt)
    throws RemoteException;
  
  public abstract void setRadius(double paramDouble)
    throws RemoteException;
  
  public abstract void setStrokeColor(int paramInt)
    throws RemoteException;
  
  public abstract void setStrokeWidth(float paramFloat)
    throws RemoteException;
  
  public abstract void setVisible(boolean paramBoolean)
    throws RemoteException;
  
  public abstract void setZIndex(float paramFloat)
    throws RemoteException;
  
  public abstract boolean zzb(zzb paramzzb)
    throws RemoteException;
  
  public static abstract class zza
    extends Binder
    implements zzb
  {
    public static zzb zzjc(IBinder paramIBinder)
    {
      if (paramIBinder == null) {
        return null;
      }
      IInterface localIInterface = paramIBinder.queryLocalInterface("com.google.android.gms.maps.model.internal.ICircleDelegate");
      if ((localIInterface != null) && ((localIInterface instanceof zzb))) {
        return (zzb)localIInterface;
      }
      return new zza(paramIBinder);
    }
    
    public boolean onTransact(int paramInt1, Parcel paramParcel1, Parcel paramParcel2, int paramInt2)
      throws RemoteException
    {
      int i = 0;
      int j = 0;
      boolean bool2 = false;
      int k = 0;
      boolean bool1 = false;
      float f;
      switch (paramInt1)
      {
      default: 
        return super.onTransact(paramInt1, paramParcel1, paramParcel2, paramInt2);
      case 1598968902: 
        paramParcel2.writeString("com.google.android.gms.maps.model.internal.ICircleDelegate");
        return true;
      case 1: 
        paramParcel1.enforceInterface("com.google.android.gms.maps.model.internal.ICircleDelegate");
        remove();
        paramParcel2.writeNoException();
        return true;
      case 2: 
        paramParcel1.enforceInterface("com.google.android.gms.maps.model.internal.ICircleDelegate");
        paramParcel1 = getId();
        paramParcel2.writeNoException();
        paramParcel2.writeString(paramParcel1);
        return true;
      case 3: 
        paramParcel1.enforceInterface("com.google.android.gms.maps.model.internal.ICircleDelegate");
        if (paramParcel1.readInt() != 0) {}
        for (paramParcel1 = (LatLng)LatLng.CREATOR.createFromParcel(paramParcel1);; paramParcel1 = null)
        {
          setCenter(paramParcel1);
          paramParcel2.writeNoException();
          return true;
        }
      case 4: 
        paramParcel1.enforceInterface("com.google.android.gms.maps.model.internal.ICircleDelegate");
        paramParcel1 = getCenter();
        paramParcel2.writeNoException();
        if (paramParcel1 != null)
        {
          paramParcel2.writeInt(1);
          paramParcel1.writeToParcel(paramParcel2, 1);
          return true;
        }
        paramParcel2.writeInt(0);
        return true;
      case 5: 
        paramParcel1.enforceInterface("com.google.android.gms.maps.model.internal.ICircleDelegate");
        setRadius(paramParcel1.readDouble());
        paramParcel2.writeNoException();
        return true;
      case 6: 
        paramParcel1.enforceInterface("com.google.android.gms.maps.model.internal.ICircleDelegate");
        double d = getRadius();
        paramParcel2.writeNoException();
        paramParcel2.writeDouble(d);
        return true;
      case 7: 
        paramParcel1.enforceInterface("com.google.android.gms.maps.model.internal.ICircleDelegate");
        setStrokeWidth(paramParcel1.readFloat());
        paramParcel2.writeNoException();
        return true;
      case 8: 
        paramParcel1.enforceInterface("com.google.android.gms.maps.model.internal.ICircleDelegate");
        f = getStrokeWidth();
        paramParcel2.writeNoException();
        paramParcel2.writeFloat(f);
        return true;
      case 9: 
        paramParcel1.enforceInterface("com.google.android.gms.maps.model.internal.ICircleDelegate");
        setStrokeColor(paramParcel1.readInt());
        paramParcel2.writeNoException();
        return true;
      case 10: 
        paramParcel1.enforceInterface("com.google.android.gms.maps.model.internal.ICircleDelegate");
        paramInt1 = getStrokeColor();
        paramParcel2.writeNoException();
        paramParcel2.writeInt(paramInt1);
        return true;
      case 11: 
        paramParcel1.enforceInterface("com.google.android.gms.maps.model.internal.ICircleDelegate");
        setFillColor(paramParcel1.readInt());
        paramParcel2.writeNoException();
        return true;
      case 12: 
        paramParcel1.enforceInterface("com.google.android.gms.maps.model.internal.ICircleDelegate");
        paramInt1 = getFillColor();
        paramParcel2.writeNoException();
        paramParcel2.writeInt(paramInt1);
        return true;
      case 13: 
        paramParcel1.enforceInterface("com.google.android.gms.maps.model.internal.ICircleDelegate");
        setZIndex(paramParcel1.readFloat());
        paramParcel2.writeNoException();
        return true;
      case 14: 
        paramParcel1.enforceInterface("com.google.android.gms.maps.model.internal.ICircleDelegate");
        f = getZIndex();
        paramParcel2.writeNoException();
        paramParcel2.writeFloat(f);
        return true;
      case 15: 
        paramParcel1.enforceInterface("com.google.android.gms.maps.model.internal.ICircleDelegate");
        if (paramParcel1.readInt() != 0) {
          bool1 = true;
        }
        setVisible(bool1);
        paramParcel2.writeNoException();
        return true;
      case 16: 
        paramParcel1.enforceInterface("com.google.android.gms.maps.model.internal.ICircleDelegate");
        bool1 = isVisible();
        paramParcel2.writeNoException();
        paramInt1 = i;
        if (bool1) {
          paramInt1 = 1;
        }
        paramParcel2.writeInt(paramInt1);
        return true;
      case 17: 
        paramParcel1.enforceInterface("com.google.android.gms.maps.model.internal.ICircleDelegate");
        bool1 = zzb(zzjc(paramParcel1.readStrongBinder()));
        paramParcel2.writeNoException();
        paramInt1 = j;
        if (bool1) {
          paramInt1 = 1;
        }
        paramParcel2.writeInt(paramInt1);
        return true;
      case 18: 
        paramParcel1.enforceInterface("com.google.android.gms.maps.model.internal.ICircleDelegate");
        paramInt1 = hashCodeRemote();
        paramParcel2.writeNoException();
        paramParcel2.writeInt(paramInt1);
        return true;
      case 19: 
        paramParcel1.enforceInterface("com.google.android.gms.maps.model.internal.ICircleDelegate");
        bool1 = bool2;
        if (paramParcel1.readInt() != 0) {
          bool1 = true;
        }
        setClickable(bool1);
        paramParcel2.writeNoException();
        return true;
      }
      paramParcel1.enforceInterface("com.google.android.gms.maps.model.internal.ICircleDelegate");
      bool1 = isClickable();
      paramParcel2.writeNoException();
      paramInt1 = k;
      if (bool1) {
        paramInt1 = 1;
      }
      paramParcel2.writeInt(paramInt1);
      return true;
    }
    
    private static class zza
      implements zzb
    {
      private IBinder zzajf;
      
      zza(IBinder paramIBinder)
      {
        this.zzajf = paramIBinder;
      }
      
      public IBinder asBinder()
      {
        return this.zzajf;
      }
      
      /* Error */
      public LatLng getCenter()
        throws RemoteException
      {
        // Byte code:
        //   0: invokestatic 31	android/os/Parcel:obtain	()Landroid/os/Parcel;
        //   3: astore_2
        //   4: invokestatic 31	android/os/Parcel:obtain	()Landroid/os/Parcel;
        //   7: astore_3
        //   8: aload_2
        //   9: ldc 33
        //   11: invokevirtual 37	android/os/Parcel:writeInterfaceToken	(Ljava/lang/String;)V
        //   14: aload_0
        //   15: getfield 18	com/google/android/gms/maps/model/internal/zzb$zza$zza:zzajf	Landroid/os/IBinder;
        //   18: iconst_4
        //   19: aload_2
        //   20: aload_3
        //   21: iconst_0
        //   22: invokeinterface 43 5 0
        //   27: pop
        //   28: aload_3
        //   29: invokevirtual 46	android/os/Parcel:readException	()V
        //   32: aload_3
        //   33: invokevirtual 50	android/os/Parcel:readInt	()I
        //   36: ifeq +24 -> 60
        //   39: getstatic 56	com/google/android/gms/maps/model/LatLng:CREATOR	Lcom/google/android/gms/maps/model/zze;
        //   42: aload_3
        //   43: invokevirtual 62	com/google/android/gms/maps/model/zze:createFromParcel	(Landroid/os/Parcel;)Ljava/lang/Object;
        //   46: checkcast 52	com/google/android/gms/maps/model/LatLng
        //   49: astore_1
        //   50: aload_3
        //   51: invokevirtual 65	android/os/Parcel:recycle	()V
        //   54: aload_2
        //   55: invokevirtual 65	android/os/Parcel:recycle	()V
        //   58: aload_1
        //   59: areturn
        //   60: aconst_null
        //   61: astore_1
        //   62: goto -12 -> 50
        //   65: astore_1
        //   66: aload_3
        //   67: invokevirtual 65	android/os/Parcel:recycle	()V
        //   70: aload_2
        //   71: invokevirtual 65	android/os/Parcel:recycle	()V
        //   74: aload_1
        //   75: athrow
        // Local variable table:
        //   start	length	slot	name	signature
        //   0	76	0	this	zza
        //   49	13	1	localLatLng	LatLng
        //   65	10	1	localObject	Object
        //   3	68	2	localParcel1	Parcel
        //   7	60	3	localParcel2	Parcel
        // Exception table:
        //   from	to	target	type
        //   8	50	65	finally
      }
      
      public int getFillColor()
        throws RemoteException
      {
        Parcel localParcel1 = Parcel.obtain();
        Parcel localParcel2 = Parcel.obtain();
        try
        {
          localParcel1.writeInterfaceToken("com.google.android.gms.maps.model.internal.ICircleDelegate");
          this.zzajf.transact(12, localParcel1, localParcel2, 0);
          localParcel2.readException();
          int i = localParcel2.readInt();
          return i;
        }
        finally
        {
          localParcel2.recycle();
          localParcel1.recycle();
        }
      }
      
      public String getId()
        throws RemoteException
      {
        Parcel localParcel1 = Parcel.obtain();
        Parcel localParcel2 = Parcel.obtain();
        try
        {
          localParcel1.writeInterfaceToken("com.google.android.gms.maps.model.internal.ICircleDelegate");
          this.zzajf.transact(2, localParcel1, localParcel2, 0);
          localParcel2.readException();
          String str = localParcel2.readString();
          return str;
        }
        finally
        {
          localParcel2.recycle();
          localParcel1.recycle();
        }
      }
      
      public double getRadius()
        throws RemoteException
      {
        Parcel localParcel1 = Parcel.obtain();
        Parcel localParcel2 = Parcel.obtain();
        try
        {
          localParcel1.writeInterfaceToken("com.google.android.gms.maps.model.internal.ICircleDelegate");
          this.zzajf.transact(6, localParcel1, localParcel2, 0);
          localParcel2.readException();
          double d = localParcel2.readDouble();
          return d;
        }
        finally
        {
          localParcel2.recycle();
          localParcel1.recycle();
        }
      }
      
      public int getStrokeColor()
        throws RemoteException
      {
        Parcel localParcel1 = Parcel.obtain();
        Parcel localParcel2 = Parcel.obtain();
        try
        {
          localParcel1.writeInterfaceToken("com.google.android.gms.maps.model.internal.ICircleDelegate");
          this.zzajf.transact(10, localParcel1, localParcel2, 0);
          localParcel2.readException();
          int i = localParcel2.readInt();
          return i;
        }
        finally
        {
          localParcel2.recycle();
          localParcel1.recycle();
        }
      }
      
      public float getStrokeWidth()
        throws RemoteException
      {
        Parcel localParcel1 = Parcel.obtain();
        Parcel localParcel2 = Parcel.obtain();
        try
        {
          localParcel1.writeInterfaceToken("com.google.android.gms.maps.model.internal.ICircleDelegate");
          this.zzajf.transact(8, localParcel1, localParcel2, 0);
          localParcel2.readException();
          float f = localParcel2.readFloat();
          return f;
        }
        finally
        {
          localParcel2.recycle();
          localParcel1.recycle();
        }
      }
      
      public float getZIndex()
        throws RemoteException
      {
        Parcel localParcel1 = Parcel.obtain();
        Parcel localParcel2 = Parcel.obtain();
        try
        {
          localParcel1.writeInterfaceToken("com.google.android.gms.maps.model.internal.ICircleDelegate");
          this.zzajf.transact(14, localParcel1, localParcel2, 0);
          localParcel2.readException();
          float f = localParcel2.readFloat();
          return f;
        }
        finally
        {
          localParcel2.recycle();
          localParcel1.recycle();
        }
      }
      
      public int hashCodeRemote()
        throws RemoteException
      {
        Parcel localParcel1 = Parcel.obtain();
        Parcel localParcel2 = Parcel.obtain();
        try
        {
          localParcel1.writeInterfaceToken("com.google.android.gms.maps.model.internal.ICircleDelegate");
          this.zzajf.transact(18, localParcel1, localParcel2, 0);
          localParcel2.readException();
          int i = localParcel2.readInt();
          return i;
        }
        finally
        {
          localParcel2.recycle();
          localParcel1.recycle();
        }
      }
      
      public boolean isClickable()
        throws RemoteException
      {
        boolean bool = false;
        Parcel localParcel1 = Parcel.obtain();
        Parcel localParcel2 = Parcel.obtain();
        try
        {
          localParcel1.writeInterfaceToken("com.google.android.gms.maps.model.internal.ICircleDelegate");
          this.zzajf.transact(20, localParcel1, localParcel2, 0);
          localParcel2.readException();
          int i = localParcel2.readInt();
          if (i != 0) {
            bool = true;
          }
          return bool;
        }
        finally
        {
          localParcel2.recycle();
          localParcel1.recycle();
        }
      }
      
      public boolean isVisible()
        throws RemoteException
      {
        boolean bool = false;
        Parcel localParcel1 = Parcel.obtain();
        Parcel localParcel2 = Parcel.obtain();
        try
        {
          localParcel1.writeInterfaceToken("com.google.android.gms.maps.model.internal.ICircleDelegate");
          this.zzajf.transact(16, localParcel1, localParcel2, 0);
          localParcel2.readException();
          int i = localParcel2.readInt();
          if (i != 0) {
            bool = true;
          }
          return bool;
        }
        finally
        {
          localParcel2.recycle();
          localParcel1.recycle();
        }
      }
      
      public void remove()
        throws RemoteException
      {
        Parcel localParcel1 = Parcel.obtain();
        Parcel localParcel2 = Parcel.obtain();
        try
        {
          localParcel1.writeInterfaceToken("com.google.android.gms.maps.model.internal.ICircleDelegate");
          this.zzajf.transact(1, localParcel1, localParcel2, 0);
          localParcel2.readException();
          return;
        }
        finally
        {
          localParcel2.recycle();
          localParcel1.recycle();
        }
      }
      
      /* Error */
      public void setCenter(LatLng paramLatLng)
        throws RemoteException
      {
        // Byte code:
        //   0: invokestatic 31	android/os/Parcel:obtain	()Landroid/os/Parcel;
        //   3: astore_2
        //   4: invokestatic 31	android/os/Parcel:obtain	()Landroid/os/Parcel;
        //   7: astore_3
        //   8: aload_2
        //   9: ldc 33
        //   11: invokevirtual 37	android/os/Parcel:writeInterfaceToken	(Ljava/lang/String;)V
        //   14: aload_1
        //   15: ifnull +41 -> 56
        //   18: aload_2
        //   19: iconst_1
        //   20: invokevirtual 95	android/os/Parcel:writeInt	(I)V
        //   23: aload_1
        //   24: aload_2
        //   25: iconst_0
        //   26: invokevirtual 99	com/google/android/gms/maps/model/LatLng:writeToParcel	(Landroid/os/Parcel;I)V
        //   29: aload_0
        //   30: getfield 18	com/google/android/gms/maps/model/internal/zzb$zza$zza:zzajf	Landroid/os/IBinder;
        //   33: iconst_3
        //   34: aload_2
        //   35: aload_3
        //   36: iconst_0
        //   37: invokeinterface 43 5 0
        //   42: pop
        //   43: aload_3
        //   44: invokevirtual 46	android/os/Parcel:readException	()V
        //   47: aload_3
        //   48: invokevirtual 65	android/os/Parcel:recycle	()V
        //   51: aload_2
        //   52: invokevirtual 65	android/os/Parcel:recycle	()V
        //   55: return
        //   56: aload_2
        //   57: iconst_0
        //   58: invokevirtual 95	android/os/Parcel:writeInt	(I)V
        //   61: goto -32 -> 29
        //   64: astore_1
        //   65: aload_3
        //   66: invokevirtual 65	android/os/Parcel:recycle	()V
        //   69: aload_2
        //   70: invokevirtual 65	android/os/Parcel:recycle	()V
        //   73: aload_1
        //   74: athrow
        // Local variable table:
        //   start	length	slot	name	signature
        //   0	75	0	this	zza
        //   0	75	1	paramLatLng	LatLng
        //   3	67	2	localParcel1	Parcel
        //   7	59	3	localParcel2	Parcel
        // Exception table:
        //   from	to	target	type
        //   8	14	64	finally
        //   18	29	64	finally
        //   29	47	64	finally
        //   56	61	64	finally
      }
      
      public void setClickable(boolean paramBoolean)
        throws RemoteException
      {
        int i = 0;
        Parcel localParcel1 = Parcel.obtain();
        Parcel localParcel2 = Parcel.obtain();
        try
        {
          localParcel1.writeInterfaceToken("com.google.android.gms.maps.model.internal.ICircleDelegate");
          if (paramBoolean) {
            i = 1;
          }
          localParcel1.writeInt(i);
          this.zzajf.transact(19, localParcel1, localParcel2, 0);
          localParcel2.readException();
          return;
        }
        finally
        {
          localParcel2.recycle();
          localParcel1.recycle();
        }
      }
      
      public void setFillColor(int paramInt)
        throws RemoteException
      {
        Parcel localParcel1 = Parcel.obtain();
        Parcel localParcel2 = Parcel.obtain();
        try
        {
          localParcel1.writeInterfaceToken("com.google.android.gms.maps.model.internal.ICircleDelegate");
          localParcel1.writeInt(paramInt);
          this.zzajf.transact(11, localParcel1, localParcel2, 0);
          localParcel2.readException();
          return;
        }
        finally
        {
          localParcel2.recycle();
          localParcel1.recycle();
        }
      }
      
      public void setRadius(double paramDouble)
        throws RemoteException
      {
        Parcel localParcel1 = Parcel.obtain();
        Parcel localParcel2 = Parcel.obtain();
        try
        {
          localParcel1.writeInterfaceToken("com.google.android.gms.maps.model.internal.ICircleDelegate");
          localParcel1.writeDouble(paramDouble);
          this.zzajf.transact(5, localParcel1, localParcel2, 0);
          localParcel2.readException();
          return;
        }
        finally
        {
          localParcel2.recycle();
          localParcel1.recycle();
        }
      }
      
      public void setStrokeColor(int paramInt)
        throws RemoteException
      {
        Parcel localParcel1 = Parcel.obtain();
        Parcel localParcel2 = Parcel.obtain();
        try
        {
          localParcel1.writeInterfaceToken("com.google.android.gms.maps.model.internal.ICircleDelegate");
          localParcel1.writeInt(paramInt);
          this.zzajf.transact(9, localParcel1, localParcel2, 0);
          localParcel2.readException();
          return;
        }
        finally
        {
          localParcel2.recycle();
          localParcel1.recycle();
        }
      }
      
      public void setStrokeWidth(float paramFloat)
        throws RemoteException
      {
        Parcel localParcel1 = Parcel.obtain();
        Parcel localParcel2 = Parcel.obtain();
        try
        {
          localParcel1.writeInterfaceToken("com.google.android.gms.maps.model.internal.ICircleDelegate");
          localParcel1.writeFloat(paramFloat);
          this.zzajf.transact(7, localParcel1, localParcel2, 0);
          localParcel2.readException();
          return;
        }
        finally
        {
          localParcel2.recycle();
          localParcel1.recycle();
        }
      }
      
      public void setVisible(boolean paramBoolean)
        throws RemoteException
      {
        int i = 0;
        Parcel localParcel1 = Parcel.obtain();
        Parcel localParcel2 = Parcel.obtain();
        try
        {
          localParcel1.writeInterfaceToken("com.google.android.gms.maps.model.internal.ICircleDelegate");
          if (paramBoolean) {
            i = 1;
          }
          localParcel1.writeInt(i);
          this.zzajf.transact(15, localParcel1, localParcel2, 0);
          localParcel2.readException();
          return;
        }
        finally
        {
          localParcel2.recycle();
          localParcel1.recycle();
        }
      }
      
      public void setZIndex(float paramFloat)
        throws RemoteException
      {
        Parcel localParcel1 = Parcel.obtain();
        Parcel localParcel2 = Parcel.obtain();
        try
        {
          localParcel1.writeInterfaceToken("com.google.android.gms.maps.model.internal.ICircleDelegate");
          localParcel1.writeFloat(paramFloat);
          this.zzajf.transact(13, localParcel1, localParcel2, 0);
          localParcel2.readException();
          return;
        }
        finally
        {
          localParcel2.recycle();
          localParcel1.recycle();
        }
      }
      
      /* Error */
      public boolean zzb(zzb paramzzb)
        throws RemoteException
      {
        // Byte code:
        //   0: iconst_0
        //   1: istore_3
        //   2: invokestatic 31	android/os/Parcel:obtain	()Landroid/os/Parcel;
        //   5: astore 4
        //   7: invokestatic 31	android/os/Parcel:obtain	()Landroid/os/Parcel;
        //   10: astore 5
        //   12: aload 4
        //   14: ldc 33
        //   16: invokevirtual 37	android/os/Parcel:writeInterfaceToken	(Ljava/lang/String;)V
        //   19: aload_1
        //   20: ifnull +62 -> 82
        //   23: aload_1
        //   24: invokeinterface 119 1 0
        //   29: astore_1
        //   30: aload 4
        //   32: aload_1
        //   33: invokevirtual 122	android/os/Parcel:writeStrongBinder	(Landroid/os/IBinder;)V
        //   36: aload_0
        //   37: getfield 18	com/google/android/gms/maps/model/internal/zzb$zza$zza:zzajf	Landroid/os/IBinder;
        //   40: bipush 17
        //   42: aload 4
        //   44: aload 5
        //   46: iconst_0
        //   47: invokeinterface 43 5 0
        //   52: pop
        //   53: aload 5
        //   55: invokevirtual 46	android/os/Parcel:readException	()V
        //   58: aload 5
        //   60: invokevirtual 50	android/os/Parcel:readInt	()I
        //   63: istore_2
        //   64: iload_2
        //   65: ifeq +5 -> 70
        //   68: iconst_1
        //   69: istore_3
        //   70: aload 5
        //   72: invokevirtual 65	android/os/Parcel:recycle	()V
        //   75: aload 4
        //   77: invokevirtual 65	android/os/Parcel:recycle	()V
        //   80: iload_3
        //   81: ireturn
        //   82: aconst_null
        //   83: astore_1
        //   84: goto -54 -> 30
        //   87: astore_1
        //   88: aload 5
        //   90: invokevirtual 65	android/os/Parcel:recycle	()V
        //   93: aload 4
        //   95: invokevirtual 65	android/os/Parcel:recycle	()V
        //   98: aload_1
        //   99: athrow
        // Local variable table:
        //   start	length	slot	name	signature
        //   0	100	0	this	zza
        //   0	100	1	paramzzb	zzb
        //   63	2	2	i	int
        //   1	80	3	bool	boolean
        //   5	89	4	localParcel1	Parcel
        //   10	79	5	localParcel2	Parcel
        // Exception table:
        //   from	to	target	type
        //   12	19	87	finally
        //   23	30	87	finally
        //   30	64	87	finally
      }
    }
  }
}


/* Location:              /home/fabian/Escritorio/Proyectos/Android/Dev/jardecompiler/TMessagesProj-fat-debug.jar!/com/google/android/gms/maps/model/internal/zzb.class
 * Java compiler version: 6 (50.0)
 * JD-Core Version:       0.7.1-SNAPSHOT-20140817
 */